Workbook

Sheet README
B2: Blockmediary — 5-Year Financial Model, Launch Path & Runway
B3: Programmable documentary escrow for SME cross-border trade. UAE launch-path and commercial refresh: 11 Aug 2026.
B5: TABLE OF CONTENTS | D5: Tabs are ordered the way the business reads: what it is, whether we can trade, how it earns, whether it works.
B6: Click any tab name to jump to it.
B7: START HERE
B8: 1 | C8: README | D8: Orientation, table of contents, open issues.
B9: 2 | C9: Dashboard | D9: The headline: raise, break-even, path to profitability.
B11: CAN WE TRADE, AND WHEN
B12: 3 | C12: Launch Readiness | D12: DIFC partner-led pilot timing, VARA scale stage, fees and restricted capital.
B14: HOW THE MONEY IS MADE
B15: 4 | C15: Tier Economics | D15: Revenue and cost per deal, split by document verification tier.
B16: 5 | C16: Revenue Risk Add-Ons | D16: Add-on revenue streams and the retained-risk costs set against them.
B18: DOES IT WORK
B19: 6 | C19: P&L 5yr | D19: Five-year profit and loss for the active scenario and launch path.
B20: 7 | C20: Cash Flow Statement | D20: 60-month cash flow: runway, funding, break-even month.
B21: 8 | C21: Scenario Engine | D21: Low / Base / High side by side. How wide is the range of outcomes.
B23: WHAT IT RESTS ON
B24: 9 | C24: Assumptions | D24: Every input in the model. The control panel — edit blue cells here.
B25: 10 | C25: Startup 6mo | D25: One-off launch spend before the business is trading.
B26: 11 | C26: Sensitivity | D26: Ranked view of the assumptions that most affect funding, margin and growth.
B27: 12 | C27: Risk Register | D27: Key legal, regulatory, commercial and operating assumptions that still need validation.
B28: 13 | C28: Driver Tables | D28: Research ranges and source notes supporting the model's cost and revenue inputs.
B30: SUPPORTING CHECKS & APPENDICES
B31: 14 | C31: Model Checks | D31: Mechanical tie-outs; must read PASS before figures are used.
B32: 15 | C32: Client Funds Memo | D32: Safeguarded client-funds balances and holding-period sensitivity; excluded from operating cash.
B40: SCOPE
B41: Blockmediary is a documentary escrow and document-verification service. It is not a lending or financing product.
B42: This workbook is an indicative university idea-presentation model, not a business-loan application, regulatory filing, legal opinion or investment commitment.
B43: Amounts are readable planning approximations. Client funds remain safeguarded and excluded from operating cash, revenue and runway.
B45: HOW TO USE
B46: 1. Edit blue inputs in Assumptions and Launch Readiness. Yellow cells are key presentation controls; formulas and linked values update automatically.
B47: 2. Assumptions!C4 selects commercial performance: 1=Low, 2=Base, 3=High. The delivered presentation default is Base.
B48: 3. Launch Readiness!B5 selects timing: 1=Early, 2=Base, 3=Delayed. The route is fixed as DIFC partner-led pilot followed by VARA expansion.
B49: 4. Startup 6mo holds core pre-revenue build costs. Launch Readiness separately times partner/DIFC pilot costs, future VARA fees and restricted capital.
B50: 5. P&L 5yr, Cash Flow Statement and Model Checks provide economics, runway and integrity; supporting tabs retain sources, sensitivities, risks and safeguarding detail.
B52: CURRENCY
B53: Model base currency = GBP (£). USD-priced vendors (Anthropic, AWS, Vercel, KYC, gas) are converted at the FX rate in Assumptions (GBPUSD).
... B64: • Confirm the final regulatory perimeter, custody/settlement responsibilities and partner fees with UAE counsel and the regulated partner.

Sheet Dashboard
B2: ■ FINANCIAL MODEL DASHBOARD
B4: The base case funds a partner-led DIFC pilot in Month 12, with VARA expansion and restricted capital shown separately.
B6: Base cases shown. Inputs: Assumptions!C4 and Launch Readiness!B5. Y4/Y5 acquisition intensity is flagged in P&L 5yr.
R9: Pitch deck metrics linked to model
C10: ="£"&ROUND('Launch Readiness'!$E$12/1000000,1)&"m" -> £2.8m | G10: ="Month "&'Launch Readiness'!$E$6 -> Month 12 | K10: ="£"&ROUND(AVERAGE(S38,S37,S36),0) -> £688 | O10: ="£"&ROUND('P&L 5yr'!$G$18/1000000,1)&"m" -> £17.8m | R10: Slide | S10: Metric | T10: Model value | U10: Pitch-copy output | V10: Source / model link | W10: Deck slot
C11: Initial operating funding need (3-month reserve) | G11: First paying pilot customer | K11: Projected Steady State CAC | O11: Y5 annual revenue — Base commercial case | R11: 7 | S11: Settlement fee range | T11: =ROUND(MIN(Assumptions!$F$70:$F$72)*100,1)&"%-"&ROUND(MAX(Assumptions!$F$70:$F$72)*100,1)&"%" -> 0.8%-3% | U11: =T11&" per trade, tier-dependent" -> 0.8%-3% per trade, tier-dependent | V11: Assumptions!F73:F75 | W11: Business model card A
C12: monthly operating deficit plus reserve; future VARA capital excluded | G12: Base partner-led DIFC pilot timing | K12: AI-enabled staffing ramp targets <=250 gross new customers per Sales/BD/CS FTE | O12: accepted commercial assumptions and UAE launch timing | R12: 7 | S12: Blended gross margin | T12: =ROUND('Scenario Engine'!$H$49*100,0)&"%-"&ROUND('Scenario Engine'!$L$49*100,0)&"%" -> 71%-79% | U12: =T12&" blended gross margin, base Y1-Y5" -> 71%-79% blended gross margin, base Y1-Y5 | V12: Scenario Engine!$H$49:$L$49 | W12: Bottom KPI
C13: Base path to profitability (£m) | K13: Funding stack (£m) | R13: 7 | S13: Average ticket | T13: ="GBP "&ROUND('Scenario Engine'!$H$9/1000,0)&"K -> GBP "&ROUND('Scenario Engine'!$J$9/1000,0)&"K" -> GBP 31K -> GBP 38K | U13: =T13&" average ticket, Y1 to Y3; GBP "&ROUND('Scenario Engine'!$L$9/1000,0)&"K by Y5" -> GBP 31K -> GBP 38K average ticket, Y1 to Y3; GBP 48K by Y5 | V13: Scenario Engine!$H$9:$L$9 | W13: Bottom KPI
B14: Revenue and EBITDA in GBP millions, Base commercial case. | C14: Revenue scales before the payroll/opex curve catches up. | I14: Initial funding stack in GBP millions; future VARA capital is excluded. | K14: Monthly-model deficit, reserve and restricted capital. | R14: 7 | S14: Processed deals | T14: =ROUND('Scenario Engine'!$H$8,0)&" -> "&ROUND('Scenario Engine'!$J$8,0) -> 3 -> 2000 | U14: =T14&" processed deals, Y1 to Y3 base case" -> 3 -> 2000 processed deals, Y1 to Y3 base case | V14: Scenario Engine!$H$8:$J$8 | W14: Bottom KPI
R15: 11 | S15: Y3 annual revenue range | T15: ="GBP "&ROUND('Scenario Engine'!$D$30/1000000,1)&"M-"&ROUND('Scenario Engine'!$P$30/1000000,1)&"M" -> GBP 1.1M-1.9M | U15: =T15&" Y3 annual revenue; base GBP "&ROUND('Scenario Engine'!$J$30/1000000,1)&"M" -> GBP 1.1M-1.9M Y3 annual revenue; base GBP 1.4M | V15: Scenario Engine!D30/J30/P30 | W15: Top KPI card
R16: 11 | S16: Y3 active customers range | T16: =ROUND('Scenario Engine'!$D$62,0)&"-"&ROUND('Scenario Engine'!$P$62,0) -> 480-320 | U16: =T16&" Y3 active customers; base "&ROUND('Scenario Engine'!$J$62,0) -> 480-320 Y3 active customers; base 333 | V16: Scenario Engine!D62/J62/P62 | W16: Top KPI card
R17: 11 | S17: Monthly cash-flow breakeven | T17: ='Cash Flow Statement'!$B$46 -> Y4 M8 | U17: ="Base monthly cash-flow break-even: "&T17&"; scenario range "&'Cash Flow Statement'!$B$47&" to "&'Cash Flow Statement'!$B$45 -> Base monthly cash-flow break-even: Y4 M8; scenario range Y4 M4 to Beyond Month 60 | V17: Cash Flow Statement!B45:B47 | W17: Top KPI card
R18: 11 | S18: Initial funding need | T18: ="GBP "&ROUND('Launch Readiness'!$E$12/1000000,2)&"M" -> GBP 2.84M | U18: =T18&" initial operating funding; future VARA capital shown separately" -> GBP 2.84M initial operating funding; future VARA capital shown separately | V18: Launch Readiness!F12 | W18: Top KPI card
R19: 11 | S19: Blended escrow take rate | T19: =IFERROR(ROUND('Tier Economics'!$E$12/'Tier Economics'!$E$9*100,1)&"% / "&ROUND('Tier Economics'!$M$12/'Tier Economics'!$M$9*100,1)&"% / "&ROUND('Tier Economics'!$U$12/'Tier Economics'!$U$9*100,1)&"%","n/a - no Year 1 volume on this launch path") -> 2% / 1.3% / 1% | U19: =IFERROR(IF(LEFT(T19,3)="n/a",T19,T19&" blended escrow take rate, base Y1 / Y3 / Y5"),"n/a - no Year 1 volume on this launch path") -> 2% / 1.3% / 1% blended escrow take rate, base Y1 / Y3 / Y5 | V19: Tier Economics total escrow fee / GMV | W19: Key assumptions
R20: 11 | S20: Tier A adoption | T20: =ROUND(Assumptions!$D$61*100,0)&"% -> "&ROUND(Assumptions!$D$152*100,0)&"%" -> 15% -> 70% | U20: =T20&" Tier A eBL mix, base Y1 to Y5" -> 15% -> 70% Tier A eBL mix, base Y1 to Y5 | V20: Assumptions!D64,D160 | W20: Key assumptions
R21: 13 | S21: Initial operating funding | T21: ="GBP "&ROUND('Launch Readiness'!$E$12/1000000,2)&"M" -> GBP 2.84M | U21: =T21&" initial operating funding need" -> GBP 2.84M initial operating funding need | V21: Launch Readiness!F12 | W21: Total seed raise
C22: Monthly cumulative operating cash (£m) | R22: 13 | S22: Engineering & product | T22: =ROUND($M$58*100,0)&"% GBP "&ROUND($L$58/1000,0)&"K" -> 19% GBP 532K | U22: =T22 -> 19% GBP 532K | V22: Dashboard!J58:M58 | W22: Use of funds
B23: Ending cash balance in GBP millions at 6-month checkpoints. | C23: Six-month checkpoints avoid unreadable 60-label charts. | K23: Scenario readout | R23: 13 | S23: Ops, people & G&A | T23: =ROUND($M$59*100,0)&"% GBP "&ROUND($L$59/1000,0)&"K" -> 35% GBP 991K | U23: =T23 -> 35% GBP 991K | V23: Dashboard!J59:M59 | W23: Use of funds
J24: Break-even timing and funding gap by scenario. | K24: Break-even timing and funding gap by case. | R24: 13 | S24: Compliance, legal & regulatory | T24: =ROUND($M$60*100,0)&"% GBP "&ROUND($L$60/1000,0)&"K" -> 34% GBP 967K | U24: =T24 -> 34% GBP 967K | V24: Dashboard!J60:M60 | W24: Use of funds
J25: Case | K25: Monthly BE | L25: Peak gap | M25: M60 cash | N25: Funding ask | R25: 13 | S25: GTM & acquisition | T25: =ROUND($M$61*100,0)&"% GBP "&ROUND($L$61/1000,0)&"K" -> 6% GBP 159K | U25: =T25 -> 6% GBP 159K | V25: Dashboard!J61:M61 | W25: Use of funds
J26: Low | K26: ='Cash Flow Statement'!B45 -> Beyond Month 60 | L26: ='Cash Flow Statement'!C45/1000000 -> 3.915862 | M26: ='Cash Flow Statement'!D45/1000000 -> -2.924278 | N26: ='Cash Flow Statement'!F45/1000000 -> 4.106889 | R26: 13 | S26: Working capital + contingency | T26: =ROUND($M$62*100,0)&"% GBP "&ROUND($L$62/1000,0)&"K" -> 7% GBP 191K | U26: =T26 -> 7% GBP 191K | V26: Dashboard!J62:M62 | W26: Use of funds
J27: Base | K27: ='Cash Flow Statement'!B46 -> Y4 M8 | L27: ='Cash Flow Statement'!C46/1000000 -> 2.649418 | M27: ='Cash Flow Statement'!D46/1000000 -> 12.947967 | N27: ='Cash Flow Statement'!F46/1000000 -> 2.840446 | R27: 13 | S27: Future VARA restricted capital | T27: ="GBP "&ROUND('Launch Readiness'!$E$17/1000,0)&"K" -> GBP 319K | U27: =T27&" future scale-stage restricted capital; excluded from initial operating ask" -> GBP 319K future scale-stage restricted capital; excluded from initial operating ask | V27: Launch Readiness!F17 | W27: Scale-stage callout
J28: High | K28: ='Cash Flow Statement'!B47 -> Y4 M4 | L28: ='Cash Flow Statement'!C47/1000000 -> 1.946199 | M28: ='Cash Flow Statement'!D47/1000000 -> 33.92171 | N28: ='Cash Flow Statement'!F47/1000000 -> 2.137226
J29: ="- Base reaches monthly cash-flow break-even in "&'Cash Flow Statement'!$B$46&"; High reaches "&'Cash Flow Statement'!$B$47&"." -> - Base reaches monthly cash-flow break-even in Y4 M8; High reaches Y4 M4.
J30: ="- Low reaches monthly cash-flow break-even in "&'Cash Flow Statement'!$B$45&"; base Month 60 operating cash is GBP "&ROUND('Cash Flow Statement'!$D$46/1000000,1)&"M." -> - Low reaches monthly cash-flow break-even in Beyond Month 60; base Month 60 operating cash is GBP 12.9M. | R30: IMPLIED CUSTOMER ACQUISITION COST — FIVE-YEAR VIEW
J31: • No lending spread, FX trading revenue, or balance-sheet credit risk is modelled. | R31: Loaded Sales/BD/CS compensation + marketing + CRM ÷ gross new customers. Y1 includes the launch build-out.
J32: • Tier C paper collection is a priced fallback, not the strategic scale path.
J33: • Base Y4/Y5 volume is a planning target; acquisition capacity is flagged in P&L 5yr. | R33: Year | S33: Implied CAC | V33: Gross new customers | X33: New customers / Sales FTE | Z33: Capacity readout
R34: Y1 | S34: =IFERROR((('P&L 5yr'!C$36*Assumptions!$F$51*('P&L 5yr'!C$42/'P&L 5yr'!C$38))+'P&L 5yr'!C$49+'P&L 5yr'!C$53)/'P&L 5yr'!C$83,0) -> 50632.764 | V34: ='P&L 5yr'!C$83 -> 1 | X34: =IFERROR('P&L 5yr'!C$83/'P&L 5yr'!C$36,0) -> 3 | Z34: =IF(X34>Assumptions!$F$182,"Above capacity","Within capacity") -> Within capacity
R35: Y2 | S35: =IFERROR((('P&L 5yr'!D$36*Assumptions!$F$51*('P&L 5yr'!D$42/'P&L 5yr'!D$38))+'P&L 5yr'!D$49+'P&L 5yr'!D$53)/'P&L 5yr'!D$83,0) -> 1458.5782 | V35: ='P&L 5yr'!D$83 -> 124.1 | X35: =IFERROR('P&L 5yr'!D$83/'P&L 5yr'!D$36,0) -> 62.05 | Z35: =IF(X35>Assumptions!$F$182,"Above capacity","Within capacity") -> Within capacity
R36: Y3 | S36: =IFERROR((('P&L 5yr'!E$36*Assumptions!$F$51*('P&L 5yr'!E$42/'P&L 5yr'!E$38))+'P&L 5yr'!E$49+'P&L 5yr'!E$53)/'P&L 5yr'!E$83,0) -> 1231.8872 | V36: ='P&L 5yr'!E$83 -> 220.83333 | X36: =IFERROR('P&L 5yr'!E$83/'P&L 5yr'!E$36,0) -> 73.611111 | Z36: =IF(X36>Assumptions!$F$182,"Above capacity","Within capacity") -> Within capacity
R37: Y4 | S37: =IFERROR((('P&L 5yr'!F$36*Assumptions!$F$51*('P&L 5yr'!F$42/'P&L 5yr'!F$38))+'P&L 5yr'!F$49+'P&L 5yr'!F$53)/'P&L 5yr'!F$83,0) -> 346.62475 | V37: ='P&L 5yr'!F$83 -> 1575 | X37: =IFERROR('P&L 5yr'!F$83/'P&L 5yr'!F$36,0) -> 225 | Z37: =IF(X37>Assumptions!$F$182,"Above capacity","Within capacity") -> Within capacity
R38: Y5 | S38: =IFERROR((('P&L 5yr'!G$36*Assumptions!$F$51*('P&L 5yr'!G$42/'P&L 5yr'!G$38))+'P&L 5yr'!G$49+'P&L 5yr'!G$53)/'P&L 5yr'!G$83,0) -> 485.56011 | V38: ='P&L 5yr'!G$83 -> 1312.5 | X38: =IFERROR('P&L 5yr'!G$83/'P&L 5yr'!G$36,0) -> 164.0625 | Z38: =IF(X38>Assumptions!$F$182,"Above capacity","Within capacity") -> Within capacity
R39: Y1 is intentionally high: one acquired customer carries the launch-year commercial build-out.
R40: Planning cross-check, not observed CAC. AI-enabled staffing ramp targets <=250 gross new customers per Sales/BD/CS FTE (Assumptions C191:G191).
B56: Base path helper | F56: Use of funds helper | J56: Use of funds allocation helper
B57: Year | C57: Revenue | D57: EBITDA | F57: Category | G57: Amount | J57: Category | K57: Pre-scale cost driver | L57: Amount | M57: Share
B58: Y1 | C58: ='Scenario Engine'!$H$30/1000000 -> 0.00244905 | D58: ='Scenario Engine'!$H$57/1000000 -> -0.76236644 | F58: Peak operating deficit | G58: ='Cash Flow Statement'!$H$4/1000000 -> 2.649419 | J58: Engineering & product | K58: =SUM('P&L 5yr'!$C$34:$E$34)*Assumptions!$F$50+SUM('P&L 5yr'!$C$44:$E$47)+SUM('Startup 6mo'!$F$23:$F$28) -> 689360 | L58: =MAX(0,'Launch Readiness'!$E$12-$L$62)*K58/SUM($K$58:$K$61) -> 532484.9 | M58: =L58/'Launch Readiness'!$E$12 -> 0.18746524
B59: Y2 | C59: ='Scenario Engine'!$I$30/1000000 -> 0.404549 | D59: ='Scenario Engine'!$I$57/1000000 -> -0.83424883 | F59: Operating reserve | G59: ='P&L 5yr'!$G$65/1000000 -> 0.191027 | J59: Ops, people & G&A | K59: =SUM('P&L 5yr'!$C$33:$E$33)*Assumptions!$F$49+SUM('P&L 5yr'!$C$39:$E$41)+SUM('P&L 5yr'!$C$48:$E$48,'P&L 5yr'!$C$50:$E$50,'P&L 5yr'!$C$54:$E$55)+SUM('Startup 6mo'!$F$7:$F$10,'Startup 6mo'!$F$37:$F$39) -> 1282926.3 | L59: =MAX(0,'Launch Readiness'!$E$12-$L$62)*K59/SUM($K$58:$K$61) -> 990975.54 | M59: =L59/'Launch Readiness'!$E$12 -> 0.34888026
B60: Y3 | C60: ='Scenario Engine'!$J$30/1000000 -> 1.387904 | D60: ='Scenario Engine'!$J$57/1000000 -> -0.37845458 | F60: Initial restricted capital | G60: ='Launch Readiness'!$E$10/1000000 -> 0 | J60: Compliance, legal & regulatory | K60: =SUM('P&L 5yr'!$C$35:$E$35)*Assumptions!$F$51+SUM('P&L 5yr'!$C$51:$E$52)+SUM('Startup 6mo'!$F$12:$F$21) -> 1251615.8 | L60: =MAX(0,'Launch Readiness'!$E$12-$L$62)*K60/SUM($K$58:$K$61) -> 966790.25 | M60: =L60/'Launch Readiness'!$E$12 -> 0.34036565
B61: Y4 | C61: ='Scenario Engine'!$K$30/1000000 -> 8.9426919 | D61: ='Scenario Engine'!$K$57/1000000 -> 5.0020291 | F61: Initial operating funding need | G61: ='Launch Readiness'!$E$12/1000000 -> 2.840446 | J61: GTM & acquisition | K61: =SUM('P&L 5yr'!$C$36:$E$36)*Assumptions!$F$52+SUM('P&L 5yr'!$C$49:$E$49,'P&L 5yr'!$C$53:$E$53)+SUM('Startup 6mo'!$F$30:$F$35) -> 206060.8 | L61: ='Launch Readiness'!$E$12-SUM($L$58:$L$60)-$L$62 -> 159168.31 | M61: =L61/'Launch Readiness'!$E$12 -> 0.056036378
B62: Y5 | C62: ='Scenario Engine'!$L$30/1000000 -> 17.832614 | D62: ='Scenario Engine'!$L$57/1000000 -> 11.753016 | J62: Working capital + contingency | K62: ='P&L 5yr'!$G$65 -> 191027 | L62: =MIN('Launch Readiness'!$E$12,'P&L 5yr'!$G$65) -> 191027 | M62: =L62/'Launch Readiness'!$E$12 -> 0.067252467
B66: Cash runway helper
B67: Checkpoint | C67: Low | D67: Base | E67: High
B68: ='Cash Flow Statement'!G9 -> Y1 M6 | C68: ='Cash Flow Statement'!G52/1000000 -> -0.6554 | D68: ='Cash Flow Statement'!G53/1000000 -> -0.6554 | E68: ='Cash Flow Statement'!G54/1000000 -> -0.6554
B69: ='Cash Flow Statement'!M9 -> Y1 M12 | C69: ='Cash Flow Statement'!M52/1000000 -> -1.067873 | D69: ='Cash Flow Statement'!M53/1000000 -> -1.068227 | E69: ='Cash Flow Statement'!M54/1000000 -> -1.068902
B70: ='Cash Flow Statement'!S9 -> Y2 M6 | C70: ='Cash Flow Statement'!S52/1000000 -> -1.623505 | D70: ='Cash Flow Statement'!S53/1000000 -> -1.559162 | E70: ='Cash Flow Statement'!S54/1000000 -> -1.437783
B71: ='Cash Flow Statement'!Y9 -> Y2 M12 | C71: ='Cash Flow Statement'!Y52/1000000 -> -2.118265 | D71: ='Cash Flow Statement'!Y53/1000000 -> -1.976288 | E71: ='Cash Flow Statement'!Y54/1000000 -> -1.709259
B72: ='Cash Flow Statement'!AE9 -> Y3 M6 | C72: ='Cash Flow Statement'!AE52/1000000 -> -2.53607 | D72: ='Cash Flow Statement'!AE53/1000000 -> -2.240146 | E72: ='Cash Flow Statement'!AE54/1000000 -> -1.735746
B73: ='Cash Flow Statement'!AK9 -> Y3 M12 | C73: ='Cash Flow Statement'!AK52/1000000 -> -2.899562 | D73: ='Cash Flow Statement'!AK53/1000000 -> -2.436688 | E73: ='Cash Flow Statement'!AK54/1000000 -> -1.676676
B74: ='Cash Flow Statement'!AQ9 -> Y4 M6 | C74: ='Cash Flow Statement'!AQ52/1000000 -> -3.350263 | D74: ='Cash Flow Statement'!AQ53/1000000 -> -0.565238 | E74: ='Cash Flow Statement'!AQ54/1000000 -> 2.721956
B75: ='Cash Flow Statement'!AW9 -> Y4 M12 | C75: ='Cash Flow Statement'!AW52/1000000 -> -3.762259 | D75: ='Cash Flow Statement'!AW53/1000000 -> 1.935778 | E75: ='Cash Flow Statement'!AW54/1000000 -> 8.323742
B76: ='Cash Flow Statement'!BC9 -> Y5 M6 | C76: ='Cash Flow Statement'!BC52/1000000 -> -3.465142 | D76: ='Cash Flow Statement'!BC53/1000000 -> 7.071459 | E76: ='Cash Flow Statement'!BC54/1000000 -> 20.267924
B77: ='Cash Flow Statement'!BI9 -> Y5 M12 | C77: ='Cash Flow Statement'!BI52/1000000 -> -2.924278 | D77: ='Cash Flow Statement'!BI53/1000000 -> 12.947967 | E77: ='Cash Flow Statement'!BI54/1000000 -> 33.92171

Sheet Launch Readiness
A1: LAUNCH READINESS — DIFC PARTNER PILOT TO VARA SCALE
A2: Presentation planning model. Base case assumes a paid partner-led DIFC pilot in Month 12 and later VARA expansion; all permissions and fees remain subject to UAE counsel, partner and regulator confirmation.
A4: DECISION INPUTS | D4: ACTIVE BASE-CASE OUTPUTS
A5: Timing case (1=Early, 2=Base, 3=Delayed) | B5: 2 | D5: Route | E5: DIFC partner-led pilot → VARA expansion
A6: Operating reserve (months) | B6: 3 | D6: First paying pilot | E6: =MAX($C$50:$C$55)+1 -> 12
A7: Cash receipt lag (months) | B7: 1 | D7: Pre-revenue period | E7: =MAX(0,$E$6-1) -> 11
A8: DIFC / regulated-partner pilot one-off (£)**** | B8: 60000 | D8: Pilot regulatory / onboarding one-off | E8: =$B$8 -> 60000
A9: Partner-pilot annual fees and oversight (£)**** | B9: 67000 | D9: Pilot annual partner / regulatory run-rate | E9: =$B$9 -> 67000
A10: Pre-pilot share of partner run-rate | B10: 0.35 | D10: Initial restricted capital | E10: =0 -> 0
A11: Partner onboarding / application start month | B11: 2 | D11: First cash receipt | E11: =$E$6+$B$7 -> 13
A12: VARA application fee placeholder* (AED) | B12: 200000 | D12: Initial operating funding need | E12: =ROUND(MAX('P&L 5yr'!$C$66:$G$66)+$E$10,0) -> 2840446
A13: VARA annual supervision placeholder** (AED) | B13: 480000 | D13: Average pre-revenue operating burn | E13: =ROUND(-SUM('Cash Flow Statement'!$B$19:INDEX('Cash Flow Statement'!$B$19:$BI$19,1,MAX(1,$E$7)))/MAX(1,$E$7),0) -> 90941
A14: VARA restricted-capital placeholder*** (AED) | B14: 1500000 | D14: VARA scale target | E14: =INDEX($F$21:$F$23,$B$5) -> 30 | F14: VARA application start | G14: =INDEX($G$21:$G$23,$B$5) -> 18
A15: AED per USD***** | B15: 3.6725 | D15: Future VARA application fees | E15: =ROUND($B$12/(Assumptions!$F$8*$B$15),0) -> 42546
D16: Future VARA annual supervision | E16: =ROUND($B$13/(Assumptions!$F$8*$B$15),0) -> 102110
D17: Future VARA restricted capital | E17: =ROUND($B$14/(Assumptions!$F$8*$B$15),0) -> 319095
A19: TIMING CASES — ONE SEQUENTIAL UAE ROUTE
A20: Case | B20: Timing | C20: Latest pilot gate finish | D20: First paid pilot | E20: First receipt | F20: VARA target | G20: VARA application start | H20: Planning interpretation
A21: 1 | B21: Early | C21: 8 | D21: =C21+1 -> 9 | E21: =D21+$B$7 -> 10 | F21: 24 | G21: 12 | H21: Sensitivity: faster partner and regulator approvals.
A22: 2 | B22: Base | C22: 11 | D22: =C22+1 -> 12 | E22: =D22+$B$7 -> 13 | F22: 30 | G22: 18 | H22: Presentation base: one year to first paid pilot, then VARA scale.
A23: 3 | B23: Delayed | C23: 17 | D23: =C23+1 -> 18 | E23: =D23+$B$7 -> 19 | F23: 36 | G23: 24 | H23: Sensitivity: rework, partner conditions or regulatory delay.
A24: LAUNCH PHASING BY MODEL YEAR
A25: Metric | B25: Year 1 | C25: Year 2 | D25: Year 3 | E25: Year 4 | F25: Year 5
A26: Revenue-active months | B26: =MAX(0,MIN(12,12*(COLUMN()-1)-$E$6+1)) -> 1 | C26: =MAX(0,MIN(12,12*(COLUMN()-1)-$E$6+1)) -> 12 | D26: =MAX(0,MIN(12,12*(COLUMN()-1)-$E$6+1)) -> 12 | E26: =MAX(0,MIN(12,12*(COLUMN()-1)-$E$6+1)) -> 12 | F26: =MAX(0,MIN(12,12*(COLUMN()-1)-$E$6+1)) -> 12
A27: Pre-revenue months | B27: =MAX(0,MIN(12,$E$7-12*(COLUMN()-2))) -> 11 | C27: =MAX(0,MIN(12,$E$7-12*(COLUMN()-2))) -> 0 | D27: =MAX(0,MIN(12,$E$7-12*(COLUMN()-2))) -> 0 | E27: =MAX(0,MIN(12,$E$7-12*(COLUMN()-2))) -> 0 | F27: =MAX(0,MIN(12,$E$7-12*(COLUMN()-2))) -> 0
A28: Revenue activity factor | B28: =B26/12 -> 0.083333333 | C28: =C26/12 -> 1 | D28: =D26/12 -> 1 | E28: =E26/12 -> 1 | F28: =F26/12 -> 1 | G28: 0
A29: Partner / application phase months | B29: =MAX(0,MIN(12*(COLUMN()-1),$E$6-1)-MAX(12*(COLUMN()-2)+1,$B$11)+1) -> 10 | C29: =MAX(0,MIN(12*(COLUMN()-1),$E$6-1)-MAX(12*(COLUMN()-2)+1,$B$11)+1) -> 0 | D29: =MAX(0,MIN(12*(COLUMN()-1),$E$6-1)-MAX(12*(COLUMN()-2)+1,$B$11)+1) -> 0 | E29: =MAX(0,MIN(12*(COLUMN()-1),$E$6-1)-MAX(12*(COLUMN()-2)+1,$B$11)+1) -> 0 | F29: =MAX(0,MIN(12*(COLUMN()-1),$E$6-1)-MAX(12*(COLUMN()-2)+1,$B$11)+1) -> 0 | G29: 0
A30: Pre-pilot partner cost factor | B30: =B29/12 -> 0.83333333 | C30: =C29/12 -> 0 | D30: =D29/12 -> 0 | E30: =E29/12 -> 0 | F30: =F29/12 -> 0 | G30: 0
A31: VARA operating months | B31: =MAX(0,MIN(12,12*(COLUMN()-1)-$E$14+1)) -> 0 | C31: =MAX(0,MIN(12,12*(COLUMN()-1)-$E$14+1)) -> 0 | D31: =MAX(0,MIN(12,12*(COLUMN()-1)-$E$14+1)) -> 7 | E31: =MAX(0,MIN(12,12*(COLUMN()-1)-$E$14+1)) -> 12 | F31: =MAX(0,MIN(12,12*(COLUMN()-1)-$E$14+1)) -> 12 | G31: 0
A32: VARA annual fee factor | B32: =B31/12 -> 0 | C32: =C31/12 -> 0 | D32: =D31/12 -> 0.58333333 | E32: =E31/12 -> 1 | F32: =F31/12 -> 1
A33: VARA application fee timing | B33: =IF(AND($G$14>=12*(COLUMN()-2)+1,$G$14<=12*(COLUMN()-1)),1,0) -> 0 | C33: =IF(AND($G$14>=12*(COLUMN()-2)+1,$G$14<=12*(COLUMN()-1)),1,0) -> 1 | D33: =IF(AND($G$14>=12*(COLUMN()-2)+1,$G$14<=12*(COLUMN()-1)),1,0) -> 0 | E33: =IF(AND($G$14>=12*(COLUMN()-2)+1,$G$14<=12*(COLUMN()-1)),1,0) -> 0 | F33: =IF(AND($G$14>=12*(COLUMN()-2)+1,$G$14<=12*(COLUMN()-1)),1,0) -> 0
A34: Partner-pilot annual fee factor | B34: =MAX(0,B26-B31)/12 -> 0.083333333 | C34: =MAX(0,C26-C31)/12 -> 1 | D34: =MAX(0,D26-D31)/12 -> 0.41666667 | E34: =MAX(0,E26-E31)/12 -> 0 | F34: =MAX(0,F26-F31)/12 -> 0
A36: WORKFORCE TIMING — EXPLICIT AND INDEPENDENT OF LAUNCH DATE
A37: Role | B37: Start month | C37: Cost treatment | D37: Year 1 | E37: Year 2 | F37: Year 3 | G37: Year 4 | H37: Year 5
A38: Founders | B38: 1 | C38: Core team from Month 1 | D38: =MAX(0,MIN(12,12*(COLUMN()-3)-$B38+1))/12 -> 1 | E38: =MAX(0,MIN(12,12*(COLUMN()-3)-$B38+1))/12 -> 1 | F38: =MAX(0,MIN(12,12*(COLUMN()-3)-$B38+1))/12 -> 1 | G38: =MAX(0,MIN(12,12*(COLUMN()-3)-$B38+1))/12 -> 1 | H38: =MAX(0,MIN(12,12*(COLUMN()-3)-$B38+1))/12 -> 1
A39: Engineering | B39: 5 | C39: Production hardening; not delayed by launch case | D39: =MAX(0,MIN(12,12*(COLUMN()-3)-$B39+1))/12 -> 0.66666667 | E39: =MAX(0,MIN(12,12*(COLUMN()-3)-$B39+1))/12 -> 1 | F39: =MAX(0,MIN(12,12*(COLUMN()-3)-$B39+1))/12 -> 1 | G39: =MAX(0,MIN(12,12*(COLUMN()-3)-$B39+1))/12 -> 1 | H39: =MAX(0,MIN(12,12*(COLUMN()-3)-$B39+1))/12 -> 1
A40: Compliance | B40: 1 | C40: Internal control ownership from Month 1 | D40: =MAX(0,MIN(12,12*(COLUMN()-3)-$B40+1))/12 -> 1 | E40: =MAX(0,MIN(12,12*(COLUMN()-3)-$B40+1))/12 -> 1 | F40: =MAX(0,MIN(12,12*(COLUMN()-3)-$B40+1))/12 -> 1 | G40: =MAX(0,MIN(12,12*(COLUMN()-3)-$B40+1))/12 -> 1 | H40: =MAX(0,MIN(12,12*(COLUMN()-3)-$B40+1))/12 -> 1
A41: Sales | B41: 9 | C41: Pilot contracting and commercial preparation | D41: =MAX(0,MIN(12,12*(COLUMN()-3)-$B41+1))/12 -> 0.33333333 | E41: =MAX(0,MIN(12,12*(COLUMN()-3)-$B41+1))/12 -> 1 | F41: =MAX(0,MIN(12,12*(COLUMN()-3)-$B41+1))/12 -> 1 | G41: =MAX(0,MIN(12,12*(COLUMN()-3)-$B41+1))/12 -> 1 | H41: =MAX(0,MIN(12,12*(COLUMN()-3)-$B41+1))/12 -> 1
A48: CUSTOMER-LAUNCH CRITICAL PATH
A49: Workstream | B49: Start month | C49: Finish month | D49: Customer-blocking? | E49: Readout
A50: UAE regulatory perimeter (incl. payment-token treatment) | B50: 1 | C50: 3 | D50: Yes | E50: Counsel and partner confirm the permitted pilot structure, token treatment and regulated entity.
A51: DIFC pilot structure and partner term sheet | B51: 1 | C51: 4 | D51: Yes | E51: Executed terms define fees, customer contract, liability and pilot limits.
A52: Custody, settlement and responsibility matrix | B52: 2 | C52: 11 | D52: Yes | E52: Responsibilities for funds, release controls, complaints and reporting are agreed.
A53: KYB, sanctions, monitoring and review SOPs | B53: 1 | C53: 10 | D53: Yes | E53: Provider, escalation route, reviewer process and audit evidence are operational.
A54: Production security, contract audit and API hardening | B54: 2 | C54: 10 | D54: Yes | E54: Smart-contract audit, key controls, rate limits, CORS and partner API readiness.
A55: Escrow agreement, disputes, testing and go-live approval | B55: 5 | C55: 11 | D55: Yes | E55: Contract pack, objection/dispute handling and limited-pilot testing are approved.
A56: First paying pilot | B56: =$E$6 -> 12 | C56: =$E$6 -> 12 | D56: Milestone | E56: Paid partner-led DIFC pilot begins.
A57: VARA application and UAE-wide approval | B57: =$G$14 -> 18 | C57: =$E$14 -> 30 | D57: No for pilot; yes for scale | E57: Future scale stage; capital remains restricted and separate from pilot runway.
A60: SOURCES & MODEL BOUNDARIES
A61: Item | B61: Basis | C61: Source | F61: Model treatment / boundary
A62: UAE licensing route | B62: Planning route | C62: docs/Dubai_Fintech_License_Requirements.md | F62: DIFC partner-led pilot first; VARA approval is a later UAE-scale gate. Confirm the final perimeter with UAE counsel and the regulated partner.
A63: VARA application fee* | B63: Placeholder | C63: https://rulebooks.vara.ae/rulebook/schedule-2-supervision-and-authorisation-fees | F63: AED 200k is rounded. Published activity ordering may imply about AED 170k; confirm the required permissions and extension fees.
A64: VARA annual supervision** | B64: Placeholder | C64: https://rulebooks.vara.ae/rulebook/schedule-2-supervision-and-authorisation-fees | F64: AED 480k assumes Custody (200k), Transfer & Settlement (80k) and Broker-Dealer (200k) each year.
A65: VARA restricted capital*** | B65: Placeholder | C65: https://rulebooks.vara.ae/rulebook/b-paid-capital | F65: AED 1.5m sums three activity floors (600k + 500k + 400k). VARA applies the higher of each floor or its overhead test; fewer activities would reduce the total.
A66: Partner-pilot costs**** | B66: Management estimate | C66: Driver Tables row 19 / pending partner term sheet | F66: £60k setup and £67k annual oversight are internal allowances, pending the partner term sheet and responsibility matrix.
A67: FX conversion***** | B67: Planning FX | C67: https://centralbank.ae/en/forex-eibor/exchange-rates/ | F67: AED/USD 3.6725 peg; GBP/USD 1.28 planning cross-rate as at 10 Aug 2026.
A68: Competitor pricing | B68: Management pricing | C68: docs/Competitor-analysis.md | F68: The 0.8%–3.0% take rates are management hypotheses informed by listed competitors; validate through paid pilots.
A69: Production readiness | B69: Internal specification | C69: docs/technical-requirements.md | F69: Partner API, security controls, testing and audit evidence are required before live use.

Sheet Tier Economics
A1: Tier Economics - revenue, cost and risk by document-intake tier
A3: Metric | B3: Tier A eBL Y1 | C3: Tier B API Y1 | D3: Tier C Paper Y1 | E3: Total Y1 | F3: Tier A eBL Y2 | G3: Tier B API Y2 | H3: Tier C Paper Y2 | I3: Total Y2 | J3: Tier A eBL Y3 | K3: Tier B API Y3 | L3: Tier C Paper Y3 | M3: Total Y3 | N3: Tier A eBL Y4 | O3: Tier B API Y4 | P3: Tier C Paper Y4 | Q3: Total Y4 | R3: Tier A eBL Y5 | S3: Tier B API Y5 | T3: Tier C Paper Y5 | U3: Total Y5
A4: Tier mix | B4: =Assumptions!$F$61 -> 0.15 | C4: =Assumptions!$F$62 -> 0.45 | D4: =Assumptions!$F$63 -> 0.4 | E4: =SUM(B4:D4) -> 1 | F4: =Assumptions!$F$64 -> 0.3 | G4: =Assumptions!$F$65 -> 0.45 | H4: =Assumptions!$F$66 -> 0.25 | I4: =SUM(F4:H4) -> 1 | J4: =Assumptions!$F$67 -> 0.45 | K4: =Assumptions!$F$68 -> 0.4 | L4: =Assumptions!$F$69 -> 0.15 | M4: =SUM(J4:L4) -> 1 | N4: =Assumptions!$F$149 -> 0.6 | O4: =Assumptions!$F$150 -> 0.32 | P4: =Assumptions!$F$151 -> 0.08 | Q4: =SUM(N4:P4) -> 1 | R4: =Assumptions!$F$152 -> 0.7 | S4: =Assumptions!$F$153 -> 0.25 | T4: =Assumptions!$F$154 -> 0.05 | U4: =SUM(R4:T4) -> 1
A5: Deals | B5: ='P&L 5yr'!$C$7*B4 -> 0.45 | C5: ='P&L 5yr'!$C$7*C4 -> 1.35 | D5: ='P&L 5yr'!$C$7*D4 -> 1.2 | E5: =SUM(B5:D5) -> 3 | F5: ='P&L 5yr'!$D$7*F4 -> 150 | G5: ='P&L 5yr'!$D$7*G4 -> 225 | H5: ='P&L 5yr'!$D$7*H4 -> 125 | I5: =SUM(F5:H5) -> 500 | J5: ='P&L 5yr'!$E$7*J4 -> 900 | K5: ='P&L 5yr'!$E$7*K4 -> 800 | L5: ='P&L 5yr'!$E$7*L4 -> 300 | M5: =SUM(J5:L5) -> 2000 | N5: ='P&L 5yr'!$F$7*N4 -> 9000 | O5: ='P&L 5yr'!$F$7*O4 -> 4800 | P5: ='P&L 5yr'!$F$7*P4 -> 1200 | Q5: =SUM(N5:P5) -> 15000 | R5: ='P&L 5yr'!$G$7*R4 -> 21000 | S5: ='P&L 5yr'!$G$7*S4 -> 7500 | T5: ='P&L 5yr'!$G$7*T4 -> 1500 | U5: =SUM(R5:T5) -> 30000
A6: Docs per deal | B6: =Assumptions!$F$103 -> 3 | C6: =Assumptions!$F$104 -> 6 | D6: =Assumptions!$F$105 -> 9 | E6: =IF(E5=0,0,E7/E5) -> 6.75 | F6: =Assumptions!$F$103 -> 3 | G6: =Assumptions!$F$104 -> 6 | H6: =Assumptions!$F$105 -> 9 | I6: =IF(I5=0,0,I7/I5) -> 5.85 | J6: =Assumptions!$F$103 -> 3 | K6: =Assumptions!$F$104 -> 6 | L6: =Assumptions!$F$105 -> 9 | M6: =IF(M5=0,0,M7/M5) -> 5.1 | N6: =Assumptions!$F$103 -> 3 | O6: =Assumptions!$F$104 -> 6 | P6: =Assumptions!$F$105 -> 9 | Q6: =IF(Q5=0,0,Q7/Q5) -> 4.44 | R6: =Assumptions!$F$103 -> 3 | S6: =Assumptions!$F$104 -> 6 | T6: =Assumptions!$F$105 -> 9 | U6: =IF(U5=0,0,U7/U5) -> 4.05
A7: Documents processed | B7: =B5*B6 -> 1.35 | C7: =C5*C6 -> 8.1 | D7: =D5*D6 -> 10.8 | E7: =SUM(B7:D7) -> 20.25 | F7: =F5*F6 -> 450 | G7: =G5*G6 -> 1350 | H7: =H5*H6 -> 1125 | I7: =SUM(F7:H7) -> 2925 | J7: =J5*J6 -> 2700 | K7: =K5*K6 -> 4800 | L7: =L5*L6 -> 2700 | M7: =SUM(J7:L7) -> 10200 | N7: =N5*N6 -> 27000 | O7: =O5*O6 -> 28800 | P7: =P5*P6 -> 10800 | Q7: =SUM(N7:P7) -> 66600 | R7: =R5*R6 -> 63000 | S7: =S5*S6 -> 45000 | T7: =T5*T6 -> 13500 | U7: =SUM(R7:T7) -> 121500
A8: Avg deal value* | B8: =Assumptions!$F$162 -> 35000 | C8: =Assumptions!$F$164 -> 30000 | D8: =Assumptions!$F$166 -> 30000 | E8: =IF(E5=0,0,E9/E5) -> 30750 | F8: =Assumptions!$F$162*(1+Assumptions!$F$163)^1 -> 38500 | G8: =Assumptions!$F$164*(1+Assumptions!$F$165)^1 -> 32400 | H8: =Assumptions!$F$166*(1+Assumptions!$F$167)^1 -> 31500 | I8: =IF(I5=0,0,I9/I5) -> 34005 | J8: =Assumptions!$F$162*(1+Assumptions!$F$163)^2 -> 42350 | K8: =Assumptions!$F$164*(1+Assumptions!$F$165)^2 -> 34992 | L8: =Assumptions!$F$166*(1+Assumptions!$F$167)^2 -> 33075 | M8: =IF(M5=0,0,M9/M5) -> 38015.55 | N8: =Assumptions!$F$162*(1+Assumptions!$F$163)^3 -> 46585 | O8: =Assumptions!$F$164*(1+Assumptions!$F$165)^3 -> 37791.36 | P8: =Assumptions!$F$166*(1+Assumptions!$F$167)^3 -> 34728.75 | Q8: =IF(Q5=0,0,Q9/Q5) -> 42822.535 | R8: =Assumptions!$F$162*(1+Assumptions!$F$163)^4 -> 51243.5 | S8: =Assumptions!$F$164*(1+Assumptions!$F$165)^4 -> 40814.669 | T8: =Assumptions!$F$166*(1+Assumptions!$F$167)^4 -> 36465.188 | U8: =IF(U5=0,0,U9/U5) -> 47897.377
A9: GMV | B9: =B5*B8 -> 15750 | C9: =C5*C8 -> 40500 | D9: =D5*D8 -> 36000 | E9: =SUM(B9:D9) -> 92250 | F9: =F5*F8 -> 5775000 | G9: =G5*G8 -> 7290000 | H9: =H5*H8 -> 3937500 | I9: =SUM(F9:H9) -> 17002500 | J9: =J5*J8 -> 38115000 | K9: =K5*K8 -> 27993600 | L9: =L5*L8 -> 9922500 | M9: =SUM(J9:L9) -> 76031100 | N9: =N5*N8 -> 4.19265e+08 | O9: =O5*O8 -> 1.8139853e+08 | P9: =P5*P8 -> 41674500 | Q9: =SUM(N9:P9) -> 6.4233803e+08 | R9: =R5*R8 -> 1.0761135e+09 | S9: =S5*S8 -> 3.0611002e+08 | T9: =T5*T8 -> 54697781 | U9: =SUM(R9:T9) -> 1.4369213e+09
A10: Escrow take rate** | B10: =Assumptions!$F$70 -> 0.008 | C10: =Assumptions!$F$71 -> 0.015 | D10: =Assumptions!$F$72 -> 0.03 | E10: =IF(E9=0,0,SUM(B9*B10,C9*C10,D9*D10)/E9) -> 0.019658537 | F10: =Assumptions!$F$70 -> 0.008 | G10: =Assumptions!$F$71 -> 0.015 | H10: =Assumptions!$F$72 -> 0.03 | I10: =IF(I9=0,0,SUM(F9*F10,G9*G10,H9*H10)/I9) -> 0.016096162 | J10: =Assumptions!$F$70 -> 0.008 | K10: =Assumptions!$F$71 -> 0.015 | L10: =Assumptions!$F$72 -> 0.03 | M10: =IF(M9=0,0,SUM(J9*J10,K9*K10,L9*L10)/M9) -> 0.013448431 | N10: =Assumptions!$F$70 -> 0.008 | O10: =Assumptions!$F$71 -> 0.015 | P10: =Assumptions!$F$72 -> 0.03 | Q10: =IF(Q9=0,0,SUM(N9*N10,O9*O10,P9*P10)/Q9) -> 0.011404171 | R10: =Assumptions!$F$70 -> 0.008 | S10: =Assumptions!$F$71 -> 0.015 | T10: =Assumptions!$F$72 -> 0.03 | U10: =IF(U9=0,0,SUM(R9*R10,S9*S10,T9*T10)/U9) -> 0.010328674
A11: Minimum escrow fee*** | B11: =Assumptions!$F$73 -> 150 | C11: =Assumptions!$F$74 -> 250 | D11: =Assumptions!$F$75 -> 500 | E11: =IF(E5=0,0,SUM(B5*B11,C5*C11,D5*D11)/E5) -> 335 | F11: =Assumptions!$F$73 -> 150 | G11: =Assumptions!$F$74 -> 250 | H11: =Assumptions!$F$75 -> 500 | I11: =IF(I5=0,0,SUM(F5*F11,G5*G11,H5*H11)/I5) -> 282.5 | J11: =Assumptions!$F$73 -> 150 | K11: =Assumptions!$F$74 -> 250 | L11: =Assumptions!$F$75 -> 500 | M11: =IF(M5=0,0,SUM(J5*J11,K5*K11,L5*L11)/M5) -> 242.5 | N11: =Assumptions!$F$73 -> 150 | O11: =Assumptions!$F$74 -> 250 | P11: =Assumptions!$F$75 -> 500 | Q11: =IF(Q5=0,0,SUM(N5*N11,O5*O11,P5*P11)/Q5) -> 210 | R11: =Assumptions!$F$73 -> 150 | S11: =Assumptions!$F$74 -> 250 | T11: =Assumptions!$F$75 -> 500 | U11: =IF(U5=0,0,SUM(R5*R11,S5*S11,T5*T11)/U5) -> 192.5
A12: Escrow fee revenue | B12: =B5*MAX(B8*B10,B11) -> 126 | C12: =C5*MAX(C8*C10,C11) -> 607.5 | D12: =D5*MAX(D8*D10,D11) -> 1080 | E12: =SUM(B12:D12) -> 1813.5 | F12: =F5*MAX(F8*F10,F11) -> 46200 | G12: =G5*MAX(G8*G10,G11) -> 109350 | H12: =H5*MAX(H8*H10,H11) -> 118125 | I12: =SUM(F12:H12) -> 273675 | J12: =J5*MAX(J8*J10,J11) -> 304920 | K12: =K5*MAX(K8*K10,K11) -> 419904 | L12: =L5*MAX(L8*L10,L11) -> 297675 | M12: =SUM(J12:L12) -> 1022499 | N12: =N5*MAX(N8*N10,N11) -> 3354120 | O12: =O5*MAX(O8*O10,O11) -> 2720977.9 | P12: =P5*MAX(P8*P10,P11) -> 1250235 | Q12: =SUM(N12:P12) -> 7325332.9 | R12: =R5*MAX(R8*R10,R11) -> 8608908 | S12: =S5*MAX(S8*S10,S11) -> 4591650.2 | T12: =T5*MAX(T8*T10,T11) -> 1640933.4 | U12: =SUM(R12:T12) -> 14841492
A13: Doc/review fee per deal | B13: =Assumptions!$F$76 -> 25 | C13: =Assumptions!$F$77 -> 90 | D13: =Assumptions!$F$78 -> 300 | E13: =IF(E5=0,0,SUM(B5*B13,C5*C13,D5*D13)/E5) -> 164.25 | F13: =Assumptions!$F$76 -> 25 | G13: =Assumptions!$F$77 -> 90 | H13: =Assumptions!$F$78 -> 300 | I13: =IF(I5=0,0,SUM(F5*F13,G5*G13,H5*H13)/I5) -> 123 | J13: =Assumptions!$F$76 -> 25 | K13: =Assumptions!$F$77 -> 90 | L13: =Assumptions!$F$78 -> 300 | M13: =IF(M5=0,0,SUM(J5*J13,K5*K13,L5*L13)/M5) -> 92.25 | N13: =Assumptions!$F$76 -> 25 | O13: =Assumptions!$F$77 -> 90 | P13: =Assumptions!$F$78 -> 300 | Q13: =IF(Q5=0,0,SUM(N5*N13,O5*O13,P5*P13)/Q5) -> 67.8 | R13: =Assumptions!$F$76 -> 25 | S13: =Assumptions!$F$77 -> 90 | T13: =Assumptions!$F$78 -> 300 | U13: =IF(U5=0,0,SUM(R5*R13,S5*S13,T5*T13)/U5) -> 55
A14: Doc/review revenue | B14: =B5*B13 -> 11.25 | C14: =C5*C13 -> 121.5 | D14: =D5*D13 -> 360 | E14: =SUM(B14:D14) -> 492.75 | F14: =F5*F13 -> 3750 | G14: =G5*G13 -> 20250 | H14: =H5*H13 -> 37500 | I14: =SUM(F14:H14) -> 61500 | J14: =J5*J13 -> 22500 | K14: =K5*K13 -> 72000 | L14: =L5*L13 -> 90000 | M14: =SUM(J14:L14) -> 184500 | N14: =N5*N13 -> 225000 | O14: =O5*O13 -> 432000 | P14: =P5*P13 -> 360000 | Q14: =SUM(N14:P14) -> 1017000 | R14: =R5*R13 -> 525000 | S14: =S5*S13 -> 675000 | T14: =T5*T13 -> 450000 | U14: =SUM(R14:T14) -> 1650000
A15: Dispute rate | B15: =Assumptions!$F$91 -> 0.04 | C15: =Assumptions!$F$92 -> 0.1 | D15: =Assumptions!$F$93 -> 0.2 | E15: =IF(E5=0,0,E16/E5) -> 0.131 | F15: =Assumptions!$F$91 -> 0.04 | G15: =Assumptions!$F$92 -> 0.1 | H15: =Assumptions!$F$93 -> 0.2 | I15: =IF(I5=0,0,I16/I5) -> 0.107 | J15: =Assumptions!$F$91 -> 0.04 | K15: =Assumptions!$F$92 -> 0.1 | L15: =Assumptions!$F$93 -> 0.2 | M15: =IF(M5=0,0,M16/M5) -> 0.088 | N15: =Assumptions!$F$91 -> 0.04 | O15: =Assumptions!$F$92 -> 0.1 | P15: =Assumptions!$F$93 -> 0.2 | Q15: =IF(Q5=0,0,Q16/Q5) -> 0.072 | R15: =Assumptions!$F$91 -> 0.04 | S15: =Assumptions!$F$92 -> 0.1 | T15: =Assumptions!$F$93 -> 0.2 | U15: =IF(U5=0,0,U16/U5) -> 0.063
A16: Disputed deals | B16: =B5*B15 -> 0.018 | C16: =C5*C15 -> 0.135 | D16: =D5*D15 -> 0.24 | E16: =SUM(B16:D16) -> 0.393 | F16: =F5*F15 -> 6 | G16: =G5*G15 -> 22.5 | H16: =H5*H15 -> 25 | I16: =SUM(F16:H16) -> 53.5 | J16: =J5*J15 -> 36 | K16: =K5*K15 -> 80 | L16: =L5*L15 -> 60 | M16: =SUM(J16:L16) -> 176 | N16: =N5*N15 -> 360 | O16: =O5*O15 -> 480 | P16: =P5*P15 -> 240 | Q16: =SUM(N16:P16) -> 1080 | R16: =R5*R15 -> 840 | S16: =S5*S15 -> 750 | T16: =T5*T15 -> 300 | U16: =SUM(R16:T16) -> 1890
A17: Dispute/amendment fee | B17: =Assumptions!$F$79 -> 100 | C17: =Assumptions!$F$80 -> 200 | D17: =Assumptions!$F$81 -> 500 | E17: =IF(E16=0,0,SUM(B16*B17,C16*C17,D16*D17)/E16) -> 378.62595 | F17: =Assumptions!$F$79 -> 100 | G17: =Assumptions!$F$80 -> 200 | H17: =Assumptions!$F$81 -> 500 | I17: =IF(I16=0,0,SUM(F16*F17,G16*G17,H16*H17)/I16) -> 328.97196 | J17: =Assumptions!$F$79 -> 100 | K17: =Assumptions!$F$80 -> 200 | L17: =Assumptions!$F$81 -> 500 | M17: =IF(M16=0,0,SUM(J16*J17,K16*K17,L16*L17)/M16) -> 281.81818 | N17: =Assumptions!$F$79 -> 100 | O17: =Assumptions!$F$80 -> 200 | P17: =Assumptions!$F$81 -> 500 | Q17: =IF(Q16=0,0,SUM(N16*N17,O16*O17,P16*P17)/Q16) -> 233.33333 | R17: =Assumptions!$F$79 -> 100 | S17: =Assumptions!$F$80 -> 200 | T17: =Assumptions!$F$81 -> 500 | U17: =IF(U16=0,0,SUM(R16*R17,S16*S17,T16*T17)/U16) -> 203.1746
A18: Dispute/amendment revenue | B18: =B16*B17 -> 1.8 | C18: =C16*C17 -> 27 | D18: =D16*D17 -> 120 | E18: =SUM(B18:D18) -> 148.8 | F18: =F16*F17 -> 600 | G18: =G16*G17 -> 4500 | H18: =H16*H17 -> 12500 | I18: =SUM(F18:H18) -> 17600 | J18: =J16*J17 -> 3600 | K18: =K16*K17 -> 16000 | L18: =L16*L17 -> 30000 | M18: =SUM(J18:L18) -> 49600 | N18: =N16*N17 -> 36000 | O18: =O16*O17 -> 96000 | P18: =P16*P17 -> 120000 | Q18: =SUM(N18:P18) -> 252000 | R18: =R16*R17 -> 84000 | S18: =S16*S17 -> 150000 | T18: =T16*T17 -> 150000 | U18: =SUM(R18:T18) -> 384000
A19: External eBL/API/paper cost | B19: =B5*Assumptions!$F$82 -> 1.35 | C19: =C5*Assumptions!$F$83 -> 13.5 | D19: =D5*Assumptions!$F$84 -> 180 | E19: =SUM(B19:D19) -> 194.85 | F19: =F5*Assumptions!$F$82 -> 450 | G19: =G5*Assumptions!$F$83 -> 2250 | H19: =H5*Assumptions!$F$84 -> 18750 | I19: =SUM(F19:H19) -> 21450 | J19: =J5*Assumptions!$F$82 -> 2700 | K19: =K5*Assumptions!$F$83 -> 8000 | L19: =L5*Assumptions!$F$84 -> 45000 | M19: =SUM(J19:L19) -> 55700 | N19: =N5*Assumptions!$F$82 -> 27000 | O19: =O5*Assumptions!$F$83 -> 48000 | P19: =P5*Assumptions!$F$84 -> 180000 | Q19: =SUM(N19:P19) -> 255000 | R19: =R5*Assumptions!$F$82 -> 63000 | S19: =S5*Assumptions!$F$83 -> 75000 | T19: =T5*Assumptions!$F$84 -> 225000 | U19: =SUM(R19:T19) -> 363000
A20: Human review cost | B20: =B5*Assumptions!$F$85 -> 1.35 | C20: =C5*Assumptions!$F$86 -> 27 | D20: =D5*Assumptions!$F$87 -> 180 | E20: =SUM(B20:D20) -> 208.35 | F20: =F5*Assumptions!$F$85 -> 450 | G20: =G5*Assumptions!$F$86 -> 4500 | H20: =H5*Assumptions!$F$87 -> 18750 | I20: =SUM(F20:H20) -> 23700 | J20: =J5*Assumptions!$F$85 -> 2700 | K20: =K5*Assumptions!$F$86 -> 16000 | L20: =L5*Assumptions!$F$87 -> 45000 | M20: =SUM(J20:L20) -> 63700 | N20: =N5*Assumptions!$F$85 -> 27000 | O20: =O5*Assumptions!$F$86 -> 96000 | P20: =P5*Assumptions!$F$87 -> 180000 | Q20: =SUM(N20:P20) -> 303000 | R20: =R5*Assumptions!$F$85 -> 63000 | S20: =S5*Assumptions!$F$86 -> 150000 | T20: =T5*Assumptions!$F$87 -> 225000 | U20: =SUM(R20:T20) -> 438000
A21: Support cost | B21: =B5*Assumptions!$F$88 -> 0.9 | C21: =C5*Assumptions!$F$89 -> 8.1 | D21: =D5*Assumptions!$F$90 -> 24 | E21: =SUM(B21:D21) -> 33 | F21: =F5*Assumptions!$F$88 -> 300 | G21: =G5*Assumptions!$F$89 -> 1350 | H21: =H5*Assumptions!$F$90 -> 2500 | I21: =SUM(F21:H21) -> 4150 | J21: =J5*Assumptions!$F$88 -> 1800 | K21: =K5*Assumptions!$F$89 -> 4800 | L21: =L5*Assumptions!$F$90 -> 6000 | M21: =SUM(J21:L21) -> 12600 | N21: =N5*Assumptions!$F$88 -> 18000 | O21: =O5*Assumptions!$F$89 -> 28800 | P21: =P5*Assumptions!$F$90 -> 24000 | Q21: =SUM(N21:P21) -> 70800 | R21: =R5*Assumptions!$F$88 -> 42000 | S21: =S5*Assumptions!$F$89 -> 45000 | T21: =T5*Assumptions!$F$90 -> 30000 | U21: =SUM(R21:T21) -> 117000
A22: Dispute handling cost | B22: =B16*Assumptions!$F$94 -> 1.08 | C22: =C16*Assumptions!$F$95 -> 16.2 | D22: =D16*Assumptions!$F$96 -> 84 | E22: =SUM(B22:D22) -> 101.28 | F22: =F16*Assumptions!$F$94 -> 360 | G22: =G16*Assumptions!$F$95 -> 2700 | H22: =H16*Assumptions!$F$96 -> 8750 | I22: =SUM(F22:H22) -> 11810 | J22: =J16*Assumptions!$F$94 -> 2160 | K22: =K16*Assumptions!$F$95 -> 9600 | L22: =L16*Assumptions!$F$96 -> 21000 | M22: =SUM(J22:L22) -> 32760 | N22: =N16*Assumptions!$F$94 -> 21600 | O22: =O16*Assumptions!$F$95 -> 57600 | P22: =P16*Assumptions!$F$96 -> 84000 | Q22: =SUM(N22:P22) -> 163200 | R22: =R16*Assumptions!$F$94 -> 50400 | S22: =S16*Assumptions!$F$95 -> 90000 | T22: =T16*Assumptions!$F$96 -> 105000 | U22: =SUM(R22:T22) -> 245400
A23: Total tier-specific COGS | B23: =SUM(B19:B22) -> 4.68 | C23: =SUM(C19:C22) -> 64.8 | D23: =SUM(D19:D22) -> 468 | E23: =SUM(B23:D23) -> 537.48 | F23: =SUM(F19:F22) -> 1560 | G23: =SUM(G19:G22) -> 10800 | H23: =SUM(H19:H22) -> 48750 | I23: =SUM(F23:H23) -> 61110 | J23: =SUM(J19:J22) -> 9360 | K23: =SUM(K19:K22) -> 38400 | L23: =SUM(L19:L22) -> 117000 | M23: =SUM(J23:L23) -> 164760 | N23: =SUM(N19:N22) -> 93600 | O23: =SUM(O19:O22) -> 230400 | P23: =SUM(P19:P22) -> 468000 | Q23: =SUM(N23:P23) -> 792000 | R23: =SUM(R19:R22) -> 218400 | S23: =SUM(S19:S22) -> 360000 | T23: =SUM(T19:T22) -> 585000 | U23: =SUM(R23:T23) -> 1163400
A24: Tier revenue | B24: =SUM(B12,B14,B18) -> 139.05 | C24: =SUM(C12,C14,C18) -> 756 | D24: =SUM(D12,D14,D18) -> 1560 | E24: =SUM(B24:D24) -> 2455.05 | F24: =SUM(F12,F14,F18) -> 50550 | G24: =SUM(G12,G14,G18) -> 134100 | H24: =SUM(H12,H14,H18) -> 168125 | I24: =SUM(F24:H24) -> 352775 | J24: =SUM(J12,J14,J18) -> 331020 | K24: =SUM(K12,K14,K18) -> 507904 | L24: =SUM(L12,L14,L18) -> 417675 | M24: =SUM(J24:L24) -> 1256599 | N24: =SUM(N12,N14,N18) -> 3615120 | O24: =SUM(O12,O14,O18) -> 3248977.9 | P24: =SUM(P12,P14,P18) -> 1730235 | Q24: =SUM(N24:P24) -> 8594332.9 | R24: =SUM(R12,R14,R18) -> 9217908 | S24: =SUM(S12,S14,S18) -> 5416650.2 | T24: =SUM(T12,T14,T18) -> 2240933.4 | U24: =SUM(R24:T24) -> 16875492
A25: Gross profit before shared COGS | B25: =B24-B23 -> 134.37 | C25: =C24-C23 -> 691.2 | D25: =D24-D23 -> 1092 | E25: =E24-E23 -> 1917.57 | F25: =F24-F23 -> 48990 | G25: =G24-G23 -> 123300 | H25: =H24-H23 -> 119375 | I25: =I24-I23 -> 291665 | ... U25: =U24-U23 -> 15712092
A26: Gross margin | B26: =IF(B24=0,0,B25/B24) -> 0.96634304 | C26: =IF(C24=0,0,C25/C24) -> 0.91428571 | D26: =IF(D24=0,0,D25/D24) -> 0.7 | E26: =IF(E24=0,0,E25/E24) -> 0.78107167 | F26: =IF(F24=0,0,F25/F24) -> 0.96913947 | G26: =IF(G24=0,0,G25/G24) -> 0.91946309 | H26: =IF(H24=0,0,H25/H24) -> 0.71003717 | I26: =IF(I24=0,0,I25/I24) -> 0.82677344 | ... U26: =IF(U24=0,0,U25/U24) -> 0.93105979
A27: Weighted risk score | B27: =B4*Assumptions!$F$97 -> 0.15 | C27: =C4*Assumptions!$F$98 -> 1.35 | D27: =D4*Assumptions!$F$99 -> 2 | E27: =SUM(B27:D27) -> 3.5 | F27: =F4*Assumptions!$F$97 -> 0.3 | G27: =G4*Assumptions!$F$98 -> 1.35 | H27: =H4*Assumptions!$F$99 -> 1.25 | I27: =SUM(F27:H27) -> 2.9 | J27: =J4*Assumptions!$F$97 -> 0.45 | K27: =K4*Assumptions!$F$98 -> 1.2 | L27: =L4*Assumptions!$F$99 -> 0.75 | M27: =SUM(J27:L27) -> 2.4 | N27: =N4*Assumptions!$F$97 -> 0.6 | O27: =O4*Assumptions!$F$98 -> 0.96 | P27: =P4*Assumptions!$F$99 -> 0.4 | Q27: =SUM(N27:P27) -> 1.96 | R27: =R4*Assumptions!$F$97 -> 0.7 | S27: =S4*Assumptions!$F$98 -> 0.75 | T27: =T4*Assumptions!$F$99 -> 0.25 | U27: =SUM(R27:T27) -> 1.7
A28: SLA days | B28: =Assumptions!$F$100 -> 0.05 | C28: =Assumptions!$F$101 -> 0.5 | D28: =Assumptions!$F$102 -> 7 | E28: =IF(E5=0,0,SUM(B5*B28,C5*C28,D5*D28)/E5) -> 3.0325 | F28: =Assumptions!$F$100 -> 0.05 | G28: =Assumptions!$F$101 -> 0.5 | H28: =Assumptions!$F$102 -> 7 | I28: =IF(I5=0,0,SUM(F5*F28,G5*G28,H5*H28)/I5) -> 1.99 | J28: =Assumptions!$F$100 -> 0.05 | K28: =Assumptions!$F$101 -> 0.5 | L28: =Assumptions!$F$102 -> 7 | M28: =IF(M5=0,0,SUM(J5*J28,K5*K28,L5*L28)/M5) -> 1.2725 | N28: =Assumptions!$F$100 -> 0.05 | O28: =Assumptions!$F$101 -> 0.5 | P28: =Assumptions!$F$102 -> 7 | Q28: =IF(Q5=0,0,SUM(N5*N28,O5*O28,P5*P28)/Q5) -> 0.75 | R28: =Assumptions!$F$100 -> 0.05 | S28: =Assumptions!$F$101 -> 0.5 | T28: =Assumptions!$F$102 -> 7 | U28: =IF(U5=0,0,SUM(R5*R28,S5*S28,T5*T28)/U5) -> 0.51
A29: Tier mix sums check | E29: =IF(ABS(E4-1)<0.0001,"OK","CHECK MIX") -> OK | I29: =IF(ABS(I4-1)<0.0001,"OK","CHECK MIX") -> OK | M29: =IF(ABS(M4-1)<0.0001,"OK","CHECK MIX") -> OK | Q29: =IF(ABS(Q4-1)<0.0001,"OK","CHECK MIX") -> OK | U29: =IF(ABS(U4-1)<0.0001,"OK","CHECK MIX") -> OK
A30: Pricing / risk profile | B30: Fastest / lowest risk | C30: Core verified tier | D30: Highest cost / highest risk | E30: Portfolio blend | F30: Fastest / lowest risk | G30: Core verified tier | H30: Highest cost / highest risk | I30: Portfolio blend | J30: Fastest / lowest risk | K30: Core verified tier | L30: Highest cost / highest risk | M30: Portfolio blend | N30: Fastest / lowest risk | O30: Core verified tier | P30: Highest cost / highest risk | Q30: Portfolio blend | R30: Fastest / lowest risk | S30: Core verified tier | T30: Highest cost / highest risk | U30: Portfolio blend
A32: Notes | Q32: Source
A33: *Year-1 deal values (£35k Tier A; £30k Tier B/C) and 10%/8%/5% annual growth are triangulated planning averages, not observed tier-level transaction data. The research report documents the proxies, judgement and confidence limits. | Q33: ../docs/Blockmediary_Deal_Value_Research_Report.pdf
A34: **Take rates of 0.8%/1.5%/3.0% are management pricing choices informed by Tazapay, Truzo, XREX, Escrow.com and bank-LC comparables. They are paid-pilot hypotheses, not competitor quotations. | Q34: ../docs/Competitor-analysis.md
A35: ***Minimum fees (£150/£250/£500) are internal floors intended to protect contribution margin on smaller deals; no external tariff is being claimed. Validate conversion and willingness-to-pay in the pilot. | Q35: Management assumption — pilot validation required

Sheet Revenue Risk Add-Ons
A1: Revenue add-ons and retained-risk offsets
A3: Line item | B3: Year 1 | C3: Year 2 | D3: Year 3 | E3: Year 4 | F3: Year 5 | G3: Logic / note
A4: REVENUE ADD-ONS
A5: Less: first-deal discounts and credits | B5: =IFERROR(ROUND(-'P&L 5yr'!C70*('P&L 5yr'!C14/'P&L 5yr'!C7)*Assumptions!$F$112,0),0) -> -302 | C5: =IFERROR(ROUND(-MAX(0,'P&L 5yr'!D70-'P&L 5yr'!C70)*('P&L 5yr'!D14/'P&L 5yr'!D7)*Assumptions!$F$112,0),0) -> -33936 | D5: =IFERROR(ROUND(-MAX(0,'P&L 5yr'!E70-'P&L 5yr'!D70)*('P&L 5yr'!E14/'P&L 5yr'!E7)*Assumptions!$F$112,0),0) -> -53255 | E5: =IFERROR(ROUND(-MAX(0,'P&L 5yr'!F70-'P&L 5yr'!E70)*('P&L 5yr'!F14/'P&L 5yr'!F7)*Assumptions!$F$112,0),0) -> -376441 | F5: =IFERROR(ROUND(-MAX(0,'P&L 5yr'!G70-'P&L 5yr'!F70)*('P&L 5yr'!G14/'P&L 5yr'!G7)*Assumptions!$F$112,0),0) -> -278278
A6: Expedited review fees | B6: =ROUND('Tier Economics'!C5*Assumptions!$F$113*Assumptions!$F$115+'Tier Economics'!D5*Assumptions!$F$114*Assumptions!$F$116,0) -> 92 | C6: =ROUND('Tier Economics'!G5*Assumptions!$F$113*Assumptions!$F$115+'Tier Economics'!H5*Assumptions!$F$114*Assumptions!$F$116,0) -> 10875 | D6: =ROUND('Tier Economics'!K5*Assumptions!$F$113*Assumptions!$F$115+'Tier Economics'!L5*Assumptions!$F$114*Assumptions!$F$116,0) -> 30000 | E6: =ROUND('Tier Economics'!O5*Assumptions!$F$113*Assumptions!$F$115+'Tier Economics'!P5*Assumptions!$F$114*Assumptions!$F$116,0) -> 144000 | F6: =ROUND('Tier Economics'!S5*Assumptions!$F$113*Assumptions!$F$115+'Tier Economics'!T5*Assumptions!$F$114*Assumptions!$F$116,0) -> 202500
A7: KYC/KYB onboarding fees | B7: =ROUND('P&L 5yr'!C11*Assumptions!$F$117,0) -> 45 | C7: =ROUND('P&L 5yr'!D11*Assumptions!$F$117,0) -> 7500 | D7: =ROUND('P&L 5yr'!E11*Assumptions!$F$117,0) -> 30000 | E7: =ROUND('P&L 5yr'!F11*Assumptions!$F$117,0) -> 225000 | F7: =ROUND('P&L 5yr'!G11*Assumptions!$F$117,0) -> 450000 | G7: Fresh onboarding only; repeat counterparties not recharged every deal
A8: Tier C forensics pass-through margin | B8: =ROUND('Tier Economics'!D19*Assumptions!$F$118,0) -> 36 | C8: =ROUND('Tier Economics'!H19*Assumptions!$F$118,0) -> 3750 | D8: =ROUND('Tier Economics'!L19*Assumptions!$F$118,0) -> 9000 | E8: =ROUND('Tier Economics'!P19*Assumptions!$F$118,0) -> 36000 | F8: =ROUND('Tier Economics'!T19*Assumptions!$F$118,0) -> 45000
A9: Tier C courier/original handling fees | B9: =ROUND('Tier Economics'!D5*Assumptions!$F$119,0) -> 90 | C9: =ROUND('Tier Economics'!H5*Assumptions!$F$119,0) -> 9375 | D9: =ROUND('Tier Economics'!L5*Assumptions!$F$119,0) -> 22500 | E9: =ROUND('Tier Economics'!P5*Assumptions!$F$119,0) -> 90000 | F9: =ROUND('Tier Economics'!T5*Assumptions!$F$119,0) -> 112500
A10: Discrepancy cure / waiver fees | B10: =ROUND('P&L 5yr'!C12*Assumptions!$F$121*Assumptions!$F$120,0) -> 24 | C10: =ROUND('P&L 5yr'!D12*Assumptions!$F$121*Assumptions!$F$120,0) -> 3210 | D10: =ROUND('P&L 5yr'!E12*Assumptions!$F$121*Assumptions!$F$120,0) -> 10560 | E10: =ROUND('P&L 5yr'!F12*Assumptions!$F$121*Assumptions!$F$120,0) -> 64800 | F10: =ROUND('P&L 5yr'!G12*Assumptions!$F$121*Assumptions!$F$120,0) -> 113400
A11: Partner setup / integration fees | B11: =ROUND(0,0) -> 0 | C11: =ROUND(Assumptions!$F$14*Assumptions!$F$122,0) -> 22500 | D11: =ROUND(MAX(0,Assumptions!$F$110-Assumptions!$F$14)*Assumptions!$F$122,0) -> 22500 | E11: =ROUND(MAX(0,Assumptions!$F$155-Assumptions!$F$110)*Assumptions!$F$122,0) -> 30000 | F11: =ROUND(MAX(0,Assumptions!$F$156-Assumptions!$F$155)*Assumptions!$F$122,0) -> 60000 | G11: Setup fees charged on net-new partners only
A12: Monthly minimum / committed volume fees | B12: =ROUND(0,0) -> 0 | C12: =ROUND(Assumptions!$F$14*Assumptions!$F$123*12,0) -> 27000 | D12: =ROUND(Assumptions!$F$110*Assumptions!$F$123*12,0) -> 54000 | E12: =ROUND(Assumptions!$F$155*Assumptions!$F$123*12,0) -> 90000 | F12: =ROUND(Assumptions!$F$156*Assumptions!$F$123*12,0) -> 162000 | G12: Monthly minimum uses live partner count by year
A13: Archive / audit record fees | B13: =ROUND('P&L 5yr'!C7*Assumptions!$F$124,0) -> 9 | C13: =ROUND('P&L 5yr'!D7*Assumptions!$F$124,0) -> 1500 | D13: =ROUND('P&L 5yr'!E7*Assumptions!$F$124,0) -> 6000 | E13: =ROUND('P&L 5yr'!F7*Assumptions!$F$124,0) -> 45000 | F13: =ROUND('P&L 5yr'!G7*Assumptions!$F$124,0) -> 90000
A15: Total additional revenue | B15: =ROUND(SUM(B5:B14),0) -> -6 | C15: =ROUND(SUM(C5:C14),0) -> 51774 | D15: =ROUND(SUM(D5:D14),0) -> 131305 | E15: =ROUND(SUM(E5:E14),0) -> 348359 | F15: =ROUND(SUM(F5:F14),0) -> 957122
A17: RETAINED-RISK VARIABLE COSTS
A18: QA sampling + >£50k mandatory review | B18: =ROUND('P&L 5yr'!C12*Assumptions!$F$131*Assumptions!$F$132+'P&L 5yr'!C7*Assumptions!$F$176*Assumptions!$F$181,0) -> 24 | C18: =ROUND('P&L 5yr'!D12*Assumptions!$F$131*Assumptions!$F$132+'P&L 5yr'!D7*Assumptions!$F$177*Assumptions!$F$181,0) -> 7757 | D18: =ROUND('P&L 5yr'!E12*Assumptions!$F$131*Assumptions!$F$132+'P&L 5yr'!E7*Assumptions!$F$178*Assumptions!$F$181,0) -> 53345 | E18: =ROUND('P&L 5yr'!F12*Assumptions!$F$131*Assumptions!$F$132+'P&L 5yr'!F7*Assumptions!$F$179*Assumptions!$F$181,0) -> 567684 | F18: =ROUND('P&L 5yr'!G12*Assumptions!$F$131*Assumptions!$F$132+'P&L 5yr'!G7*Assumptions!$F$180*Assumptions!$F$181,0) -> 1471572 | G18: QA sampling plus deal count × share above £50k × incremental review cost
A19: External dispute forum cost | B19: =ROUND('P&L 5yr'!C12*Assumptions!$F$133*Assumptions!$F$134,0) -> 88 | C19: =ROUND('P&L 5yr'!D12*Assumptions!$F$133*Assumptions!$F$134,0) -> 12038 | D19: =ROUND('P&L 5yr'!E12*Assumptions!$F$133*Assumptions!$F$134,0) -> 39600 | E19: =ROUND('P&L 5yr'!F12*Assumptions!$F$133*Assumptions!$F$134,0) -> 243000 | F19: =ROUND('P&L 5yr'!G12*Assumptions!$F$133*Assumptions!$F$134,0) -> 425250
A20: Operational error / wrongful-release reserve | B20: =ROUND('P&L 5yr'!C18*Assumptions!$F$135,0) -> 24 | C20: =ROUND('P&L 5yr'!D18*Assumptions!$F$135,0) -> 4045 | D20: =ROUND('P&L 5yr'!E18*Assumptions!$F$135,0) -> 13879 | E20: =ROUND('P&L 5yr'!F18*Assumptions!$F$135,0) -> 89427 | F20: =ROUND('P&L 5yr'!G18*Assumptions!$F$135,0) -> 178326
A21: Partner/channel commission | B21: 0 | C21: =ROUND('P&L 5yr'!D18*Assumptions!$F$159*Assumptions!$F$139,0) -> 6068 | D21: =ROUND('P&L 5yr'!E18*Assumptions!$F$159*Assumptions!$F$139,0) -> 20819 | E21: =ROUND('P&L 5yr'!F18*Assumptions!$F$159*Assumptions!$F$139,0) -> 134140 | F21: =ROUND('P&L 5yr'!G18*Assumptions!$F$159*Assumptions!$F$139,0) -> 267489
A22: Fee collection leakage | B22: =ROUND((B7+B10+B12)*Assumptions!$F$140,0) -> 1 | C22: =ROUND((C7+C10+C12)*Assumptions!$F$140,0) -> 377 | D22: =ROUND((D7+D10+D12)*Assumptions!$F$140,0) -> 946 | E22: =ROUND((E7+E10+E12)*Assumptions!$F$140,0) -> 3798 | F22: =ROUND((F7+F10+F12)*Assumptions!$F$140,0) -> 7254
A23: Partner/API outage fallback | B23: =ROUND('Tier Economics'!C5*Assumptions!$F$141*Assumptions!$F$142,0) -> 3 | C23: =ROUND('Tier Economics'!G5*Assumptions!$F$141*Assumptions!$F$142,0) -> 506 | D23: =ROUND('Tier Economics'!K5*Assumptions!$F$141*Assumptions!$F$142,0) -> 1800 | E23: =ROUND('Tier Economics'!O5*Assumptions!$F$141*Assumptions!$F$142,0) -> 10800 | F23: =ROUND('Tier Economics'!S5*Assumptions!$F$141*Assumptions!$F$142,0) -> 16875
A24: Total variable retained-risk costs | B24: =ROUND(SUM(B18:B23),0) -> 140 | C24: =ROUND(SUM(C18:C23),0) -> 30791 | D24: =ROUND(SUM(D18:D23),0) -> 130389 | E24: =ROUND(SUM(E18:E23),0) -> 1048849 | F24: =ROUND(SUM(F18:F23),0) -> 2366766
A26: RETAINED-RISK FIXED COSTS
A27: Carrier/eBL integration maintenance | B27: =ROUND(Assumptions!$F$127*1,0) -> 15000 | C27: =ROUND(Assumptions!$F$127*1.25,0) -> 18750 | D27: =ROUND(Assumptions!$F$127*1.5,0) -> 22500 | E27: =ROUND(Assumptions!$F$127*1.75,0) -> 26250 | F27: =ROUND(Assumptions!$F$127*2,0) -> 30000
A28: Forensics partner retainer | B28: =ROUND(Assumptions!$F$128*1,0) -> 20000 | C28: =ROUND(Assumptions!$F$128*1.25,0) -> 25000 | D28: =ROUND(Assumptions!$F$128*1.5,0) -> 30000 | E28: =ROUND(Assumptions!$F$128*1.75,0) -> 35000 | F28: =ROUND(Assumptions!$F$128*2,0) -> 40000
A29: Fraud database build / governance | B29: =ROUND(Assumptions!$F$129+Assumptions!$F$130,0) -> 55000 | C29: =ROUND(Assumptions!$F$130,0) -> 15000 | D29: =ROUND(Assumptions!$F$130,0) -> 15000 | E29: =ROUND(Assumptions!$F$130,0) -> 15000 | F29: =ROUND(Assumptions!$F$130,0) -> 15000
A30: KMS / multisig / key security ops | B30: =ROUND(Assumptions!$F$137*1,0) -> 12000 | C30: =ROUND(Assumptions!$F$137*1.25,0) -> 15000 | D30: =ROUND(Assumptions!$F$137*1.5,0) -> 18000 | E30: =ROUND(Assumptions!$F$137*1.75,0) -> 21000 | F30: =ROUND(Assumptions!$F$137*2,0) -> 24000
A31: Regulatory reporting ops | B31: =ROUND(Assumptions!$F$138*1,0) -> 18000 | C31: =ROUND(Assumptions!$F$138*1.25,0) -> 22500 | D31: =ROUND(Assumptions!$F$138*1.5,0) -> 27000 | E31: =ROUND(Assumptions!$F$138*1.75,0) -> 31500 | F31: =ROUND(Assumptions!$F$138*2,0) -> 36000
A32: Insurance deductible reserve | B32: =ROUND(Assumptions!$F$136,0) -> 15000 | C32: =ROUND(Assumptions!$F$136,0) -> 15000 | D32: =ROUND(Assumptions!$F$136,0) -> 15000 | E32: =ROUND(Assumptions!$F$136,0) -> 15000 | F32: =ROUND(Assumptions!$F$136,0) -> 15000
A33: Smart contract incident reserve | B33: =ROUND(Assumptions!$F$143*1,0) -> 30000 | C33: =ROUND(Assumptions!$F$143*1,0) -> 30000 | D33: =ROUND(Assumptions!$F$143*1,0) -> 30000 | E33: =ROUND(Assumptions!$F$143*1.25,0) -> 37500 | F33: =ROUND(Assumptions!$F$143*1.5,0) -> 45000
A34: Liability wording legal review | B34: =ROUND(Assumptions!$F$144,0) -> 7500 | C34: =ROUND(0,0) -> 0 | D34: =ROUND(0,0) -> 0 | E34: =ROUND(0,0) -> 0 | F34: =ROUND(0,0) -> 0
A35: Document-source indemnity legal review | B35: =ROUND(Assumptions!$F$145,0) -> 7500 | C35: =ROUND(0,0) -> 0 | D35: =ROUND(0,0) -> 0 | E35: =ROUND(0,0) -> 0 | F35: =ROUND(0,0) -> 0
A36: Total fixed retained-risk costs | B36: =ROUND(SUM(B27:B35),0) -> 180000 | C36: =ROUND(SUM(C27:C35),0) -> 141250 | D36: =ROUND(SUM(D27:D35),0) -> 157500 | E36: =ROUND(SUM(E27:E35),0) -> 181250 | F36: =ROUND(SUM(F27:F35),0) -> 205000

Sheet P&L 5yr
B2: 5-Year P&L (annual) - driven by Assumptions sheet
B3: All figures GBP. Revenue & COGS scale with deal volume. Active scenario shown; change Assumptions!C4.
B5: Line item | C5: Year 1 | D5: Year 2 | E5: Year 3 | F5: Year 4 | G5: Year 5 | H5: Unit / note
B6: VOLUME & DRIVERS
B7: Deals processed | C7: =ROUND(Assumptions!$F$10*'Launch Readiness'!$B$28,0) -> 3 | D7: =ROUND(Assumptions!$F$11*'Launch Readiness'!$C$28,0) -> 500 | E7: =ROUND(Assumptions!$F$12*'Launch Readiness'!$D$28,0) -> 2000 | F7: =ROUND(Assumptions!$F$147*'Launch Readiness'!$E$28,0) -> 15000 | G7: =ROUND(Assumptions!$F$148*'Launch Readiness'!$F$28,0) -> 30000 | H7: From Assumptions
B8: Avg deal value (£) | C8: =IF(C7=0,0,C9/C7) -> 30750 | D8: =IF(D7=0,0,D9/D7) -> 34005 | E8: =IF(E7=0,0,E9/E7) -> 38015.55 | F8: =IF(F7=0,0,F9/F7) -> 42822.535 | G8: =IF(G7=0,0,G9/G7) -> 47897.377 | H8: GMV per deal
B9: Gross trade value processed (GMV) | C9: ='Tier Economics'!E9 -> 92250 | D9: ='Tier Economics'!I9 -> 17002500 | E9: ='Tier Economics'!M9 -> 76031100 | F9: ='Tier Economics'!Q9 -> 6.4233803e+08 | G9: ='Tier Economics'!U9 -> 1.4369213e+09 | H9: Deals × avg value (NOT revenue)
B10: Documents processed | C10: ='Tier Economics'!E7 -> 20.25 | D10: ='Tier Economics'!I7 -> 2925 | E10: ='Tier Economics'!M7 -> 10200 | F10: ='Tier Economics'!Q7 -> 66600 | G10: ='Tier Economics'!U7 -> 121500 | H10: Tier-weighted docs/deal from Tier Economics
B11: New counterparties onboarded | C11: =C7*Assumptions!$F$13*Assumptions!$F$59 -> 3 | D11: =D7*Assumptions!$F$13*Assumptions!$F$59 -> 500 | E11: =E7*Assumptions!$F$13*Assumptions!$F$59 -> 2000 | F11: =F7*Assumptions!$F$13*Assumptions!$F$59 -> 15000 | G11: =G7*Assumptions!$F$13*Assumptions!$F$59 -> 30000 | H11: Deals x parties/deal x new-counterparty onboarding share
B12: Disputed/amended deals | C12: ='Tier Economics'!E16 -> 0.393 | D12: ='Tier Economics'!I16 -> 53.5 | E12: ='Tier Economics'!M16 -> 176 | F12: ='Tier Economics'!Q16 -> 1080 | G12: ='Tier Economics'!U16 -> 1890 | H12: Tier-weighted dispute rates
B13: REVENUE
B14: Gross escrow transaction fees | C14: ='Tier Economics'!E12 -> 1813.5 | D14: ='Tier Economics'!I12 -> 273675 | E14: ='Tier Economics'!M12 -> 1022499 | F14: ='Tier Economics'!Q12 -> 7325332.9 | G14: ='Tier Economics'!U12 -> 14841492 | H14: Tiered fee by A/B/C mix, before launch discounts
B15: Less: first-deal discounts and credits | C15: ='Revenue Risk Add-Ons'!B5 -> -302 | D15: ='Revenue Risk Add-Ons'!C5 -> -33936 | E15: ='Revenue Risk Add-Ons'!D5 -> -53255 | F15: ='Revenue Risk Add-Ons'!E5 -> -376441 | G15: ='Revenue Risk Add-Ons'!F5 -> -278278 | H15: Shown separately so discounts do not make add-on revenue negative
B16: Document + dispute / amendment fees | C16: ='Tier Economics'!E14+'Tier Economics'!E18 -> 641.55 | D16: ='Tier Economics'!I14+'Tier Economics'!I18 -> 79100 | E16: ='Tier Economics'!M14+'Tier Economics'!M18 -> 234100 | F16: ='Tier Economics'!Q14+'Tier Economics'!Q18 -> 1269000 | G16: ='Tier Economics'!U14+'Tier Economics'!U18 -> 2034000 | H16: Tiered document and dispute / amendment fees
B17: Partner/API + other operating add-ons | C17: ='Revenue Risk Add-Ons'!B15-'Revenue Risk Add-Ons'!B5 -> 296 | D17: ='Revenue Risk Add-Ons'!C15-'Revenue Risk Add-Ons'!C5 -> 85710 | E17: ='Revenue Risk Add-Ons'!D15-'Revenue Risk Add-Ons'!D5 -> 184560 | F17: ='Revenue Risk Add-Ons'!E15-'Revenue Risk Add-Ons'!E5 -> 724800 | G17: ='Revenue Risk Add-Ons'!F15-'Revenue Risk Add-Ons'!F5 -> 1235400 | H17: SaaS/API, setup/minimums, KYC, archive, expedited and Tier C pass-through
B18: Total revenue | C18: =SUM(C14:C17) -> 2449.05 | D18: =SUM(D14:D17) -> 404549 | E18: =SUM(E14:E17) -> 1387904 | F18: =SUM(F14:F17) -> 8942691.9 | G18: =SUM(G14:G17) -> 17832614 | H18: Sum of revenue lines
B19: COGS / VARIABLE COSTS
B20: Claude API (doc extraction) | C20: =C10*Assumptions!$F$23/Assumptions!$F$8 -> 4.7460938 | D20: =D10*Assumptions!$F$23/Assumptions!$F$8 -> 685.54688 | E20: =E10*Assumptions!$F$23/Assumptions!$F$8 -> 2390.625 | F20: =F10*Assumptions!$F$23/Assumptions!$F$8 -> 15609.375 | G20: =G10*Assumptions!$F$23/Assumptions!$F$8 -> 28476.562 | H20: USD→GBP
B21: KYB business onboarding | C21: =C11*Assumptions!$F$24/Assumptions!$F$8 -> 8.203125 | D21: =D11*Assumptions!$F$24/Assumptions!$F$8 -> 1367.1875 | E21: =E11*Assumptions!$F$24/Assumptions!$F$8 -> 5468.75 | F21: =F11*Assumptions!$F$24/Assumptions!$F$8 -> 41015.625 | G21: =G11*Assumptions!$F$24/Assumptions!$F$8 -> 82031.25 | H21: Fresh KYB only for new counterparties
B22: KYC/UBO + sanctions onboarding | C22: =C11*Assumptions!$F$25/Assumptions!$F$8 -> 3.1640625 | D22: =D11*Assumptions!$F$25/Assumptions!$F$8 -> 527.34375 | E22: =E11*Assumptions!$F$25/Assumptions!$F$8 -> 2109.375 | F22: =F11*Assumptions!$F$25/Assumptions!$F$8 -> 15820.312 | G22: =G11*Assumptions!$F$25/Assumptions!$F$8 -> 31640.625 | H22: Fresh KYC/KYB only for new counterparties
B23: Tiered document verification ops | C23: =CHOOSE(Assumptions!$C$4,'Scenario Engine'!B36,'Scenario Engine'!H36,'Scenario Engine'!N36) -> 403.2 | D23: =CHOOSE(Assumptions!$C$4,'Scenario Engine'!C36,'Scenario Engine'!I36,'Scenario Engine'!O36) -> 45150 | E23: =CHOOSE(Assumptions!$C$4,'Scenario Engine'!D36,'Scenario Engine'!J36,'Scenario Engine'!P36) -> 119400 | F23: =CHOOSE(Assumptions!$C$4,'Scenario Engine'!E36,'Scenario Engine'!K36,'Scenario Engine'!Q36) -> 558000 | G23: =CHOOSE(Assumptions!$C$4,'Scenario Engine'!F36,'Scenario Engine'!L36,'Scenario Engine'!R36) -> 801000 | H23: External eBL/API/paper + human examiner cost
B24: Blockchain gas | C24: =C7*Assumptions!$F$26/Assumptions!$F$8 -> 0.46875 | D24: =D7*Assumptions!$F$26/Assumptions!$F$8 -> 78.125 | E24: =E7*Assumptions!$F$26/Assumptions!$F$8 -> 312.5 | F24: =F7*Assumptions!$F$26/Assumptions!$F$8 -> 2343.75 | G24: =G7*Assumptions!$F$26/Assumptions!$F$8 -> 4687.5 | H24: Base L2 USD→GBP
B25: RPC / node provider | C25: =C7*Assumptions!$F$27/Assumptions!$F$8 -> 0.0234375 | D25: =D7*Assumptions!$F$27/Assumptions!$F$8 -> 3.90625 | E25: =E7*Assumptions!$F$27/Assumptions!$F$8 -> 15.625 | F25: =F7*Assumptions!$F$27/Assumptions!$F$8 -> 117.1875 | G25: =G7*Assumptions!$F$27/Assumptions!$F$8 -> 234.375 | H25: Deals x RPC cost; USD to GBP
B26: Document / ledger storage | C26: =C7*Assumptions!$F$28/Assumptions!$F$8 -> 0.0703125 | D26: =D7*Assumptions!$F$28/Assumptions!$F$8 -> 11.71875 | E26: =E7*Assumptions!$F$28/Assumptions!$F$8 -> 46.875 | F26: =F7*Assumptions!$F$28/Assumptions!$F$8 -> 351.5625 | G26: =G7*Assumptions!$F$28/Assumptions!$F$8 -> 703.125 | H26: Deals x storage cost; USD to GBP
B27: Customer support | C27: =CHOOSE(Assumptions!$C$4,'Scenario Engine'!B40,'Scenario Engine'!H40,'Scenario Engine'!N40) -> 33 | D27: =CHOOSE(Assumptions!$C$4,'Scenario Engine'!C40,'Scenario Engine'!I40,'Scenario Engine'!O40) -> 4150 | E27: =CHOOSE(Assumptions!$C$4,'Scenario Engine'!D40,'Scenario Engine'!J40,'Scenario Engine'!P40) -> 12600 | F27: =CHOOSE(Assumptions!$C$4,'Scenario Engine'!E40,'Scenario Engine'!K40,'Scenario Engine'!Q40) -> 70800 | G27: =CHOOSE(Assumptions!$C$4,'Scenario Engine'!F40,'Scenario Engine'!L40,'Scenario Engine'!R40) -> 117000 | H27: Tiered support load
B28: Dispute handling + retained-risk variable costs | C28: =CHOOSE(Assumptions!$C$4,SUM('Scenario Engine'!B41:B46),SUM('Scenario Engine'!H41:H46),SUM('Scenario Engine'!N41:N46)) -> 254.28 | D28: =CHOOSE(Assumptions!$C$4,SUM('Scenario Engine'!C41:C46),SUM('Scenario Engine'!I41:I46),SUM('Scenario Engine'!O41:O46)) -> 44744 | E28: =CHOOSE(Assumptions!$C$4,SUM('Scenario Engine'!D41:D46),SUM('Scenario Engine'!J41:J46),SUM('Scenario Engine'!P41:P46)) -> 171904 | F28: =CHOOSE(Assumptions!$C$4,SUM('Scenario Engine'!E41:E46),SUM('Scenario Engine'!K41:K46),SUM('Scenario Engine'!Q41:Q46)) -> 1278865 | G28: =CHOOSE(Assumptions!$C$4,SUM('Scenario Engine'!F41:F46),SUM('Scenario Engine'!L41:L46),SUM('Scenario Engine'!R41:R46)) -> 2747094 | H28: Dispute handling plus QA, forum, reserves, commissions, fallback, leakage
B29: Total COGS | C29: =SUM(C20:C28) -> 707.15578 | D29: =SUM(D20:D28) -> 96717.828 | E29: =SUM(E20:E28) -> 314247.75 | F29: =SUM(F20:F28) -> 1982922.8 | G29: =SUM(G20:G28) -> 3812867.4 | H29: Sum of COGS lines
B30: Gross profit | C30: =C18-C29 -> 1741.8942 | D30: =D18-D29 -> 307831.17 | E30: =E18-E29 -> 1073656.2 | F30: =F18-F29 -> 6959769.1 | G30: =G18-G29 -> 14019746 | H30: Total revenue minus total COGS
B31: Gross margin % | C31: =IF(C18=0,0,C30/C18) -> 0.71125302 | D31: =IF(D18=0,0,D30/D18) -> 0.76092432 | E31: =IF(E18=0,0,E30/E18) -> 0.77358106 | F31: =IF(F18=0,0,F30/F18) -> 0.77826332 | G31: =IF(G18=0,0,G30/G18) -> 0.78618572 | H31: Gross profit / revenue
B32: HEADCOUNT & PAYROLL
B33: Founders (FTE) | C33: =Assumptions!$F$43*'Launch Readiness'!$D$38 -> 4 | D33: =Assumptions!$F$43*'Launch Readiness'!$E$38 -> 4 | E33: =Assumptions!$F$43*'Launch Readiness'!$F$38 -> 4 | F33: =Assumptions!$F$43*'Launch Readiness'!$G$38 -> 4 | G33: =Assumptions!$F$43*'Launch Readiness'!$H$38 -> 4 | H33: Founder headcount held flat
B34: Engineers (FTE) | C34: =(Assumptions!$F$44+0)*'Launch Readiness'!$D$39 -> 1.3333333 | D34: =(Assumptions!$F$44+1)*'Launch Readiness'!$E$39 -> 3 | E34: =(Assumptions!$F$44+2)*'Launch Readiness'!$F$39 -> 4 | F34: =(Assumptions!$F$44+3)*'Launch Readiness'!$G$39 -> 5 | G34: =(Assumptions!$F$44+4)*'Launch Readiness'!$H$39 -> 6 | H34: Ramp +1/yr
B35: Compliance/ops (FTE) | C35: =(Assumptions!$F$45+0)*'Launch Readiness'!$D$40 -> 2 | D35: =(Assumptions!$F$45+1)*'Launch Readiness'!$E$40 -> 3 | E35: =(Assumptions!$F$45+2)*'Launch Readiness'!$F$40 -> 4 | F35: =(Assumptions!$F$45+3)*'Launch Readiness'!$G$40 -> 5 | G35: =(Assumptions!$F$45+4)*'Launch Readiness'!$H$40 -> 6 | H35: Ramp
B36: Sales/BD/CS (FTE) | C36: =Assumptions!C$183*'Launch Readiness'!D$41 -> 0.33333333 | D36: =Assumptions!D$183*'Launch Readiness'!E$41 -> 2 | E36: =Assumptions!E$183*'Launch Readiness'!F$41 -> 3 | F36: =Assumptions!F$183*'Launch Readiness'!G$41 -> 7 | G36: =Assumptions!G$183*'Launch Readiness'!H$41 -> 8 | H36: Explicit AI-enabled ramp from Assumptions C191:G191
B37: Total FTE | C37: =C33+C34+C35+C36 -> 7.6666667 | D37: =D33+D34+D35+D36 -> 12 | E37: =E33+E34+E35+E36 -> 15 | F37: =F33+F34+F35+F36 -> 21 | G37: =G33+G34+G35+G36 -> 24 | H37: Founders + engineers + compliance/ops + sales/BD/CS
B38: Gross salaries | C38: =C33*Assumptions!$F$48+C34*Assumptions!$F$49+C35*Assumptions!$F$50+C36*Assumptions!$F$51 -> 410000 | D38: =D33*Assumptions!$F$48+D34*Assumptions!$F$49+D35*Assumptions!$F$50+D36*Assumptions!$F$51 -> 670000 | E38: =E33*Assumptions!$F$48+E34*Assumptions!$F$49+E35*Assumptions!$F$50+E36*Assumptions!$F$51 -> 850000 | F38: =F33*Assumptions!$F$48+F34*Assumptions!$F$49+F35*Assumptions!$F$50+F36*Assumptions!$F$51 -> 1180000 | G38: =G33*Assumptions!$F$48+G34*Assumptions!$F$49+G35*Assumptions!$F$50+G36*Assumptions!$F$51 -> 1360000 | H38: FTE × salary
B39: Employer NI | C39: =MAX(0,(C38-Assumptions!$F$53*C37)*Assumptions!$F$52-Assumptions!$F$57) -> 45250 | D39: =MAX(0,(D38-Assumptions!$F$53*D37)*Assumptions!$F$52-Assumptions!$F$57) -> 81000 | E39: =MAX(0,(E38-Assumptions!$F$53*E37)*Assumptions!$F$52-Assumptions!$F$57) -> 105750 | F39: =MAX(0,(F38-Assumptions!$F$53*F37)*Assumptions!$F$52-Assumptions!$F$57) -> 150750 | G39: =MAX(0,(G38-Assumptions!$F$53*G37)*Assumptions!$F$52-Assumptions!$F$57) -> 175500 | H39: 15% above threshold, less Employment Allowance; confirm eligibility
B40: Employer pension | C40: =C38*Assumptions!$F$54 -> 16400 | D40: =D38*Assumptions!$F$54 -> 26800 | E40: =E38*Assumptions!$F$54 -> 34000 | F40: =F38*Assumptions!$F$54 -> 47200 | G40: =G38*Assumptions!$F$54 -> 54400 | H40: Gross salaries x pension contribution
B41: Other employment on-costs | C41: =C38*Assumptions!$F$55 -> 12300 | D41: =D38*Assumptions!$F$55 -> 20100 | E41: =E38*Assumptions!$F$55 -> 25500 | F41: =F38*Assumptions!$F$55 -> 35400 | G41: =G38*Assumptions!$F$55 -> 40800 | H41: Gross salaries x other employment on-costs
B42: Total payroll cost | C42: =C38+C39+C40+C41 -> 483950 | D42: =D38+D39+D40+D41 -> 797900 | E42: =E38+E39+E40+E41 -> 1015250 | F42: =F38+F39+F40+F41 -> 1413350 | G42: =G38+G39+G40+G41 -> 1630700 | H42: Gross salaries + employer NI + pension + other on-costs
B43: FIXED OPERATING COSTS (annual = monthly ×12)
B44: Cloud hosting (Vercel/AWS) | C44: =Assumptions!$F$30*12*1 -> 4200 | D44: =Assumptions!$F$30*12*1.5 -> 6300 | E44: =Assumptions!$F$30*12*2.5 -> 10500 | F44: =Assumptions!$F$30*12*4 -> 16800 | G44: =Assumptions!$F$30*12*6 -> 25200 | H44: Monthly base × scale factor
B45: Database + object storage | C45: =Assumptions!$F$31*12*1 -> 2640 | D45: =Assumptions!$F$31*12*1.5 -> 3960 | E45: =Assumptions!$F$31*12*2.5 -> 6600 | F45: =Assumptions!$F$31*12*4 -> 10560 | G45: =Assumptions!$F$31*12*6 -> 15840 | H45: Monthly base × scale factor
B46: Monitoring/logging/security tools | C46: =Assumptions!$F$32*12*1 -> 3000 | D46: =Assumptions!$F$32*12*1.5 -> 4500 | E46: =Assumptions!$F$32*12*2.5 -> 7500 | F46: =Assumptions!$F$32*12*4 -> 12000 | G46: =Assumptions!$F$32*12*6 -> 18000 | H46: Monthly base × scale factor
B47: GitHub + dev SaaS | C47: =Assumptions!$F$33*12*C37/6 -> 920 | D47: =Assumptions!$F$33*12*D37/6 -> 1440 | E47: =Assumptions!$F$33*12*E37/6 -> 1800 | F47: =Assumptions!$F$33*12*F37/6 -> 2520 | G47: =Assumptions!$F$33*12*G37/6 -> 2880 | H47: Monthly base × FTE scale
B48: Google Workspace / collab | C48: =Assumptions!$F$34*12*C37/6 -> 1380 | D48: =Assumptions!$F$34*12*D37/6 -> 2160 | E48: =Assumptions!$F$34*12*E37/6 -> 2700 | F48: =Assumptions!$F$34*12*F37/6 -> 3780 | G48: =Assumptions!$F$34*12*G37/6 -> 4320 | H48: Monthly base × FTE scale
B49: CRM + BD tooling | C49: =Assumptions!$F$35*12*MAX(1,C36) -> 960 | D49: =Assumptions!$F$35*12*MAX(1,D36) -> 1920 | E49: =Assumptions!$F$35*12*MAX(1,E36) -> 2880 | F49: =Assumptions!$F$35*12*MAX(1,F36) -> 6720 | G49: =Assumptions!$F$35*12*MAX(1,G36) -> 7680 | H49: Monthly base × sales/BD scale
B50: Accounting/payroll/bookkeeping | C50: =Assumptions!$F$36*12*1 -> 4200 | D50: =Assumptions!$F$36*12*1.25 -> 5250 | E50: =Assumptions!$F$36*12*1.5 -> 6300 | F50: =Assumptions!$F$36*12*1.75 -> 7350 | G50: =Assumptions!$F$36*12*2 -> 8400 | H50: Monthly base × scale factor
B51: Legal retainer (ongoing) | C51: =Assumptions!$F$37*12*1 -> 7200 | D51: =Assumptions!$F$37*12*1.5 -> 10800 | E51: =Assumptions!$F$37*12*2 -> 14400 | F51: =Assumptions!$F$37*12*2.5 -> 18000 | G51: =Assumptions!$F$37*12*3 -> 21600 | H51: Monthly base × complexity scale
B52: Compliance / MLRO + retained-risk + staged UAE fees | C52: =(Assumptions!$F$38*12*1+'Revenue Risk Add-Ons'!B36)+'Launch Readiness'!$E$9*'Launch Readiness'!$B$34+'Launch Readiness'!$E$9*'Launch Readiness'!$B$10*'Launch Readiness'!$B$30+'Launch Readiness'!$E$16*'Launch Readiness'!$B$32 -> 219525 | D52: =(Assumptions!$F$38*12*1.5+'Revenue Risk Add-Ons'!C36)+'Launch Readiness'!$E$9*'Launch Readiness'!$C$34+'Launch Readiness'!$E$9*'Launch Readiness'!$B$10*'Launch Readiness'!$C$30+'Launch Readiness'!$E$16*'Launch Readiness'!$C$32 -> 229850 | E52: =(Assumptions!$F$38*12*2+'Revenue Risk Add-Ons'!D36)+'Launch Readiness'!$E$9*'Launch Readiness'!$D$34+'Launch Readiness'!$E$9*'Launch Readiness'!$B$10*'Launch Readiness'!$D$30+'Launch Readiness'!$E$16*'Launch Readiness'!$D$32 -> 273780.83 | F52: =(Assumptions!$F$38*12*2.5+'Revenue Risk Add-Ons'!E36)+'Launch Readiness'!$E$9*'Launch Readiness'!$E$34+'Launch Readiness'!$E$9*'Launch Readiness'!$B$10*'Launch Readiness'!$E$30+'Launch Readiness'!$E$16*'Launch Readiness'!$E$32 -> 319360 | G52: =(Assumptions!$F$38*12*3+'Revenue Risk Add-Ons'!F36)+'Launch Readiness'!$E$9*'Launch Readiness'!$F$34+'Launch Readiness'!$E$9*'Launch Readiness'!$B$10*'Launch Readiness'!$F$30+'Launch Readiness'!$E$16*'Launch Readiness'!$F$32 -> 350310 | H52: Internal compliance payroll is separate; this line contains MLRO support, retained-risk costs, partner-pilot fees and later VARA supervision.
B53: Marketing / conferences / partnerships | C53: =Assumptions!$F$39*12*1 -> 30000 | D53: =Assumptions!$F$39*12*2 -> 60000 | E53: =Assumptions!$F$39*12*3 -> 90000 | F53: =Assumptions!$F$39*12*4 -> 120000 | G53: =Assumptions!$F$39*12*5 -> 150000 | H53: Monthly base × sales/BD scale
B54: Office / coworking | C54: =Assumptions!$F$40*12*C37/6 -> 6133.3333 | D54: =Assumptions!$F$40*12*D37/6 -> 9600 | E54: =Assumptions!$F$40*12*E37/6 -> 12000 | F54: =Assumptions!$F$40*12*F37/6 -> 16800 | G54: =Assumptions!$F$40*12*G37/6 -> 19200 | H54: Monthly base × FTE scale
B55: Insurance (PI+cyber+D&O) / mo | C55: =0 -> 0 | D55: =Assumptions!$F$41*12*1 -> 8400 | E55: =Assumptions!$F$41*12*1 -> 8400 | F55: =Assumptions!$F$41*12*1.25 -> 10500 | G55: =Assumptions!$F$41*12*1.5 -> 12600 | H55: Year 1 prepaid; Years 2–3 monthly ×12
B56: Total fixed opex | C56: =SUM(C44:C55) -> 280158.33 | D56: =SUM(D44:D55) -> 344180 | E56: =SUM(E44:E55) -> 436860.83 | F56: =SUM(F44:F55) -> 544390 | G56: =SUM(G44:G55) -> 636030 | H56: Sum of fixed opex lines
B57: ONE-OFF & STARTUP COSTS
B58: Startup + staged UAE regulatory one-off costs | C58: =IF(COLUMN()-2=1,'Startup 6mo'!$F$44,0)+'Launch Readiness'!$E$8*'Launch Readiness'!B$27/MAX(1,'Launch Readiness'!$E$7)+'Launch Readiness'!$E$15*'Launch Readiness'!B$33 -> 303412.45 | D58: =IF(COLUMN()-2=1,'Startup 6mo'!$F$44,0)+'Launch Readiness'!$E$8*'Launch Readiness'!C$27/MAX(1,'Launch Readiness'!$E$7)+'Launch Readiness'!$E$15*'Launch Readiness'!C$33 -> 42546 | E58: =IF(COLUMN()-2=1,'Startup 6mo'!$F$44,0)+'Launch Readiness'!$E$8*'Launch Readiness'!D$27/MAX(1,'Launch Readiness'!$E$7)+'Launch Readiness'!$E$15*'Launch Readiness'!D$33 -> 0 | F58: =IF(COLUMN()-2=1,'Startup 6mo'!$F$44,0)+'Launch Readiness'!$E$8*'Launch Readiness'!E$27/MAX(1,'Launch Readiness'!$E$7)+'Launch Readiness'!$E$15*'Launch Readiness'!E$33 -> 0 | G58: =IF(COLUMN()-2=1,'Startup 6mo'!$F$44,0)+'Launch Readiness'!$E$8*'Launch Readiness'!F$27/MAX(1,'Launch Readiness'!$E$7)+'Launch Readiness'!$E$15*'Launch Readiness'!F$33 -> 0 | H58: Core startup spend, pilot onboarding cost and later VARA application fees.
B59: RESULT
B60: Total operating expenditure | C60: =C42+C56+C58 -> 1067520.8 | D60: =D42+D56+D58 -> 1184626 | E60: =E42+E56+E58 -> 1452110.8 | F60: =F42+F56+F58 -> 1957740 | G60: =G42+G56+G58 -> 2266730 | H60: Payroll+opex+one-off
B61: EBITDA (pre one-off) | C61: =C30-C42-C56 -> -762366.44 | D61: =D30-D42-D56 -> -834248.83 | E61: =E30-E42-E56 -> -378454.58 | F61: =F30-F42-F56 -> 5002029.1 | G61: =G30-G42-G56 -> 11753016 | H61: Gross profit − payroll − opex
B62: Net profit / (loss) incl. one-off | C62: =C30-C60 -> -1065778.9 | D62: =D30-D60 -> -876794.83 | E62: =E30-E60 -> -378454.58 | F62: =F30-F60 -> 5002029.1 | G62: =G30-G60 -> 11753016 | H62: Gross profit minus total operating expenditure
B63: Cumulative net result | C63: =C62 -> -1065778.9 | D63: =C63+D62 -> -1942573.7 | E63: =D63+E62 -> -2321028.3 | F63: =E63+F62 -> 2681000.8 | G63: =F63+G62 -> 14434017 | H63: Running total
B64: Peak cumulative operating deficit | C64: =-MIN(0,'Cash Flow Statement'!$B$38:$M$38) -> 1068227 | D64: =-MIN(0,'Cash Flow Statement'!$B$38:$Y$38) -> 1976300 | E64: =-MIN(0,'Cash Flow Statement'!$B$38:$AK$38) -> 2436689 | F64: =-MIN(0,'Cash Flow Statement'!$B$38:$AW$38) -> 2649419 | G64: =-MIN(0,'Cash Flow Statement'!$B$38:$BI$38) -> 2649419 | H64: Peak monthly-model operating deficit through each year
B65: Operating reserve target | C65: =ROUND('Launch Readiness'!$B$6*(INDEX($C$42:$G$42,1,MIN(5,ROUNDUP('Launch Readiness'!$E$6/12,0)))+INDEX($C$56:$G$56,1,MIN(5,ROUNDUP('Launch Readiness'!$E$6/12,0))))/12,0) -> 191027 | D65: =ROUND('Launch Readiness'!$B$6*(INDEX($C$42:$G$42,1,MIN(5,ROUNDUP('Launch Readiness'!$E$6/12,0)))+INDEX($C$56:$G$56,1,MIN(5,ROUNDUP('Launch Readiness'!$E$6/12,0))))/12,0) -> 191027 | E65: =ROUND('Launch Readiness'!$B$6*(INDEX($C$42:$G$42,1,MIN(5,ROUNDUP('Launch Readiness'!$E$6/12,0)))+INDEX($C$56:$G$56,1,MIN(5,ROUNDUP('Launch Readiness'!$E$6/12,0))))/12,0) -> 191027 | F65: =ROUND('Launch Readiness'!$B$6*(INDEX($C$42:$G$42,1,MIN(5,ROUNDUP('Launch Readiness'!$E$6/12,0)))+INDEX($C$56:$G$56,1,MIN(5,ROUNDUP('Launch Readiness'!$E$6/12,0))))/12,0) -> 191027 | G65: =ROUND('Launch Readiness'!$B$6*(INDEX($C$42:$G$42,1,MIN(5,ROUNDUP('Launch Readiness'!$E$6/12,0)))+INDEX($C$56:$G$56,1,MIN(5,ROUNDUP('Launch Readiness'!$E$6/12,0))))/12,0) -> 191027 | H65: Selected reserve months × launch-year payroll and fixed opex
B66: Operating funding ask incl. reserve | C66: =ROUND(C64+C65,0) -> 1259254 | D66: =ROUND(D64+D65,0) -> 2167327 | E66: =ROUND(E64+E65,0) -> 2627716 | F66: =ROUND(F64+F65,0) -> 2840446 | G66: =ROUND(G64+G65,0) -> 2840446 | H66: Monthly-model cash need plus operating reserve
B67: COMMERCIAL SCALE & ACQUISITION CHECK
B68: Line item | C68: Year 1 | D68: Year 2 | E68: Year 3 | F68: Year 4 | G68: Year 5 | H68: Unit / note
B69: Deals / active customer / year | C69: =Assumptions!$F$107 -> 3 | D69: =Assumptions!$F$108 -> 4 | E69: =Assumptions!$F$109 -> 6 | F69: =Assumptions!$F$157 -> 8 | G69: =Assumptions!$F$158 -> 10 | H69: Commercial sanity check from Assumptions
B70: Implied active customers | C70: =IF(C69=0,0,C7/C69) -> 1 | D70: =IF(D69=0,0,D7/D69) -> 125 | E70: =IF(E69=0,0,E7/E69) -> 333.33333 | F70: =IF(F69=0,0,F7/F69) -> 1875 | G70: =IF(G69=0,0,G7/G69) -> 3000 | H70: Deals / deals per active customer
B71: Revenue / deal | C71: =IF(C7=0,0,C18/C7) -> 816.35 | D71: =IF(D7=0,0,D18/D7) -> 809.098 | E71: =IF(E7=0,0,E18/E7) -> 693.952 | F71: =IF(F7=0,0,F18/F7) -> 596.17946 | G71: =IF(G7=0,0,G18/G7) -> 594.42046 | H71: Total revenue / deals
B72: Revenue / active customer | C72: =IF(C70=0,0,C18/C70) -> 2449.05 | D72: =IF(D70=0,0,D18/D70) -> 3236.392 | E72: =IF(E70=0,0,E18/E70) -> 4163.712 | F72: =IF(F70=0,0,F18/F70) -> 4769.4357 | G72: =IF(G70=0,0,G18/G70) -> 5944.2046 | H72: Total revenue / implied customers
B73: VAT registration flag | C73: =IF(C18>Assumptions!$F$58,"Register / confirm VAT treatment","Below threshold") -> Below threshold | D73: =IF(D18>Assumptions!$F$58,"Register / confirm VAT treatment","Below threshold") -> Register / confirm VAT treatment | E73: =IF(E18>Assumptions!$F$58,"Register / confirm VAT treatment","Below threshold") -> Register / confirm VAT treatment | F73: =IF(F18>Assumptions!$F$58,"Register / confirm VAT treatment","Below threshold") -> Register / confirm VAT treatment | G73: =IF(G18>Assumptions!$F$58,"Register / confirm VAT treatment","Below threshold") -> Register / confirm VAT treatment | H73: Revenue > threshold
B74: Gross margin sanity check | C74: =IF(AND(C31>0.9,C23>0),"Review COGS: margin may be optimistic","OK") -> OK | D74: =IF(AND(D31>0.9,D23>0),"Review COGS: margin may be optimistic","OK") -> OK | E74: =IF(AND(E31>0.9,E23>0),"Review COGS: margin may be optimistic","OK") -> OK | F74: =IF(AND(F31>0.9,F23>0),"Review COGS: margin may be optimistic","OK") -> OK | G74: =IF(AND(G31>0.9,G23>0),"Review COGS: margin may be optimistic","OK") -> OK | H74: Warn if >90% and tiered document-verification COGS is nonzero
B75: Gross new customers / Sales-BD-CS FTE | C75: =IF(C36=0,0,C84/C36) -> 3 | D75: =IF(D36=0,0,D84/D36) -> 62.5 | E75: =IF(E36=0,0,E84/E36) -> 111.11111 | F75: =IF(F36=0,0,F84/F36) -> 267.85714 | G75: =IF(G36=0,0,G84/G36) -> 375 | H75: Capacity warning above Assumptions!F190; target volumes still drive revenue
B76: CUSTOMER RETENTION — REQUIRED ACQUISITION CHECK
B77: Line item | C77: Year 1 | D77: Year 2 | E77: Year 3 | F77: Year 4 | G77: Year 5 | H77: Unit / note
B78: Target ending active customers | C78: =C70 -> 1 | D78: =D70 -> 125 | E78: =E70 -> 333.33333 | F78: =F70 -> 1875 | G78: =G70 -> 3000 | H78: Net commercial target implied by annual deal volume.
B79: Beginning active customers | C79: =0 -> 0 | D79: =C84 -> 1 | E79: =D84 -> 125 | F79: =E84 -> 333.33333 | G79: =F84 -> 1875 | H79: Prior-year ending cohort; Year 1 begins at zero.
B80: Annual customer churn rate | C80: =0 -> 0 | D80: =Assumptions!$F$170 -> 0.1 | E80: =Assumptions!$F$170 -> 0.1 | F80: =Assumptions!$F$170 -> 0.1 | G80: =Assumptions!$F$170 -> 0.1 | H80: Prior-year ending cohort; revenue remains driven by the selected deal-volume target.
B81: Churned customers | C81: =C79*C80 -> 0 | D81: =D79*D80 -> 0.1 | E81: =E79*E80 -> 12.5 | F81: =F79*F80 -> 33.333333 | G81: =G79*G80 -> 187.5 | H81: Opening customers expected to leave during the year.
B82: Retained opening customers | C82: =C79-C81 -> 0 | D82: =D79-D81 -> 0.9 | E82: =E79-E81 -> 112.5 | F82: =F79-F81 -> 300 | G82: =G79-G81 -> 1687.5 | H82: Opening customers remaining after churn.
B83: Gross new customers required | C83: =MAX(0,C78-C82) -> 1 | D83: =MAX(0,D78-D82) -> 124.1 | E83: =MAX(0,E78-E82) -> 220.83333 | F83: =MAX(0,F78-F82) -> 1575 | G83: =MAX(0,G78-G82) -> 1312.5 | H83: New logos required to achieve the net ending-customer target.
B84: Ending active customers | C84: =C82+C83 -> 1 | D84: =D82+D83 -> 125 | E84: =E82+E83 -> 333.33333 | F84: =F82+F83 -> 1875 | G84: =G82+G83 -> 3000 | H84: Retained opening customers plus gross new customers.
B85: Bridge check | C85: =C84-C78 -> 0 | D85: =D84-D78 -> 0 | E85: =E84-E78 -> 0 | F85: =F84-F78 -> 0 | G85: =G84-G78 -> 0 | H85: Must equal zero in every year.
B88: RUNWAY RESERVE SENSITIVITY
B89: Metric | C89: 3 | D89: 6 | E89: 9 | H89: Planning sensitivity; base case remains 3 months
B90: Operating reserve | C90: ="£"&ROUND(ROUND(C$89*(INDEX($C$42:$G$42,1,MIN(5,ROUNDUP('Launch Readiness'!$E$6/12,0)))+INDEX($C$56:$G$56,1,MIN(5,ROUNDUP('Launch Readiness'!$E$6/12,0))))/12,0)/1000000,1)&"m" -> £0.2m | D90: ="£"&ROUND(ROUND(D$89*(INDEX($C$42:$G$42,1,MIN(5,ROUNDUP('Launch Readiness'!$E$6/12,0)))+INDEX($C$56:$G$56,1,MIN(5,ROUNDUP('Launch Readiness'!$E$6/12,0))))/12,0)/1000000,1)&"m" -> £0.4m | E90: ="£"&ROUND(ROUND(E$89*(INDEX($C$42:$G$42,1,MIN(5,ROUNDUP('Launch Readiness'!$E$6/12,0)))+INDEX($C$56:$G$56,1,MIN(5,ROUNDUP('Launch Readiness'!$E$6/12,0))))/12,0)/1000000,1)&"m" -> £0.6m | H90: Launch-year payroll plus fixed operating costs
B91: Operating funding need | C91: ="£"&ROUND((MAX($C$64:$G$64)+ROUND(C$89*(INDEX($C$42:$G$42,1,MIN(5,ROUNDUP('Launch Readiness'!$E$6/12,0)))+INDEX($C$56:$G$56,1,MIN(5,ROUNDUP('Launch Readiness'!$E$6/12,0))))/12,0)+'Launch Readiness'!$E$10)/1000000,1)&"m" -> £2.8m | D91: ="£"&ROUND((MAX($C$64:$G$64)+ROUND(D$89*(INDEX($C$42:$G$42,1,MIN(5,ROUNDUP('Launch Readiness'!$E$6/12,0)))+INDEX($C$56:$G$56,1,MIN(5,ROUNDUP('Launch Readiness'!$E$6/12,0))))/12,0)+'Launch Readiness'!$E$10)/1000000,1)&"m" -> £3m | E91: ="£"&ROUND((MAX($C$64:$G$64)+ROUND(E$89*(INDEX($C$42:$G$42,1,MIN(5,ROUNDUP('Launch Readiness'!$E$6/12,0)))+INDEX($C$56:$G$56,1,MIN(5,ROUNDUP('Launch Readiness'!$E$6/12,0))))/12,0)+'Launch Readiness'!$E$10)/1000000,1)&"m" -> £3.2m | H91: Peak monthly operating deficit plus reserve; future VARA capital separate

Sheet Cash Flow Statement
A1: CASH FLOW STATEMENT — MONTHLY 60-MONTH PROJECTION
A2: Base case: paid partner-led DIFC pilot in Month 12; one-month receipt lag; future VARA fees and restricted capital staged separately from the initial operating ask.
G3: Peak monthly-model operating deficit | J3: Month 60 cumulative operating cash
A4: Active scenario | B4: =Assumptions!$D$4 -> BASE | D4: Cash-flow break-even month | E4: =IF(MAX(B38:BI38)<0,"Beyond Month 60",INDEX($B$9:$BI$9,1,MATCH("Reached",B58:BI58,0))) -> Y4 M8 | H4: =ROUND(-MIN(0,B38:BI38),0) -> 2649419 | K4: =ROUND(BI38,0) -> 12947943
A6: Month # | B6: 1 | C6: 2 | D6: 3 | E6: 4 | F6: 5 | G6: 6 | H6: 7 | I6: 8 | J6: 9 | K6: 10 | L6: 11 | M6: 12 | N6: 13 | O6: 14 | P6: 15 | Q6: 16 | R6: 17 | S6: 18 | T6: 19 | U6: 20 | V6: 21 | W6: 22 | X6: 23 | Y6: 24 | Z6: 25 | AA6: 26 | AB6: 27 | AC6: 28 | AD6: 29 | AE6: 30 | AF6: 31 | AG6: 32 | AH6: 33 | AI6: 34 | AJ6: 35 | AK6: 36 | AL6: 37 | AM6: 38 | AN6: 39 | AO6: 40 | AP6: 41 | AQ6: 42 | AR6: 43 | AS6: 44 | AT6: 45 | AU6: 46 | AV6: 47 | AW6: 48 | AX6: 49 | AY6: 50 | AZ6: 51 | BA6: 52 | BB6: 53 | BC6: 54 | BD6: 55 | BE6: 56 | BF6: 57 | BG6: 58 | BH6: 59 | BI6: 60 | BK6: Logic / note
A7: Model year | B7: =ROUNDUP(B$6/12,0) -> 1 | C7: =ROUNDUP(C$6/12,0) -> 1 | D7: =ROUNDUP(D$6/12,0) -> 1 | E7: =ROUNDUP(E$6/12,0) -> 1 | F7: =ROUNDUP(F$6/12,0) -> 1 | G7: =ROUNDUP(G$6/12,0) -> 1 | H7: =ROUNDUP(H$6/12,0) -> 1 | I7: =ROUNDUP(I$6/12,0) -> 1 | ... BI7: =ROUNDUP(BI$6/12,0) -> 5
A8: Month in year | B8: =MOD(B$6-1,12)+1 -> 1 | C8: =MOD(C$6-1,12)+1 -> 2 | D8: =MOD(D$6-1,12)+1 -> 3 | E8: =MOD(E$6-1,12)+1 -> 4 | F8: =MOD(F$6-1,12)+1 -> 5 | G8: =MOD(G$6-1,12)+1 -> 6 | H8: =MOD(H$6-1,12)+1 -> 7 | I8: =MOD(I$6-1,12)+1 -> 8 | ... BI8: =MOD(BI$6-1,12)+1 -> 12
A9: Period | B9: ="Y"&B$7&" M"&B$8 -> Y1 M1 | C9: ="Y"&C$7&" M"&C$8 -> Y1 M2 | D9: ="Y"&D$7&" M"&D$8 -> Y1 M3 | E9: ="Y"&E$7&" M"&E$8 -> Y1 M4 | F9: ="Y"&F$7&" M"&F$8 -> Y1 M5 | G9: ="Y"&G$7&" M"&G$8 -> Y1 M6 | H9: ="Y"&H$7&" M"&H$8 -> Y1 M7 | I9: ="Y"&I$7&" M"&I$8 -> Y1 M8 | ... BI9: ="Y"&BI$7&" M"&BI$8 -> Y5 M12
A11: CASH FLOWS FROM OPERATING ACTIVITIES
A12: Customer receipts | B12: =ROUND(IF(B$6<='Launch Readiness'!$B$7,0,IF((B$6-'Launch Readiness'!$B$7)<'Launch Readiness'!$E$6,0,INDEX('P&L 5yr'!$C$18:$G$18,1,ROUNDUP((B$6-'Launch Readiness'!$B$7)/12,0))/MAX(1,INDEX('Launch Readiness'!$B$26:$F$26,1,ROUNDUP((B$6-'Launch Readiness'!$B$7)/12,0))))),0) -> 0 | C12: =ROUND(IF(C$6<='Launch Readiness'!$B$7,0,IF((C$6-'Launch Readiness'!$B$7)<'Launch Readiness'!$E$6,0,INDEX('P&L 5yr'!$C$18:$G$18,1,ROUNDUP((C$6-'Launch Readiness'!$B$7)/12,0))/MAX(1,INDEX('Launch Readiness'!$B$26:$F$26,1,ROUNDUP((C$6-'Launch Readiness'!$B$7)/12,0))))),0) -> 0 | D12: =ROUND(IF(D$6<='Launch Readiness'!$B$7,0,IF((D$6-'Launch Readiness'!$B$7)<'Launch Readiness'!$E$6,0,INDEX('P&L 5yr'!$C$18:$G$18,1,ROUNDUP((D$6-'Launch Readiness'!$B$7)/12,0))/MAX(1,INDEX('Launch Readiness'!$B$26:$F$26,1,ROUNDUP((D$6-'Launch Readiness'!$B$7)/12,0))))),0) -> 0 | E12: =ROUND(IF(E$6<='Launch Readiness'!$B$7,0,IF((E$6-'Launch Readiness'!$B$7)<'Launch Readiness'!$E$6,0,INDEX('P&L 5yr'!$C$18:$G$18,1,ROUNDUP((E$6-'Launch Readiness'!$B$7)/12,0))/MAX(1,INDEX('Launch Readiness'!$B$26:$F$26,1,ROUNDUP((E$6-'Launch Readiness'!$B$7)/12,0))))),0) -> 0 | F12: =ROUND(IF(F$6<='Launch Readiness'!$B$7,0,IF((F$6-'Launch Readiness'!$B$7)<'Launch Readiness'!$E$6,0,INDEX('P&L 5yr'!$C$18:$G$18,1,ROUNDUP((F$6-'Launch Readiness'!$B$7)/12,0))/MAX(1,INDEX('Launch Readiness'!$B$26:$F$26,1,ROUNDUP((F$6-'Launch Readiness'!$B$7)/12,0))))),0) -> 0 | G12: =ROUND(IF(G$6<='Launch Readiness'!$B$7,0,IF((G$6-'Launch Readiness'!$B$7)<'Launch Readiness'!$E$6,0,INDEX('P&L 5yr'!$C$18:$G$18,1,ROUNDUP((G$6-'Launch Readiness'!$B$7)/12,0))/MAX(1,INDEX('Launch Readiness'!$B$26:$F$26,1,ROUNDUP((G$6-'Launch Readiness'!$B$7)/12,0))))),0) -> 0 | H12: =ROUND(IF(H$6<='Launch Readiness'!$B$7,0,IF((H$6-'Launch Readiness'!$B$7)<'Launch Readiness'!$E$6,0,INDEX('P&L 5yr'!$C$18:$G$18,1,ROUNDUP((H$6-'Launch Readiness'!$B$7)/12,0))/MAX(1,INDEX('Launch Readiness'!$B$26:$F$26,1,ROUNDUP((H$6-'Launch Readiness'!$B$7)/12,0))))),0) -> 0 | I12: =ROUND(IF(I$6<='Launch Readiness'!$B$7,0,IF((I$6-'Launch Readiness'!$B$7)<'Launch Readiness'!$E$6,0,INDEX('P&L 5yr'!$C$18:$G$18,1,ROUNDUP((I$6-'Launch Readiness'!$B$7)/12,0))/MAX(1,INDEX('Launch Readiness'!$B$26:$F$26,1,ROUNDUP((I$6-'Launch Readiness'!$B$7)/12,0))))),0) -> 0 | ... BI12: =ROUND(IF(BI$6<='Launch Readiness'!$B$7,0,IF((BI$6-'Launch Readiness'!$B$7)<'Launch Readiness'!$E$6,0,INDEX('P&L 5yr'!$C$18:$G$18,1,ROUNDUP((BI$6-'Launch Readiness'!$B$7)/12,0))/MAX(1,INDEX('Launch Readiness'!$B$26:$F$26,1,ROUNDUP((BI$6-'Launch Readiness'!$B$7)/12,0))))),0) -> 1486051 | BK12: Revenue receipts are phased after Year 1 pre-revenue months; Years 2-5 are straight-lined monthly.
A13: Variable COGS cash payments | B13: =ROUND(-IF(B$6<'Launch Readiness'!$E$6,0,INDEX('P&L 5yr'!$C$29:$G$29,1,B$7)/MAX(1,INDEX('Launch Readiness'!$B$26:$F$26,1,B$7))),0) -> 0 | C13: =ROUND(-IF(C$6<'Launch Readiness'!$E$6,0,INDEX('P&L 5yr'!$C$29:$G$29,1,C$7)/MAX(1,INDEX('Launch Readiness'!$B$26:$F$26,1,C$7))),0) -> 0 | D13: =ROUND(-IF(D$6<'Launch Readiness'!$E$6,0,INDEX('P&L 5yr'!$C$29:$G$29,1,D$7)/MAX(1,INDEX('Launch Readiness'!$B$26:$F$26,1,D$7))),0) -> 0 | E13: =ROUND(-IF(E$6<'Launch Readiness'!$E$6,0,INDEX('P&L 5yr'!$C$29:$G$29,1,E$7)/MAX(1,INDEX('Launch Readiness'!$B$26:$F$26,1,E$7))),0) -> 0 | F13: =ROUND(-IF(F$6<'Launch Readiness'!$E$6,0,INDEX('P&L 5yr'!$C$29:$G$29,1,F$7)/MAX(1,INDEX('Launch Readiness'!$B$26:$F$26,1,F$7))),0) -> 0 | G13: =ROUND(-IF(G$6<'Launch Readiness'!$E$6,0,INDEX('P&L 5yr'!$C$29:$G$29,1,G$7)/MAX(1,INDEX('Launch Readiness'!$B$26:$F$26,1,G$7))),0) -> 0 | H13: =ROUND(-IF(H$6<'Launch Readiness'!$E$6,0,INDEX('P&L 5yr'!$C$29:$G$29,1,H$7)/MAX(1,INDEX('Launch Readiness'!$B$26:$F$26,1,H$7))),0) -> 0 | I13: =ROUND(-IF(I$6<'Launch Readiness'!$E$6,0,INDEX('P&L 5yr'!$C$29:$G$29,1,I$7)/MAX(1,INDEX('Launch Readiness'!$B$26:$F$26,1,I$7))),0) -> 0 | ... BI13: =ROUND(-IF(BI$6<'Launch Readiness'!$E$6,0,INDEX('P&L 5yr'!$C$29:$G$29,1,BI$7)/MAX(1,INDEX('Launch Readiness'!$B$26:$F$26,1,BI$7))),0) -> -317739 | BK13: COGS follows the same revenue phasing.
A14: Gross operating cash margin | B14: =ROUND(SUM(B12:B13),0) -> 0 | C14: =ROUND(SUM(C12:C13),0) -> 0 | D14: =ROUND(SUM(D12:D13),0) -> 0 | E14: =ROUND(SUM(E12:E13),0) -> 0 | F14: =ROUND(SUM(F12:F13),0) -> 0 | G14: =ROUND(SUM(G12:G13),0) -> 0 | H14: =ROUND(SUM(H12:H13),0) -> 0 | I14: =ROUND(SUM(I12:I13),0) -> 0 | ... BI14: =ROUND(SUM(BI12:BI13),0) -> 1168312
A15: Payroll cash payments | B15: =ROUND((-INDEX('P&L 5yr'!$C$42:$G$42,1,B$7)/12),0) -> -40329 | C15: =ROUND((-INDEX('P&L 5yr'!$C$42:$G$42,1,C$7)/12),0) -> -40329 | D15: =ROUND((-INDEX('P&L 5yr'!$C$42:$G$42,1,D$7)/12),0) -> -40329 | E15: =ROUND((-INDEX('P&L 5yr'!$C$42:$G$42,1,E$7)/12),0) -> -40329 | F15: =ROUND((-INDEX('P&L 5yr'!$C$42:$G$42,1,F$7)/12),0) -> -40329 | G15: =ROUND((-INDEX('P&L 5yr'!$C$42:$G$42,1,G$7)/12),0) -> -40329 | H15: =ROUND((-INDEX('P&L 5yr'!$C$42:$G$42,1,H$7)/12),0) -> -40329 | I15: =ROUND((-INDEX('P&L 5yr'!$C$42:$G$42,1,I$7)/12),0) -> -40329 | ... BI15: =ROUND((-INDEX('P&L 5yr'!$C$42:$G$42,1,BI$7)/12),0) -> -135892 | BK15: Annual payroll from P&L 5yr divided by 12.
A16: Fixed opex cash payments | B16: =ROUND(-((INDEX('P&L 5yr'!$C$56:$G$56,1,B$7)-'Launch Readiness'!$E$9*INDEX('Launch Readiness'!$B$34:$F$34,1,B$7)-'Launch Readiness'!$E$9*'Launch Readiness'!$B$10*INDEX('Launch Readiness'!$B$30:$F$30,1,B$7)-'Launch Readiness'!$E$16*INDEX('Launch Readiness'!$B$32:$F$32,1,B$7))/12+IF(AND(B$6>='Launch Readiness'!$E$6,B$6<'Launch Readiness'!$E$14),'Launch Readiness'!$E$9/12,0)+IF(AND(B$6>='Launch Readiness'!$B$11,B$6<'Launch Readiness'!$E$6),'Launch Readiness'!$E$9*'Launch Readiness'!$B$10/12,0)+IF(B$6>='Launch Readiness'!$E$14,'Launch Readiness'!$E$16/12,0)),0) -> -21253 | C16: =ROUND(-((INDEX('P&L 5yr'!$C$56:$G$56,1,C$7)-'Launch Readiness'!$E$9*INDEX('Launch Readiness'!$B$34:$F$34,1,C$7)-'Launch Readiness'!$E$9*'Launch Readiness'!$B$10*INDEX('Launch Readiness'!$B$30:$F$30,1,C$7)-'Launch Readiness'!$E$16*INDEX('Launch Readiness'!$B$32:$F$32,1,C$7))/12+IF(AND(C$6>='Launch Readiness'!$E$6,C$6<'Launch Readiness'!$E$14),'Launch Readiness'!$E$9/12,0)+IF(AND(C$6>='Launch Readiness'!$B$11,C$6<'Launch Readiness'!$E$6),'Launch Readiness'!$E$9*'Launch Readiness'!$B$10/12,0)+IF(C$6>='Launch Readiness'!$E$14,'Launch Readiness'!$E$16/12,0)),0) -> -23207 | D16: =ROUND(-((INDEX('P&L 5yr'!$C$56:$G$56,1,D$7)-'Launch Readiness'!$E$9*INDEX('Launch Readiness'!$B$34:$F$34,1,D$7)-'Launch Readiness'!$E$9*'Launch Readiness'!$B$10*INDEX('Launch Readiness'!$B$30:$F$30,1,D$7)-'Launch Readiness'!$E$16*INDEX('Launch Readiness'!$B$32:$F$32,1,D$7))/12+IF(AND(D$6>='Launch Readiness'!$E$6,D$6<'Launch Readiness'!$E$14),'Launch Readiness'!$E$9/12,0)+IF(AND(D$6>='Launch Readiness'!$B$11,D$6<'Launch Readiness'!$E$6),'Launch Readiness'!$E$9*'Launch Readiness'!$B$10/12,0)+IF(D$6>='Launch Readiness'!$E$14,'Launch Readiness'!$E$16/12,0)),0) -> -23207 | E16: =ROUND(-((INDEX('P&L 5yr'!$C$56:$G$56,1,E$7)-'Launch Readiness'!$E$9*INDEX('Launch Readiness'!$B$34:$F$34,1,E$7)-'Launch Readiness'!$E$9*'Launch Readiness'!$B$10*INDEX('Launch Readiness'!$B$30:$F$30,1,E$7)-'Launch Readiness'!$E$16*INDEX('Launch Readiness'!$B$32:$F$32,1,E$7))/12+IF(AND(E$6>='Launch Readiness'!$E$6,E$6<'Launch Readiness'!$E$14),'Launch Readiness'!$E$9/12,0)+IF(AND(E$6>='Launch Readiness'!$B$11,E$6<'Launch Readiness'!$E$6),'Launch Readiness'!$E$9*'Launch Readiness'!$B$10/12,0)+IF(E$6>='Launch Readiness'!$E$14,'Launch Readiness'!$E$16/12,0)),0) -> -23207 | F16: =ROUND(-((INDEX('P&L 5yr'!$C$56:$G$56,1,F$7)-'Launch Readiness'!$E$9*INDEX('Launch Readiness'!$B$34:$F$34,1,F$7)-'Launch Readiness'!$E$9*'Launch Readiness'!$B$10*INDEX('Launch Readiness'!$B$30:$F$30,1,F$7)-'Launch Readiness'!$E$16*INDEX('Launch Readiness'!$B$32:$F$32,1,F$7))/12+IF(AND(F$6>='Launch Readiness'!$E$6,F$6<'Launch Readiness'!$E$14),'Launch Readiness'!$E$9/12,0)+IF(AND(F$6>='Launch Readiness'!$B$11,F$6<'Launch Readiness'!$E$6),'Launch Readiness'!$E$9*'Launch Readiness'!$B$10/12,0)+IF(F$6>='Launch Readiness'!$E$14,'Launch Readiness'!$E$16/12,0)),0) -> -23207 | G16: =ROUND(-((INDEX('P&L 5yr'!$C$56:$G$56,1,G$7)-'Launch Readiness'!$E$9*INDEX('Launch Readiness'!$B$34:$F$34,1,G$7)-'Launch Readiness'!$E$9*'Launch Readiness'!$B$10*INDEX('Launch Readiness'!$B$30:$F$30,1,G$7)-'Launch Readiness'!$E$16*INDEX('Launch Readiness'!$B$32:$F$32,1,G$7))/12+IF(AND(G$6>='Launch Readiness'!$E$6,G$6<'Launch Readiness'!$E$14),'Launch Readiness'!$E$9/12,0)+IF(AND(G$6>='Launch Readiness'!$B$11,G$6<'Launch Readiness'!$E$6),'Launch Readiness'!$E$9*'Launch Readiness'!$B$10/12,0)+IF(G$6>='Launch Readiness'!$E$14,'Launch Readiness'!$E$16/12,0)),0) -> -23207 | H16: =ROUND(-((INDEX('P&L 5yr'!$C$56:$G$56,1,H$7)-'Launch Readiness'!$E$9*INDEX('Launch Readiness'!$B$34:$F$34,1,H$7)-'Launch Readiness'!$E$9*'Launch Readiness'!$B$10*INDEX('Launch Readiness'!$B$30:$F$30,1,H$7)-'Launch Readiness'!$E$16*INDEX('Launch Readiness'!$B$32:$F$32,1,H$7))/12+IF(AND(H$6>='Launch Readiness'!$E$6,H$6<'Launch Readiness'!$E$14),'Launch Readiness'!$E$9/12,0)+IF(AND(H$6>='Launch Readiness'!$B$11,H$6<'Launch Readiness'!$E$6),'Launch Readiness'!$E$9*'Launch Readiness'!$B$10/12,0)+IF(H$6>='Launch Readiness'!$E$14,'Launch Readiness'!$E$16/12,0)),0) -> -23207 | I16: =ROUND(-((INDEX('P&L 5yr'!$C$56:$G$56,1,I$7)-'Launch Readiness'!$E$9*INDEX('Launch Readiness'!$B$34:$F$34,1,I$7)-'Launch Readiness'!$E$9*'Launch Readiness'!$B$10*INDEX('Launch Readiness'!$B$30:$F$30,1,I$7)-'Launch Readiness'!$E$16*INDEX('Launch Readiness'!$B$32:$F$32,1,I$7))/12+IF(AND(I$6>='Launch Readiness'!$E$6,I$6<'Launch Readiness'!$E$14),'Launch Readiness'!$E$9/12,0)+IF(AND(I$6>='Launch Readiness'!$B$11,I$6<'Launch Readiness'!$E$6),'Launch Readiness'!$E$9*'Launch Readiness'!$B$10/12,0)+IF(I$6>='Launch Readiness'!$E$14,'Launch Readiness'!$E$16/12,0)),0) -> -23207 | ... BI16: =ROUND(-((INDEX('P&L 5yr'!$C$56:$G$56,1,BI$7)-'Launch Readiness'!$E$9*INDEX('Launch Readiness'!$B$34:$F$34,1,BI$7)-'Launch Readiness'!$E$9*'Launch Readiness'!$B$10*INDEX('Launch Readiness'!$B$30:$F$30,1,BI$7)-'Launch Readiness'!$E$16*INDEX('Launch Readiness'!$B$32:$F$32,1,BI$7))/12+IF(AND(BI$6>='Launch Readiness'!$E$6,BI$6<'Launch Readiness'!$E$14),'Launch Readiness'!$E$9/12,0)+IF(AND(BI$6>='Launch Readiness'!$B$11,BI$6<'Launch Readiness'!$E$6),'Launch Readiness'!$E$9*'Launch Readiness'!$B$10/12,0)+IF(BI$6>='Launch Readiness'!$E$14,'Launch Readiness'!$E$16/12,0)),0) -> -53003 | BK16: Annual fixed opex from P&L 5yr divided by 12.
A17: Startup / one-off cash payments | B17: =ROUND(-(IF(B$6<=6,'Startup 6mo'!$F$44/6,0)+IF(B$6<'Launch Readiness'!$E$6,'Launch Readiness'!$E$8/MAX(1,'Launch Readiness'!$E$7),0)+IF(B$6='Launch Readiness'!$G$14,'Launch Readiness'!$E$15,0)),0) -> -46023 | C17: =ROUND(-(IF(C$6<=6,'Startup 6mo'!$F$44/6,0)+IF(C$6<'Launch Readiness'!$E$6,'Launch Readiness'!$E$8/MAX(1,'Launch Readiness'!$E$7),0)+IF(C$6='Launch Readiness'!$G$14,'Launch Readiness'!$E$15,0)),0) -> -46023 | D17: =ROUND(-(IF(D$6<=6,'Startup 6mo'!$F$44/6,0)+IF(D$6<'Launch Readiness'!$E$6,'Launch Readiness'!$E$8/MAX(1,'Launch Readiness'!$E$7),0)+IF(D$6='Launch Readiness'!$G$14,'Launch Readiness'!$E$15,0)),0) -> -46023 | E17: =ROUND(-(IF(E$6<=6,'Startup 6mo'!$F$44/6,0)+IF(E$6<'Launch Readiness'!$E$6,'Launch Readiness'!$E$8/MAX(1,'Launch Readiness'!$E$7),0)+IF(E$6='Launch Readiness'!$G$14,'Launch Readiness'!$E$15,0)),0) -> -46023 | F17: =ROUND(-(IF(F$6<=6,'Startup 6mo'!$F$44/6,0)+IF(F$6<'Launch Readiness'!$E$6,'Launch Readiness'!$E$8/MAX(1,'Launch Readiness'!$E$7),0)+IF(F$6='Launch Readiness'!$G$14,'Launch Readiness'!$E$15,0)),0) -> -46023 | G17: =ROUND(-(IF(G$6<=6,'Startup 6mo'!$F$44/6,0)+IF(G$6<'Launch Readiness'!$E$6,'Launch Readiness'!$E$8/MAX(1,'Launch Readiness'!$E$7),0)+IF(G$6='Launch Readiness'!$G$14,'Launch Readiness'!$E$15,0)),0) -> -46023 | H17: =ROUND(-(IF(H$6<=6,'Startup 6mo'!$F$44/6,0)+IF(H$6<'Launch Readiness'!$E$6,'Launch Readiness'!$E$8/MAX(1,'Launch Readiness'!$E$7),0)+IF(H$6='Launch Readiness'!$G$14,'Launch Readiness'!$E$15,0)),0) -> -5455 | I17: =ROUND(-(IF(I$6<=6,'Startup 6mo'!$F$44/6,0)+IF(I$6<'Launch Readiness'!$E$6,'Launch Readiness'!$E$8/MAX(1,'Launch Readiness'!$E$7),0)+IF(I$6='Launch Readiness'!$G$14,'Launch Readiness'!$E$15,0)),0) -> -5455 | ... BI17: =ROUND(-(IF(BI$6<=6,'Startup 6mo'!$F$44/6,0)+IF(BI$6<'Launch Readiness'!$E$6,'Launch Readiness'!$E$8/MAX(1,'Launch Readiness'!$E$7),0)+IF(BI$6='Launch Readiness'!$G$14,'Launch Readiness'!$E$15,0)),0) -> 0 | BK17: Startup 6mo / Year 1 one-off spend paid over months 1-6.
A18: Operating working capital (client escrow excluded) | B18: =ROUND(0,0) -> 0 | C18: =ROUND(0,0) -> 0 | D18: =ROUND(0,0) -> 0 | E18: =ROUND(0,0) -> 0 | F18: =ROUND(0,0) -> 0 | G18: =ROUND(0,0) -> 0 | H18: =ROUND(0,0) -> 0 | I18: =ROUND(0,0) -> 0 | ... BI18: =ROUND(0,0) -> 0 | BK18: Client escrow funds remain restricted/off-balance-sheet; no settlement float benefit is modelled.
A19: Net cash from operating activities | B19: =ROUND(B14+SUM(B15:B18),0) -> -107605 | C19: =ROUND(C14+SUM(C15:C18),0) -> -109559 | D19: =ROUND(D14+SUM(D15:D18),0) -> -109559 | E19: =ROUND(E14+SUM(E15:E18),0) -> -109559 | F19: =ROUND(F14+SUM(F15:F18),0) -> -109559 | G19: =ROUND(G14+SUM(G15:G18),0) -> -109559 | H19: =ROUND(H14+SUM(H15:H18),0) -> -68991 | I19: =ROUND(I14+SUM(I15:I18),0) -> -68991 | ... BI19: =ROUND(BI14+SUM(BI15:BI18),0) -> 979417
A21: CASH FLOWS FROM INVESTING ACTIVITIES
A22: Capitalised development / capex | B22: =0 -> 0 | C22: =0 -> 0 | D22: =0 -> 0 | E22: =0 -> 0 | F22: =0 -> 0 | G22: =0 -> 0 | H22: =0 -> 0 | I22: =0 -> 0 | ... BI22: =0 -> 0
A23: Net cash from investing activities | B23: =ROUND(SUM(B21:B22),0) -> 0 | C23: =ROUND(SUM(C21:C22),0) -> 0 | D23: =ROUND(SUM(D21:D22),0) -> 0 | E23: =ROUND(SUM(E21:E22),0) -> 0 | F23: =ROUND(SUM(F21:F22),0) -> 0 | G23: =ROUND(SUM(G21:G22),0) -> 0 | H23: =ROUND(SUM(H21:H22),0) -> 0 | I23: =ROUND(SUM(I21:I22),0) -> 0 | ... BI23: =ROUND(SUM(BI21:BI22),0) -> 0
A25: CASH FLOWS FROM FINANCING ACTIVITIES
A26: External funding raised — operating need plus separately timed restricted capital | B26: =ROUND(IF(B$8=1,IF(B$7=1,'P&L 5yr'!$C$66,MAX(0,INDEX('P&L 5yr'!$C$66:$G$66,1,B$7)-INDEX('P&L 5yr'!$C$66:$G$66,1,B$7-1))),0)+IF(B$6=MAX(1,'Launch Readiness'!$E$6-1),'Launch Readiness'!$E$10,0)+IF(B$6=MAX(1,'Launch Readiness'!$E$14-1),'Launch Readiness'!$E$17,0),0) -> 1259254 | C26: =ROUND(IF(C$8=1,IF(C$7=1,'P&L 5yr'!$C$66,MAX(0,INDEX('P&L 5yr'!$C$66:$G$66,1,C$7)-INDEX('P&L 5yr'!$C$66:$G$66,1,C$7-1))),0)+IF(C$6=MAX(1,'Launch Readiness'!$E$6-1),'Launch Readiness'!$E$10,0)+IF(C$6=MAX(1,'Launch Readiness'!$E$14-1),'Launch Readiness'!$E$17,0),0) -> 0 | D26: =ROUND(IF(D$8=1,IF(D$7=1,'P&L 5yr'!$C$66,MAX(0,INDEX('P&L 5yr'!$C$66:$G$66,1,D$7)-INDEX('P&L 5yr'!$C$66:$G$66,1,D$7-1))),0)+IF(D$6=MAX(1,'Launch Readiness'!$E$6-1),'Launch Readiness'!$E$10,0)+IF(D$6=MAX(1,'Launch Readiness'!$E$14-1),'Launch Readiness'!$E$17,0),0) -> 0 | E26: =ROUND(IF(E$8=1,IF(E$7=1,'P&L 5yr'!$C$66,MAX(0,INDEX('P&L 5yr'!$C$66:$G$66,1,E$7)-INDEX('P&L 5yr'!$C$66:$G$66,1,E$7-1))),0)+IF(E$6=MAX(1,'Launch Readiness'!$E$6-1),'Launch Readiness'!$E$10,0)+IF(E$6=MAX(1,'Launch Readiness'!$E$14-1),'Launch Readiness'!$E$17,0),0) -> 0 | F26: =ROUND(IF(F$8=1,IF(F$7=1,'P&L 5yr'!$C$66,MAX(0,INDEX('P&L 5yr'!$C$66:$G$66,1,F$7)-INDEX('P&L 5yr'!$C$66:$G$66,1,F$7-1))),0)+IF(F$6=MAX(1,'Launch Readiness'!$E$6-1),'Launch Readiness'!$E$10,0)+IF(F$6=MAX(1,'Launch Readiness'!$E$14-1),'Launch Readiness'!$E$17,0),0) -> 0 | G26: =ROUND(IF(G$8=1,IF(G$7=1,'P&L 5yr'!$C$66,MAX(0,INDEX('P&L 5yr'!$C$66:$G$66,1,G$7)-INDEX('P&L 5yr'!$C$66:$G$66,1,G$7-1))),0)+IF(G$6=MAX(1,'Launch Readiness'!$E$6-1),'Launch Readiness'!$E$10,0)+IF(G$6=MAX(1,'Launch Readiness'!$E$14-1),'Launch Readiness'!$E$17,0),0) -> 0 | H26: =ROUND(IF(H$8=1,IF(H$7=1,'P&L 5yr'!$C$66,MAX(0,INDEX('P&L 5yr'!$C$66:$G$66,1,H$7)-INDEX('P&L 5yr'!$C$66:$G$66,1,H$7-1))),0)+IF(H$6=MAX(1,'Launch Readiness'!$E$6-1),'Launch Readiness'!$E$10,0)+IF(H$6=MAX(1,'Launch Readiness'!$E$14-1),'Launch Readiness'!$E$17,0),0) -> 0 | I26: =ROUND(IF(I$8=1,IF(I$7=1,'P&L 5yr'!$C$66,MAX(0,INDEX('P&L 5yr'!$C$66:$G$66,1,I$7)-INDEX('P&L 5yr'!$C$66:$G$66,1,I$7-1))),0)+IF(I$6=MAX(1,'Launch Readiness'!$E$6-1),'Launch Readiness'!$E$10,0)+IF(I$6=MAX(1,'Launch Readiness'!$E$14-1),'Launch Readiness'!$E$17,0),0) -> 0 | ... BI26: =ROUND(IF(BI$8=1,IF(BI$7=1,'P&L 5yr'!$C$66,MAX(0,INDEX('P&L 5yr'!$C$66:$G$66,1,BI$7)-INDEX('P&L 5yr'!$C$66:$G$66,1,BI$7-1))),0)+IF(BI$6=MAX(1,'Launch Readiness'!$E$6-1),'Launch Readiness'!$E$10,0)+IF(BI$6=MAX(1,'Launch Readiness'!$E$14-1),'Launch Readiness'!$E$17,0),0) -> 0 | BK26: Raised in month 1 of any year when the cumulative funding ask steps up.
A27: Restricted regulatory capital placed | B27: =ROUND(-IF(B$6=MAX(1,'Launch Readiness'!$E$6-1),'Launch Readiness'!$E$10,0)-IF(B$6=MAX(1,'Launch Readiness'!$E$14-1),'Launch Readiness'!$E$17,0),0) -> 0 | C27: =ROUND(-IF(C$6=MAX(1,'Launch Readiness'!$E$6-1),'Launch Readiness'!$E$10,0)-IF(C$6=MAX(1,'Launch Readiness'!$E$14-1),'Launch Readiness'!$E$17,0),0) -> 0 | D27: =ROUND(-IF(D$6=MAX(1,'Launch Readiness'!$E$6-1),'Launch Readiness'!$E$10,0)-IF(D$6=MAX(1,'Launch Readiness'!$E$14-1),'Launch Readiness'!$E$17,0),0) -> 0 | E27: =ROUND(-IF(E$6=MAX(1,'Launch Readiness'!$E$6-1),'Launch Readiness'!$E$10,0)-IF(E$6=MAX(1,'Launch Readiness'!$E$14-1),'Launch Readiness'!$E$17,0),0) -> 0 | F27: =ROUND(-IF(F$6=MAX(1,'Launch Readiness'!$E$6-1),'Launch Readiness'!$E$10,0)-IF(F$6=MAX(1,'Launch Readiness'!$E$14-1),'Launch Readiness'!$E$17,0),0) -> 0 | G27: =ROUND(-IF(G$6=MAX(1,'Launch Readiness'!$E$6-1),'Launch Readiness'!$E$10,0)-IF(G$6=MAX(1,'Launch Readiness'!$E$14-1),'Launch Readiness'!$E$17,0),0) -> 0 | H27: =ROUND(-IF(H$6=MAX(1,'Launch Readiness'!$E$6-1),'Launch Readiness'!$E$10,0)-IF(H$6=MAX(1,'Launch Readiness'!$E$14-1),'Launch Readiness'!$E$17,0),0) -> 0 | I27: =ROUND(-IF(I$6=MAX(1,'Launch Readiness'!$E$6-1),'Launch Readiness'!$E$10,0)-IF(I$6=MAX(1,'Launch Readiness'!$E$14-1),'Launch Readiness'!$E$17,0),0) -> 0 | ... BI27: =ROUND(-IF(BI$6=MAX(1,'Launch Readiness'!$E$6-1),'Launch Readiness'!$E$10,0)-IF(BI$6=MAX(1,'Launch Readiness'!$E$14-1),'Launch Readiness'!$E$17,0),0) -> 0 | BK27: Funding-only contingency reserve is separated from unrestricted operating cash.
A28: Net cash from financing activities | B28: =ROUND(SUM(B26:B27),0) -> 1259254 | C28: =ROUND(SUM(C26:C27),0) -> 0 | D28: =ROUND(SUM(D26:D27),0) -> 0 | E28: =ROUND(SUM(E26:E27),0) -> 0 | F28: =ROUND(SUM(F26:F27),0) -> 0 | G28: =ROUND(SUM(G26:G27),0) -> 0 | H28: =ROUND(SUM(H26:H27),0) -> 0 | I28: =ROUND(SUM(I26:I27),0) -> 0 | ... BI28: =ROUND(SUM(BI26:BI27),0) -> 0
A30: CASH RECONCILIATION
A31: Opening unrestricted cash | B31: =0 -> 0 | C31: =B33 -> 1151649 | D31: =C33 -> 1042090 | E31: =D33 -> 932531 | F31: =E33 -> 822972 | G31: =F33 -> 713413 | H31: =G33 -> 603854 | I31: =H33 -> 534863 | J31: =I33 -> 465872 | ... BI31: =BH33 -> 14808972
A32: Net change in unrestricted cash | B32: =ROUND(B19+B23+B28,0) -> 1151649 | C32: =ROUND(C19+C23+C28,0) -> -109559 | D32: =ROUND(D19+D23+D28,0) -> -109559 | E32: =ROUND(E19+E23+E28,0) -> -109559 | F32: =ROUND(F19+F23+F28,0) -> -109559 | G32: =ROUND(G19+G23+G28,0) -> -109559 | H32: =ROUND(H19+H23+H28,0) -> -68991 | I32: =ROUND(I19+I23+I28,0) -> -68991 | ... BI32: =ROUND(BI19+BI23+BI28,0) -> 979417
A33: Closing unrestricted cash | B33: =ROUND(B31+B32,0) -> 1151649 | C33: =ROUND(C31+C32,0) -> 1042090 | D33: =ROUND(D31+D32,0) -> 932531 | E33: =ROUND(E31+E32,0) -> 822972 | F33: =ROUND(F31+F32,0) -> 713413 | G33: =ROUND(G31+G32,0) -> 603854 | H33: =ROUND(H31+H32,0) -> 534863 | I33: =ROUND(I31+I32,0) -> 465872 | ... BI33: =ROUND(BI31+BI32,0) -> 15788389
A34: Restricted regulatory capital held | B34: =ROUND(-SUM($B$27:B$27),0) -> 0 | C34: =ROUND(-SUM($B$27:C$27),0) -> 0 | D34: =ROUND(-SUM($B$27:D$27),0) -> 0 | E34: =ROUND(-SUM($B$27:E$27),0) -> 0 | F34: =ROUND(-SUM($B$27:F$27),0) -> 0 | G34: =ROUND(-SUM($B$27:G$27),0) -> 0 | H34: =ROUND(-SUM($B$27:H$27),0) -> 0 | I34: =ROUND(-SUM($B$27:I$27),0) -> 0 | ... BI34: =ROUND(-SUM($B$27:BI$27),0) -> 319095
A35: Total cash incl. restricted capital | B35: =ROUND(B33+B34,0) -> 1151649 | C35: =ROUND(C33+C34,0) -> 1042090 | D35: =ROUND(D33+D34,0) -> 932531 | E35: =ROUND(E33+E34,0) -> 822972 | F35: =ROUND(F33+F34,0) -> 713413 | G35: =ROUND(G33+G34,0) -> 603854 | H35: =ROUND(H33+H34,0) -> 534863 | I35: =ROUND(I33+I34,0) -> 465872 | ... BI35: =ROUND(BI33+BI34,0) -> 16107484
A37: BREAKEVEN / RUNWAY
A38: Operating cumulative cash flow before financing | B38: =ROUND(B19+B23,0) -> -107605 | C38: =ROUND(B38+C19+C23,0) -> -217164 | D38: =ROUND(C38+D19+D23,0) -> -326723 | E38: =ROUND(D38+E19+E23,0) -> -436282 | F38: =ROUND(E38+F19+F23,0) -> -545841 | G38: =ROUND(F38+G19+G23,0) -> -655400 | H38: =ROUND(G38+H19+H23,0) -> -724391 | I38: =ROUND(H38+I19+I23,0) -> -793382 | J38: =ROUND(I38+J19+J23,0) -> -862373 | ... BI38: =ROUND(BH38+BI19+BI23,0) -> 12947943 | BK38: This is the monthly cash-flow break-even test before external financing.
A39: Cash-flow break-even status | B39: =IF(B38>=0,"Reached","Not yet") -> Not yet | C39: =IF(C38>=0,"Reached","Not yet") -> Not yet | D39: =IF(D38>=0,"Reached","Not yet") -> Not yet | E39: =IF(E38>=0,"Reached","Not yet") -> Not yet | F39: =IF(F38>=0,"Reached","Not yet") -> Not yet | G39: =IF(G38>=0,"Reached","Not yet") -> Not yet | H39: =IF(H38>=0,"Reached","Not yet") -> Not yet | I39: =IF(I38>=0,"Reached","Not yet") -> Not yet | ... BI39: =IF(BI38>=0,"Reached","Not yet") -> Reached
A40: Runway warning | B40: =IF(B33<0,"Cash shortfall","Funded") -> Funded | C40: =IF(C33<0,"Cash shortfall","Funded") -> Funded | D40: =IF(D33<0,"Cash shortfall","Funded") -> Funded | E40: =IF(E33<0,"Cash shortfall","Funded") -> Funded | F40: =IF(F33<0,"Cash shortfall","Funded") -> Funded | G40: =IF(G33<0,"Cash shortfall","Funded") -> Funded | H40: =IF(H33<0,"Cash shortfall","Funded") -> Funded | I40: =IF(I33<0,"Cash shortfall","Funded") -> Funded | ... BI40: =IF(BI33<0,"Cash shortfall","Funded") -> Funded
A43: Scenario comparison - monthly cash-flow break-even
A44: Scenario | B44: Cash-flow break-even month | C44: Peak cumulative operating deficit | D44: Month 60 cumulative operating cash | E44: EBITDA break-even | F44: Funding ask incl. reserve
A45: Low | B45: =IF(MAX(B52:BI52)<0,"Beyond Month 60",INDEX($B$9:$BI$9,1,MATCH("Reached",B55:BI55,0))) -> Beyond Month 60 | C45: =-MIN(0,B52:BI52) -> 3915862 | D45: =BI52 -> -2924278 | E45: =IF('Scenario Engine'!$B$57>=0,"Year 1",IF('Scenario Engine'!$C$57>=0,"Year 2",IF('Scenario Engine'!$D$57>=0,"Year 3",IF('Scenario Engine'!$E$57>=0,"Year 4",IF('Scenario Engine'!$F$57>=0,"Year 5","Beyond Year 5"))))) -> Year 5 | F45: =MAX('Scenario Engine'!$B$60:$F$60) -> 4106889
A46: Base | B46: =IF(MAX(B53:BI53)<0,"Beyond Month 60",INDEX($B$9:$BI$9,1,MATCH("Reached",B56:BI56,0))) -> Y4 M8 | C46: =-MIN(0,B53:BI53) -> 2649418 | D46: =BI53 -> 12947967 | E46: =IF('Scenario Engine'!$H$57>=0,"Year 1",IF('Scenario Engine'!$I$57>=0,"Year 2",IF('Scenario Engine'!$J$57>=0,"Year 3",IF('Scenario Engine'!$K$57>=0,"Year 4",IF('Scenario Engine'!$L$57>=0,"Year 5","Beyond Year 5"))))) -> Year 4 | F46: =MAX('Scenario Engine'!$H$60:$L$60) -> 2840446
A47: High | B47: =IF(MAX(B54:BI54)<0,"Beyond Month 60",INDEX($B$9:$BI$9,1,MATCH("Reached",B57:BI57,0))) -> Y4 M4 | C47: =-MIN(0,B54:BI54) -> 1946199 | D47: =BI54 -> 33921710 | E47: =IF('Scenario Engine'!$N$57>=0,"Year 1",IF('Scenario Engine'!$O$57>=0,"Year 2",IF('Scenario Engine'!$P$57>=0,"Year 3",IF('Scenario Engine'!$Q$57>=0,"Year 4",IF('Scenario Engine'!$R$57>=0,"Year 5","Beyond Year 5"))))) -> Year 3 | F47: =MAX('Scenario Engine'!$N$60:$R$60) -> 2137226
A49: Scenario cumulative operating cash flow before financing - monthly
A51: Scenario | B51: ='Cash Flow Statement'!B9 -> Y1 M1 | C51: ='Cash Flow Statement'!C9 -> Y1 M2 | D51: ='Cash Flow Statement'!D9 -> Y1 M3 | E51: ='Cash Flow Statement'!E9 -> Y1 M4 | F51: ='Cash Flow Statement'!F9 -> Y1 M5 | G51: ='Cash Flow Statement'!G9 -> Y1 M6 | H51: ='Cash Flow Statement'!H9 -> Y1 M7 | I51: ='Cash Flow Statement'!I9 -> Y1 M8 | ... BI51: ='Cash Flow Statement'!BI9 -> Y5 M12
A52: Low | B52: =ROUND((IF(B$6<='Launch Readiness'!$B$7,0,IF((B$6-'Launch Readiness'!$B$7)<'Launch Readiness'!$E$6,0,INDEX('Scenario Engine'!$B$30:$F$30,1,ROUNDUP((B$6-'Launch Readiness'!$B$7)/12,0))/MAX(1,INDEX('Launch Readiness'!$B$26:$F$26,1,ROUNDUP((B$6-'Launch Readiness'!$B$7)/12,0))))))-IF(B$6<'Launch Readiness'!$E$6,0,INDEX('Scenario Engine'!$B$47:$F$47,1,B$7)/MAX(1,INDEX('Launch Readiness'!$B$26:$F$26,1,B$7)))-INDEX('Scenario Engine'!$B$52:$F$52,1,B$7)/12-((INDEX('Scenario Engine'!$B$53:$F$53,1,B$7)-'Launch Readiness'!$E$9*INDEX('Launch Readiness'!$B$34:$F$34,1,B$7)-'Launch Readiness'!$E$9*'Launch Readiness'!$B$10*INDEX('Launch Readiness'!$B$30:$F$30,1,B$7)-'Launch Readiness'!$E$16*INDEX('Launch Readiness'!$B$32:$F$32,1,B$7))/12+IF(AND(B$6>='Launch Readiness'!$E$6,B$6<'Launch Readiness'!$E$14),'Launch Readiness'!$E$9/12,0)+IF(AND(B$6>='Launch Readiness'!$B$11,B$6<'Launch Readiness'!$E$6),'Launch Readiness'!$E$9*'Launch Readiness'!$B$10/12,0)+IF(B$6>='Launch Readiness'!$E$14,'Launch Readiness'!$E$16/12,0))-(IF(B$6<=6,'Startup 6mo'!$F$44/6,0)+IF(B$6<'Launch Readiness'!$E$6,'Launch Readiness'!$E$8/MAX(1,'Launch Readiness'!$E$7),0)+IF(B$6='Launch Readiness'!$G$14,'Launch Readiness'!$E$15,0)),0) -> -107605 | C52: =ROUND(B52+(IF(C$6<='Launch Readiness'!$B$7,0,IF((C$6-'Launch Readiness'!$B$7)<'Launch Readiness'!$E$6,0,INDEX('Scenario Engine'!$B$30:$F$30,1,ROUNDUP((C$6-'Launch Readiness'!$B$7)/12,0))/MAX(1,INDEX('Launch Readiness'!$B$26:$F$26,1,ROUNDUP((C$6-'Launch Readiness'!$B$7)/12,0))))))-IF(C$6<'Launch Readiness'!$E$6,0,INDEX('Scenario Engine'!$B$47:$F$47,1,C$7)/MAX(1,INDEX('Launch Readiness'!$B$26:$F$26,1,C$7)))-INDEX('Scenario Engine'!$B$52:$F$52,1,C$7)/12-((INDEX('Scenario Engine'!$B$53:$F$53,1,C$7)-'Launch Readiness'!$E$9*INDEX('Launch Readiness'!$B$34:$F$34,1,C$7)-'Launch Readiness'!$E$9*'Launch Readiness'!$B$10*INDEX('Launch Readiness'!$B$30:$F$30,1,C$7)-'Launch Readiness'!$E$16*INDEX('Launch Readiness'!$B$32:$F$32,1,C$7))/12+IF(AND(C$6>='Launch Readiness'!$E$6,C$6<'Launch Readiness'!$E$14),'Launch Readiness'!$E$9/12,0)+IF(AND(C$6>='Launch Readiness'!$B$11,C$6<'Launch Readiness'!$E$6),'Launch Readiness'!$E$9*'Launch Readiness'!$B$10/12,0)+IF(C$6>='Launch Readiness'!$E$14,'Launch Readiness'!$E$16/12,0))-(IF(C$6<=6,'Startup 6mo'!$F$44/6,0)+IF(C$6<'Launch Readiness'!$E$6,'Launch Readiness'!$E$8/MAX(1,'Launch Readiness'!$E$7),0)+IF(C$6='Launch Readiness'!$G$14,'Launch Readiness'!$E$15,0)),0) -> -217164 | D52: =ROUND(C52+(IF(D$6<='Launch Readiness'!$B$7,0,IF((D$6-'Launch Readiness'!$B$7)<'Launch Readiness'!$E$6,0,INDEX('Scenario Engine'!$B$30:$F$30,1,ROUNDUP((D$6-'Launch Readiness'!$B$7)/12,0))/MAX(1,INDEX('Launch Readiness'!$B$26:$F$26,1,ROUNDUP((D$6-'Launch Readiness'!$B$7)/12,0))))))-IF(D$6<'Launch Readiness'!$E$6,0,INDEX('Scenario Engine'!$B$47:$F$47,1,D$7)/MAX(1,INDEX('Launch Readiness'!$B$26:$F$26,1,D$7)))-INDEX('Scenario Engine'!$B$52:$F$52,1,D$7)/12-((INDEX('Scenario Engine'!$B$53:$F$53,1,D$7)-'Launch Readiness'!$E$9*INDEX('Launch Readiness'!$B$34:$F$34,1,D$7)-'Launch Readiness'!$E$9*'Launch Readiness'!$B$10*INDEX('Launch Readiness'!$B$30:$F$30,1,D$7)-'Launch Readiness'!$E$16*INDEX('Launch Readiness'!$B$32:$F$32,1,D$7))/12+IF(AND(D$6>='Launch Readiness'!$E$6,D$6<'Launch Readiness'!$E$14),'Launch Readiness'!$E$9/12,0)+IF(AND(D$6>='Launch Readiness'!$B$11,D$6<'Launch Readiness'!$E$6),'Launch Readiness'!$E$9*'Launch Readiness'!$B$10/12,0)+IF(D$6>='Launch Readiness'!$E$14,'Launch Readiness'!$E$16/12,0))-(IF(D$6<=6,'Startup 6mo'!$F$44/6,0)+IF(D$6<'Launch Readiness'!$E$6,'Launch Readiness'!$E$8/MAX(1,'Launch Readiness'!$E$7),0)+IF(D$6='Launch Readiness'!$G$14,'Launch Readiness'!$E$15,0)),0) -> -326723 | E52: =ROUND(D52+(IF(E$6<='Launch Readiness'!$B$7,0,IF((E$6-'Launch Readiness'!$B$7)<'Launch Readiness'!$E$6,0,INDEX('Scenario Engine'!$B$30:$F$30,1,ROUNDUP((E$6-'Launch Readiness'!$B$7)/12,0))/MAX(1,INDEX('Launch Readiness'!$B$26:$F$26,1,ROUNDUP((E$6-'Launch Readiness'!$B$7)/12,0))))))-IF(E$6<'Launch Readiness'!$E$6,0,INDEX('Scenario Engine'!$B$47:$F$47,1,E$7)/MAX(1,INDEX('Launch Readiness'!$B$26:$F$26,1,E$7)))-INDEX('Scenario Engine'!$B$52:$F$52,1,E$7)/12-((INDEX('Scenario Engine'!$B$53:$F$53,1,E$7)-'Launch Readiness'!$E$9*INDEX('Launch Readiness'!$B$34:$F$34,1,E$7)-'Launch Readiness'!$E$9*'Launch Readiness'!$B$10*INDEX('Launch Readiness'!$B$30:$F$30,1,E$7)-'Launch Readiness'!$E$16*INDEX('Launch Readiness'!$B$32:$F$32,1,E$7))/12+IF(AND(E$6>='Launch Readiness'!$E$6,E$6<'Launch Readiness'!$E$14),'Launch Readiness'!$E$9/12,0)+IF(AND(E$6>='Launch Readiness'!$B$11,E$6<'Launch Readiness'!$E$6),'Launch Readiness'!$E$9*'Launch Readiness'!$B$10/12,0)+IF(E$6>='Launch Readiness'!$E$14,'Launch Readiness'!$E$16/12,0))-(IF(E$6<=6,'Startup 6mo'!$F$44/6,0)+IF(E$6<'Launch Readiness'!$E$6,'Launch Readiness'!$E$8/MAX(1,'Launch Readiness'!$E$7),0)+IF(E$6='Launch Readiness'!$G$14,'Launch Readiness'!$E$15,0)),0) -> -436282 | F52: =ROUND(E52+(IF(F$6<='Launch Readiness'!$B$7,0,IF((F$6-'Launch Readiness'!$B$7)<'Launch Readiness'!$E$6,0,INDEX('Scenario Engine'!$B$30:$F$30,1,ROUNDUP((F$6-'Launch Readiness'!$B$7)/12,0))/MAX(1,INDEX('Launch Readiness'!$B$26:$F$26,1,ROUNDUP((F$6-'Launch Readiness'!$B$7)/12,0))))))-IF(F$6<'Launch Readiness'!$E$6,0,INDEX('Scenario Engine'!$B$47:$F$47,1,F$7)/MAX(1,INDEX('Launch Readiness'!$B$26:$F$26,1,F$7)))-INDEX('Scenario Engine'!$B$52:$F$52,1,F$7)/12-((INDEX('Scenario Engine'!$B$53:$F$53,1,F$7)-'Launch Readiness'!$E$9*INDEX('Launch Readiness'!$B$34:$F$34,1,F$7)-'Launch Readiness'!$E$9*'Launch Readiness'!$B$10*INDEX('Launch Readiness'!$B$30:$F$30,1,F$7)-'Launch Readiness'!$E$16*INDEX('Launch Readiness'!$B$32:$F$32,1,F$7))/12+IF(AND(F$6>='Launch Readiness'!$E$6,F$6<'Launch Readiness'!$E$14),'Launch Readiness'!$E$9/12,0)+IF(AND(F$6>='Launch Readiness'!$B$11,F$6<'Launch Readiness'!$E$6),'Launch Readiness'!$E$9*'Launch Readiness'!$B$10/12,0)+IF(F$6>='Launch Readiness'!$E$14,'Launch Readiness'!$E$16/12,0))-(IF(F$6<=6,'Startup 6mo'!$F$44/6,0)+IF(F$6<'Launch Readiness'!$E$6,'Launch Readiness'!$E$8/MAX(1,'Launch Readiness'!$E$7),0)+IF(F$6='Launch Readiness'!$G$14,'Launch Readiness'!$E$15,0)),0) -> -545841 | G52: =ROUND(F52+(IF(G$6<='Launch Readiness'!$B$7,0,IF((G$6-'Launch Readiness'!$B$7)<'Launch Readiness'!$E$6,0,INDEX('Scenario Engine'!$B$30:$F$30,1,ROUNDUP((G$6-'Launch Readiness'!$B$7)/12,0))/MAX(1,INDEX('Launch Readiness'!$B$26:$F$26,1,ROUNDUP((G$6-'Launch Readiness'!$B$7)/12,0))))))-IF(G$6<'Launch Readiness'!$E$6,0,INDEX('Scenario Engine'!$B$47:$F$47,1,G$7)/MAX(1,INDEX('Launch Readiness'!$B$26:$F$26,1,G$7)))-INDEX('Scenario Engine'!$B$52:$F$52,1,G$7)/12-((INDEX('Scenario Engine'!$B$53:$F$53,1,G$7)-'Launch Readiness'!$E$9*INDEX('Launch Readiness'!$B$34:$F$34,1,G$7)-'Launch Readiness'!$E$9*'Launch Readiness'!$B$10*INDEX('Launch Readiness'!$B$30:$F$30,1,G$7)-'Launch Readiness'!$E$16*INDEX('Launch Readiness'!$B$32:$F$32,1,G$7))/12+IF(AND(G$6>='Launch Readiness'!$E$6,G$6<'Launch Readiness'!$E$14),'Launch Readiness'!$E$9/12,0)+IF(AND(G$6>='Launch Readiness'!$B$11,G$6<'Launch Readiness'!$E$6),'Launch Readiness'!$E$9*'Launch Readiness'!$B$10/12,0)+IF(G$6>='Launch Readiness'!$E$14,'Launch Readiness'!$E$16/12,0))-(IF(G$6<=6,'Startup 6mo'!$F$44/6,0)+IF(G$6<'Launch Readiness'!$E$6,'Launch Readiness'!$E$8/MAX(1,'Launch Readiness'!$E$7),0)+IF(G$6='Launch Readiness'!$G$14,'Launch Readiness'!$E$15,0)),0) -> -655400 | H52: =ROUND(G52+(IF(H$6<='Launch Readiness'!$B$7,0,IF((H$6-'Launch Readiness'!$B$7)<'Launch Readiness'!$E$6,0,INDEX('Scenario Engine'!$B$30:$F$30,1,ROUNDUP((H$6-'Launch Readiness'!$B$7)/12,0))/MAX(1,INDEX('Launch Readiness'!$B$26:$F$26,1,ROUNDUP((H$6-'Launch Readiness'!$B$7)/12,0))))))-IF(H$6<'Launch Readiness'!$E$6,0,INDEX('Scenario Engine'!$B$47:$F$47,1,H$7)/MAX(1,INDEX('Launch Readiness'!$B$26:$F$26,1,H$7)))-INDEX('Scenario Engine'!$B$52:$F$52,1,H$7)/12-((INDEX('Scenario Engine'!$B$53:$F$53,1,H$7)-'Launch Readiness'!$E$9*INDEX('Launch Readiness'!$B$34:$F$34,1,H$7)-'Launch Readiness'!$E$9*'Launch Readiness'!$B$10*INDEX('Launch Readiness'!$B$30:$F$30,1,H$7)-'Launch Readiness'!$E$16*INDEX('Launch Readiness'!$B$32:$F$32,1,H$7))/12+IF(AND(H$6>='Launch Readiness'!$E$6,H$6<'Launch Readiness'!$E$14),'Launch Readiness'!$E$9/12,0)+IF(AND(H$6>='Launch Readiness'!$B$11,H$6<'Launch Readiness'!$E$6),'Launch Readiness'!$E$9*'Launch Readiness'!$B$10/12,0)+IF(H$6>='Launch Readiness'!$E$14,'Launch Readiness'!$E$16/12,0))-(IF(H$6<=6,'Startup 6mo'!$F$44/6,0)+IF(H$6<'Launch Readiness'!$E$6,'Launch Readiness'!$E$8/MAX(1,'Launch Readiness'!$E$7),0)+IF(H$6='Launch Readiness'!$G$14,'Launch Readiness'!$E$15,0)),0) -> -724391 | I52: =ROUND(H52+(IF(I$6<='Launch Readiness'!$B$7,0,IF((I$6-'Launch Readiness'!$B$7)<'Launch Readiness'!$E$6,0,INDEX('Scenario Engine'!$B$30:$F$30,1,ROUNDUP((I$6-'Launch Readiness'!$B$7)/12,0))/MAX(1,INDEX('Launch Readiness'!$B$26:$F$26,1,ROUNDUP((I$6-'Launch Readiness'!$B$7)/12,0))))))-IF(I$6<'Launch Readiness'!$E$6,0,INDEX('Scenario Engine'!$B$47:$F$47,1,I$7)/MAX(1,INDEX('Launch Readiness'!$B$26:$F$26,1,I$7)))-INDEX('Scenario Engine'!$B$52:$F$52,1,I$7)/12-((INDEX('Scenario Engine'!$B$53:$F$53,1,I$7)-'Launch Readiness'!$E$9*INDEX('Launch Readiness'!$B$34:$F$34,1,I$7)-'Launch Readiness'!$E$9*'Launch Readiness'!$B$10*INDEX('Launch Readiness'!$B$30:$F$30,1,I$7)-'Launch Readiness'!$E$16*INDEX('Launch Readiness'!$B$32:$F$32,1,I$7))/12+IF(AND(I$6>='Launch Readiness'!$E$6,I$6<'Launch Readiness'!$E$14),'Launch Readiness'!$E$9/12,0)+IF(AND(I$6>='Launch Readiness'!$B$11,I$6<'Launch Readiness'!$E$6),'Launch Readiness'!$E$9*'Launch Readiness'!$B$10/12,0)+IF(I$6>='Launch Readiness'!$E$14,'Launch Readiness'!$E$16/12,0))-(IF(I$6<=6,'Startup 6mo'!$F$44/6,0)+IF(I$6<'Launch Readiness'!$E$6,'Launch Readiness'!$E$8/MAX(1,'Launch Readiness'!$E$7),0)+IF(I$6='Launch Readiness'!$G$14,'Launch Readiness'!$E$15,0)),0) -> -793382 | J52: =ROUND(I52+(IF(J$6<='Launch Readiness'!$B$7,0,IF((J$6-'Launch Readiness'!$B$7)<'Launch Readiness'!$E$6,0,INDEX('Scenario Engine'!$B$30:$F$30,1,ROUNDUP((J$6-'Launch Readiness'!$B$7)/12,0))/MAX(1,INDEX('Launch Readiness'!$B$26:$F$26,1,ROUNDUP((J$6-'Launch Readiness'!$B$7)/12,0))))))-IF(J$6<'Launch Readiness'!$E$6,0,INDEX('Scenario Engine'!$B$47:$F$47,1,J$7)/MAX(1,INDEX('Launch Readiness'!$B$26:$F$26,1,J$7)))-INDEX('Scenario Engine'!$B$52:$F$52,1,J$7)/12-((INDEX('Scenario Engine'!$B$53:$F$53,1,J$7)-'Launch Readiness'!$E$9*INDEX('Launch Readiness'!$B$34:$F$34,1,J$7)-'Launch Readiness'!$E$9*'Launch Readiness'!$B$10*INDEX('Launch Readiness'!$B$30:$F$30,1,J$7)-'Launch Readiness'!$E$16*INDEX('Launch Readiness'!$B$32:$F$32,1,J$7))/12+IF(AND(J$6>='Launch Readiness'!$E$6,J$6<'Launch Readiness'!$E$14),'Launch Readiness'!$E$9/12,0)+IF(AND(J$6>='Launch Readiness'!$B$11,J$6<'Launch Readiness'!$E$6),'Launch Readiness'!$E$9*'Launch Readiness'!$B$10/12,0)+IF(J$6>='Launch Readiness'!$E$14,'Launch Readiness'!$E$16/12,0))-(IF(J$6<=6,'Startup 6mo'!$F$44/6,0)+IF(J$6<'Launch Readiness'!$E$6,'Launch Readiness'!$E$8/MAX(1,'Launch Readiness'!$E$7),0)+IF(J$6='Launch Readiness'!$G$14,'Launch Readiness'!$E$15,0)),0) -> -862373 | ... BI52: =ROUND(BH52+(IF(BI$6<='Launch Readiness'!$B$7,0,IF((BI$6-'Launch Readiness'!$B$7)<'Launch Readiness'!$E$6,0,INDEX('Scenario Engine'!$B$30:$F$30,1,ROUNDUP((BI$6-'Launch Readiness'!$B$7)/12,0))/MAX(1,INDEX('Launch Readiness'!$B$26:$F$26,1,ROUNDUP((BI$6-'Launch Readiness'!$B$7)/12,0))))))-IF(BI$6<'Launch Readiness'!$E$6,0,INDEX('Scenario Engine'!$B$47:$F$47,1,BI$7)/MAX(1,INDEX('Launch Readiness'!$B$26:$F$26,1,BI$7)))-INDEX('Scenario Engine'!$B$52:$F$52,1,BI$7)/12-((INDEX('Scenario Engine'!$B$53:$F$53,1,BI$7)-'Launch Readiness'!$E$9*INDEX('Launch Readiness'!$B$34:$F$34,1,BI$7)-'Launch Readiness'!$E$9*'Launch Readiness'!$B$10*INDEX('Launch Readiness'!$B$30:$F$30,1,BI$7)-'Launch Readiness'!$E$16*INDEX('Launch Readiness'!$B$32:$F$32,1,BI$7))/12+IF(AND(BI$6>='Launch Readiness'!$E$6,BI$6<'Launch Readiness'!$E$14),'Launch Readiness'!$E$9/12,0)+IF(AND(BI$6>='Launch Readiness'!$B$11,BI$6<'Launch Readiness'!$E$6),'Launch Readiness'!$E$9*'Launch Readiness'!$B$10/12,0)+IF(BI$6>='Launch Readiness'!$E$14,'Launch Readiness'!$E$16/12,0))-(IF(BI$6<=6,'Startup 6mo'!$F$44/6,0)+IF(BI$6<'Launch Readiness'!$E$6,'Launch Readiness'!$E$8/MAX(1,'Launch Readiness'!$E$7),0)+IF(BI$6='Launch Readiness'!$G$14,'Launch Readiness'!$E$15,0)),0) -> -2924278
A53: Base | B53: =ROUND((IF(B$6<='Launch Readiness'!$B$7,0,IF((B$6-'Launch Readiness'!$B$7)<'Launch Readiness'!$E$6,0,INDEX('Scenario Engine'!$H$30:$L$30,1,ROUNDUP((B$6-'Launch Readiness'!$B$7)/12,0))/MAX(1,INDEX('Launch Readiness'!$B$26:$F$26,1,ROUNDUP((B$6-'Launch Readiness'!$B$7)/12,0))))))-IF(B$6<'Launch Readiness'!$E$6,0,INDEX('Scenario Engine'!$H$47:$L$47,1,B$7)/MAX(1,INDEX('Launch Readiness'!$B$26:$F$26,1,B$7)))-INDEX('Scenario Engine'!$H$52:$L$52,1,B$7)/12-((INDEX('Scenario Engine'!$H$53:$L$53,1,B$7)-'Launch Readiness'!$E$9*INDEX('Launch Readiness'!$B$34:$F$34,1,B$7)-'Launch Readiness'!$E$9*'Launch Readiness'!$B$10*INDEX('Launch Readiness'!$B$30:$F$30,1,B$7)-'Launch Readiness'!$E$16*INDEX('Launch Readiness'!$B$32:$F$32,1,B$7))/12+IF(AND(B$6>='Launch Readiness'!$E$6,B$6<'Launch Readiness'!$E$14),'Launch Readiness'!$E$9/12,0)+IF(AND(B$6>='Launch Readiness'!$B$11,B$6<'Launch Readiness'!$E$6),'Launch Readiness'!$E$9*'Launch Readiness'!$B$10/12,0)+IF(B$6>='Launch Readiness'!$E$14,'Launch Readiness'!$E$16/12,0))-(IF(B$6<=6,'Startup 6mo'!$F$44/6,0)+IF(B$6<'Launch Readiness'!$E$6,'Launch Readiness'!$E$8/MAX(1,'Launch Readiness'!$E$7),0)+IF(B$6='Launch Readiness'!$G$14,'Launch Readiness'!$E$15,0)),0) -> -107605 | C53: =ROUND(B53+(IF(C$6<='Launch Readiness'!$B$7,0,IF((C$6-'Launch Readiness'!$B$7)<'Launch Readiness'!$E$6,0,INDEX('Scenario Engine'!$H$30:$L$30,1,ROUNDUP((C$6-'Launch Readiness'!$B$7)/12,0))/MAX(1,INDEX('Launch Readiness'!$B$26:$F$26,1,ROUNDUP((C$6-'Launch Readiness'!$B$7)/12,0))))))-IF(C$6<'Launch Readiness'!$E$6,0,INDEX('Scenario Engine'!$H$47:$L$47,1,C$7)/MAX(1,INDEX('Launch Readiness'!$B$26:$F$26,1,C$7)))-INDEX('Scenario Engine'!$H$52:$L$52,1,C$7)/12-((INDEX('Scenario Engine'!$H$53:$L$53,1,C$7)-'Launch Readiness'!$E$9*INDEX('Launch Readiness'!$B$34:$F$34,1,C$7)-'Launch Readiness'!$E$9*'Launch Readiness'!$B$10*INDEX('Launch Readiness'!$B$30:$F$30,1,C$7)-'Launch Readiness'!$E$16*INDEX('Launch Readiness'!$B$32:$F$32,1,C$7))/12+IF(AND(C$6>='Launch Readiness'!$E$6,C$6<'Launch Readiness'!$E$14),'Launch Readiness'!$E$9/12,0)+IF(AND(C$6>='Launch Readiness'!$B$11,C$6<'Launch Readiness'!$E$6),'Launch Readiness'!$E$9*'Launch Readiness'!$B$10/12,0)+IF(C$6>='Launch Readiness'!$E$14,'Launch Readiness'!$E$16/12,0))-(IF(C$6<=6,'Startup 6mo'!$F$44/6,0)+IF(C$6<'Launch Readiness'!$E$6,'Launch Readiness'!$E$8/MAX(1,'Launch Readiness'!$E$7),0)+IF(C$6='Launch Readiness'!$G$14,'Launch Readiness'!$E$15,0)),0) -> -217164 | D53: =ROUND(C53+(IF(D$6<='Launch Readiness'!$B$7,0,IF((D$6-'Launch Readiness'!$B$7)<'Launch Readiness'!$E$6,0,INDEX('Scenario Engine'!$H$30:$L$30,1,ROUNDUP((D$6-'Launch Readiness'!$B$7)/12,0))/MAX(1,INDEX('Launch Readiness'!$B$26:$F$26,1,ROUNDUP((D$6-'Launch Readiness'!$B$7)/12,0))))))-IF(D$6<'Launch Readiness'!$E$6,0,INDEX('Scenario Engine'!$H$47:$L$47,1,D$7)/MAX(1,INDEX('Launch Readiness'!$B$26:$F$26,1,D$7)))-INDEX('Scenario Engine'!$H$52:$L$52,1,D$7)/12-((INDEX('Scenario Engine'!$H$53:$L$53,1,D$7)-'Launch Readiness'!$E$9*INDEX('Launch Readiness'!$B$34:$F$34,1,D$7)-'Launch Readiness'!$E$9*'Launch Readiness'!$B$10*INDEX('Launch Readiness'!$B$30:$F$30,1,D$7)-'Launch Readiness'!$E$16*INDEX('Launch Readiness'!$B$32:$F$32,1,D$7))/12+IF(AND(D$6>='Launch Readiness'!$E$6,D$6<'Launch Readiness'!$E$14),'Launch Readiness'!$E$9/12,0)+IF(AND(D$6>='Launch Readiness'!$B$11,D$6<'Launch Readiness'!$E$6),'Launch Readiness'!$E$9*'Launch Readiness'!$B$10/12,0)+IF(D$6>='Launch Readiness'!$E$14,'Launch Readiness'!$E$16/12,0))-(IF(D$6<=6,'Startup 6mo'!$F$44/6,0)+IF(D$6<'Launch Readiness'!$E$6,'Launch Readiness'!$E$8/MAX(1,'Launch Readiness'!$E$7),0)+IF(D$6='Launch Readiness'!$G$14,'Launch Readiness'!$E$15,0)),0) -> -326723 | E53: =ROUND(D53+(IF(E$6<='Launch Readiness'!$B$7,0,IF((E$6-'Launch Readiness'!$B$7)<'Launch Readiness'!$E$6,0,INDEX('Scenario Engine'!$H$30:$L$30,1,ROUNDUP((E$6-'Launch Readiness'!$B$7)/12,0))/MAX(1,INDEX('Launch Readiness'!$B$26:$F$26,1,ROUNDUP((E$6-'Launch Readiness'!$B$7)/12,0))))))-IF(E$6<'Launch Readiness'!$E$6,0,INDEX('Scenario Engine'!$H$47:$L$47,1,E$7)/MAX(1,INDEX('Launch Readiness'!$B$26:$F$26,1,E$7)))-INDEX('Scenario Engine'!$H$52:$L$52,1,E$7)/12-((INDEX('Scenario Engine'!$H$53:$L$53,1,E$7)-'Launch Readiness'!$E$9*INDEX('Launch Readiness'!$B$34:$F$34,1,E$7)-'Launch Readiness'!$E$9*'Launch Readiness'!$B$10*INDEX('Launch Readiness'!$B$30:$F$30,1,E$7)-'Launch Readiness'!$E$16*INDEX('Launch Readiness'!$B$32:$F$32,1,E$7))/12+IF(AND(E$6>='Launch Readiness'!$E$6,E$6<'Launch Readiness'!$E$14),'Launch Readiness'!$E$9/12,0)+IF(AND(E$6>='Launch Readiness'!$B$11,E$6<'Launch Readiness'!$E$6),'Launch Readiness'!$E$9*'Launch Readiness'!$B$10/12,0)+IF(E$6>='Launch Readiness'!$E$14,'Launch Readiness'!$E$16/12,0))-(IF(E$6<=6,'Startup 6mo'!$F$44/6,0)+IF(E$6<'Launch Readiness'!$E$6,'Launch Readiness'!$E$8/MAX(1,'Launch Readiness'!$E$7),0)+IF(E$6='Launch Readiness'!$G$14,'Launch Readiness'!$E$15,0)),0) -> -436282 | F53: =ROUND(E53+(IF(F$6<='Launch Readiness'!$B$7,0,IF((F$6-'Launch Readiness'!$B$7)<'Launch Readiness'!$E$6,0,INDEX('Scenario Engine'!$H$30:$L$30,1,ROUNDUP((F$6-'Launch Readiness'!$B$7)/12,0))/MAX(1,INDEX('Launch Readiness'!$B$26:$F$26,1,ROUNDUP((F$6-'Launch Readiness'!$B$7)/12,0))))))-IF(F$6<'Launch Readiness'!$E$6,0,INDEX('Scenario Engine'!$H$47:$L$47,1,F$7)/MAX(1,INDEX('Launch Readiness'!$B$26:$F$26,1,F$7)))-INDEX('Scenario Engine'!$H$52:$L$52,1,F$7)/12-((INDEX('Scenario Engine'!$H$53:$L$53,1,F$7)-'Launch Readiness'!$E$9*INDEX('Launch Readiness'!$B$34:$F$34,1,F$7)-'Launch Readiness'!$E$9*'Launch Readiness'!$B$10*INDEX('Launch Readiness'!$B$30:$F$30,1,F$7)-'Launch Readiness'!$E$16*INDEX('Launch Readiness'!$B$32:$F$32,1,F$7))/12+IF(AND(F$6>='Launch Readiness'!$E$6,F$6<'Launch Readiness'!$E$14),'Launch Readiness'!$E$9/12,0)+IF(AND(F$6>='Launch Readiness'!$B$11,F$6<'Launch Readiness'!$E$6),'Launch Readiness'!$E$9*'Launch Readiness'!$B$10/12,0)+IF(F$6>='Launch Readiness'!$E$14,'Launch Readiness'!$E$16/12,0))-(IF(F$6<=6,'Startup 6mo'!$F$44/6,0)+IF(F$6<'Launch Readiness'!$E$6,'Launch Readiness'!$E$8/MAX(1,'Launch Readiness'!$E$7),0)+IF(F$6='Launch Readiness'!$G$14,'Launch Readiness'!$E$15,0)),0) -> -545841 | G53: =ROUND(F53+(IF(G$6<='Launch Readiness'!$B$7,0,IF((G$6-'Launch Readiness'!$B$7)<'Launch Readiness'!$E$6,0,INDEX('Scenario Engine'!$H$30:$L$30,1,ROUNDUP((G$6-'Launch Readiness'!$B$7)/12,0))/MAX(1,INDEX('Launch Readiness'!$B$26:$F$26,1,ROUNDUP((G$6-'Launch Readiness'!$B$7)/12,0))))))-IF(G$6<'Launch Readiness'!$E$6,0,INDEX('Scenario Engine'!$H$47:$L$47,1,G$7)/MAX(1,INDEX('Launch Readiness'!$B$26:$F$26,1,G$7)))-INDEX('Scenario Engine'!$H$52:$L$52,1,G$7)/12-((INDEX('Scenario Engine'!$H$53:$L$53,1,G$7)-'Launch Readiness'!$E$9*INDEX('Launch Readiness'!$B$34:$F$34,1,G$7)-'Launch Readiness'!$E$9*'Launch Readiness'!$B$10*INDEX('Launch Readiness'!$B$30:$F$30,1,G$7)-'Launch Readiness'!$E$16*INDEX('Launch Readiness'!$B$32:$F$32,1,G$7))/12+IF(AND(G$6>='Launch Readiness'!$E$6,G$6<'Launch Readiness'!$E$14),'Launch Readiness'!$E$9/12,0)+IF(AND(G$6>='Launch Readiness'!$B$11,G$6<'Launch Readiness'!$E$6),'Launch Readiness'!$E$9*'Launch Readiness'!$B$10/12,0)+IF(G$6>='Launch Readiness'!$E$14,'Launch Readiness'!$E$16/12,0))-(IF(G$6<=6,'Startup 6mo'!$F$44/6,0)+IF(G$6<'Launch Readiness'!$E$6,'Launch Readiness'!$E$8/MAX(1,'Launch Readiness'!$E$7),0)+IF(G$6='Launch Readiness'!$G$14,'Launch Readiness'!$E$15,0)),0) -> -655400 | H53: =ROUND(G53+(IF(H$6<='Launch Readiness'!$B$7,0,IF((H$6-'Launch Readiness'!$B$7)<'Launch Readiness'!$E$6,0,INDEX('Scenario Engine'!$H$30:$L$30,1,ROUNDUP((H$6-'Launch Readiness'!$B$7)/12,0))/MAX(1,INDEX('Launch Readiness'!$B$26:$F$26,1,ROUNDUP((H$6-'Launch Readiness'!$B$7)/12,0))))))-IF(H$6<'Launch Readiness'!$E$6,0,INDEX('Scenario Engine'!$H$47:$L$47,1,H$7)/MAX(1,INDEX('Launch Readiness'!$B$26:$F$26,1,H$7)))-INDEX('Scenario Engine'!$H$52:$L$52,1,H$7)/12-((INDEX('Scenario Engine'!$H$53:$L$53,1,H$7)-'Launch Readiness'!$E$9*INDEX('Launch Readiness'!$B$34:$F$34,1,H$7)-'Launch Readiness'!$E$9*'Launch Readiness'!$B$10*INDEX('Launch Readiness'!$B$30:$F$30,1,H$7)-'Launch Readiness'!$E$16*INDEX('Launch Readiness'!$B$32:$F$32,1,H$7))/12+IF(AND(H$6>='Launch Readiness'!$E$6,H$6<'Launch Readiness'!$E$14),'Launch Readiness'!$E$9/12,0)+IF(AND(H$6>='Launch Readiness'!$B$11,H$6<'Launch Readiness'!$E$6),'Launch Readiness'!$E$9*'Launch Readiness'!$B$10/12,0)+IF(H$6>='Launch Readiness'!$E$14,'Launch Readiness'!$E$16/12,0))-(IF(H$6<=6,'Startup 6mo'!$F$44/6,0)+IF(H$6<'Launch Readiness'!$E$6,'Launch Readiness'!$E$8/MAX(1,'Launch Readiness'!$E$7),0)+IF(H$6='Launch Readiness'!$G$14,'Launch Readiness'!$E$15,0)),0) -> -724391 | I53: =ROUND(H53+(IF(I$6<='Launch Readiness'!$B$7,0,IF((I$6-'Launch Readiness'!$B$7)<'Launch Readiness'!$E$6,0,INDEX('Scenario Engine'!$H$30:$L$30,1,ROUNDUP((I$6-'Launch Readiness'!$B$7)/12,0))/MAX(1,INDEX('Launch Readiness'!$B$26:$F$26,1,ROUNDUP((I$6-'Launch Readiness'!$B$7)/12,0))))))-IF(I$6<'Launch Readiness'!$E$6,0,INDEX('Scenario Engine'!$H$47:$L$47,1,I$7)/MAX(1,INDEX('Launch Readiness'!$B$26:$F$26,1,I$7)))-INDEX('Scenario Engine'!$H$52:$L$52,1,I$7)/12-((INDEX('Scenario Engine'!$H$53:$L$53,1,I$7)-'Launch Readiness'!$E$9*INDEX('Launch Readiness'!$B$34:$F$34,1,I$7)-'Launch Readiness'!$E$9*'Launch Readiness'!$B$10*INDEX('Launch Readiness'!$B$30:$F$30,1,I$7)-'Launch Readiness'!$E$16*INDEX('Launch Readiness'!$B$32:$F$32,1,I$7))/12+IF(AND(I$6>='Launch Readiness'!$E$6,I$6<'Launch Readiness'!$E$14),'Launch Readiness'!$E$9/12,0)+IF(AND(I$6>='Launch Readiness'!$B$11,I$6<'Launch Readiness'!$E$6),'Launch Readiness'!$E$9*'Launch Readiness'!$B$10/12,0)+IF(I$6>='Launch Readiness'!$E$14,'Launch Readiness'!$E$16/12,0))-(IF(I$6<=6,'Startup 6mo'!$F$44/6,0)+IF(I$6<'Launch Readiness'!$E$6,'Launch Readiness'!$E$8/MAX(1,'Launch Readiness'!$E$7),0)+IF(I$6='Launch Readiness'!$G$14,'Launch Readiness'!$E$15,0)),0) -> -793382 | J53: =ROUND(I53+(IF(J$6<='Launch Readiness'!$B$7,0,IF((J$6-'Launch Readiness'!$B$7)<'Launch Readiness'!$E$6,0,INDEX('Scenario Engine'!$H$30:$L$30,1,ROUNDUP((J$6-'Launch Readiness'!$B$7)/12,0))/MAX(1,INDEX('Launch Readiness'!$B$26:$F$26,1,ROUNDUP((J$6-'Launch Readiness'!$B$7)/12,0))))))-IF(J$6<'Launch Readiness'!$E$6,0,INDEX('Scenario Engine'!$H$47:$L$47,1,J$7)/MAX(1,INDEX('Launch Readiness'!$B$26:$F$26,1,J$7)))-INDEX('Scenario Engine'!$H$52:$L$52,1,J$7)/12-((INDEX('Scenario Engine'!$H$53:$L$53,1,J$7)-'Launch Readiness'!$E$9*INDEX('Launch Readiness'!$B$34:$F$34,1,J$7)-'Launch Readiness'!$E$9*'Launch Readiness'!$B$10*INDEX('Launch Readiness'!$B$30:$F$30,1,J$7)-'Launch Readiness'!$E$16*INDEX('Launch Readiness'!$B$32:$F$32,1,J$7))/12+IF(AND(J$6>='Launch Readiness'!$E$6,J$6<'Launch Readiness'!$E$14),'Launch Readiness'!$E$9/12,0)+IF(AND(J$6>='Launch Readiness'!$B$11,J$6<'Launch Readiness'!$E$6),'Launch Readiness'!$E$9*'Launch Readiness'!$B$10/12,0)+IF(J$6>='Launch Readiness'!$E$14,'Launch Readiness'!$E$16/12,0))-(IF(J$6<=6,'Startup 6mo'!$F$44/6,0)+IF(J$6<'Launch Readiness'!$E$6,'Launch Readiness'!$E$8/MAX(1,'Launch Readiness'!$E$7),0)+IF(J$6='Launch Readiness'!$G$14,'Launch Readiness'!$E$15,0)),0) -> -862373 | ... BI53: =ROUND(BH53+(IF(BI$6<='Launch Readiness'!$B$7,0,IF((BI$6-'Launch Readiness'!$B$7)<'Launch Readiness'!$E$6,0,INDEX('Scenario Engine'!$H$30:$L$30,1,ROUNDUP((BI$6-'Launch Readiness'!$B$7)/12,0))/MAX(1,INDEX('Launch Readiness'!$B$26:$F$26,1,ROUNDUP((BI$6-'Launch Readiness'!$B$7)/12,0))))))-IF(BI$6<'Launch Readiness'!$E$6,0,INDEX('Scenario Engine'!$H$47:$L$47,1,BI$7)/MAX(1,INDEX('Launch Readiness'!$B$26:$F$26,1,BI$7)))-INDEX('Scenario Engine'!$H$52:$L$52,1,BI$7)/12-((INDEX('Scenario Engine'!$H$53:$L$53,1,BI$7)-'Launch Readiness'!$E$9*INDEX('Launch Readiness'!$B$34:$F$34,1,BI$7)-'Launch Readiness'!$E$9*'Launch Readiness'!$B$10*INDEX('Launch Readiness'!$B$30:$F$30,1,BI$7)-'Launch Readiness'!$E$16*INDEX('Launch Readiness'!$B$32:$F$32,1,BI$7))/12+IF(AND(BI$6>='Launch Readiness'!$E$6,BI$6<'Launch Readiness'!$E$14),'Launch Readiness'!$E$9/12,0)+IF(AND(BI$6>='Launch Readiness'!$B$11,BI$6<'Launch Readiness'!$E$6),'Launch Readiness'!$E$9*'Launch Readiness'!$B$10/12,0)+IF(BI$6>='Launch Readiness'!$E$14,'Launch Readiness'!$E$16/12,0))-(IF(BI$6<=6,'Startup 6mo'!$F$44/6,0)+IF(BI$6<'Launch Readiness'!$E$6,'Launch Readiness'!$E$8/MAX(1,'Launch Readiness'!$E$7),0)+IF(BI$6='Launch Readiness'!$G$14,'Launch Readiness'!$E$15,0)),0) -> 12947967
A54: High | B54: =ROUND((IF(B$6<='Launch Readiness'!$B$7,0,IF((B$6-'Launch Readiness'!$B$7)<'Launch Readiness'!$E$6,0,INDEX('Scenario Engine'!$N$30:$R$30,1,ROUNDUP((B$6-'Launch Readiness'!$B$7)/12,0))/MAX(1,INDEX('Launch Readiness'!$B$26:$F$26,1,ROUNDUP((B$6-'Launch Readiness'!$B$7)/12,0))))))-IF(B$6<'Launch Readiness'!$E$6,0,INDEX('Scenario Engine'!$N$47:$R$47,1,B$7)/MAX(1,INDEX('Launch Readiness'!$B$26:$F$26,1,B$7)))-INDEX('Scenario Engine'!$N$52:$R$52,1,B$7)/12-((INDEX('Scenario Engine'!$N$53:$R$53,1,B$7)-'Launch Readiness'!$E$9*INDEX('Launch Readiness'!$B$34:$F$34,1,B$7)-'Launch Readiness'!$E$9*'Launch Readiness'!$B$10*INDEX('Launch Readiness'!$B$30:$F$30,1,B$7)-'Launch Readiness'!$E$16*INDEX('Launch Readiness'!$B$32:$F$32,1,B$7))/12+IF(AND(B$6>='Launch Readiness'!$E$6,B$6<'Launch Readiness'!$E$14),'Launch Readiness'!$E$9/12,0)+IF(AND(B$6>='Launch Readiness'!$B$11,B$6<'Launch Readiness'!$E$6),'Launch Readiness'!$E$9*'Launch Readiness'!$B$10/12,0)+IF(B$6>='Launch Readiness'!$E$14,'Launch Readiness'!$E$16/12,0))-(IF(B$6<=6,'Startup 6mo'!$F$44/6,0)+IF(B$6<'Launch Readiness'!$E$6,'Launch Readiness'!$E$8/MAX(1,'Launch Readiness'!$E$7),0)+IF(B$6='Launch Readiness'!$G$14,'Launch Readiness'!$E$15,0)),0) -> -107605 | C54: =ROUND(B54+(IF(C$6<='Launch Readiness'!$B$7,0,IF((C$6-'Launch Readiness'!$B$7)<'Launch Readiness'!$E$6,0,INDEX('Scenario Engine'!$N$30:$R$30,1,ROUNDUP((C$6-'Launch Readiness'!$B$7)/12,0))/MAX(1,INDEX('Launch Readiness'!$B$26:$F$26,1,ROUNDUP((C$6-'Launch Readiness'!$B$7)/12,0))))))-IF(C$6<'Launch Readiness'!$E$6,0,INDEX('Scenario Engine'!$N$47:$R$47,1,C$7)/MAX(1,INDEX('Launch Readiness'!$B$26:$F$26,1,C$7)))-INDEX('Scenario Engine'!$N$52:$R$52,1,C$7)/12-((INDEX('Scenario Engine'!$N$53:$R$53,1,C$7)-'Launch Readiness'!$E$9*INDEX('Launch Readiness'!$B$34:$F$34,1,C$7)-'Launch Readiness'!$E$9*'Launch Readiness'!$B$10*INDEX('Launch Readiness'!$B$30:$F$30,1,C$7)-'Launch Readiness'!$E$16*INDEX('Launch Readiness'!$B$32:$F$32,1,C$7))/12+IF(AND(C$6>='Launch Readiness'!$E$6,C$6<'Launch Readiness'!$E$14),'Launch Readiness'!$E$9/12,0)+IF(AND(C$6>='Launch Readiness'!$B$11,C$6<'Launch Readiness'!$E$6),'Launch Readiness'!$E$9*'Launch Readiness'!$B$10/12,0)+IF(C$6>='Launch Readiness'!$E$14,'Launch Readiness'!$E$16/12,0))-(IF(C$6<=6,'Startup 6mo'!$F$44/6,0)+IF(C$6<'Launch Readiness'!$E$6,'Launch Readiness'!$E$8/MAX(1,'Launch Readiness'!$E$7),0)+IF(C$6='Launch Readiness'!$G$14,'Launch Readiness'!$E$15,0)),0) -> -217164 | D54: =ROUND(C54+(IF(D$6<='Launch Readiness'!$B$7,0,IF((D$6-'Launch Readiness'!$B$7)<'Launch Readiness'!$E$6,0,INDEX('Scenario Engine'!$N$30:$R$30,1,ROUNDUP((D$6-'Launch Readiness'!$B$7)/12,0))/MAX(1,INDEX('Launch Readiness'!$B$26:$F$26,1,ROUNDUP((D$6-'Launch Readiness'!$B$7)/12,0))))))-IF(D$6<'Launch Readiness'!$E$6,0,INDEX('Scenario Engine'!$N$47:$R$47,1,D$7)/MAX(1,INDEX('Launch Readiness'!$B$26:$F$26,1,D$7)))-INDEX('Scenario Engine'!$N$52:$R$52,1,D$7)/12-((INDEX('Scenario Engine'!$N$53:$R$53,1,D$7)-'Launch Readiness'!$E$9*INDEX('Launch Readiness'!$B$34:$F$34,1,D$7)-'Launch Readiness'!$E$9*'Launch Readiness'!$B$10*INDEX('Launch Readiness'!$B$30:$F$30,1,D$7)-'Launch Readiness'!$E$16*INDEX('Launch Readiness'!$B$32:$F$32,1,D$7))/12+IF(AND(D$6>='Launch Readiness'!$E$6,D$6<'Launch Readiness'!$E$14),'Launch Readiness'!$E$9/12,0)+IF(AND(D$6>='Launch Readiness'!$B$11,D$6<'Launch Readiness'!$E$6),'Launch Readiness'!$E$9*'Launch Readiness'!$B$10/12,0)+IF(D$6>='Launch Readiness'!$E$14,'Launch Readiness'!$E$16/12,0))-(IF(D$6<=6,'Startup 6mo'!$F$44/6,0)+IF(D$6<'Launch Readiness'!$E$6,'Launch Readiness'!$E$8/MAX(1,'Launch Readiness'!$E$7),0)+IF(D$6='Launch Readiness'!$G$14,'Launch Readiness'!$E$15,0)),0) -> -326723 | E54: =ROUND(D54+(IF(E$6<='Launch Readiness'!$B$7,0,IF((E$6-'Launch Readiness'!$B$7)<'Launch Readiness'!$E$6,0,INDEX('Scenario Engine'!$N$30:$R$30,1,ROUNDUP((E$6-'Launch Readiness'!$B$7)/12,0))/MAX(1,INDEX('Launch Readiness'!$B$26:$F$26,1,ROUNDUP((E$6-'Launch Readiness'!$B$7)/12,0))))))-IF(E$6<'Launch Readiness'!$E$6,0,INDEX('Scenario Engine'!$N$47:$R$47,1,E$7)/MAX(1,INDEX('Launch Readiness'!$B$26:$F$26,1,E$7)))-INDEX('Scenario Engine'!$N$52:$R$52,1,E$7)/12-((INDEX('Scenario Engine'!$N$53:$R$53,1,E$7)-'Launch Readiness'!$E$9*INDEX('Launch Readiness'!$B$34:$F$34,1,E$7)-'Launch Readiness'!$E$9*'Launch Readiness'!$B$10*INDEX('Launch Readiness'!$B$30:$F$30,1,E$7)-'Launch Readiness'!$E$16*INDEX('Launch Readiness'!$B$32:$F$32,1,E$7))/12+IF(AND(E$6>='Launch Readiness'!$E$6,E$6<'Launch Readiness'!$E$14),'Launch Readiness'!$E$9/12,0)+IF(AND(E$6>='Launch Readiness'!$B$11,E$6<'Launch Readiness'!$E$6),'Launch Readiness'!$E$9*'Launch Readiness'!$B$10/12,0)+IF(E$6>='Launch Readiness'!$E$14,'Launch Readiness'!$E$16/12,0))-(IF(E$6<=6,'Startup 6mo'!$F$44/6,0)+IF(E$6<'Launch Readiness'!$E$6,'Launch Readiness'!$E$8/MAX(1,'Launch Readiness'!$E$7),0)+IF(E$6='Launch Readiness'!$G$14,'Launch Readiness'!$E$15,0)),0) -> -436282 | F54: =ROUND(E54+(IF(F$6<='Launch Readiness'!$B$7,0,IF((F$6-'Launch Readiness'!$B$7)<'Launch Readiness'!$E$6,0,INDEX('Scenario Engine'!$N$30:$R$30,1,ROUNDUP((F$6-'Launch Readiness'!$B$7)/12,0))/MAX(1,INDEX('Launch Readiness'!$B$26:$F$26,1,ROUNDUP((F$6-'Launch Readiness'!$B$7)/12,0))))))-IF(F$6<'Launch Readiness'!$E$6,0,INDEX('Scenario Engine'!$N$47:$R$47,1,F$7)/MAX(1,INDEX('Launch Readiness'!$B$26:$F$26,1,F$7)))-INDEX('Scenario Engine'!$N$52:$R$52,1,F$7)/12-((INDEX('Scenario Engine'!$N$53:$R$53,1,F$7)-'Launch Readiness'!$E$9*INDEX('Launch Readiness'!$B$34:$F$34,1,F$7)-'Launch Readiness'!$E$9*'Launch Readiness'!$B$10*INDEX('Launch Readiness'!$B$30:$F$30,1,F$7)-'Launch Readiness'!$E$16*INDEX('Launch Readiness'!$B$32:$F$32,1,F$7))/12+IF(AND(F$6>='Launch Readiness'!$E$6,F$6<'Launch Readiness'!$E$14),'Launch Readiness'!$E$9/12,0)+IF(AND(F$6>='Launch Readiness'!$B$11,F$6<'Launch Readiness'!$E$6),'Launch Readiness'!$E$9*'Launch Readiness'!$B$10/12,0)+IF(F$6>='Launch Readiness'!$E$14,'Launch Readiness'!$E$16/12,0))-(IF(F$6<=6,'Startup 6mo'!$F$44/6,0)+IF(F$6<'Launch Readiness'!$E$6,'Launch Readiness'!$E$8/MAX(1,'Launch Readiness'!$E$7),0)+IF(F$6='Launch Readiness'!$G$14,'Launch Readiness'!$E$15,0)),0) -> -545841 | G54: =ROUND(F54+(IF(G$6<='Launch Readiness'!$B$7,0,IF((G$6-'Launch Readiness'!$B$7)<'Launch Readiness'!$E$6,0,INDEX('Scenario Engine'!$N$30:$R$30,1,ROUNDUP((G$6-'Launch Readiness'!$B$7)/12,0))/MAX(1,INDEX('Launch Readiness'!$B$26:$F$26,1,ROUNDUP((G$6-'Launch Readiness'!$B$7)/12,0))))))-IF(G$6<'Launch Readiness'!$E$6,0,INDEX('Scenario Engine'!$N$47:$R$47,1,G$7)/MAX(1,INDEX('Launch Readiness'!$B$26:$F$26,1,G$7)))-INDEX('Scenario Engine'!$N$52:$R$52,1,G$7)/12-((INDEX('Scenario Engine'!$N$53:$R$53,1,G$7)-'Launch Readiness'!$E$9*INDEX('Launch Readiness'!$B$34:$F$34,1,G$7)-'Launch Readiness'!$E$9*'Launch Readiness'!$B$10*INDEX('Launch Readiness'!$B$30:$F$30,1,G$7)-'Launch Readiness'!$E$16*INDEX('Launch Readiness'!$B$32:$F$32,1,G$7))/12+IF(AND(G$6>='Launch Readiness'!$E$6,G$6<'Launch Readiness'!$E$14),'Launch Readiness'!$E$9/12,0)+IF(AND(G$6>='Launch Readiness'!$B$11,G$6<'Launch Readiness'!$E$6),'Launch Readiness'!$E$9*'Launch Readiness'!$B$10/12,0)+IF(G$6>='Launch Readiness'!$E$14,'Launch Readiness'!$E$16/12,0))-(IF(G$6<=6,'Startup 6mo'!$F$44/6,0)+IF(G$6<'Launch Readiness'!$E$6,'Launch Readiness'!$E$8/MAX(1,'Launch Readiness'!$E$7),0)+IF(G$6='Launch Readiness'!$G$14,'Launch Readiness'!$E$15,0)),0) -> -655400 | H54: =ROUND(G54+(IF(H$6<='Launch Readiness'!$B$7,0,IF((H$6-'Launch Readiness'!$B$7)<'Launch Readiness'!$E$6,0,INDEX('Scenario Engine'!$N$30:$R$30,1,ROUNDUP((H$6-'Launch Readiness'!$B$7)/12,0))/MAX(1,INDEX('Launch Readiness'!$B$26:$F$26,1,ROUNDUP((H$6-'Launch Readiness'!$B$7)/12,0))))))-IF(H$6<'Launch Readiness'!$E$6,0,INDEX('Scenario Engine'!$N$47:$R$47,1,H$7)/MAX(1,INDEX('Launch Readiness'!$B$26:$F$26,1,H$7)))-INDEX('Scenario Engine'!$N$52:$R$52,1,H$7)/12-((INDEX('Scenario Engine'!$N$53:$R$53,1,H$7)-'Launch Readiness'!$E$9*INDEX('Launch Readiness'!$B$34:$F$34,1,H$7)-'Launch Readiness'!$E$9*'Launch Readiness'!$B$10*INDEX('Launch Readiness'!$B$30:$F$30,1,H$7)-'Launch Readiness'!$E$16*INDEX('Launch Readiness'!$B$32:$F$32,1,H$7))/12+IF(AND(H$6>='Launch Readiness'!$E$6,H$6<'Launch Readiness'!$E$14),'Launch Readiness'!$E$9/12,0)+IF(AND(H$6>='Launch Readiness'!$B$11,H$6<'Launch Readiness'!$E$6),'Launch Readiness'!$E$9*'Launch Readiness'!$B$10/12,0)+IF(H$6>='Launch Readiness'!$E$14,'Launch Readiness'!$E$16/12,0))-(IF(H$6<=6,'Startup 6mo'!$F$44/6,0)+IF(H$6<'Launch Readiness'!$E$6,'Launch Readiness'!$E$8/MAX(1,'Launch Readiness'!$E$7),0)+IF(H$6='Launch Readiness'!$G$14,'Launch Readiness'!$E$15,0)),0) -> -724391 | I54: =ROUND(H54+(IF(I$6<='Launch Readiness'!$B$7,0,IF((I$6-'Launch Readiness'!$B$7)<'Launch Readiness'!$E$6,0,INDEX('Scenario Engine'!$N$30:$R$30,1,ROUNDUP((I$6-'Launch Readiness'!$B$7)/12,0))/MAX(1,INDEX('Launch Readiness'!$B$26:$F$26,1,ROUNDUP((I$6-'Launch Readiness'!$B$7)/12,0))))))-IF(I$6<'Launch Readiness'!$E$6,0,INDEX('Scenario Engine'!$N$47:$R$47,1,I$7)/MAX(1,INDEX('Launch Readiness'!$B$26:$F$26,1,I$7)))-INDEX('Scenario Engine'!$N$52:$R$52,1,I$7)/12-((INDEX('Scenario Engine'!$N$53:$R$53,1,I$7)-'Launch Readiness'!$E$9*INDEX('Launch Readiness'!$B$34:$F$34,1,I$7)-'Launch Readiness'!$E$9*'Launch Readiness'!$B$10*INDEX('Launch Readiness'!$B$30:$F$30,1,I$7)-'Launch Readiness'!$E$16*INDEX('Launch Readiness'!$B$32:$F$32,1,I$7))/12+IF(AND(I$6>='Launch Readiness'!$E$6,I$6<'Launch Readiness'!$E$14),'Launch Readiness'!$E$9/12,0)+IF(AND(I$6>='Launch Readiness'!$B$11,I$6<'Launch Readiness'!$E$6),'Launch Readiness'!$E$9*'Launch Readiness'!$B$10/12,0)+IF(I$6>='Launch Readiness'!$E$14,'Launch Readiness'!$E$16/12,0))-(IF(I$6<=6,'Startup 6mo'!$F$44/6,0)+IF(I$6<'Launch Readiness'!$E$6,'Launch Readiness'!$E$8/MAX(1,'Launch Readiness'!$E$7),0)+IF(I$6='Launch Readiness'!$G$14,'Launch Readiness'!$E$15,0)),0) -> -793382 | J54: =ROUND(I54+(IF(J$6<='Launch Readiness'!$B$7,0,IF((J$6-'Launch Readiness'!$B$7)<'Launch Readiness'!$E$6,0,INDEX('Scenario Engine'!$N$30:$R$30,1,ROUNDUP((J$6-'Launch Readiness'!$B$7)/12,0))/MAX(1,INDEX('Launch Readiness'!$B$26:$F$26,1,ROUNDUP((J$6-'Launch Readiness'!$B$7)/12,0))))))-IF(J$6<'Launch Readiness'!$E$6,0,INDEX('Scenario Engine'!$N$47:$R$47,1,J$7)/MAX(1,INDEX('Launch Readiness'!$B$26:$F$26,1,J$7)))-INDEX('Scenario Engine'!$N$52:$R$52,1,J$7)/12-((INDEX('Scenario Engine'!$N$53:$R$53,1,J$7)-'Launch Readiness'!$E$9*INDEX('Launch Readiness'!$B$34:$F$34,1,J$7)-'Launch Readiness'!$E$9*'Launch Readiness'!$B$10*INDEX('Launch Readiness'!$B$30:$F$30,1,J$7)-'Launch Readiness'!$E$16*INDEX('Launch Readiness'!$B$32:$F$32,1,J$7))/12+IF(AND(J$6>='Launch Readiness'!$E$6,J$6<'Launch Readiness'!$E$14),'Launch Readiness'!$E$9/12,0)+IF(AND(J$6>='Launch Readiness'!$B$11,J$6<'Launch Readiness'!$E$6),'Launch Readiness'!$E$9*'Launch Readiness'!$B$10/12,0)+IF(J$6>='Launch Readiness'!$E$14,'Launch Readiness'!$E$16/12,0))-(IF(J$6<=6,'Startup 6mo'!$F$44/6,0)+IF(J$6<'Launch Readiness'!$E$6,'Launch Readiness'!$E$8/MAX(1,'Launch Readiness'!$E$7),0)+IF(J$6='Launch Readiness'!$G$14,'Launch Readiness'!$E$15,0)),0) -> -862373 | ... BI54: =ROUND(BH54+(IF(BI$6<='Launch Readiness'!$B$7,0,IF((BI$6-'Launch Readiness'!$B$7)<'Launch Readiness'!$E$6,0,INDEX('Scenario Engine'!$N$30:$R$30,1,ROUNDUP((BI$6-'Launch Readiness'!$B$7)/12,0))/MAX(1,INDEX('Launch Readiness'!$B$26:$F$26,1,ROUNDUP((BI$6-'Launch Readiness'!$B$7)/12,0))))))-IF(BI$6<'Launch Readiness'!$E$6,0,INDEX('Scenario Engine'!$N$47:$R$47,1,BI$7)/MAX(1,INDEX('Launch Readiness'!$B$26:$F$26,1,BI$7)))-INDEX('Scenario Engine'!$N$52:$R$52,1,BI$7)/12-((INDEX('Scenario Engine'!$N$53:$R$53,1,BI$7)-'Launch Readiness'!$E$9*INDEX('Launch Readiness'!$B$34:$F$34,1,BI$7)-'Launch Readiness'!$E$9*'Launch Readiness'!$B$10*INDEX('Launch Readiness'!$B$30:$F$30,1,BI$7)-'Launch Readiness'!$E$16*INDEX('Launch Readiness'!$B$32:$F$32,1,BI$7))/12+IF(AND(BI$6>='Launch Readiness'!$E$6,BI$6<'Launch Readiness'!$E$14),'Launch Readiness'!$E$9/12,0)+IF(AND(BI$6>='Launch Readiness'!$B$11,BI$6<'Launch Readiness'!$E$6),'Launch Readiness'!$E$9*'Launch Readiness'!$B$10/12,0)+IF(BI$6>='Launch Readiness'!$E$14,'Launch Readiness'!$E$16/12,0))-(IF(BI$6<=6,'Startup 6mo'!$F$44/6,0)+IF(BI$6<'Launch Readiness'!$E$6,'Launch Readiness'!$E$8/MAX(1,'Launch Readiness'!$E$7),0)+IF(BI$6='Launch Readiness'!$G$14,'Launch Readiness'!$E$15,0)),0) -> 33921710
A55: Low break-even helper | B55: =IF(B52>=0,"Reached","") | C55: =IF(C52>=0,"Reached","") | D55: =IF(D52>=0,"Reached","") | E55: =IF(E52>=0,"Reached","") | F55: =IF(F52>=0,"Reached","") | G55: =IF(G52>=0,"Reached","") | H55: =IF(H52>=0,"Reached","") | I55: =IF(I52>=0,"Reached","") | ... BI55: =IF(BI52>=0,"Reached","")
A56: Base break-even helper | B56: =IF(B53>=0,"Reached","") | C56: =IF(C53>=0,"Reached","") | D56: =IF(D53>=0,"Reached","") | E56: =IF(E53>=0,"Reached","") | F56: =IF(F53>=0,"Reached","") | G56: =IF(G53>=0,"Reached","") | H56: =IF(H53>=0,"Reached","") | I56: =IF(I53>=0,"Reached","") | ... BI56: =IF(BI53>=0,"Reached","") -> Reached
A57: High break-even helper | B57: =IF(B54>=0,"Reached","") | C57: =IF(C54>=0,"Reached","") | D57: =IF(D54>=0,"Reached","") | E57: =IF(E54>=0,"Reached","") | F57: =IF(F54>=0,"Reached","") | G57: =IF(G54>=0,"Reached","") | H57: =IF(H54>=0,"Reached","") | I57: =IF(I54>=0,"Reached","") | ... BI57: =IF(BI54>=0,"Reached","") -> Reached
A58: Active break-even helper | B58: =IF(B38>=0,"Reached","") | C58: =IF(C38>=0,"Reached","") | D58: =IF(D38>=0,"Reached","") | E58: =IF(E38>=0,"Reached","") | F58: =IF(F38>=0,"Reached","") | G58: =IF(G38>=0,"Reached","") | H58: =IF(H38>=0,"Reached","") | I58: =IF(I38>=0,"Reached","") | ... BI58: =IF(BI38>=0,"Reached","") -> Reached

Sheet Scenario Engine
A1: Scenario Engine — Low / Base / High in one sheet
A2: only two things vary by scenario: deal count and tier mix. Everything else is the fixed price book in Assumptions column F, so it is computed once per scenario-year rather than in three parallel P&Ls.
A3: Payroll, fixed opex and one-off cost are scenario-invariant and link straight to P&L 5yr. Green cells are links to other sheets.
B4: LOW SCENARIO | H4: BASE SCENARIO | N4: HIGH SCENARIO
B5: Year 1 | C5: Year 2 | D5: Year 3 | E5: Year 4 | F5: Year 5 | H5: Year 1 | I5: Year 2 | J5: Year 3 | K5: Year 4 | L5: Year 5 | N5: Year 1 | O5: Year 2 | P5: Year 3 | Q5: Year 4 | R5: Year 5
A7: VOLUME & DRIVERS
A8: Deals processed | B8: =ROUND(Assumptions!$C$10*'Launch Readiness'!$B$28,0) -> 1 | C8: =ROUND(Assumptions!$C$11*'Launch Readiness'!$C$28,0) -> 250 | D8: =ROUND(Assumptions!$C$12*'Launch Readiness'!$D$28,0) -> 1200 | E8: =ROUND(Assumptions!$C$147*'Launch Readiness'!$E$28,0) -> 1800 | F8: =ROUND(Assumptions!$C$148*'Launch Readiness'!$F$28,0) -> 6000 | H8: =ROUND(Assumptions!$D$10*'Launch Readiness'!$B$28,0) -> 3 | I8: =ROUND(Assumptions!$D$11*'Launch Readiness'!$C$28,0) -> 500 | J8: =ROUND(Assumptions!$D$12*'Launch Readiness'!$D$28,0) -> 2000 | K8: =ROUND(Assumptions!$D$147*'Launch Readiness'!$E$28,0) -> 15000 | L8: =ROUND(Assumptions!$D$148*'Launch Readiness'!$F$28,0) -> 30000 | N8: =ROUND(Assumptions!$E$10*'Launch Readiness'!$B$28,0) -> 9 | O8: =ROUND(Assumptions!$E$11*'Launch Readiness'!$C$28,0) -> 1000 | P8: =ROUND(Assumptions!$E$12*'Launch Readiness'!$D$28,0) -> 3200 | Q8: =ROUND(Assumptions!$E$147*'Launch Readiness'!$E$28,0) -> 32000 | R8: =ROUND(Assumptions!$E$148*'Launch Readiness'!$F$28,0) -> 70000
A9: Avg deal value (GBP) | B9: =IF(B8=0,0,B10/B8) -> 30250 | C9: =IF(C8=0,0,C10/C8) -> 32515 | D9: =IF(D8=0,0,D10/D8) -> 35696.8 | E9: =IF(E8=0,0,E10/E8) -> 39663.8 | F9: =IF(F8=0,0,F10/F8) -> 44333.779 | H9: =IF(H8=0,0,H10/H8) -> 30750 | I9: =IF(I8=0,0,I10/I8) -> 34005 | J9: =IF(J8=0,0,J10/J8) -> 38015.55 | K9: =IF(K8=0,0,K10/K8) -> 42822.535 | L9: =IF(L8=0,0,L10/L8) -> 47897.377 | N9: =IF(N8=0,0,N10/N8) -> 31500 | O9: =IF(O8=0,0,O10/O8) -> 35055 | P9: =IF(P8=0,0,P10/P8) -> 39678.85 | Q9: =IF(Q8=0,0,Q10/Q8) -> 44325.338 | R9: =IF(R8=0,0,R10/R8) -> 49322.816
A10: Gross trade value processed (GMV) | B10: =B8*(B11*'Tier Economics'!$B$8+B12*'Tier Economics'!$C$8+B13*'Tier Economics'!$D$8) -> 30250 | C10: =C8*(C11*'Tier Economics'!$F$8+C12*'Tier Economics'!$G$8+C13*'Tier Economics'!$H$8) -> 8128750 | D10: =D8*(D11*'Tier Economics'!$J$8+D12*'Tier Economics'!$K$8+D13*'Tier Economics'!$L$8) -> 42836160 | E10: =E8*(E11*'Tier Economics'!$N$8+E12*'Tier Economics'!$O$8+E13*'Tier Economics'!$P$8) -> 71394839 | F10: =F8*(F11*'Tier Economics'!$R$8+F12*'Tier Economics'!$S$8+F13*'Tier Economics'!$T$8) -> 2.6600267e+08 | H10: =H8*(H11*'Tier Economics'!$B$8+H12*'Tier Economics'!$C$8+H13*'Tier Economics'!$D$8) -> 92250 | I10: =I8*(I11*'Tier Economics'!$F$8+I12*'Tier Economics'!$G$8+I13*'Tier Economics'!$H$8) -> 17002500 | J10: =J8*(J11*'Tier Economics'!$J$8+J12*'Tier Economics'!$K$8+J13*'Tier Economics'!$L$8) -> 76031100 | K10: =K8*(K11*'Tier Economics'!$N$8+K12*'Tier Economics'!$O$8+K13*'Tier Economics'!$P$8) -> 6.4233803e+08 | L10: =L8*(L11*'Tier Economics'!$R$8+L12*'Tier Economics'!$S$8+L13*'Tier Economics'!$T$8) -> 1.4369213e+09 | N10: =N8*(N11*'Tier Economics'!$B$8+N12*'Tier Economics'!$C$8+N13*'Tier Economics'!$D$8) -> 283500 | O10: =O8*(O11*'Tier Economics'!$F$8+O12*'Tier Economics'!$G$8+O13*'Tier Economics'!$H$8) -> 35055000 | P10: =P8*(P11*'Tier Economics'!$J$8+P12*'Tier Economics'!$K$8+P13*'Tier Economics'!$L$8) -> 1.2697232e+08 | Q10: =Q8*(Q11*'Tier Economics'!$N$8+Q12*'Tier Economics'!$O$8+Q13*'Tier Economics'!$P$8) -> 1.4184108e+09 | R10: =R8*(R11*'Tier Economics'!$R$8+R12*'Tier Economics'!$S$8+R13*'Tier Economics'!$T$8) -> 3.4525971e+09
A11: Tier A eBL mix | B11: =Assumptions!$C$61 -> 0.05 | C11: =Assumptions!$C$64 -> 0.1 | D11: =Assumptions!$C$67 -> 0.2 | E11: =Assumptions!$C$149 -> 0.3 | F11: =Assumptions!$C$152 -> 0.4 | H11: =Assumptions!$D$61 -> 0.15 | I11: =Assumptions!$D$64 -> 0.3 | J11: =Assumptions!$D$67 -> 0.45 | K11: =Assumptions!$D$149 -> 0.6 | L11: =Assumptions!$D$152 -> 0.7 | N11: =Assumptions!$E$61 -> 0.3 | O11: =Assumptions!$E$64 -> 0.45 | P11: =Assumptions!$E$67 -> 0.65 | Q11: =Assumptions!$E$149 -> 0.75 | R11: =Assumptions!$E$152 -> 0.82
A12: Tier B carrier/API mix | B12: =Assumptions!$C$62 -> 0.25 | C12: =Assumptions!$C$65 -> 0.35 | D12: =Assumptions!$C$68 -> 0.4 | E12: =Assumptions!$C$150 -> 0.45 | F12: =Assumptions!$C$153 -> 0.45 | H12: =Assumptions!$D$62 -> 0.45 | I12: =Assumptions!$D$65 -> 0.45 | J12: =Assumptions!$D$68 -> 0.4 | K12: =Assumptions!$D$150 -> 0.32 | L12: =Assumptions!$D$153 -> 0.25 | N12: =Assumptions!$E$62 -> 0.5 | O12: =Assumptions!$E$65 -> 0.45 | P12: =Assumptions!$E$68 -> 0.3 | Q12: =Assumptions!$E$150 -> 0.23 | R12: =Assumptions!$E$153 -> 0.17
A13: Tier C paper mix | B13: =Assumptions!$C$63 -> 0.7 | C13: =Assumptions!$C$66 -> 0.55 | D13: =Assumptions!$C$69 -> 0.4 | E13: =Assumptions!$C$151 -> 0.25 | F13: =Assumptions!$C$154 -> 0.15 | H13: =Assumptions!$D$63 -> 0.4 | I13: =Assumptions!$D$66 -> 0.25 | J13: =Assumptions!$D$69 -> 0.15 | K13: =Assumptions!$D$151 -> 0.08 | L13: =Assumptions!$D$154 -> 0.05 | N13: =Assumptions!$E$63 -> 0.2 | O13: =Assumptions!$E$66 -> 0.1 | P13: =Assumptions!$E$69 -> 0.05 | Q13: =Assumptions!$E$151 -> 0.02 | R13: =Assumptions!$E$154 -> 0.01
A14: Documents processed | B14: =B8*(B11*Assumptions!$F$103+B12*Assumptions!$F$104+B13*Assumptions!$F$105) -> 7.95 | C14: =C8*(C11*Assumptions!$F$103+C12*Assumptions!$F$104+C13*Assumptions!$F$105) -> 1837.5 | D14: =D8*(D11*Assumptions!$F$103+D12*Assumptions!$F$104+D13*Assumptions!$F$105) -> 7920 | E14: =E8*(E11*Assumptions!$F$103+E12*Assumptions!$F$104+E13*Assumptions!$F$105) -> 10530 | F14: =F8*(F11*Assumptions!$F$103+F12*Assumptions!$F$104+F13*Assumptions!$F$105) -> 31500 | H14: =H8*(H11*Assumptions!$F$103+H12*Assumptions!$F$104+H13*Assumptions!$F$105) -> 20.25 | I14: =I8*(I11*Assumptions!$F$103+I12*Assumptions!$F$104+I13*Assumptions!$F$105) -> 2925 | J14: =J8*(J11*Assumptions!$F$103+J12*Assumptions!$F$104+J13*Assumptions!$F$105) -> 10200 | K14: =K8*(K11*Assumptions!$F$103+K12*Assumptions!$F$104+K13*Assumptions!$F$105) -> 66600 | L14: =L8*(L11*Assumptions!$F$103+L12*Assumptions!$F$104+L13*Assumptions!$F$105) -> 121500 | N14: =N8*(N11*Assumptions!$F$103+N12*Assumptions!$F$104+N13*Assumptions!$F$105) -> 51.3 | O14: =O8*(O11*Assumptions!$F$103+O12*Assumptions!$F$104+O13*Assumptions!$F$105) -> 4950 | P14: =P8*(P11*Assumptions!$F$103+P12*Assumptions!$F$104+P13*Assumptions!$F$105) -> 13440 | Q14: =Q8*(Q11*Assumptions!$F$103+Q12*Assumptions!$F$104+Q13*Assumptions!$F$105) -> 121920 | R14: =R8*(R11*Assumptions!$F$103+R12*Assumptions!$F$104+R13*Assumptions!$F$105) -> 249900
A15: New counterparties onboarded | B15: =B8*Assumptions!$F$13*Assumptions!$F$59 -> 1 | C15: =C8*Assumptions!$F$13*Assumptions!$F$59 -> 250 | D15: =D8*Assumptions!$F$13*Assumptions!$F$59 -> 1200 | E15: =E8*Assumptions!$F$13*Assumptions!$F$59 -> 1800 | F15: =F8*Assumptions!$F$13*Assumptions!$F$59 -> 6000 | H15: =H8*Assumptions!$F$13*Assumptions!$F$59 -> 3 | I15: =I8*Assumptions!$F$13*Assumptions!$F$59 -> 500 | J15: =J8*Assumptions!$F$13*Assumptions!$F$59 -> 2000 | K15: =K8*Assumptions!$F$13*Assumptions!$F$59 -> 15000 | L15: =L8*Assumptions!$F$13*Assumptions!$F$59 -> 30000 | N15: =N8*Assumptions!$F$13*Assumptions!$F$59 -> 9 | O15: =O8*Assumptions!$F$13*Assumptions!$F$59 -> 1000 | P15: =P8*Assumptions!$F$13*Assumptions!$F$59 -> 3200 | Q15: =Q8*Assumptions!$F$13*Assumptions!$F$59 -> 32000 | R15: =R8*Assumptions!$F$13*Assumptions!$F$59 -> 70000
A16: Disputed / amended deals | B16: =B8*(B11*Assumptions!$F$91+B12*Assumptions!$F$92+B13*Assumptions!$F$93) -> 0.167 | C16: =C8*(C11*Assumptions!$F$91+C12*Assumptions!$F$92+C13*Assumptions!$F$93) -> 37.25 | D16: =D8*(D11*Assumptions!$F$91+D12*Assumptions!$F$92+D13*Assumptions!$F$93) -> 153.6 | E16: =E8*(E11*Assumptions!$F$91+E12*Assumptions!$F$92+E13*Assumptions!$F$93) -> 192.6 | F16: =F8*(F11*Assumptions!$F$91+F12*Assumptions!$F$92+F13*Assumptions!$F$93) -> 546 | H16: =H8*(H11*Assumptions!$F$91+H12*Assumptions!$F$92+H13*Assumptions!$F$93) -> 0.393 | I16: =I8*(I11*Assumptions!$F$91+I12*Assumptions!$F$92+I13*Assumptions!$F$93) -> 53.5 | J16: =J8*(J11*Assumptions!$F$91+J12*Assumptions!$F$92+J13*Assumptions!$F$93) -> 176 | K16: =K8*(K11*Assumptions!$F$91+K12*Assumptions!$F$92+K13*Assumptions!$F$93) -> 1080 | L16: =L8*(L11*Assumptions!$F$91+L12*Assumptions!$F$92+L13*Assumptions!$F$93) -> 1890 | N16: =N8*(N11*Assumptions!$F$91+N12*Assumptions!$F$92+N13*Assumptions!$F$93) -> 0.918 | O16: =O8*(O11*Assumptions!$F$91+O12*Assumptions!$F$92+O13*Assumptions!$F$93) -> 83 | P16: =P8*(P11*Assumptions!$F$91+P12*Assumptions!$F$92+P13*Assumptions!$F$93) -> 211.2 | Q16: =Q8*(Q11*Assumptions!$F$91+Q12*Assumptions!$F$92+Q13*Assumptions!$F$93) -> 1824 | R16: =R8*(R11*Assumptions!$F$91+R12*Assumptions!$F$92+R13*Assumptions!$F$93) -> 3626
A18: REVENUE
A19: Escrow transaction fees | B19: =B8*(B11*MAX('Tier Economics'!$B$8*Assumptions!$F$70,Assumptions!$F$73)+B12*MAX('Tier Economics'!$C$8*Assumptions!$F$71,Assumptions!$F$74)+B13*MAX('Tier Economics'!$D$8*Assumptions!$F$72,Assumptions!$F$75)) -> 756.5 | C19: =C8*(C11*MAX('Tier Economics'!$F$8*Assumptions!$F$70,Assumptions!$F$73)+C12*MAX('Tier Economics'!$G$8*Assumptions!$F$71,Assumptions!$F$74)+C13*MAX('Tier Economics'!$H$8*Assumptions!$F$72,Assumptions!$F$75)) -> 180162.5 | D19: =D8*(D11*MAX('Tier Economics'!$J$8*Assumptions!$F$70,Assumptions!$F$73)+D12*MAX('Tier Economics'!$K$8*Assumptions!$F$71,Assumptions!$F$74)+D13*MAX('Tier Economics'!$L$8*Assumptions!$F$72,Assumptions!$F$75)) -> 809534.4 | E19: =E8*(E11*MAX('Tier Economics'!$N$8*Assumptions!$F$70,Assumptions!$F$73)+E12*MAX('Tier Economics'!$O$8*Assumptions!$F$71,Assumptions!$F$74)+E13*MAX('Tier Economics'!$P$8*Assumptions!$F$72,Assumptions!$F$75)) -> 1129250.3 | F19: =F8*(F11*MAX('Tier Economics'!$R$8*Assumptions!$F$70,Assumptions!$F$73)+F12*MAX('Tier Economics'!$S$8*Assumptions!$F$71,Assumptions!$F$74)+F13*MAX('Tier Economics'!$T$8*Assumptions!$F$72,Assumptions!$F$75)) -> 3621429.3 | H19: =H8*(H11*MAX('Tier Economics'!$B$8*Assumptions!$F$70,Assumptions!$F$73)+H12*MAX('Tier Economics'!$C$8*Assumptions!$F$71,Assumptions!$F$74)+H13*MAX('Tier Economics'!$D$8*Assumptions!$F$72,Assumptions!$F$75)) -> 1813.5 | I19: =I8*(I11*MAX('Tier Economics'!$F$8*Assumptions!$F$70,Assumptions!$F$73)+I12*MAX('Tier Economics'!$G$8*Assumptions!$F$71,Assumptions!$F$74)+I13*MAX('Tier Economics'!$H$8*Assumptions!$F$72,Assumptions!$F$75)) -> 273675 | J19: =J8*(J11*MAX('Tier Economics'!$J$8*Assumptions!$F$70,Assumptions!$F$73)+J12*MAX('Tier Economics'!$K$8*Assumptions!$F$71,Assumptions!$F$74)+J13*MAX('Tier Economics'!$L$8*Assumptions!$F$72,Assumptions!$F$75)) -> 1022499 | K19: =K8*(K11*MAX('Tier Economics'!$N$8*Assumptions!$F$70,Assumptions!$F$73)+K12*MAX('Tier Economics'!$O$8*Assumptions!$F$71,Assumptions!$F$74)+K13*MAX('Tier Economics'!$P$8*Assumptions!$F$72,Assumptions!$F$75)) -> 7325332.9 | L19: =L8*(L11*MAX('Tier Economics'!$R$8*Assumptions!$F$70,Assumptions!$F$73)+L12*MAX('Tier Economics'!$S$8*Assumptions!$F$71,Assumptions!$F$74)+L13*MAX('Tier Economics'!$T$8*Assumptions!$F$72,Assumptions!$F$75)) -> 14841492 | N19: =N8*(N11*MAX('Tier Economics'!$B$8*Assumptions!$F$70,Assumptions!$F$73)+N12*MAX('Tier Economics'!$C$8*Assumptions!$F$71,Assumptions!$F$74)+N13*MAX('Tier Economics'!$D$8*Assumptions!$F$72,Assumptions!$F$75)) -> 4401 | O19: =O8*(O11*MAX('Tier Economics'!$F$8*Assumptions!$F$70,Assumptions!$F$73)+O12*MAX('Tier Economics'!$G$8*Assumptions!$F$71,Assumptions!$F$74)+O13*MAX('Tier Economics'!$H$8*Assumptions!$F$72,Assumptions!$F$75)) -> 451800 | P19: =P8*(P11*MAX('Tier Economics'!$J$8*Assumptions!$F$70,Assumptions!$F$73)+P12*MAX('Tier Economics'!$K$8*Assumptions!$F$71,Assumptions!$F$74)+P13*MAX('Tier Economics'!$L$8*Assumptions!$F$72,Assumptions!$F$75)) -> 1367348.8 | Q19: =Q8*(Q11*MAX('Tier Economics'!$N$8*Assumptions!$F$70,Assumptions!$F$73)+Q12*MAX('Tier Economics'!$O$8*Assumptions!$F$71,Assumptions!$F$74)+Q13*MAX('Tier Economics'!$P$8*Assumptions!$F$72,Assumptions!$F$75)) -> 13783278 | R19: =R8*(R11*MAX('Tier Economics'!$R$8*Assumptions!$F$70,Assumptions!$F$73)+R12*MAX('Tier Economics'!$S$8*Assumptions!$F$71,Assumptions!$F$74)+R13*MAX('Tier Economics'!$T$8*Assumptions!$F$72,Assumptions!$F$75)) -> 31582203
A20: Document review fees | B20: =B8*(B11*Assumptions!$F$76+B12*Assumptions!$F$77+B13*Assumptions!$F$78) -> 233.75 | C20: =C8*(C11*Assumptions!$F$76+C12*Assumptions!$F$77+C13*Assumptions!$F$78) -> 49750 | D20: =D8*(D11*Assumptions!$F$76+D12*Assumptions!$F$77+D13*Assumptions!$F$78) -> 193200 | E20: =E8*(E11*Assumptions!$F$76+E12*Assumptions!$F$77+E13*Assumptions!$F$78) -> 221400 | F20: =F8*(F11*Assumptions!$F$76+F12*Assumptions!$F$77+F13*Assumptions!$F$78) -> 573000 | H20: =H8*(H11*Assumptions!$F$76+H12*Assumptions!$F$77+H13*Assumptions!$F$78) -> 492.75 | I20: =I8*(I11*Assumptions!$F$76+I12*Assumptions!$F$77+I13*Assumptions!$F$78) -> 61500 | J20: =J8*(J11*Assumptions!$F$76+J12*Assumptions!$F$77+J13*Assumptions!$F$78) -> 184500 | K20: =K8*(K11*Assumptions!$F$76+K12*Assumptions!$F$77+K13*Assumptions!$F$78) -> 1017000 | L20: =L8*(L11*Assumptions!$F$76+L12*Assumptions!$F$77+L13*Assumptions!$F$78) -> 1650000 | N20: =N8*(N11*Assumptions!$F$76+N12*Assumptions!$F$77+N13*Assumptions!$F$78) -> 1012.5 | O20: =O8*(O11*Assumptions!$F$76+O12*Assumptions!$F$77+O13*Assumptions!$F$78) -> 81750 | P20: =P8*(P11*Assumptions!$F$76+P12*Assumptions!$F$77+P13*Assumptions!$F$78) -> 186400 | Q20: =Q8*(Q11*Assumptions!$F$76+Q12*Assumptions!$F$77+Q13*Assumptions!$F$78) -> 1454400 | R20: =R8*(R11*Assumptions!$F$76+R12*Assumptions!$F$77+R13*Assumptions!$F$78) -> 2716000
A21: Dispute / amendment fees | B21: =B8*(B11*Assumptions!$F$91*Assumptions!$F$79+B12*Assumptions!$F$92*Assumptions!$F$80+B13*Assumptions!$F$93*Assumptions!$F$81) -> 75.2 | C21: =C8*(C11*Assumptions!$F$91*Assumptions!$F$79+C12*Assumptions!$F$92*Assumptions!$F$80+C13*Assumptions!$F$93*Assumptions!$F$81) -> 15600 | D21: =D8*(D11*Assumptions!$F$91*Assumptions!$F$79+D12*Assumptions!$F$92*Assumptions!$F$80+D13*Assumptions!$F$93*Assumptions!$F$81) -> 58560 | E21: =E8*(E11*Assumptions!$F$91*Assumptions!$F$79+E12*Assumptions!$F$92*Assumptions!$F$80+E13*Assumptions!$F$93*Assumptions!$F$81) -> 63360 | F21: =F8*(F11*Assumptions!$F$91*Assumptions!$F$79+F12*Assumptions!$F$92*Assumptions!$F$80+F13*Assumptions!$F$93*Assumptions!$F$81) -> 153600 | H21: =H8*(H11*Assumptions!$F$91*Assumptions!$F$79+H12*Assumptions!$F$92*Assumptions!$F$80+H13*Assumptions!$F$93*Assumptions!$F$81) -> 148.8 | I21: =I8*(I11*Assumptions!$F$91*Assumptions!$F$79+I12*Assumptions!$F$92*Assumptions!$F$80+I13*Assumptions!$F$93*Assumptions!$F$81) -> 17600 | J21: =J8*(J11*Assumptions!$F$91*Assumptions!$F$79+J12*Assumptions!$F$92*Assumptions!$F$80+J13*Assumptions!$F$93*Assumptions!$F$81) -> 49600 | K21: =K8*(K11*Assumptions!$F$91*Assumptions!$F$79+K12*Assumptions!$F$92*Assumptions!$F$80+K13*Assumptions!$F$93*Assumptions!$F$81) -> 252000 | L21: =L8*(L11*Assumptions!$F$91*Assumptions!$F$79+L12*Assumptions!$F$92*Assumptions!$F$80+L13*Assumptions!$F$93*Assumptions!$F$81) -> 384000 | N21: =N8*(N11*Assumptions!$F$91*Assumptions!$F$79+N12*Assumptions!$F$92*Assumptions!$F$80+N13*Assumptions!$F$93*Assumptions!$F$81) -> 280.8 | O21: =O8*(O11*Assumptions!$F$91*Assumptions!$F$79+O12*Assumptions!$F$92*Assumptions!$F$80+O13*Assumptions!$F$93*Assumptions!$F$81) -> 20800 | P21: =P8*(P11*Assumptions!$F$91*Assumptions!$F$79+P12*Assumptions!$F$92*Assumptions!$F$80+P13*Assumptions!$F$93*Assumptions!$F$81) -> 43520 | Q21: =Q8*(Q11*Assumptions!$F$91*Assumptions!$F$79+Q12*Assumptions!$F$92*Assumptions!$F$80+Q13*Assumptions!$F$93*Assumptions!$F$81) -> 307200 | R21: =R8*(R11*Assumptions!$F$91*Assumptions!$F$79+R12*Assumptions!$F$92*Assumptions!$F$80+R13*Assumptions!$F$93*Assumptions!$F$81) -> 537600
A22: First-deal discount drag | B22: =IFERROR(ROUND(-B62*(B19/B8)*Assumptions!$F$112,0),0) -> -252 | C22: =IFERROR(ROUND(-MAX(0,C62-B62)*(C19/C8)*Assumptions!$F$112,0),0) -> -44800 | D22: =IFERROR(ROUND(-MAX(0,D62-C62)*(D19/D8)*Assumptions!$F$112,0),0) -> -119744 | E22: =IFERROR(ROUND(-MAX(0,E62-D62)*(E19/E8)*Assumptions!$F$112,0),0) -> -37642 | F22: =IFERROR(ROUND(-MAX(0,F62-E62)*(F19/F8)*Assumptions!$F$112,0),0) -> -271607 | H22: =IFERROR(ROUND(-H62*(H19/H8)*Assumptions!$F$112,0),0) -> -302 | I22: =IFERROR(ROUND(-MAX(0,I62-H62)*(I19/I8)*Assumptions!$F$112,0),0) -> -33936 | J22: =IFERROR(ROUND(-MAX(0,J62-I62)*(J19/J8)*Assumptions!$F$112,0),0) -> -53255 | K22: =IFERROR(ROUND(-MAX(0,K62-J62)*(K19/K8)*Assumptions!$F$112,0),0) -> -376441 | L22: =IFERROR(ROUND(-MAX(0,L62-K62)*(L19/L8)*Assumptions!$F$112,0),0) -> -278278 | N22: =IFERROR(ROUND(-N62*(N19/N8)*Assumptions!$F$112,0),0) -> -440 | O22: =IFERROR(ROUND(-MAX(0,O62-N62)*(O19/O8)*Assumptions!$F$112,0),0) -> -37243 | P22: =IFERROR(ROUND(-MAX(0,P62-O62)*(P19/P8)*Assumptions!$F$112,0),0) -> -32759 | Q22: =IFERROR(ROUND(-MAX(0,Q62-P62)*(Q19/Q8)*Assumptions!$F$112,0),0) -> -505387 | R22: =IFERROR(ROUND(-MAX(0,R62-Q62)*(R19/R8)*Assumptions!$F$112,0),0) -> -451174
A23: Expedited review fees | B23: =ROUND(B8*B12*Assumptions!$F$113*Assumptions!$F$115+B8*B13*Assumptions!$F$114*Assumptions!$F$116,0) -> 46 | C23: =ROUND(C8*C12*Assumptions!$F$113*Assumptions!$F$115+C8*C13*Assumptions!$F$114*Assumptions!$F$116,0) -> 9563 | D23: =ROUND(D8*D12*Assumptions!$F$113*Assumptions!$F$115+D8*D13*Assumptions!$F$114*Assumptions!$F$116,0) -> 36000 | E23: =ROUND(E8*E12*Assumptions!$F$113*Assumptions!$F$115+E8*E13*Assumptions!$F$114*Assumptions!$F$116,0) -> 39150 | F23: =ROUND(F8*F12*Assumptions!$F$113*Assumptions!$F$115+F8*F13*Assumptions!$F$114*Assumptions!$F$116,0) -> 94500 | H23: =ROUND(H8*H12*Assumptions!$F$113*Assumptions!$F$115+H8*H13*Assumptions!$F$114*Assumptions!$F$116,0) -> 92 | I23: =ROUND(I8*I12*Assumptions!$F$113*Assumptions!$F$115+I8*I13*Assumptions!$F$114*Assumptions!$F$116,0) -> 10875 | J23: =ROUND(J8*J12*Assumptions!$F$113*Assumptions!$F$115+J8*J13*Assumptions!$F$114*Assumptions!$F$116,0) -> 30000 | K23: =ROUND(K8*K12*Assumptions!$F$113*Assumptions!$F$115+K8*K13*Assumptions!$F$114*Assumptions!$F$116,0) -> 144000 | L23: =ROUND(L8*L12*Assumptions!$F$113*Assumptions!$F$115+L8*L13*Assumptions!$F$114*Assumptions!$F$116,0) -> 202500 | N23: =ROUND(N8*N12*Assumptions!$F$113*Assumptions!$F$115+N8*N13*Assumptions!$F$114*Assumptions!$F$116,0) -> 176 | O23: =ROUND(O8*O12*Assumptions!$F$113*Assumptions!$F$115+O8*O13*Assumptions!$F$114*Assumptions!$F$116,0) -> 12750 | P23: =ROUND(P8*P12*Assumptions!$F$113*Assumptions!$F$115+P8*P13*Assumptions!$F$114*Assumptions!$F$116,0) -> 24000 | Q23: =ROUND(Q8*Q12*Assumptions!$F$113*Assumptions!$F$115+Q8*Q13*Assumptions!$F$114*Assumptions!$F$116,0) -> 148800 | R23: =ROUND(R8*R12*Assumptions!$F$113*Assumptions!$F$115+R8*R13*Assumptions!$F$114*Assumptions!$F$116,0) -> 220500
A24: KYC/KYB onboarding fees | B24: =ROUND(B15*Assumptions!$F$117,0) -> 15 | C24: =ROUND(C15*Assumptions!$F$117,0) -> 3750 | D24: =ROUND(D15*Assumptions!$F$117,0) -> 18000 | E24: =ROUND(E15*Assumptions!$F$117,0) -> 27000 | F24: =ROUND(F15*Assumptions!$F$117,0) -> 90000 | H24: =ROUND(H15*Assumptions!$F$117,0) -> 45 | I24: =ROUND(I15*Assumptions!$F$117,0) -> 7500 | J24: =ROUND(J15*Assumptions!$F$117,0) -> 30000 | K24: =ROUND(K15*Assumptions!$F$117,0) -> 225000 | L24: =ROUND(L15*Assumptions!$F$117,0) -> 450000 | N24: =ROUND(N15*Assumptions!$F$117,0) -> 135 | O24: =ROUND(O15*Assumptions!$F$117,0) -> 15000 | P24: =ROUND(P15*Assumptions!$F$117,0) -> 48000 | Q24: =ROUND(Q15*Assumptions!$F$117,0) -> 480000 | R24: =ROUND(R15*Assumptions!$F$117,0) -> 1050000
A25: Tier C forensics pass-through margin | B25: =ROUND(B8*B13*Assumptions!$F$84*Assumptions!$F$118,0) -> 21 | C25: =ROUND(C8*C13*Assumptions!$F$84*Assumptions!$F$118,0) -> 4125 | D25: =ROUND(D8*D13*Assumptions!$F$84*Assumptions!$F$118,0) -> 14400 | E25: =ROUND(E8*E13*Assumptions!$F$84*Assumptions!$F$118,0) -> 13500 | F25: =ROUND(F8*F13*Assumptions!$F$84*Assumptions!$F$118,0) -> 27000 | H25: =ROUND(H8*H13*Assumptions!$F$84*Assumptions!$F$118,0) -> 36 | I25: =ROUND(I8*I13*Assumptions!$F$84*Assumptions!$F$118,0) -> 3750 | J25: =ROUND(J8*J13*Assumptions!$F$84*Assumptions!$F$118,0) -> 9000 | K25: =ROUND(K8*K13*Assumptions!$F$84*Assumptions!$F$118,0) -> 36000 | L25: =ROUND(L8*L13*Assumptions!$F$84*Assumptions!$F$118,0) -> 45000 | N25: =ROUND(N8*N13*Assumptions!$F$84*Assumptions!$F$118,0) -> 54 | O25: =ROUND(O8*O13*Assumptions!$F$84*Assumptions!$F$118,0) -> 3000 | P25: =ROUND(P8*P13*Assumptions!$F$84*Assumptions!$F$118,0) -> 4800 | Q25: =ROUND(Q8*Q13*Assumptions!$F$84*Assumptions!$F$118,0) -> 19200 | R25: =ROUND(R8*R13*Assumptions!$F$84*Assumptions!$F$118,0) -> 21000
A26: Tier C courier / original handling fees | B26: =ROUND(B8*B13*Assumptions!$F$119,0) -> 53 | C26: =ROUND(C8*C13*Assumptions!$F$119,0) -> 10313 | D26: =ROUND(D8*D13*Assumptions!$F$119,0) -> 36000 | E26: =ROUND(E8*E13*Assumptions!$F$119,0) -> 33750 | F26: =ROUND(F8*F13*Assumptions!$F$119,0) -> 67500 | H26: =ROUND(H8*H13*Assumptions!$F$119,0) -> 90 | I26: =ROUND(I8*I13*Assumptions!$F$119,0) -> 9375 | J26: =ROUND(J8*J13*Assumptions!$F$119,0) -> 22500 | K26: =ROUND(K8*K13*Assumptions!$F$119,0) -> 90000 | L26: =ROUND(L8*L13*Assumptions!$F$119,0) -> 112500 | N26: =ROUND(N8*N13*Assumptions!$F$119,0) -> 135 | O26: =ROUND(O8*O13*Assumptions!$F$119,0) -> 7500 | P26: =ROUND(P8*P13*Assumptions!$F$119,0) -> 12000 | Q26: =ROUND(Q8*Q13*Assumptions!$F$119,0) -> 48000 | R26: =ROUND(R8*R13*Assumptions!$F$119,0) -> 52500
A27: Discrepancy cure / waiver fees | B27: =ROUND(B16*Assumptions!$F$121*Assumptions!$F$120,0) -> 10 | C27: =ROUND(C16*Assumptions!$F$121*Assumptions!$F$120,0) -> 2235 | D27: =ROUND(D16*Assumptions!$F$121*Assumptions!$F$120,0) -> 9216 | E27: =ROUND(E16*Assumptions!$F$121*Assumptions!$F$120,0) -> 11556 | F27: =ROUND(F16*Assumptions!$F$121*Assumptions!$F$120,0) -> 32760 | H27: =ROUND(H16*Assumptions!$F$121*Assumptions!$F$120,0) -> 24 | I27: =ROUND(I16*Assumptions!$F$121*Assumptions!$F$120,0) -> 3210 | J27: =ROUND(J16*Assumptions!$F$121*Assumptions!$F$120,0) -> 10560 | K27: =ROUND(K16*Assumptions!$F$121*Assumptions!$F$120,0) -> 64800 | L27: =ROUND(L16*Assumptions!$F$121*Assumptions!$F$120,0) -> 113400 | N27: =ROUND(N16*Assumptions!$F$121*Assumptions!$F$120,0) -> 55 | O27: =ROUND(O16*Assumptions!$F$121*Assumptions!$F$120,0) -> 4980 | P27: =ROUND(P16*Assumptions!$F$121*Assumptions!$F$120,0) -> 12672 | Q27: =ROUND(Q16*Assumptions!$F$121*Assumptions!$F$120,0) -> 109440 | R27: =ROUND(R16*Assumptions!$F$121*Assumptions!$F$120,0) -> 217560
A28: Partner setup & committed-volume fees | B28: =0 -> 0 | C28: =ROUND(Assumptions!$C$14*Assumptions!$F$122,0)+ROUND(Assumptions!$C$14*Assumptions!$F$123*12,0) -> 0 | D28: =ROUND(MAX(0,Assumptions!$C$110-Assumptions!$C$14)*Assumptions!$F$122,0)+ROUND(Assumptions!$C$110*Assumptions!$F$123*12,0) -> 0 | E28: =ROUND(MAX(0,Assumptions!$C$155-Assumptions!$C$110)*Assumptions!$F$122,0)+ROUND(Assumptions!$C$155*Assumptions!$F$123*12,0) -> 16500 | F28: =ROUND(MAX(0,Assumptions!$C$156-Assumptions!$C$155)*Assumptions!$F$122,0)+ROUND(Assumptions!$C$156*Assumptions!$F$123*12,0) -> 42000 | H28: =0 -> 0 | I28: =ROUND(Assumptions!$D$14*Assumptions!$F$122,0)+ROUND(Assumptions!$D$14*Assumptions!$F$123*12,0) -> 49500 | J28: =ROUND(MAX(0,Assumptions!$D$110-Assumptions!$D$14)*Assumptions!$F$122,0)+ROUND(Assumptions!$D$110*Assumptions!$F$123*12,0) -> 76500 | K28: =ROUND(MAX(0,Assumptions!$D$155-Assumptions!$D$110)*Assumptions!$F$122,0)+ROUND(Assumptions!$D$155*Assumptions!$F$123*12,0) -> 120000 | L28: =ROUND(MAX(0,Assumptions!$D$156-Assumptions!$D$155)*Assumptions!$F$122,0)+ROUND(Assumptions!$D$156*Assumptions!$F$123*12,0) -> 222000 | N28: =0 -> 0 | O28: =ROUND(Assumptions!$E$14*Assumptions!$F$122,0)+ROUND(Assumptions!$E$14*Assumptions!$F$123*12,0) -> 165000 | P28: =ROUND(MAX(0,Assumptions!$E$110-Assumptions!$E$14)*Assumptions!$F$122,0)+ROUND(Assumptions!$E$110*Assumptions!$F$123*12,0) -> 255000 | Q28: =ROUND(MAX(0,Assumptions!$E$155-Assumptions!$E$110)*Assumptions!$F$122,0)+ROUND(Assumptions!$E$155*Assumptions!$F$123*12,0) -> 427500 | R28: =ROUND(MAX(0,Assumptions!$E$156-Assumptions!$E$155)*Assumptions!$F$122,0)+ROUND(Assumptions!$E$156*Assumptions!$F$123*12,0) -> 727500
A29: Archive / audit record fees | B29: =ROUND(B8*Assumptions!$F$124,0) -> 3 | C29: =ROUND(C8*Assumptions!$F$124,0) -> 750 | D29: =ROUND(D8*Assumptions!$F$124,0) -> 3600 | E29: =ROUND(E8*Assumptions!$F$124,0) -> 5400 | F29: =ROUND(F8*Assumptions!$F$124,0) -> 18000 | H29: =ROUND(H8*Assumptions!$F$124,0) -> 9 | I29: =ROUND(I8*Assumptions!$F$124,0) -> 1500 | J29: =ROUND(J8*Assumptions!$F$124,0) -> 6000 | K29: =ROUND(K8*Assumptions!$F$124,0) -> 45000 | L29: =ROUND(L8*Assumptions!$F$124,0) -> 90000 | N29: =ROUND(N8*Assumptions!$F$124,0) -> 27 | O29: =ROUND(O8*Assumptions!$F$124,0) -> 3000 | P29: =ROUND(P8*Assumptions!$F$124,0) -> 9600 | Q29: =ROUND(Q8*Assumptions!$F$124,0) -> 96000 | R29: =ROUND(R8*Assumptions!$F$124,0) -> 210000
A30: Total revenue | B30: =SUM(B19:B29) -> 961.45 | C30: =SUM(C19:C29) -> 231448.5 | D30: =SUM(D19:D29) -> 1058766.4 | E30: =SUM(E19:E29) -> 1523224.3 | F30: =SUM(F19:F29) -> 4448182.3 | H30: =SUM(H19:H29) -> 2449.05 | I30: =SUM(I19:I29) -> 404549 | J30: =SUM(J19:J29) -> 1387904 | K30: =SUM(K19:K29) -> 8942691.9 | L30: =SUM(L19:L29) -> 17832614 | N30: =SUM(N19:N29) -> 5836.3 | O30: =SUM(O19:O29) -> 728337 | P30: =SUM(P19:P29) -> 1930581.8 | Q30: =SUM(Q19:Q29) -> 16368431 | R30: =SUM(R19:R29) -> 36883689
A32: COGS / VARIABLE COSTS
A33: Claude API (doc extraction) | B33: =B14*Assumptions!$F$23/Assumptions!$F$8 -> 1.8632812 | C33: =C14*Assumptions!$F$23/Assumptions!$F$8 -> 430.66406 | D33: =D14*Assumptions!$F$23/Assumptions!$F$8 -> 1856.25 | E33: =E14*Assumptions!$F$23/Assumptions!$F$8 -> 2467.9688 | F33: =F14*Assumptions!$F$23/Assumptions!$F$8 -> 7382.8125 | H33: =H14*Assumptions!$F$23/Assumptions!$F$8 -> 4.7460938 | I33: =I14*Assumptions!$F$23/Assumptions!$F$8 -> 685.54688 | J33: =J14*Assumptions!$F$23/Assumptions!$F$8 -> 2390.625 | K33: =K14*Assumptions!$F$23/Assumptions!$F$8 -> 15609.375 | L33: =L14*Assumptions!$F$23/Assumptions!$F$8 -> 28476.562 | N33: =N14*Assumptions!$F$23/Assumptions!$F$8 -> 12.023438 | O33: =O14*Assumptions!$F$23/Assumptions!$F$8 -> 1160.1563 | P33: =P14*Assumptions!$F$23/Assumptions!$F$8 -> 3150 | Q33: =Q14*Assumptions!$F$23/Assumptions!$F$8 -> 28575 | R33: =R14*Assumptions!$F$23/Assumptions!$F$8 -> 58570.312
A34: KYB business onboarding | B34: =B15*Assumptions!$F$24/Assumptions!$F$8 -> 2.734375 | C34: =C15*Assumptions!$F$24/Assumptions!$F$8 -> 683.59375 | D34: =D15*Assumptions!$F$24/Assumptions!$F$8 -> 3281.25 | E34: =E15*Assumptions!$F$24/Assumptions!$F$8 -> 4921.875 | F34: =F15*Assumptions!$F$24/Assumptions!$F$8 -> 16406.25 | H34: =H15*Assumptions!$F$24/Assumptions!$F$8 -> 8.203125 | I34: =I15*Assumptions!$F$24/Assumptions!$F$8 -> 1367.1875 | J34: =J15*Assumptions!$F$24/Assumptions!$F$8 -> 5468.75 | K34: =K15*Assumptions!$F$24/Assumptions!$F$8 -> 41015.625 | L34: =L15*Assumptions!$F$24/Assumptions!$F$8 -> 82031.25 | N34: =N15*Assumptions!$F$24/Assumptions!$F$8 -> 24.609375 | O34: =O15*Assumptions!$F$24/Assumptions!$F$8 -> 2734.375 | P34: =P15*Assumptions!$F$24/Assumptions!$F$8 -> 8750 | Q34: =Q15*Assumptions!$F$24/Assumptions!$F$8 -> 87500 | R34: =R15*Assumptions!$F$24/Assumptions!$F$8 -> 191406.25
A35: KYC/UBO + sanctions onboarding | B35: =B15*Assumptions!$F$25/Assumptions!$F$8 -> 1.0546875 | C35: =C15*Assumptions!$F$25/Assumptions!$F$8 -> 263.67188 | D35: =D15*Assumptions!$F$25/Assumptions!$F$8 -> 1265.625 | E35: =E15*Assumptions!$F$25/Assumptions!$F$8 -> 1898.4375 | F35: =F15*Assumptions!$F$25/Assumptions!$F$8 -> 6328.125 | H35: =H15*Assumptions!$F$25/Assumptions!$F$8 -> 3.1640625 | I35: =I15*Assumptions!$F$25/Assumptions!$F$8 -> 527.34375 | J35: =J15*Assumptions!$F$25/Assumptions!$F$8 -> 2109.375 | K35: =K15*Assumptions!$F$25/Assumptions!$F$8 -> 15820.312 | L35: =L15*Assumptions!$F$25/Assumptions!$F$8 -> 31640.625 | N35: =N15*Assumptions!$F$25/Assumptions!$F$8 -> 9.4921875 | O35: =O15*Assumptions!$F$25/Assumptions!$F$8 -> 1054.6875 | P35: =P15*Assumptions!$F$25/Assumptions!$F$8 -> 3375 | Q35: =Q15*Assumptions!$F$25/Assumptions!$F$8 -> 33750 | R35: =R15*Assumptions!$F$25/Assumptions!$F$8 -> 73828.125
A36: Tiered document verification ops | B36: =B8*(B11*Assumptions!$F$82+B12*Assumptions!$F$83+B13*Assumptions!$F$84)+B8*(B11*Assumptions!$F$85+B12*Assumptions!$F$86+B13*Assumptions!$F$87) -> 217.8 | C36: =C8*(C11*Assumptions!$F$82+C12*Assumptions!$F$83+C13*Assumptions!$F$84)+C8*(C11*Assumptions!$F$85+C12*Assumptions!$F$86+C13*Assumptions!$F$87) -> 44025 | D36: =D8*(D11*Assumptions!$F$82+D12*Assumptions!$F$83+D13*Assumptions!$F$84)+D8*(D11*Assumptions!$F$85+D12*Assumptions!$F$86+D13*Assumptions!$F$87) -> 159840 | E36: =E8*(E11*Assumptions!$F$82+E12*Assumptions!$F$83+E13*Assumptions!$F$84)+E8*(E11*Assumptions!$F$85+E12*Assumptions!$F$86+E13*Assumptions!$F$87) -> 162540 | F36: =F8*(F11*Assumptions!$F$82+F12*Assumptions!$F$83+F13*Assumptions!$F$84)+F8*(F11*Assumptions!$F$85+F12*Assumptions!$F$86+F13*Assumptions!$F$87) -> 365400 | H36: =H8*(H11*Assumptions!$F$82+H12*Assumptions!$F$83+H13*Assumptions!$F$84)+H8*(H11*Assumptions!$F$85+H12*Assumptions!$F$86+H13*Assumptions!$F$87) -> 403.2 | I36: =I8*(I11*Assumptions!$F$82+I12*Assumptions!$F$83+I13*Assumptions!$F$84)+I8*(I11*Assumptions!$F$85+I12*Assumptions!$F$86+I13*Assumptions!$F$87) -> 45150 | J36: =J8*(J11*Assumptions!$F$82+J12*Assumptions!$F$83+J13*Assumptions!$F$84)+J8*(J11*Assumptions!$F$85+J12*Assumptions!$F$86+J13*Assumptions!$F$87) -> 119400 | K36: =K8*(K11*Assumptions!$F$82+K12*Assumptions!$F$83+K13*Assumptions!$F$84)+K8*(K11*Assumptions!$F$85+K12*Assumptions!$F$86+K13*Assumptions!$F$87) -> 558000 | L36: =L8*(L11*Assumptions!$F$82+L12*Assumptions!$F$83+L13*Assumptions!$F$84)+L8*(L11*Assumptions!$F$85+L12*Assumptions!$F$86+L13*Assumptions!$F$87) -> 801000 | N36: =N8*(N11*Assumptions!$F$82+N12*Assumptions!$F$83+N13*Assumptions!$F$84)+N8*(N11*Assumptions!$F$85+N12*Assumptions!$F$86+N13*Assumptions!$F$87) -> 691.2 | O36: =O8*(O11*Assumptions!$F$82+O12*Assumptions!$F$83+O13*Assumptions!$F$84)+O8*(O11*Assumptions!$F$85+O12*Assumptions!$F$86+O13*Assumptions!$F$87) -> 46200 | P36: =P8*(P11*Assumptions!$F$82+P12*Assumptions!$F$83+P13*Assumptions!$F$84)+P8*(P11*Assumptions!$F$85+P12*Assumptions!$F$86+P13*Assumptions!$F$87) -> 89280 | Q36: =Q8*(Q11*Assumptions!$F$82+Q12*Assumptions!$F$83+Q13*Assumptions!$F$84)+Q8*(Q11*Assumptions!$F$85+Q12*Assumptions!$F$86+Q13*Assumptions!$F$87) -> 556800 | R36: =R8*(R11*Assumptions!$F$82+R12*Assumptions!$F$83+R13*Assumptions!$F$84)+R8*(R11*Assumptions!$F$85+R12*Assumptions!$F$86+R13*Assumptions!$F$87) -> 911400
A37: Blockchain gas | B37: =B8*Assumptions!$F$26/Assumptions!$F$8 -> 0.15625 | C37: =C8*Assumptions!$F$26/Assumptions!$F$8 -> 39.0625 | D37: =D8*Assumptions!$F$26/Assumptions!$F$8 -> 187.5 | E37: =E8*Assumptions!$F$26/Assumptions!$F$8 -> 281.25 | F37: =F8*Assumptions!$F$26/Assumptions!$F$8 -> 937.5 | H37: =H8*Assumptions!$F$26/Assumptions!$F$8 -> 0.46875 | I37: =I8*Assumptions!$F$26/Assumptions!$F$8 -> 78.125 | J37: =J8*Assumptions!$F$26/Assumptions!$F$8 -> 312.5 | K37: =K8*Assumptions!$F$26/Assumptions!$F$8 -> 2343.75 | L37: =L8*Assumptions!$F$26/Assumptions!$F$8 -> 4687.5 | N37: =N8*Assumptions!$F$26/Assumptions!$F$8 -> 1.40625 | O37: =O8*Assumptions!$F$26/Assumptions!$F$8 -> 156.25 | P37: =P8*Assumptions!$F$26/Assumptions!$F$8 -> 500 | Q37: =Q8*Assumptions!$F$26/Assumptions!$F$8 -> 5000 | R37: =R8*Assumptions!$F$26/Assumptions!$F$8 -> 10937.5
A38: RPC / node provider | B38: =B8*Assumptions!$F$27/Assumptions!$F$8 -> 0.0078125 | C38: =C8*Assumptions!$F$27/Assumptions!$F$8 -> 1.953125 | D38: =D8*Assumptions!$F$27/Assumptions!$F$8 -> 9.375 | E38: =E8*Assumptions!$F$27/Assumptions!$F$8 -> 14.0625 | F38: =F8*Assumptions!$F$27/Assumptions!$F$8 -> 46.875 | H38: =H8*Assumptions!$F$27/Assumptions!$F$8 -> 0.0234375 | I38: =I8*Assumptions!$F$27/Assumptions!$F$8 -> 3.90625 | J38: =J8*Assumptions!$F$27/Assumptions!$F$8 -> 15.625 | K38: =K8*Assumptions!$F$27/Assumptions!$F$8 -> 117.1875 | L38: =L8*Assumptions!$F$27/Assumptions!$F$8 -> 234.375 | N38: =N8*Assumptions!$F$27/Assumptions!$F$8 -> 0.0703125 | O38: =O8*Assumptions!$F$27/Assumptions!$F$8 -> 7.8125 | P38: =P8*Assumptions!$F$27/Assumptions!$F$8 -> 25 | Q38: =Q8*Assumptions!$F$27/Assumptions!$F$8 -> 250 | R38: =R8*Assumptions!$F$27/Assumptions!$F$8 -> 546.875
A39: Document / ledger storage | B39: =B8*Assumptions!$F$28/Assumptions!$F$8 -> 0.0234375 | C39: =C8*Assumptions!$F$28/Assumptions!$F$8 -> 5.859375 | D39: =D8*Assumptions!$F$28/Assumptions!$F$8 -> 28.125 | E39: =E8*Assumptions!$F$28/Assumptions!$F$8 -> 42.1875 | F39: =F8*Assumptions!$F$28/Assumptions!$F$8 -> 140.625 | H39: =H8*Assumptions!$F$28/Assumptions!$F$8 -> 0.0703125 | I39: =I8*Assumptions!$F$28/Assumptions!$F$8 -> 11.71875 | J39: =J8*Assumptions!$F$28/Assumptions!$F$8 -> 46.875 | K39: =K8*Assumptions!$F$28/Assumptions!$F$8 -> 351.5625 | L39: =L8*Assumptions!$F$28/Assumptions!$F$8 -> 703.125 | N39: =N8*Assumptions!$F$28/Assumptions!$F$8 -> 0.2109375 | O39: =O8*Assumptions!$F$28/Assumptions!$F$8 -> 23.4375 | P39: =P8*Assumptions!$F$28/Assumptions!$F$8 -> 75 | Q39: =Q8*Assumptions!$F$28/Assumptions!$F$8 -> 750 | R39: =R8*Assumptions!$F$28/Assumptions!$F$8 -> 1640.625
A40: Customer support | B40: =B8*(B11*Assumptions!$F$88+B12*Assumptions!$F$89+B13*Assumptions!$F$90) -> 15.6 | C40: =C8*(C11*Assumptions!$F$88+C12*Assumptions!$F$89+C13*Assumptions!$F$90) -> 3325 | D40: =D8*(D11*Assumptions!$F$88+D12*Assumptions!$F$89+D13*Assumptions!$F$90) -> 12960 | E40: =E8*(E11*Assumptions!$F$88+E12*Assumptions!$F$89+E13*Assumptions!$F$90) -> 14940 | F40: =F8*(F11*Assumptions!$F$88+F12*Assumptions!$F$89+F13*Assumptions!$F$90) -> 39000 | H40: =H8*(H11*Assumptions!$F$88+H12*Assumptions!$F$89+H13*Assumptions!$F$90) -> 33 | I40: =I8*(I11*Assumptions!$F$88+I12*Assumptions!$F$89+I13*Assumptions!$F$90) -> 4150 | J40: =J8*(J11*Assumptions!$F$88+J12*Assumptions!$F$89+J13*Assumptions!$F$90) -> 12600 | K40: =K8*(K11*Assumptions!$F$88+K12*Assumptions!$F$89+K13*Assumptions!$F$90) -> 70800 | L40: =L8*(L11*Assumptions!$F$88+L12*Assumptions!$F$89+L13*Assumptions!$F$90) -> 117000 | N40: =N8*(N11*Assumptions!$F$88+N12*Assumptions!$F$89+N13*Assumptions!$F$90) -> 68.4 | O40: =O8*(O11*Assumptions!$F$88+O12*Assumptions!$F$89+O13*Assumptions!$F$90) -> 5600 | P40: =P8*(P11*Assumptions!$F$88+P12*Assumptions!$F$89+P13*Assumptions!$F$90) -> 13120 | Q40: =Q8*(Q11*Assumptions!$F$88+Q12*Assumptions!$F$89+Q13*Assumptions!$F$90) -> 104960 | R40: =R8*(R11*Assumptions!$F$88+R12*Assumptions!$F$89+R13*Assumptions!$F$90) -> 200200
A41: Dispute handling | B41: =B8*(B11*Assumptions!$F$91*Assumptions!$F$94+B12*Assumptions!$F$92*Assumptions!$F$95+B13*Assumptions!$F$93*Assumptions!$F$96) -> 52.12 | C41: =C8*(C11*Assumptions!$F$91*Assumptions!$F$94+C12*Assumptions!$F$92*Assumptions!$F$95+C13*Assumptions!$F$93*Assumptions!$F$96) -> 10735 | D41: =D8*(D11*Assumptions!$F$91*Assumptions!$F$94+D12*Assumptions!$F$92*Assumptions!$F$95+D13*Assumptions!$F$93*Assumptions!$F$96) -> 39936 | E41: =E8*(E11*Assumptions!$F$91*Assumptions!$F$94+E12*Assumptions!$F$92*Assumptions!$F$95+E13*Assumptions!$F$93*Assumptions!$F$96) -> 42516 | F41: =F8*(F11*Assumptions!$F$91*Assumptions!$F$94+F12*Assumptions!$F$92*Assumptions!$F$95+F13*Assumptions!$F$93*Assumptions!$F$96) -> 101160 | H41: =H8*(H11*Assumptions!$F$91*Assumptions!$F$94+H12*Assumptions!$F$92*Assumptions!$F$95+H13*Assumptions!$F$93*Assumptions!$F$96) -> 101.28 | I41: =I8*(I11*Assumptions!$F$91*Assumptions!$F$94+I12*Assumptions!$F$92*Assumptions!$F$95+I13*Assumptions!$F$93*Assumptions!$F$96) -> 11810 | J41: =J8*(J11*Assumptions!$F$91*Assumptions!$F$94+J12*Assumptions!$F$92*Assumptions!$F$95+J13*Assumptions!$F$93*Assumptions!$F$96) -> 32760 | K41: =K8*(K11*Assumptions!$F$91*Assumptions!$F$94+K12*Assumptions!$F$92*Assumptions!$F$95+K13*Assumptions!$F$93*Assumptions!$F$96) -> 163200 | L41: =L8*(L11*Assumptions!$F$91*Assumptions!$F$94+L12*Assumptions!$F$92*Assumptions!$F$95+L13*Assumptions!$F$93*Assumptions!$F$96) -> 245400 | N41: =N8*(N11*Assumptions!$F$91*Assumptions!$F$94+N12*Assumptions!$F$92*Assumptions!$F$95+N13*Assumptions!$F$93*Assumptions!$F$96) -> 186.48 | O41: =O8*(O11*Assumptions!$F$91*Assumptions!$F$94+O12*Assumptions!$F$92*Assumptions!$F$95+O13*Assumptions!$F$93*Assumptions!$F$96) -> 13480 | P41: =P8*(P11*Assumptions!$F$91*Assumptions!$F$94+P12*Assumptions!$F$92*Assumptions!$F$95+P13*Assumptions!$F$93*Assumptions!$F$96) -> 27712 | Q41: =Q8*(Q11*Assumptions!$F$91*Assumptions!$F$94+Q12*Assumptions!$F$92*Assumptions!$F$95+Q13*Assumptions!$F$93*Assumptions!$F$96) -> 190720 | R41: =R8*(R11*Assumptions!$F$91*Assumptions!$F$94+R12*Assumptions!$F$92*Assumptions!$F$95+R13*Assumptions!$F$93*Assumptions!$F$96) -> 329560
A42: QA sampling + >£50k mandatory review | B42: =ROUND(B8*Assumptions!$F$131*Assumptions!$F$132+B8*Assumptions!$F$176*Assumptions!$F$181,0) -> 12 | C42: =ROUND(C8*Assumptions!$F$131*Assumptions!$F$132+C8*Assumptions!$F$177*Assumptions!$F$181,0) -> 4950 | D42: =ROUND(D8*Assumptions!$F$131*Assumptions!$F$132+D8*Assumptions!$F$178*Assumptions!$F$181,0) -> 37260 | E42: =ROUND(E8*Assumptions!$F$131*Assumptions!$F$132+E8*Assumptions!$F$179*Assumptions!$F$181,0) -> 76140 | F42: =ROUND(F8*Assumptions!$F$131*Assumptions!$F$132+F8*Assumptions!$F$180*Assumptions!$F$181,0) -> 321300 | H42: =ROUND(H8*Assumptions!$F$131*Assumptions!$F$132+H8*Assumptions!$F$176*Assumptions!$F$181,0) -> 37 | I42: =ROUND(I8*Assumptions!$F$131*Assumptions!$F$132+I8*Assumptions!$F$177*Assumptions!$F$181,0) -> 9900 | J42: =ROUND(J8*Assumptions!$F$131*Assumptions!$F$132+J8*Assumptions!$F$178*Assumptions!$F$181,0) -> 62100 | K42: =ROUND(K8*Assumptions!$F$131*Assumptions!$F$132+K8*Assumptions!$F$179*Assumptions!$F$181,0) -> 634500 | L42: =ROUND(L8*Assumptions!$F$131*Assumptions!$F$132+L8*Assumptions!$F$180*Assumptions!$F$181,0) -> 1606500 | N42: =ROUND(N8*Assumptions!$F$131*Assumptions!$F$132+N8*Assumptions!$F$176*Assumptions!$F$181,0) -> 111 | O42: =ROUND(O8*Assumptions!$F$131*Assumptions!$F$132+O8*Assumptions!$F$177*Assumptions!$F$181,0) -> 19800 | P42: =ROUND(P8*Assumptions!$F$131*Assumptions!$F$132+P8*Assumptions!$F$178*Assumptions!$F$181,0) -> 99360 | Q42: =ROUND(Q8*Assumptions!$F$131*Assumptions!$F$132+Q8*Assumptions!$F$179*Assumptions!$F$181,0) -> 1353600 | R42: =ROUND(R8*Assumptions!$F$131*Assumptions!$F$132+R8*Assumptions!$F$180*Assumptions!$F$181,0) -> 3748500
A43: External dispute forum cost | B43: =ROUND(B16*Assumptions!$F$133*Assumptions!$F$134,0) -> 38 | C43: =ROUND(C16*Assumptions!$F$133*Assumptions!$F$134,0) -> 8381 | D43: =ROUND(D16*Assumptions!$F$133*Assumptions!$F$134,0) -> 34560 | E43: =ROUND(E16*Assumptions!$F$133*Assumptions!$F$134,0) -> 43335 | F43: =ROUND(F16*Assumptions!$F$133*Assumptions!$F$134,0) -> 122850 | H43: =ROUND(H16*Assumptions!$F$133*Assumptions!$F$134,0) -> 88 | I43: =ROUND(I16*Assumptions!$F$133*Assumptions!$F$134,0) -> 12038 | J43: =ROUND(J16*Assumptions!$F$133*Assumptions!$F$134,0) -> 39600 | K43: =ROUND(K16*Assumptions!$F$133*Assumptions!$F$134,0) -> 243000 | L43: =ROUND(L16*Assumptions!$F$133*Assumptions!$F$134,0) -> 425250 | N43: =ROUND(N16*Assumptions!$F$133*Assumptions!$F$134,0) -> 207 | O43: =ROUND(O16*Assumptions!$F$133*Assumptions!$F$134,0) -> 18675 | P43: =ROUND(P16*Assumptions!$F$133*Assumptions!$F$134,0) -> 47520 | Q43: =ROUND(Q16*Assumptions!$F$133*Assumptions!$F$134,0) -> 410400 | R43: =ROUND(R16*Assumptions!$F$133*Assumptions!$F$134,0) -> 815850
A44: Operational error / wrongful-release reserve | B44: =ROUND(B30*Assumptions!$F$135,0) -> 10 | C44: =ROUND(C30*Assumptions!$F$135,0) -> 2314 | D44: =ROUND(D30*Assumptions!$F$135,0) -> 10588 | E44: =ROUND(E30*Assumptions!$F$135,0) -> 15232 | F44: =ROUND(F30*Assumptions!$F$135,0) -> 44482 | H44: =ROUND(H30*Assumptions!$F$135,0) -> 24 | I44: =ROUND(I30*Assumptions!$F$135,0) -> 4045 | J44: =ROUND(J30*Assumptions!$F$135,0) -> 13879 | K44: =ROUND(K30*Assumptions!$F$135,0) -> 89427 | L44: =ROUND(L30*Assumptions!$F$135,0) -> 178326 | N44: =ROUND(N30*Assumptions!$F$135,0) -> 58 | O44: =ROUND(O30*Assumptions!$F$135,0) -> 7283 | P44: =ROUND(P30*Assumptions!$F$135,0) -> 19306 | Q44: =ROUND(Q30*Assumptions!$F$135,0) -> 163684 | R44: =ROUND(R30*Assumptions!$F$135,0) -> 368837
A45: Partner / channel commission | B45: =0 -> 0 | C45: =ROUND(C30*Assumptions!$F$159*Assumptions!$F$139,0) -> 3472 | D45: =ROUND(D30*Assumptions!$F$159*Assumptions!$F$139,0) -> 15881 | E45: =ROUND(E30*Assumptions!$F$159*Assumptions!$F$139,0) -> 22848 | F45: =ROUND(F30*Assumptions!$F$159*Assumptions!$F$139,0) -> 66723 | H45: =0 -> 0 | I45: =ROUND(I30*Assumptions!$F$159*Assumptions!$F$139,0) -> 6068 | J45: =ROUND(J30*Assumptions!$F$159*Assumptions!$F$139,0) -> 20819 | K45: =ROUND(K30*Assumptions!$F$159*Assumptions!$F$139,0) -> 134140 | L45: =ROUND(L30*Assumptions!$F$159*Assumptions!$F$139,0) -> 267489 | N45: =0 -> 0 | O45: =ROUND(O30*Assumptions!$F$159*Assumptions!$F$139,0) -> 10925 | P45: =ROUND(P30*Assumptions!$F$159*Assumptions!$F$139,0) -> 28959 | Q45: =ROUND(Q30*Assumptions!$F$159*Assumptions!$F$139,0) -> 245526 | R45: =ROUND(R30*Assumptions!$F$159*Assumptions!$F$139,0) -> 553255
A46: Other retained-risk variable (leakage, outage) | B46: =ROUND((B24+B27+0)*Assumptions!$F$140,0)+ROUND(B8*B12*Assumptions!$F$141*Assumptions!$F$142,0) -> 1 | C46: =ROUND((C24+C27+ROUND(Assumptions!$C$14*Assumptions!$F$123*12,0))*Assumptions!$F$140,0)+ROUND(C8*C12*Assumptions!$F$141*Assumptions!$F$142,0) -> 257 | D46: =ROUND((D24+D27+ROUND(Assumptions!$C$110*Assumptions!$F$123*12,0))*Assumptions!$F$140,0)+ROUND(D8*D12*Assumptions!$F$141*Assumptions!$F$142,0) -> 1352 | E46: =ROUND((E24+E27+ROUND(Assumptions!$C$155*Assumptions!$F$123*12,0))*Assumptions!$F$140,0)+ROUND(E8*E12*Assumptions!$F$141*Assumptions!$F$142,0) -> 2299 | F46: =ROUND((F24+F27+ROUND(Assumptions!$C$156*Assumptions!$F$123*12,0))*Assumptions!$F$140,0)+ROUND(F8*F12*Assumptions!$F$141*Assumptions!$F$142,0) -> 7573 | H46: =ROUND((H24+H27+0)*Assumptions!$F$140,0)+ROUND(H8*H12*Assumptions!$F$141*Assumptions!$F$142,0) -> 4 | I46: =ROUND((I24+I27+ROUND(Assumptions!$D$14*Assumptions!$F$123*12,0))*Assumptions!$F$140,0)+ROUND(I8*I12*Assumptions!$F$141*Assumptions!$F$142,0) -> 883 | J46: =ROUND((J24+J27+ROUND(Assumptions!$D$110*Assumptions!$F$123*12,0))*Assumptions!$F$140,0)+ROUND(J8*J12*Assumptions!$F$141*Assumptions!$F$142,0) -> 2746 | K46: =ROUND((K24+K27+ROUND(Assumptions!$D$155*Assumptions!$F$123*12,0))*Assumptions!$F$140,0)+ROUND(K8*K12*Assumptions!$F$141*Assumptions!$F$142,0) -> 14598 | L46: =ROUND((L24+L27+ROUND(Assumptions!$D$156*Assumptions!$F$123*12,0))*Assumptions!$F$140,0)+ROUND(L8*L12*Assumptions!$F$141*Assumptions!$F$142,0) -> 24129 | N46: =ROUND((N24+N27+0)*Assumptions!$F$140,0)+ROUND(N8*N12*Assumptions!$F$141*Assumptions!$F$142,0) -> 12 | O46: =ROUND((O24+O27+ROUND(Assumptions!$E$14*Assumptions!$F$123*12,0))*Assumptions!$F$140,0)+ROUND(O8*O12*Assumptions!$F$141*Assumptions!$F$142,0) -> 2113 | P46: =ROUND((P24+P27+ROUND(Assumptions!$E$110*Assumptions!$F$123*12,0))*Assumptions!$F$140,0)+ROUND(P8*P12*Assumptions!$F$141*Assumptions!$F$142,0) -> 4567 | Q46: =ROUND((Q24+Q27+ROUND(Assumptions!$E$155*Assumptions!$F$123*12,0))*Assumptions!$F$140,0)+ROUND(Q8*Q12*Assumptions!$F$141*Assumptions!$F$142,0) -> 25604 | R46: =ROUND((R24+R27+ROUND(Assumptions!$E$156*Assumptions!$F$123*12,0))*Assumptions!$F$140,0)+ROUND(R8*R12*Assumptions!$F$141*Assumptions!$F$142,0) -> 44851
A47: Total COGS | B47: =SUM(B33:B46) -> 352.35984 | C47: =SUM(C33:C46) -> 78883.805 | D47: =SUM(D33:D46) -> 319005.12 | E47: =SUM(E33:E46) -> 389475.78 | F47: =SUM(F33:F46) -> 1099730.2 | H47: =SUM(H33:H46) -> 707.15578 | I47: =SUM(I33:I46) -> 96717.828 | J47: =SUM(J33:J46) -> 314247.75 | K47: =SUM(K33:K46) -> 1982922.8 | L47: =SUM(L33:L46) -> 3812867.4 | N47: =SUM(N33:N46) -> 1381.8925 | O47: =SUM(O33:O46) -> 129212.72 | P47: =SUM(P33:P46) -> 345699 | Q47: =SUM(Q33:Q46) -> 3207119 | R47: =SUM(R33:R46) -> 7309382.7
A48: Gross profit | B48: =B30-B47 -> 609.09016 | C48: =C30-C47 -> 152564.7 | D48: =D30-D47 -> 739761.28 | E48: =E30-E47 -> 1133748.6 | F48: =F30-F47 -> 3348452.2 | H48: =H30-H47 -> 1741.8942 | I48: =I30-I47 -> 307831.17 | J48: =J30-J47 -> 1073656.2 | K48: =K30-K47 -> 6959769.1 | L48: =L30-L47 -> 14019746 | N48: =N30-N47 -> 4454.4075 | O48: =O30-O47 -> 599124.28 | P48: =P30-P47 -> 1584882.8 | Q48: =Q30-Q47 -> 13161312 | R48: =R30-R47 -> 29574306
A49: Gross margin % | B49: =IF(B30=0,0,B48/B30) -> 0.63351205 | C49: =IF(C30=0,0,C48/C30) -> 0.6591734 | D49: =IF(D30=0,0,D48/D30) -> 0.69870113 | E49: =IF(E30=0,0,E48/E30) -> 0.74430833 | F49: =IF(F30=0,0,F48/F30) -> 0.75276864 | H49: =IF(H30=0,0,H48/H30) -> 0.71125302 | I49: =IF(I30=0,0,I48/I30) -> 0.76092432 | J49: =IF(J30=0,0,J48/J30) -> 0.77358106 | K49: =IF(K30=0,0,K48/K30) -> 0.77826332 | L49: =IF(L30=0,0,L48/L30) -> 0.78618572 | N49: =IF(N30=0,0,N48/N30) -> 0.76322456 | O49: =IF(O30=0,0,O48/O30) -> 0.82259213 | P49: =IF(P30=0,0,P48/P30) -> 0.82093533 | Q49: =IF(Q30=0,0,Q48/Q30) -> 0.80406681 | R49: =IF(R30=0,0,R48/R30) -> 0.80182615
A51: SCENARIO-INVARIANT COSTS (linked from P&L 5yr)
A52: Total payroll cost | B52: ='P&L 5yr'!C$42 -> 483950 | C52: ='P&L 5yr'!D$42 -> 797900 | D52: ='P&L 5yr'!E$42 -> 1015250 | E52: ='P&L 5yr'!F$42 -> 1413350 | F52: ='P&L 5yr'!G$42 -> 1630700 | H52: ='P&L 5yr'!C$42 -> 483950 | I52: ='P&L 5yr'!D$42 -> 797900 | J52: ='P&L 5yr'!E$42 -> 1015250 | K52: ='P&L 5yr'!F$42 -> 1413350 | L52: ='P&L 5yr'!G$42 -> 1630700 | N52: ='P&L 5yr'!C$42 -> 483950 | O52: ='P&L 5yr'!D$42 -> 797900 | P52: ='P&L 5yr'!E$42 -> 1015250 | Q52: ='P&L 5yr'!F$42 -> 1413350 | R52: ='P&L 5yr'!G$42 -> 1630700
A53: Total fixed opex | B53: ='P&L 5yr'!C$56 -> 280158.33 | C53: ='P&L 5yr'!D$56 -> 344180 | D53: ='P&L 5yr'!E$56 -> 436860.83 | E53: ='P&L 5yr'!F$56 -> 544390 | F53: ='P&L 5yr'!G$56 -> 636030 | H53: ='P&L 5yr'!C$56 -> 280158.33 | I53: ='P&L 5yr'!D$56 -> 344180 | J53: ='P&L 5yr'!E$56 -> 436860.83 | K53: ='P&L 5yr'!F$56 -> 544390 | L53: ='P&L 5yr'!G$56 -> 636030 | N53: ='P&L 5yr'!C$56 -> 280158.33 | O53: ='P&L 5yr'!D$56 -> 344180 | P53: ='P&L 5yr'!E$56 -> 436860.83 | Q53: ='P&L 5yr'!F$56 -> 544390 | R53: ='P&L 5yr'!G$56 -> 636030
A54: Startup & regulatory one-off costs | B54: ='P&L 5yr'!C$58 -> 303412.45 | C54: ='P&L 5yr'!D$58 -> 42546 | D54: ='P&L 5yr'!E$58 -> 0 | E54: ='P&L 5yr'!F$58 -> 0 | F54: ='P&L 5yr'!G$58 -> 0 | H54: ='P&L 5yr'!C$58 -> 303412.45 | I54: ='P&L 5yr'!D$58 -> 42546 | J54: ='P&L 5yr'!E$58 -> 0 | K54: ='P&L 5yr'!F$58 -> 0 | L54: ='P&L 5yr'!G$58 -> 0 | N54: ='P&L 5yr'!C$58 -> 303412.45 | O54: ='P&L 5yr'!D$58 -> 42546 | P54: ='P&L 5yr'!E$58 -> 0 | Q54: ='P&L 5yr'!F$58 -> 0 | R54: ='P&L 5yr'!G$58 -> 0
A56: RESULT
A57: EBITDA (pre one-off) | B57: =B48-B52-B53 -> -763499.24 | C57: =C48-C52-C53 -> -989515.3 | D57: =D48-D52-D53 -> -712349.56 | E57: =E48-E52-E53 -> -823991.43 | F57: =F48-F52-F53 -> 1081722.2 | H57: =H48-H52-H53 -> -762366.44 | I57: =I48-I52-I53 -> -834248.83 | J57: =J48-J52-J53 -> -378454.58 | K57: =K48-K52-K53 -> 5002029.1 | L57: =L48-L52-L53 -> 11753016 | N57: =N48-N52-N53 -> -759653.93 | O57: =O48-O52-O53 -> -542955.72 | P57: =P48-P52-P53 -> 132771.97 | Q57: =Q48-Q52-Q53 -> 11203572 | R57: =R48-R52-R53 -> 27307576
A58: Peak cumulative operating deficit | B58: =-MIN(0,'Cash Flow Statement'!$B$52:$M$52) -> 1067873 | C58: =-MIN(0,'Cash Flow Statement'!$B$52:$Y$52) -> 2118265 | D58: =-MIN(0,'Cash Flow Statement'!$B$52:$AK$52) -> 2899562 | E58: =-MIN(0,'Cash Flow Statement'!$B$52:$AW$52) -> 3762259 | F58: =-MIN(0,'Cash Flow Statement'!$B$52:$BI$52) -> 3915862 | H58: =IF(Assumptions!$C$4=2,-MIN(0,'Cash Flow Statement'!$B$38:$M$38),-MIN(0,'Cash Flow Statement'!$B$53:$M$53)) -> 1068227 | I58: =IF(Assumptions!$C$4=2,-MIN(0,'Cash Flow Statement'!$B$38:$Y$38),-MIN(0,'Cash Flow Statement'!$B$53:$Y$53)) -> 1976300 | J58: =IF(Assumptions!$C$4=2,-MIN(0,'Cash Flow Statement'!$B$38:$AK$38),-MIN(0,'Cash Flow Statement'!$B$53:$AK$53)) -> 2436689 | K58: =IF(Assumptions!$C$4=2,-MIN(0,'Cash Flow Statement'!$B$38:$AW$38),-MIN(0,'Cash Flow Statement'!$B$53:$AW$53)) -> 2649419 | L58: =IF(Assumptions!$C$4=2,-MIN(0,'Cash Flow Statement'!$B$38:$BI$38),-MIN(0,'Cash Flow Statement'!$B$53:$BI$53)) -> 2649419 | N58: =-MIN(0,'Cash Flow Statement'!$B$54:$M$54) -> 1068902 | O58: =-MIN(0,'Cash Flow Statement'!$B$54:$Y$54) -> 1709259 | P58: =-MIN(0,'Cash Flow Statement'!$B$54:$AK$54) -> 1796675 | Q58: =-MIN(0,'Cash Flow Statement'!$B$54:$AW$54) -> 1946199 | R58: =-MIN(0,'Cash Flow Statement'!$B$54:$BI$54) -> 1946199
