Workbook

Sheet README
B2: Blockmediary - 5-Year Financial Model & Assumptions Pack
B3: Programmable documentary escrow layer for SME cross-border trade (UK / EU / Middle East). Built June 2026.
B5: SCOPE
B6: Blockmediary is a documentary escrow + document-verification SERVICE. It is NOT a lending / financing product.
B7: EXCLUDED by design: lending capital, credit losses, financing spread, invoice advances, FX trading revenue, balance-sheet funding costs.
B8: Buyer prefunds stablecoin into smart-contract escrow; funds release when document rules are satisfied. Blockmediary never takes balance-sheet credit risk.
B10: HOW TO USE
B11: 1. 'Assumptions' is the single control sheet. Blue cells are inputs you change. Black cells are formulas.
B12: 2. The yellow 'Scenario' switch (Assumptions!C4) drives the whole model: 1=Low, 2=Base, 3=High.
B13: 3. 'Startup_6mo' details the first 6 months one-off + ramp costs. 'P&L_5yr' is the annual five-year P&L and 'Cash_Flow_Statement' shows operating cash flow, financing, and break-even.
B14: 4. 'Driver_Tables' holds every researched cost/revenue driver with Low/Base/High, source URL and source quality.
B15: 5. 'Sensitivity' lists the 10 assumptions that move the model most. 'Risk_Register' flags items needing legal/regulatory sign-off.
... B66: Operating cash flow excludes any working-capital timing. Receipts are recognised in the month the annual revenue is smoothed into, with no lag between deal completion and fee collection. In reality there's a gap (and you model "fee collection leakage" at 1% but not timing). A 30–60 day receipts lag would deepen the month-24 trough. Given how thin that trough already is, I'd add even a crude lag to test it.

Sheet Dashboard
B2: ■ INVESTOR DASHBOARD
B4: The base case works if repeat usage compounds before overhead does.
B6: Slide-ready view of the current model: base-case path to EBITDA, monthly cash-flow break-even, funding use, and the downside/base/upside runway spread.
R9: Pitch deck metrics linked to model
C10: =MAX(Scenario_Base_PL!C66:G66)/1000000 -> 1.650223 | G10: =Cash_Flow_Statement!B46 -> Y4 M5 | K10: =Scenario_Base_PL!G18/1000000 -> 14.740255 | O10: =Scenario_Base_PL!G70 -> 1800 | R10: Slide | S10: Metric | T10: Model value | U10: Pitch-copy output | V10: Source / model link | W10: Deck slot
C11: Base funding ask | G11: Base monthly break-even | K11: Y5 annual revenue | O11: Y5 active customers | R11: 7 | S11: Settlement fee range | T11: =ROUND(MIN(Assumptions!$F$73:$F$75)*100,1)&"%-"&ROUND(MAX(Assumptions!$F$73:$F$75)*100,1)&"%" -> 0.6%-1.5% | U11: =T11&" per trade, tier-dependent" -> 0.6%-1.5% per trade, tier-dependent | V11: Assumptions!F73:F75 | W11: Business model card A
C12: peak cash need incl. contingency | G12: cumulative operating cash before financing | K12: base case; escrow + document fees | O12: implied repeat-usage customer base | R12: 7 | S12: Blended gross margin | T12: =ROUND(Scenario_Base_PL!$C$31*100,0)&"%-"&ROUND(Scenario_Base_PL!$G$31*100,0)&"%" -> 57%-83% | U12: =T12&" blended gross margin, base Y1-Y5" -> 57%-83% blended gross margin, base Y1-Y5 | V12: Scenario_Base_PL!C31:G31 | W12: Bottom KPI
R13: 7 | S13: Average ticket | T13: ="GBP "&ROUND(Scenario_Base_PL!$C$8/1000,0)&"K -> GBP "&ROUND(Scenario_Base_PL!$E$8/1000,0)&"K" -> GBP 30K -> GBP 55K | U13: =T13&" average ticket, Y1 to Y3; GBP "&ROUND(Scenario_Base_PL!$G$8/1000,0)&"K by Y5" -> GBP 30K -> GBP 55K average ticket, Y1 to Y3; GBP 100K by Y5 | V13: Scenario_Base_PL!C8:G8 | W13: Bottom KPI
R14: 7 | S14: Processed deals | T14: =ROUND(Scenario_Base_PL!$C$7,0)&" -> "&ROUND(Scenario_Base_PL!$E$7,0) -> 180 -> 3000 | U14: =T14&" processed deals, Y1 to Y3 base case" -> 180 -> 3000 processed deals, Y1 to Y3 base case | V14: Scenario_Base_PL!C7:E7 | W14: Bottom KPI
R15: 11 | S15: Y3 annual revenue range | T15: ="GBP "&ROUND(Scenario_Low_PL!$E$18/1000000,1)&"M-GBP "&ROUND(Scenario_High_PL!$E$18/1000000,1)&"M" -> GBP 0.8M-GBP 4.3M | U15: =T15&" Y3 annual revenue; base GBP "&ROUND(Scenario_Base_PL!$E$18/1000000,1)&"M" -> GBP 0.8M-GBP 4.3M Y3 annual revenue; base GBP 2M | V15: Scenario_*_PL!E18 | W15: Top KPI card
R16: 11 | S16: Y3 active customers range | T16: =ROUND(Scenario_Low_PL!$E$70,0)&"-"&ROUND(Scenario_High_PL!$E$70,0) -> 360-800 | U16: =T16&" Y3 active customers; base "&ROUND(Scenario_Base_PL!$E$70,0) -> 360-800 Y3 active customers; base 500 | V16: Scenario_*_PL!E70 | W16: Top KPI card
C17: Base path to profitability (£m) | K17: Use of funds from Base ask | R17: 11 | S17: Monthly cash-flow breakeven | T17: =Cash_Flow_Statement!$B$46 -> Y4 M5 | U17: ="Base monthly cash-flow break-even: "&T17&"; scenario range "&Cash_Flow_Statement!$B$47&" to "&Cash_Flow_Statement!$B$45 -> Base monthly cash-flow break-even: Y4 M5; scenario range Y3 M5 to Y5 M9 | V17: Cash_Flow_Statement!B45:B47 | W17: Top KPI card
B18: Revenue and EBITDA in GBP millions, by fiscal year. | C18: Revenue scales before the payroll/opex curve catches up. | J18: Use of funds in GBP millions, tied to the modelled funding requirement. | K18: Allocation is tied to the modelled peak funding requirement. | R18: 11 | S18: Seed ask / funding need | T18: ="GBP "&ROUND(Cash_Flow_Statement!$F$46/1000000,2)&"M" -> GBP 1.65M | U18: =T18&" base seed ask; downside funding case GBP "&ROUND(Cash_Flow_Statement!$F$45/1000000,2)&"M" -> GBP 1.65M base seed ask; downside funding case GBP 2.98M | V18: Cash_Flow_Statement!F45:F47 | W18: Top KPI card
R19: 11 | S19: Blended escrow take rate | T19: =ROUND(Tier_Economics!$E$12/Tier_Economics!$E$9*100,1)&"% / "&ROUND(Tier_Economics!$M$12/Tier_Economics!$M$9*100,1)&"% / "&ROUND(Tier_Economics!$U$12/Tier_Economics!$U$9*100,1)&"%" -> 1.1% / 0.8% / 0.7% | U19: =T19&" blended escrow take rate, base Y1 / Y3 / Y5" -> 1.1% / 0.8% / 0.7% blended escrow take rate, base Y1 / Y3 / Y5 | V19: Tier_Economics total escrow fee / GMV | W19: Key assumptions
R20: 11 | S20: Tier A adoption | T20: =ROUND(Assumptions!$D$64*100,0)&"% -> "&ROUND(Assumptions!$D$160*100,0)&"%" -> 15% -> 70% | U20: =T20&" Tier A eBL mix, base Y1 to Y5" -> 15% -> 70% Tier A eBL mix, base Y1 to Y5 | V20: Assumptions!D64,D160 | W20: Key assumptions
R21: 13 | S21: Total seed raise | T21: ="GBP "&ROUND(MAX(Scenario_Base_PL!$C$66:$G$66)/1000000,2)&"M" -> GBP 1.65M | U21: =T21&" total seed raise" -> GBP 1.65M total seed raise | V21: MAX(Scenario_Base_PL!C66:G66) | W21: Total seed raise
R22: 13 | S22: Engineering & product | T22: =ROUND($H$58*100,0)&"% GBP "&ROUND($G$58*1000,0)&"K" -> 40% GBP 660K | U22: =T22 -> 40% GBP 660K | V22: Dashboard!G58:H58 | W22: Use of funds
R23: 13 | S23: Ops, people & G&A | T23: =ROUND($H$59*100,0)&"% GBP "&ROUND($G$59*1000,0)&"K" -> 22% GBP 363K | U23: =T23 -> 22% GBP 363K | V23: Dashboard!G59:H59 | W23: Use of funds
R24: 13 | S24: Compliance, legal & regulatory | T24: =ROUND($H$60*100,0)&"% GBP "&ROUND($G$60*1000,0)&"K" -> 18% GBP 297K | U24: =T24 -> 18% GBP 297K | V24: Dashboard!G60:H60 | W24: Use of funds
R25: 13 | S25: GTM & acquisition | T25: =ROUND($H$61*100,0)&"% GBP "&ROUND($G$61*1000,0)&"K" -> 15% GBP 248K | U25: =T25 -> 15% GBP 248K | V25: Dashboard!G61:H61 | W25: Use of funds
R26: 13 | S26: Working capital + contingency | T26: =ROUND($H$62*100,0)&"% GBP "&ROUND($G$62*1000,0)&"K" -> 5% GBP 83K | U26: =T26 -> 5% GBP 83K | V26: Dashboard!G62:H62 | W26: Use of funds
C35: Monthly cumulative operating cash (£m) | K35: Scenario readout
B36: Ending cash balance in GBP millions at 6-month checkpoints. | C36: Six-month checkpoints avoid unreadable 60-label charts. | J36: Break-even timing and funding gap by scenario. | K36: Break-even timing and funding gap by case.
J37: Case | K37: Monthly BE | L37: Peak gap | M37: M60 cash | N37: Funding ask
J38: Low | K38: =Cash_Flow_Statement!B45 -> Y5 M9 | L38: =Cash_Flow_Statement!C45/1000000 -> 2.2904747 | M38: =Cash_Flow_Statement!D45/1000000 -> 0.98335342 | N38: =Cash_Flow_Statement!F45/1000000 -> 2.977617
J39: Base | K39: =Cash_Flow_Statement!B46 -> Y4 M5 | L39: =Cash_Flow_Statement!C46/1000000 -> 1.2694021 | M39: =Cash_Flow_Statement!D46/1000000 -> 12.220136 | N39: =Cash_Flow_Statement!F46/1000000 -> 1.650223
J40: High | K40: =Cash_Flow_Statement!B47 -> Y3 M5 | L40: =Cash_Flow_Statement!C47/1000000 -> 0.76667051 | M40: =Cash_Flow_Statement!D47/1000000 -> 31.816705 | N40: =Cash_Flow_Statement!F47/1000000 -> 1.236672
K43: ="- Base reaches monthly cash-flow break-even in "&Cash_Flow_Statement!$B$46&"; High reaches "&Cash_Flow_Statement!$B$47&"." -> - Base reaches monthly cash-flow break-even in Y4 M5; High reaches Y3 M5.
K44: ="- Low reaches monthly cash-flow break-even in "&Cash_Flow_Statement!$B$45&"; base Month 60 operating cash is GBP "&ROUND(Cash_Flow_Statement!$D$46/1000000,1)&"M." -> - Low reaches monthly cash-flow break-even in Y5 M9; base Month 60 operating cash is GBP 12.2M.
K45: • No lending spread, FX trading revenue, or balance-sheet credit risk is modelled.
K46: • Tier C paper collection is a priced fallback, not the strategic scale path.
B56: Base path helper | F56: Use of funds helper
B57: Year | C57: Revenue | D57: EBITDA | F57: Category | G57: Amount | H57: %
B58: Y1 | C58: =Scenario_Base_PL!C18/1000000 -> 0.107505 | D58: =Scenario_Base_PL!C61/1000000 -> -0.57636506 | F58: Engineering/product | G58: =MAX(Scenario_Base_PL!C66:G66)*H58/1000000 -> 0.6600892 | H58: 0.4
B59: Y2 | C59: =Scenario_Base_PL!D18/1000000 -> 0.59877675 | D59: =Scenario_Base_PL!D61/1000000 -> -0.45192455 | F59: Ops/people/G&A | G59: =MAX(Scenario_Base_PL!C66:G66)*H59/1000000 -> 0.36304906 | H59: 0.22
B60: Y3 | C60: =Scenario_Base_PL!E18/1000000 -> 1.9593487 | D60: =Scenario_Base_PL!E61/1000000 -> 0.30703247 | F60: Compliance/legal | G60: =MAX(Scenario_Base_PL!C66:G66)*H60/1000000 -> 0.29704014 | H60: 0.18
B61: Y4 | C61: =Scenario_Base_PL!F18/1000000 -> 5.2198545 | D61: =Scenario_Base_PL!F61/1000000 -> 2.6945588 | F61: GTM/acquisition | G61: =MAX(Scenario_Base_PL!C66:G66)*H61/1000000 -> 0.24753345 | H61: 0.15
B62: Y5 | C62: =Scenario_Base_PL!G18/1000000 -> 14.740255 | D62: =Scenario_Base_PL!G61/1000000 -> 10.487947 | F62: Contingency | G62: =MAX(Scenario_Base_PL!C66:G66)*H62/1000000 -> 0.08251115 | H62: 0.05
B66: Cash runway helper
B67: Checkpoint | C67: Low | D67: Base | E67: High
B68: =Cash_Flow_Statement!G9 -> Y1 M6 | C68: =Cash_Flow_Statement!G52/1000000 -> -0.55981245 | D68: =Cash_Flow_Statement!G53/1000000 -> -0.55981245 | E68: =Cash_Flow_Statement!G54/1000000 -> -0.55981245
B69: =Cash_Flow_Statement!M9 -> Y1 M12 | C69: =Cash_Flow_Statement!M52/1000000 -> -0.85604442 | D69: =Cash_Flow_Statement!M53/1000000 -> -0.81747751 | E69: =Cash_Flow_Statement!M54/1000000 -> -0.76667051
B70: =Cash_Flow_Statement!S9 -> Y2 M6 | C70: =Cash_Flow_Statement!S52/1000000 -> -1.2057634 | D70: =Cash_Flow_Statement!S53/1000000 -> -1.0434398 | E70: =Cash_Flow_Statement!S54/1000000 -> -0.7596076
B71: =Cash_Flow_Statement!Y9 -> Y2 M12 | C71: =Cash_Flow_Statement!Y52/1000000 -> -1.5554823 | D71: =Cash_Flow_Statement!Y53/1000000 -> -1.2694021 | E71: =Cash_Flow_Statement!Y54/1000000 -> -0.75254468
B72: =Cash_Flow_Statement!AE9 -> Y3 M6 | C72: =Cash_Flow_Statement!AE52/1000000 -> -1.8472086 | D72: =Cash_Flow_Statement!AE53/1000000 -> -1.1158858 | E72: =Cash_Flow_Statement!AE54/1000000 -> 0.30384382
B73: =Cash_Flow_Statement!AK9 -> Y3 M12 | C73: =Cash_Flow_Statement!AK52/1000000 -> -2.1389349 | D73: =Cash_Flow_Statement!AK53/1000000 -> -0.96236959 | E73: =Cash_Flow_Statement!AK54/1000000 -> 1.3602323
B74: =Cash_Flow_Statement!AQ9 -> Y4 M6 | C74: =Cash_Flow_Statement!AQ52/1000000 -> -2.2147048 | D74: =Cash_Flow_Statement!AQ53/1000000 -> 0.38490981 | E74: =Cash_Flow_Statement!AQ54/1000000 -> 5.045144
B75: =Cash_Flow_Statement!AW9 -> Y4 M12 | C75: =Cash_Flow_Statement!AW52/1000000 -> -2.2904747 | D75: =Cash_Flow_Statement!AW53/1000000 -> 1.7321892 | E75: =Cash_Flow_Statement!AW54/1000000 -> 8.7300557
B76: =Cash_Flow_Statement!BC9 -> Y5 M6 | C76: =Cash_Flow_Statement!BC52/1000000 -> -0.65356065 | D76: =Cash_Flow_Statement!BC53/1000000 -> 6.9761627 | E76: =Cash_Flow_Statement!BC54/1000000 -> 20.27338
B77: =Cash_Flow_Statement!BI9 -> Y5 M12 | C77: =Cash_Flow_Statement!BI52/1000000 -> 0.98335342 | D77: =Cash_Flow_Statement!BI53/1000000 -> 12.220136 | E77: =Cash_Flow_Statement!BI54/1000000 -> 31.816705

Sheet Assumptions
B2: Assumptions — Control Panel
B3: Scenario columns are only used for true adoption/mix drivers. Fixed inputs use one value in column F and flow through every downstream sheet.
B4: SCENARIO SWITCH (1/2/3) | C4: 2 | D4: =CHOOSE($C$4,"LOW","BASE","HIGH") -> BASE
B6: Assumption | C6: Low scenario | D6: Base scenario | E6: High scenario | F6: Active / fixed value | G6: Unit | H6: Notes / source quality
B7: -- GLOBAL --
B8: GBP:USD FX rate | F8: 1.28 | G8: $/£ | H8: Fixed input; not scenario-driven. Planning rate; verify at build time (estimate)
B9: Months modelled per year | F9: 12 | G9: months | H9: Fixed input; not scenario-driven.
B10: -- DEAL VOLUME / CORE OPERATING DRIVERS --
B11: Year 1 deals (total) | C11: 60 | D11: 180 | E11: 400 | F11: =CHOOSE($C$4,C11,D11,E11) -> 180 | G11: deals/yr | H11: Pilot→paid ramp. Pre-seed B2B fintech (estimate)
B12: Year 2 deals (total) | C12: 300 | D12: 900 | E12: 2200 | F12: =CHOOSE($C$4,C12,D12,E12) -> 900 | G12: deals/yr | H12: estimate
B13: Year 3 deals (total) | C13: 900 | D13: 3000 | E13: 8000 | F13: =CHOOSE($C$4,C13,D13,E13) -> 3000 | G13: deals/yr | H13: estimate
B14: Avg intitial deal (trade) value (first year) | F14: 30000 | G14: £/deal | H14: Fixed input; not scenario-driven. Avg SME cross-border invoice (estimate)
B15: Avg deal (trade) value growth (yearly) | F15: 0.35 | G15: %/yr | H15: Fixed input; annual growth applied to avg deal value in active and scenario P&L models.
B16: Avg counterparties / deal before repeat adjustment | F16: 2 | G16: parties/deal | H16: Fixed input; not scenario-driven. Buyer + seller before repeat-customer onboarding adjustment
B17: Partner count Yr2 | C17: 0 | D17: 3 | E17: 10 | F17: =CHOOSE($C$4,C17,D17,E17) -> 3 | G17: partners | H17: API/platform partners live by Year 2
B18: -- TRANSACTION COGS --
B19: Claude API cost / document | F19: 0.03 | G19: $/doc | H19: Fixed input; not scenario-driven. Haiku/Sonnet extraction. Anthropic $1/$5–$3/$15 MTok (vendor)
B20: KYB screening / business party | F20: 3.5 | G20: $/party | H20: Fixed input; not scenario-driven. Didit fr $2, Sumsub tier (vendor)
B21: KYC/UBO+sanctions / person | F21: 1.35 | G21: $/person | H21: Fixed input; not scenario-driven. Didit $0.30 / Sumsub $1.35 (vendor)
B22: Blockchain gas / deal (multi-tx) | F22: 0.2 | G22: $/deal | H22: Fixed input; not scenario-driven. Base L2, several txns/deal (official: Base docs)
B23: RPC/node provider / deal | F23: 0.01 | G23: $/deal | H23: Fixed input; not scenario-driven. Alchemy/QuickNode metered (vendor/estimate)
B24: Doc + audit-ledger storage / deal | F24: 0.03 | G24: $/deal | H24: Fixed input; not scenario-driven. S3/object storage per deal (vendor/estimate)
B25: -- FIXED OPEX --
B26: Cloud hosting (Vercel/AWS) | F26: 250 | G26: £/mo | H26: Fixed input; not scenario-driven. Vercel Pro $20/seat + AWS/usage (vendor)
B27: Database + object storage | F27: 120 | G27: £/mo | H27: Fixed input; not scenario-driven. Managed Postgres + S3 (vendor/estimate)
B28: Monitoring/logging/security tools | F28: 150 | G28: £/mo | H28: Fixed input; not scenario-driven. Sentry/Datadog/Snyk tiers (vendor/estimate)
B29: GitHub + dev SaaS | F29: 60 | G29: £/mo | H29: Fixed input; not scenario-driven. GitHub $4–21/user (vendor)
B30: Google Workspace / collab | F30: 90 | G30: £/mo | H30: Fixed input; not scenario-driven. ~£12/user Business Standard (vendor)
B31: CRM + BD tooling | F31: 80 | G31: £/mo | H31: Fixed input; not scenario-driven. HubSpot/Pipedrive (vendor/estimate)
B32: Accounting/payroll/bookkeeping | F32: 350 | G32: £/mo | H32: Fixed input; not scenario-driven. Outsourced (estimate)
B33: Legal retainer (ongoing) | F33: 600 | G33: £/mo | H33: Fixed input; not scenario-driven. Commercial + regulatory queries (estimate)
B34: Compliance / MLRO support | F34: 1200 | G34: £/mo | H34: Fixed input; not scenario-driven. Fractional MLRO/consultant (benchmark/estimate)
B35: Marketing / conferences / partnerships | F35: 1500 | G35: £/mo | H35: Fixed input; not scenario-driven. Trade events, content (estimate)
B36: Office / coworking | F36: 400 | G36: £/mo | H36: Fixed input; not scenario-driven. Hot-desk → small office (estimate)
B37: Insurance (PI+cyber+D&O) / mo | F37: 700 | G37: £/mo | H37: Fixed input; not scenario-driven. Annualised /12; fintech loading (benchmark/estimate)
B38: -- HEADCOUNT BASELINE --
B39: Founders (FTE) | F39: 2 | G39: FTE | H39: Fixed input; not scenario-driven.
B40: Engineers Yr1 baseline | F40: 2 | G40: FTE Yr1 | H40: Fixed input; not scenario-driven. Scaled in P&L by year (benchmark)
B41: Compliance/ops Yr1 baseline | F41: 1 | G41: FTE Yr1 | H41: Fixed input; not scenario-driven. Compliance/ops baseline headcount starts at one FTE.
B42: Sales/BD + CS Yr1 baseline | F42: 1 | G42: FTE Yr1 | H42: Fixed input; not scenario-driven. (benchmark)
B43: -- SALARIES --
B44: Founder salary | F44: 45000 | G44: £/yr | H44: Fixed input; not scenario-driven. Pre-seed founder (benchmark)
B45: Engineer salary | F45: 70000 | G45: £/yr | H45: Fixed input; not scenario-driven. UK fintech SWE (benchmark)
B46: Compliance/ops salary | F46: 60000 | G46: £/yr | H46: Fixed input; not scenario-driven. FS compliance officer (benchmark)
B47: Sales/BD/CS salary | F47: 50000 | G47: £/yr | H47: Fixed input; not scenario-driven. (benchmark)
B48: Employer NI rate | F48: 0.15 | G48: % of pay >£5k | H48: Fixed input; not scenario-driven. 15% above £5,000 ST 2026/27 (official: HMRC)
B49: Employer NI secondary threshold | F49: 5000 | G49: £/yr | H49: Fixed input; not scenario-driven. Frozen to 2030/31 (official)
B50: Employer pension contribution | F50: 0.04 | G50: % of salary | H50: Fixed input; not scenario-driven. Auto-enrolment min 3% (official: TPR)
B51: Other employment on-costs | F51: 0.03 | G51: % of salary | H51: Fixed input; not scenario-driven. Equipment, benefits, software/seat (estimate)
B52: -- CONTRACTOR DAY RATES --
B53: Smart-contract dev day rate | F53: 900 | G53: £/day | H53: Fixed input; not scenario-driven. Specialist Solidity (benchmark/estimate)
B54: Full-stack dev day rate | F54: 600 | G54: £/day | H54: Fixed input; not scenario-driven. (benchmark)
B55: Compliance consultant day rate | F55: 900 | G55: £/day | H55: Fixed input; not scenario-driven. Crypto reg specialist (benchmark/estimate)
B56: UX/design day rate | F56: 500 | G56: £/day | H56: Fixed input; not scenario-driven. (benchmark)
B57: -- FUNDING / CASH FLOW --
B58: Cash buffer on peak deficit | F58: 0.3 | G58: % buffer | H58: Fixed input; not scenario-driven. Applied to funding ask, linked into P&L_5yr and Cash_Flow_Statement
B59: Pre-revenue/pilot months in Year 1 | F59: 6 | G59: months | H59: Fixed input; not scenario-driven. Used to phase Yr1 revenue after startup build
B60: Employment allowance | F60: 10500 | G60: GBP/yr | H60: Fixed input; not scenario-driven. UK Employment Allowance 2026/27; confirm eligibility
B61: VAT registration threshold | F61: 90000 | G61: GBP revenue | H61: Fixed input; not scenario-driven. Flag threshold only; VAT cash timing not modelled in P&L
B62: New counterparty onboarding share | F62: 0.5 | G62: % screened parties | H62: Fixed input; not scenario-driven. Only this share gets fresh KYC/KYB onboarding; repeat checks assumed lower-touch/opex
B63: -- DOCUMENT INTAKE MIX + TIER PRICE BOOK --
B64: Tier A eBL mix Yr1 | C64: 0.05 | D64: 0.15 | E64: 0.3 | F64: =CHOOSE($C$4,C64,D64,E64) -> 0.15 | G64: % deals | H64: Lowest operational risk; source-of-truth digital document rail
B65: Tier B carrier/API mix Yr1 | C65: 0.25 | D65: 0.45 | E65: 0.5 | F65: =CHOOSE($C$4,C65,D65,E65) -> 0.45 | G65: % deals | H65: Paper docs with DCSA/carrier/API verification
B66: Tier C paper collection mix Yr1 | C66: 0.7 | D66: 0.4 | E66: 0.2 | F66: =CHOOSE($C$4,C66,D66,E66) -> 0.4 | G66: % deals | H66: Paper originals / manual collection / forensic fallback
B67: Tier A eBL mix Yr2 | C67: 0.1 | D67: 0.3 | E67: 0.45 | F67: =CHOOSE($C$4,C67,D67,E67) -> 0.3 | G67: % deals | H67: Mix improves as eBL adoption grows
B68: Tier B carrier/API mix Yr2 | C68: 0.35 | D68: 0.45 | E68: 0.45 | F68: =CHOOSE($C$4,C68,D68,E68) -> 0.45 | G68: % deals | H68: Core commercial tier
B69: Tier C paper collection mix Yr2 | C69: 0.55 | D69: 0.25 | E69: 0.1 | F69: =CHOOSE($C$4,C69,D69,E69) -> 0.25 | G69: % deals | H69: Should shrink over time
B70: Tier A eBL mix Yr3 | C70: 0.2 | D70: 0.45 | E70: 0.65 | F70: =CHOOSE($C$4,C70,D70,E70) -> 0.45 | G70: % deals | H70: Best-margin scaled tier
B71: Tier B carrier/API mix Yr3 | C71: 0.4 | D71: 0.4 | E71: 0.3 | F71: =CHOOSE($C$4,C71,D71,E71) -> 0.4 | G71: % deals | H71: Carrier/API verified middle tier
B72: Tier C paper collection mix Yr3 | C72: 0.4 | D72: 0.15 | E72: 0.05 | F72: =CHOOSE($C$4,C72,D72,E72) -> 0.15 | G72: % deals | H72: High-risk fallback, not strategic core
B73: Tier A escrow take rate | F73: 0.006 | G73: % GMV | H73: Fixed input; not scenario-driven. Tier A eBL/source-of-truth rail: 0.30% GMV; below typical LC issuance economics.
B74: Tier B escrow take rate | F74: 0.0085 | G74: % GMV | H74: Fixed input; not scenario-driven. Tier B carrier/API-verified docs: 0.45% GMV; below many LC/corporate escrow all-in alternatives.
B75: Tier C escrow take rate | F75: 0.015 | G75: % GMV | H75: Fixed input; not scenario-driven. Tier C paper/originals fallback: 0.70% GMV; priced for manual risk but still LC-competitive.
B76: Tier A minimum escrow fee | F76: 150 | G76: GBP/deal | H76: Fixed input; not scenario-driven. Single price-book assumption repeated across Low/Base/High; scenarios now vary adoption/mix/risk, not customer pricing. Benchmarked as an LC-like service below typical bank LC all-in economics.
B77: Tier B minimum escrow fee | F77: 250 | G77: GBP/deal | H77: Fixed input; not scenario-driven. Single price-book assumption repeated across Low/Base/High; scenarios now vary adoption/mix/risk, not customer pricing. Benchmarked as an LC-like service below typical bank LC all-in economics.
B78: Tier C minimum escrow fee | F78: 500 | G78: GBP/deal | H78: Fixed input; not scenario-driven. Single price-book assumption repeated across Low/Base/High; scenarios now vary adoption/mix/risk, not customer pricing. Benchmarked as an LC-like service below typical bank LC all-in economics.
B79: Tier A document/review fee | F79: 25 | G79: GBP/deal | H79: Fixed input; not scenario-driven. Tier A light document/release-rule review fee; familiar admin-fee style pricing.
B80: Tier B document/review fee | F80: 90 | G80: GBP/deal | H80: Fixed input; not scenario-driven. Tier B API-assisted document review fee; below many bank discrepancy/amendment fee stacks.
B81: Tier C document/review fee | F81: 300 | G81: GBP/deal | H81: Fixed input; not scenario-driven. Tier C manual/paper review fee; priced for higher work but still LC-competitive all-in.
B82: Tier A dispute/amendment fee | F82: 100 | G82: GBP/event | H82: Fixed input; not scenario-driven. Dispute/amendment admin fee within familiar LC admin-fee range.
B83: Tier B dispute/amendment fee | F83: 200 | G83: GBP/event | H83: Fixed input; not scenario-driven. Dispute/amendment admin fee within familiar LC admin-fee range.
B84: Tier C dispute/amendment fee | F84: 500 | G84: GBP/event | H84: Fixed input; not scenario-driven. Paper/originals discrepancy handling; premium manual workflow fee.
... B108: Tier C docs/deal | F108: 9 | G108: docs/deal | H108: Fixed input; not scenario-driven. Paper/originals bundle
B109: -- CUSTOMER ACQUISITION CROSS-CHECK --
B110: Deals per active customer Yr1 | C110: 1.5 | D110: 3 | E110: 5 | F110: =CHOOSE($C$4,C110,D110,E110) -> 3 | G110: deals/customer/yr | H110: Commercial sanity check; P&L remains driven by deal count
B111: Deals per active customer Yr2 | C111: 2 | D111: 4 | E111: 6 | F111: =CHOOSE($C$4,C111,D111,E111) -> 4 | G111: deals/customer/yr | H111: Commercial sanity check; should improve with repeat usage
B112: Deals per active customer Yr3 | C112: 2.5 | D112: 6 | E112: 10 | F112: =CHOOSE($C$4,C112,D112,E112) -> 6 | G112: deals/customer/yr | H112: Commercial sanity check; high case assumes repeat platform usage
B113: Partner count Yr3 | C113: 0 | D113: 6 | E113: 20 | F113: =CHOOSE($C$4,C113,D113,E113) -> 6 | G113: partners | H113: Total API/platform partners by Year 3; setup fee charges only net-new partners
B114: -- OPTIONAL FEES / ADD-ONS --
B115: First-deal discount rate | F115: 0.5 | G115: % discount | H115: Fixed input; not scenario-driven. Commercial launch discount policy; repeated across scenarios.
B116: Tier B expedited review uptake | F116: 0.1 | G116: % Tier B deals | H116: Fixed input; not scenario-driven. Scenario-driven customer uptake of optional expedited Tier B review; fee itself is fixed in row 129.
B117: Tier C expedited review uptake | F117: 0.2 | G117: % Tier C deals | H117: Fixed input; not scenario-driven. Scenario-driven customer uptake of optional expedited Tier C review; fee itself is fixed in row 130.
B118: Tier B expedited review fee | F118: 150 | G118: GBP/deal | H118: Fixed input; not scenario-driven. Optional expedited Tier B review; price-book assumption, not scenario sensitivity.
B119: Tier C expedited review fee | F119: 300 | G119: GBP/deal | H119: Fixed input; not scenario-driven. Optional expedited Tier C paper/originals workflow; price-book assumption.
B120: KYC/KYB onboarding fee / counterparty | F120: 15 | G120: GBP/party | H120: Fixed input; not scenario-driven. KYC/KYB onboarding admin fee; can be charged or bundled into first deal.
B121: Tier C forensics pass-through markup | F121: 0.2 | G121: % over cost | H121: Fixed input; not scenario-driven. Pass-through markup on paper/forensics partner costs.
B122: Tier C courier/original handling fee | F122: 75 | G122: GBP/deal | H122: Fixed input; not scenario-driven. Tier C courier/original handling admin fee.
B123: Discrepancy cure / waiver fee | F123: 150 | G123: GBP/case | H123: Fixed input; not scenario-driven. Discrepancy cure/waiver fee in familiar LC admin-fee range.
B124: % disputed deals resolved as cure/waiver | F124: 0.4 | G124: % disputed | H124: Fixed input; not scenario-driven. Scenario-driven share of disputed deals resolved through lighter cure/waiver workflow.
B125: Partner setup / integration fee | F125: 7500 | G125: GBP/new partner | H125: Fixed input; not scenario-driven. Forwarder/platform/API setup fee; price-book assumption.
...

Sheet Startup_6mo
B2: First 6 Months — Startup Costs (one-off + setup ramp)
B3: One-off costs incurred in months 0-6. Recurring opex/payroll lives in P&L_5yr. Scenario-driven (Low/Base/High).
B5: Cost driver | C5: Low | D5: Base | E5: High | F5: Active | G5: Cur | H5: Notes / source quality
B6: COMPANY FORMATION & FILINGS
B7: Companies House digital incorporation | C7: 100 | D7: 100 | E7: 100 | F7: =CHOOSE(Assumptions!$C$4,C7,D7,E7) -> 100 | G7: £ | H7: £100 from 1 Feb 2026 (official: Companies House)
B8: Registered office / address service (6mo) | C8: 30 | D8: 90 | E8: 180 | F8: =CHOOSE(Assumptions!$C$4,C8,D8,E8) -> 90 | G8: £ | H8: Virtual office (vendor/estimate)
B9: Director ID verification / ACSP | C9: 0 | D9: 63 | E9: 63 | F9: =CHOOSE(Assumptions!$C$4,C9,D9,E9) -> 63 | G9: £ | H9: ACSP £63; One Login free (official)
B10: Confirmation statement (annual) | C10: 50 | D10: 50 | E10: 50 | F10: =CHOOSE(Assumptions!$C$4,C10,D10,E10) -> 50 | G10: £ | H10: £50 digital from Feb 2026 (official)
B11: LEGAL SETUP
B12: Shareholder agreement | C12: 375 | D12: 1500 | E12: 3000 | F12: =CHOOSE(Assumptions!$C$4,C12,D12,E12) -> 1500 | G12: £ | H12: £375–£3,000 fixed-fee (benchmark)
B13: IP assignment (founders/contractors) | C13: 200 | D13: 600 | E13: 1500 | F13: =CHOOSE(Assumptions!$C$4,C13,D13,E13) -> 600 | G13: £ | H13: Assign IP into company (estimate)
B14: Articles / cap table / SAFE setup | C14: 0 | D14: 1000 | E14: 3000 | F14: =CHOOSE(Assumptions!$C$4,C14,D14,E14) -> 1000 | G14: £ | H14: SAFE/ASA template + review (estimate)
B15: Website terms + privacy policy | C15: 300 | D15: 900 | E15: 2500 | F15: =CHOOSE(Assumptions!$C$4,C15,D15,E15) -> 900 | G15: £ | H15: Bespoke for fintech (estimate)
B16: Trade Escrow Agreement template (bespoke) | C16: 3000 | D16: 8000 | E16: 18000 | F16: =CHOOSE(Assumptions!$C$4,C16,D16,E16) -> 8000 | G16: £ | H16: Core product contract; bespoke drafting (estimate)
B17: REGULATORY & COMPLIANCE SETUP
B18: Regulatory perimeter advice (crypto/stablecoin escrow) | C18: 8000 | D18: 25000 | E18: 60000 | F18: =CHOOSE(Assumptions!$C$4,C18,D18,E18) -> 25000 | G18: £ | H18: HIGH RISK. FCA crypto regime 2027; safeguarding may be in-scope (estimate)
B19: AML/KYC/sanctions policy + procedures | C19: 2000 | D19: 6000 | E19: 15000 | F19: =CHOOSE(Assumptions!$C$4,C19,D19,E19) -> 6000 | G19: £ | H19: MLR 2017 policy pack + MLRO setup (estimate)
B20: Data protection / GDPR setup (DPIA, ROPA) | C20: 1000 | D20: 3000 | E20: 8000 | F20: =CHOOSE(Assumptions!$C$4,C20,D20,E20) -> 3000 | G20: £ | H20: ICO registration £40–60 + advice (official+estimate)
B21: ICO data protection fee | C21: 52 | D21: 60 | E21: 60 | F21: =CHOOSE(Assumptions!$C$4,C21,D21,E21) -> 60 | G21: £ | H21: ICO annual fee tier (official: ICO)
B22: SECURITY
B23: Smart-contract audit / security review | C23: 12000 | D23: 30000 | E23: 60000 | F23: =CHOOSE(Assumptions!$C$4,C23,D23,E23) -> 30000 | G23: £ | H23: Moderate-complexity escrow contracts (benchmark)
B24: Penetration test (web app) | C24: 3000 | D24: 7000 | E24: 15000 | F24: =CHOOSE(Assumptions!$C$4,C24,D24,E24) -> 7000 | G24: £ | H24: Pre-launch pentest (vendor/estimate)
B25: PRODUCT BUILD (one-off, pre-revenue)
B26: Smart-contract development (contract) | C26: 15000 | D26: 40000 | E26: 90000 | F26: =CHOOSE(Assumptions!$C$4,C26,D26,E26) -> 40000 | G26: £ | H26: Solidity build; days × day-rate (estimate)
B27: Web app / full-stack build (contract) | C27: 20000 | D27: 50000 | E27: 110000 | F27: =CHOOSE(Assumptions!$C$4,C27,D27,E27) -> 50000 | G27: £ | H27: MVP build incl. integrations (estimate)
B28: UI/UX design | C28: 3000 | D28: 9000 | E28: 20000 | F28: =CHOOSE(Assumptions!$C$4,C28,D28,E28) -> 9000 | G28: £ | H28: (estimate)
B29: BRAND, DECK & WEB
B30: Pitch deck + brand identity | C30: 1500 | D30: 5000 | E30: 12000 | F30: =CHOOSE(Assumptions!$C$4,C30,D30,E30) -> 5000 | G30: £ | H30: (estimate)
B31: Marketing website | C31: 1000 | D31: 4000 | E31: 10000 | F31: =CHOOSE(Assumptions!$C$4,C31,D31,E31) -> 4000 | G31: £ | H31: (estimate)
B32: Domain + email + initial SaaS | C32: 100 | D32: 300 | E32: 800 | F32: =CHOOSE(Assumptions!$C$4,C32,D32,E32) -> 300 | G32: £ | H32: Domain, Workspace setup (vendor)
B33: BUSINESS DEVELOPMENT (setup)
B34: Pilot outreach / travel (UK/EU/ME) | C34: 1000 | D34: 5000 | E34: 15000 | F34: =CHOOSE(Assumptions!$C$4,C34,D34,E34) -> 5000 | G34: £ | H34: ME travel pushes high end (estimate)
B35: Conferences / trade events (first 6mo) | C35: 1000 | D35: 4000 | E35: 12000 | F35: =CHOOSE(Assumptions!$C$4,C35,D35,E35) -> 4000 | G35: £ | H35: (estimate)
B36: INSURANCE (first-year, paid upfront)
B37: Professional indemnity (annual) | C37: 1200 | D37: 3500 | E37: 9000 | F37: =CHOOSE(Assumptions!$C$4,C37,D37,E37) -> 3500 | G37: £ | H37: Prepaid first-year insurance; do not also include Year 1 monthly insurance in P&L.
B38: Cyber insurance (annual) | C38: 1000 | D38: 3000 | E38: 8000 | F38: =CHOOSE(Assumptions!$C$4,C38,D38,E38) -> 3000 | G38: £ | H38: Prepaid first-year insurance; do not also include Year 1 monthly insurance in P&L.
B39: D&O insurance (annual) | C39: 800 | D39: 2500 | E39: 7000 | F39: =CHOOSE(Assumptions!$C$4,C39,D39,E39) -> 2500 | G39: £ | H39: Prepaid first-year insurance; do not also include Year 1 monthly insurance in P&L.
B40: CONTINGENCY
B41: Contingency on one-off costs | C41: 0.1 | D41: 0.15 | E41: 0.2 | F41: =CHOOSE(Assumptions!$C$4,C41,D41,E41) -> 0.15 | G41: % | H41: Applied to subtotal (estimate)
B42: Subtotal one-off costs (ex-contingency) | F42: =SUMIF($G$6:$G$40,"£",$F$6:$F$40) -> 209663
B43: Contingency amount | F43: =F42*F41 -> 31449.45
B44: TOTAL FIRST-6-MONTHS ONE-OFF COSTS | F44: =F42+F43 -> 241112.45

Sheet Cash_Flow_Statement
A1: Cash Flow Statement - monthly 60-month projection
A2: Active scenario is controlled by Assumptions!C4. Year 1 revenue/COGS are phased after the pre-revenue months; startup costs are paid over months 1-6; financing is staged as the implied funding ask steps up.
G3: Peak cumulative operating deficit | J3: Month 60 operating cash
A4: Active scenario | B4: =Assumptions!$D$4 -> BASE | D4: Cash-flow break-even month | E4: =IF(MAX(B38:BI38)<0,"Beyond Month 60",INDEX($B$9:$BI$9,1,MATCH(TRUE,INDEX(B38:BI38>=0,0),0))) -> Y4 M5 | H4: =-MIN(0,B38:BI38) -> 1269402.1 | K4: =BI38 -> 12220136
A6: Month # | B6: 1 | C6: 2 | D6: 3 | E6: 4 | F6: 5 | G6: 6 | H6: 7 | I6: 8 | J6: 9 | K6: 10 | L6: 11 | M6: 12 | N6: 13 | O6: 14 | P6: 15 | Q6: 16 | R6: 17 | S6: 18 | T6: 19 | U6: 20 | V6: 21 | W6: 22 | X6: 23 | Y6: 24 | Z6: 25 | AA6: 26 | AB6: 27 | AC6: 28 | AD6: 29 | AE6: 30 | AF6: 31 | AG6: 32 | AH6: 33 | AI6: 34 | AJ6: 35 | AK6: 36 | AL6: 37 | AM6: 38 | AN6: 39 | AO6: 40 | AP6: 41 | AQ6: 42 | AR6: 43 | AS6: 44 | AT6: 45 | AU6: 46 | AV6: 47 | AW6: 48 | AX6: 49 | AY6: 50 | AZ6: 51 | BA6: 52 | BB6: 53 | BC6: 54 | BD6: 55 | BE6: 56 | BF6: 57 | BG6: 58 | BH6: 59 | BI6: 60 | BK6: Logic / note
A7: Model year | B7: =ROUNDUP(B$6/12,0) -> 1 | C7: =ROUNDUP(C$6/12,0) -> 1 | D7: =ROUNDUP(D$6/12,0) -> 1 | E7: =ROUNDUP(E$6/12,0) -> 1 | F7: =ROUNDUP(F$6/12,0) -> 1 | G7: =ROUNDUP(G$6/12,0) -> 1 | H7: =ROUNDUP(H$6/12,0) -> 1 | I7: =ROUNDUP(I$6/12,0) -> 1 | ... BI7: =ROUNDUP(BI$6/12,0) -> 5
A8: Month in year | B8: =MOD(B$6-1,12)+1 -> 1 | C8: =MOD(C$6-1,12)+1 -> 2 | D8: =MOD(D$6-1,12)+1 -> 3 | E8: =MOD(E$6-1,12)+1 -> 4 | F8: =MOD(F$6-1,12)+1 -> 5 | G8: =MOD(G$6-1,12)+1 -> 6 | H8: =MOD(H$6-1,12)+1 -> 7 | I8: =MOD(I$6-1,12)+1 -> 8 | ... BI8: =MOD(BI$6-1,12)+1 -> 12
A9: Period | B9: ="Y"&B$7&" M"&B$8 -> Y1 M1 | C9: ="Y"&C$7&" M"&C$8 -> Y1 M2 | D9: ="Y"&D$7&" M"&D$8 -> Y1 M3 | E9: ="Y"&E$7&" M"&E$8 -> Y1 M4 | F9: ="Y"&F$7&" M"&F$8 -> Y1 M5 | G9: ="Y"&G$7&" M"&G$8 -> Y1 M6 | H9: ="Y"&H$7&" M"&H$8 -> Y1 M7 | I9: ="Y"&I$7&" M"&I$8 -> Y1 M8 | ... BI9: ="Y"&BI$7&" M"&BI$8 -> Y5 M12
A11: CASH FLOWS FROM OPERATING ACTIVITIES
A12: Customer receipts | B12: =IF(B$7=1,IF(B$8<=Assumptions!$F$59,0,INDEX('P&L_5yr'!$C$18:$G$18,1,B$7)/MAX(1,12-Assumptions!$F$59)),INDEX('P&L_5yr'!$C$18:$G$18,1,B$7)/12) -> 0 | C12: =IF(C$7=1,IF(C$8<=Assumptions!$F$59,0,INDEX('P&L_5yr'!$C$18:$G$18,1,C$7)/MAX(1,12-Assumptions!$F$59)),INDEX('P&L_5yr'!$C$18:$G$18,1,C$7)/12) -> 0 | D12: =IF(D$7=1,IF(D$8<=Assumptions!$F$59,0,INDEX('P&L_5yr'!$C$18:$G$18,1,D$7)/MAX(1,12-Assumptions!$F$59)),INDEX('P&L_5yr'!$C$18:$G$18,1,D$7)/12) -> 0 | E12: =IF(E$7=1,IF(E$8<=Assumptions!$F$59,0,INDEX('P&L_5yr'!$C$18:$G$18,1,E$7)/MAX(1,12-Assumptions!$F$59)),INDEX('P&L_5yr'!$C$18:$G$18,1,E$7)/12) -> 0 | F12: =IF(F$7=1,IF(F$8<=Assumptions!$F$59,0,INDEX('P&L_5yr'!$C$18:$G$18,1,F$7)/MAX(1,12-Assumptions!$F$59)),INDEX('P&L_5yr'!$C$18:$G$18,1,F$7)/12) -> 0 | G12: =IF(G$7=1,IF(G$8<=Assumptions!$F$59,0,INDEX('P&L_5yr'!$C$18:$G$18,1,G$7)/MAX(1,12-Assumptions!$F$59)),INDEX('P&L_5yr'!$C$18:$G$18,1,G$7)/12) -> 0 | H12: =IF(H$7=1,IF(H$8<=Assumptions!$F$59,0,INDEX('P&L_5yr'!$C$18:$G$18,1,H$7)/MAX(1,12-Assumptions!$F$59)),INDEX('P&L_5yr'!$C$18:$G$18,1,H$7)/12) -> 17917.5 | I12: =IF(I$7=1,IF(I$8<=Assumptions!$F$59,0,INDEX('P&L_5yr'!$C$18:$G$18,1,I$7)/MAX(1,12-Assumptions!$F$59)),INDEX('P&L_5yr'!$C$18:$G$18,1,I$7)/12) -> 17917.5 | ... BI12: =IF(BI$7=1,IF(BI$8<=Assumptions!$F$59,0,INDEX('P&L_5yr'!$C$18:$G$18,1,BI$7)/MAX(1,12-Assumptions!$F$59)),INDEX('P&L_5yr'!$C$18:$G$18,1,BI$7)/12) -> 1228354.6 | BK12: Revenue receipts are phased after Year 1 pre-revenue months; Years 2-5 are straight-lined monthly.
A13: Variable COGS cash payments | B13: =-IF(B$7=1,IF(B$8<=Assumptions!$F$59,0,INDEX('P&L_5yr'!$C$29:$G$29,1,B$7)/MAX(1,12-Assumptions!$F$59)),INDEX('P&L_5yr'!$C$29:$G$29,1,B$7)/12) -> 0 | C13: =-IF(C$7=1,IF(C$8<=Assumptions!$F$59,0,INDEX('P&L_5yr'!$C$29:$G$29,1,C$7)/MAX(1,12-Assumptions!$F$59)),INDEX('P&L_5yr'!$C$29:$G$29,1,C$7)/12) -> 0 | D13: =-IF(D$7=1,IF(D$8<=Assumptions!$F$59,0,INDEX('P&L_5yr'!$C$29:$G$29,1,D$7)/MAX(1,12-Assumptions!$F$59)),INDEX('P&L_5yr'!$C$29:$G$29,1,D$7)/12) -> 0 | E13: =-IF(E$7=1,IF(E$8<=Assumptions!$F$59,0,INDEX('P&L_5yr'!$C$29:$G$29,1,E$7)/MAX(1,12-Assumptions!$F$59)),INDEX('P&L_5yr'!$C$29:$G$29,1,E$7)/12) -> 0 | F13: =-IF(F$7=1,IF(F$8<=Assumptions!$F$59,0,INDEX('P&L_5yr'!$C$29:$G$29,1,F$7)/MAX(1,12-Assumptions!$F$59)),INDEX('P&L_5yr'!$C$29:$G$29,1,F$7)/12) -> 0 | G13: =-IF(G$7=1,IF(G$8<=Assumptions!$F$59,0,INDEX('P&L_5yr'!$C$29:$G$29,1,G$7)/MAX(1,12-Assumptions!$F$59)),INDEX('P&L_5yr'!$C$29:$G$29,1,G$7)/12) -> 0 | H13: =-IF(H$7=1,IF(H$8<=Assumptions!$F$59,0,INDEX('P&L_5yr'!$C$29:$G$29,1,H$7)/MAX(1,12-Assumptions!$F$59)),INDEX('P&L_5yr'!$C$29:$G$29,1,H$7)/12) -> -7745.0096 | I13: =-IF(I$7=1,IF(I$8<=Assumptions!$F$59,0,INDEX('P&L_5yr'!$C$29:$G$29,1,I$7)/MAX(1,12-Assumptions!$F$59)),INDEX('P&L_5yr'!$C$29:$G$29,1,I$7)/12) -> -7745.0096 | ... BI13: =-IF(BI$7=1,IF(BI$8<=Assumptions!$F$59,0,INDEX('P&L_5yr'!$C$29:$G$29,1,BI$7)/MAX(1,12-Assumptions!$F$59)),INDEX('P&L_5yr'!$C$29:$G$29,1,BI$7)/12) -> -211688.98 | BK13: COGS follows the same revenue phasing.
A14: Gross operating cash margin | B14: =SUM(B12:B13) -> 0 | C14: =SUM(C12:C13) -> 0 | D14: =SUM(D12:D13) -> 0 | E14: =SUM(E12:E13) -> 0 | F14: =SUM(F12:F13) -> 0 | G14: =SUM(G12:G13) -> 0 | H14: =SUM(H12:H13) -> 10172.49 | I14: =SUM(I12:I13) -> 10172.49 | ... BI14: =SUM(BI12:BI13) -> 1016665.6
A15: Payroll cash payments | B15: =-INDEX('P&L_5yr'!$C$42:$G$42,1,B$7)/12 -> -33316.667 | C15: =-INDEX('P&L_5yr'!$C$42:$G$42,1,C$7)/12 -> -33316.667 | D15: =-INDEX('P&L_5yr'!$C$42:$G$42,1,D$7)/12 -> -33316.667 | E15: =-INDEX('P&L_5yr'!$C$42:$G$42,1,E$7)/12 -> -33316.667 | F15: =-INDEX('P&L_5yr'!$C$42:$G$42,1,F$7)/12 -> -33316.667 | G15: =-INDEX('P&L_5yr'!$C$42:$G$42,1,G$7)/12 -> -33316.667 | H15: =-INDEX('P&L_5yr'!$C$42:$G$42,1,H$7)/12 -> -33316.667 | I15: =-INDEX('P&L_5yr'!$C$42:$G$42,1,I$7)/12 -> -33316.667 | ... BI15: =-INDEX('P&L_5yr'!$C$42:$G$42,1,BI$7)/12 -> -105766.67 | BK15: Annual payroll from P&L_5yr divided by 12.
A16: Fixed opex cash payments | B16: =-INDEX('P&L_5yr'!$C$56:$G$56,1,B$7)/12 -> -19800 | C16: =-INDEX('P&L_5yr'!$C$56:$G$56,1,C$7)/12 -> -19800 | D16: =-INDEX('P&L_5yr'!$C$56:$G$56,1,D$7)/12 -> -19800 | E16: =-INDEX('P&L_5yr'!$C$56:$G$56,1,E$7)/12 -> -19800 | F16: =-INDEX('P&L_5yr'!$C$56:$G$56,1,F$7)/12 -> -19800 | G16: =-INDEX('P&L_5yr'!$C$56:$G$56,1,G$7)/12 -> -19800 | H16: =-INDEX('P&L_5yr'!$C$56:$G$56,1,H$7)/12 -> -19800 | I16: =-INDEX('P&L_5yr'!$C$56:$G$56,1,I$7)/12 -> -19800 | ... BI16: =-INDEX('P&L_5yr'!$C$56:$G$56,1,BI$7)/12 -> -36903.333 | BK16: Annual fixed opex from P&L_5yr divided by 12.
A17: Startup / one-off cash payments | B17: =-IF(B$6<=6,'P&L_5yr'!$C$58/6,0) -> -40185.408 | C17: =-IF(C$6<=6,'P&L_5yr'!$C$58/6,0) -> -40185.408 | D17: =-IF(D$6<=6,'P&L_5yr'!$C$58/6,0) -> -40185.408 | E17: =-IF(E$6<=6,'P&L_5yr'!$C$58/6,0) -> -40185.408 | F17: =-IF(F$6<=6,'P&L_5yr'!$C$58/6,0) -> -40185.408 | G17: =-IF(G$6<=6,'P&L_5yr'!$C$58/6,0) -> -40185.408 | H17: =-IF(H$6<=6,'P&L_5yr'!$C$58/6,0) -> 0 | I17: =-IF(I$6<=6,'P&L_5yr'!$C$58/6,0) -> 0 | ... BI17: =-IF(BI$6<=6,'P&L_5yr'!$C$58/6,0) -> 0 | BK17: Startup_6mo / Year 1 one-off spend paid over months 1-6.
A18: Working capital / settlement float | B18: =0 -> 0 | C18: =0 -> 0 | D18: =0 -> 0 | E18: =0 -> 0 | F18: =0 -> 0 | G18: =0 -> 0 | H18: =0 -> 0 | I18: =0 -> 0 | ... BI18: =0 -> 0 | BK18: Client escrow funds remain restricted/off-balance-sheet; no settlement float benefit is modelled.
A19: Net cash from operating activities | B19: =B14+SUM(B15:B18) -> -93302.075 | C19: =C14+SUM(C15:C18) -> -93302.075 | D19: =D14+SUM(D15:D18) -> -93302.075 | E19: =E14+SUM(E15:E18) -> -93302.075 | F19: =F14+SUM(F15:F18) -> -93302.075 | G19: =G14+SUM(G15:G18) -> -93302.075 | H19: =H14+SUM(H15:H18) -> -42944.176 | I19: =I14+SUM(I15:I18) -> -42944.176 | ... BI19: =BI14+SUM(BI15:BI18) -> 873995.58
A21: CASH FLOWS FROM INVESTING ACTIVITIES
A22: Capitalised development / capex | B22: =0 -> 0 | C22: =0 -> 0 | D22: =0 -> 0 | E22: =0 -> 0 | F22: =0 -> 0 | G22: =0 -> 0 | H22: =0 -> 0 | I22: =0 -> 0 | ... BI22: =0 -> 0
A23: Net cash from investing activities | B23: =B22 -> 0 | C23: =C22 -> 0 | D23: =D22 -> 0 | E23: =E22 -> 0 | F23: =F22 -> 0 | G23: =G22 -> 0 | H23: =H22 -> 0 | I23: =I22 -> 0 | ... BI23: =BI22 -> 0
A25: CASH FLOWS FROM FINANCING ACTIVITIES
A26: External funding raised | B26: =IF(B$8=1,IF(B$7=1,'P&L_5yr'!$C$66,MAX(0,INDEX('P&L_5yr'!$C$66:$G$66,1,B$7)-INDEX('P&L_5yr'!$C$66:$G$66,1,B$7-1))),0) -> 1302721 | C26: =IF(C$8=1,IF(C$7=1,'P&L_5yr'!$C$66,MAX(0,INDEX('P&L_5yr'!$C$66:$G$66,1,C$7)-INDEX('P&L_5yr'!$C$66:$G$66,1,C$7-1))),0) -> 0 | D26: =IF(D$8=1,IF(D$7=1,'P&L_5yr'!$C$66,MAX(0,INDEX('P&L_5yr'!$C$66:$G$66,1,D$7)-INDEX('P&L_5yr'!$C$66:$G$66,1,D$7-1))),0) -> 0 | E26: =IF(E$8=1,IF(E$7=1,'P&L_5yr'!$C$66,MAX(0,INDEX('P&L_5yr'!$C$66:$G$66,1,E$7)-INDEX('P&L_5yr'!$C$66:$G$66,1,E$7-1))),0) -> 0 | F26: =IF(F$8=1,IF(F$7=1,'P&L_5yr'!$C$66,MAX(0,INDEX('P&L_5yr'!$C$66:$G$66,1,F$7)-INDEX('P&L_5yr'!$C$66:$G$66,1,F$7-1))),0) -> 0 | G26: =IF(G$8=1,IF(G$7=1,'P&L_5yr'!$C$66,MAX(0,INDEX('P&L_5yr'!$C$66:$G$66,1,G$7)-INDEX('P&L_5yr'!$C$66:$G$66,1,G$7-1))),0) -> 0 | H26: =IF(H$8=1,IF(H$7=1,'P&L_5yr'!$C$66,MAX(0,INDEX('P&L_5yr'!$C$66:$G$66,1,H$7)-INDEX('P&L_5yr'!$C$66:$G$66,1,H$7-1))),0) -> 0 | I26: =IF(I$8=1,IF(I$7=1,'P&L_5yr'!$C$66,MAX(0,INDEX('P&L_5yr'!$C$66:$G$66,1,I$7)-INDEX('P&L_5yr'!$C$66:$G$66,1,I$7-1))),0) -> 0 | ... BI26: =IF(BI$8=1,IF(BI$7=1,'P&L_5yr'!$C$66,MAX(0,INDEX('P&L_5yr'!$C$66:$G$66,1,BI$7)-INDEX('P&L_5yr'!$C$66:$G$66,1,BI$7-1))),0) -> 0 | BK26: Raised in month 1 of any year when the cumulative funding ask steps up.
A27: Restricted contingency reserve set aside | B27: =IF(B$8=1,-INDEX('P&L_5yr'!$C$65:$G$65,1,B$7),0) -> -240000 | C27: =IF(C$8=1,-INDEX('P&L_5yr'!$C$65:$G$65,1,C$7),0) -> 0 | D27: =IF(D$8=1,-INDEX('P&L_5yr'!$C$65:$G$65,1,D$7),0) -> 0 | E27: =IF(E$8=1,-INDEX('P&L_5yr'!$C$65:$G$65,1,E$7),0) -> 0 | F27: =IF(F$8=1,-INDEX('P&L_5yr'!$C$65:$G$65,1,F$7),0) -> 0 | G27: =IF(G$8=1,-INDEX('P&L_5yr'!$C$65:$G$65,1,G$7),0) -> 0 | H27: =IF(H$8=1,-INDEX('P&L_5yr'!$C$65:$G$65,1,H$7),0) -> 0 | I27: =IF(I$8=1,-INDEX('P&L_5yr'!$C$65:$G$65,1,I$7),0) -> 0 | ... BI27: =IF(BI$8=1,-INDEX('P&L_5yr'!$C$65:$G$65,1,BI$7),0) -> 0 | BK27: Funding-only contingency reserve is separated from unrestricted operating cash.
A28: Net cash from financing activities | B28: =SUM(B26:B27) -> 1062721 | C28: =SUM(C26:C27) -> 0 | D28: =SUM(D26:D27) -> 0 | E28: =SUM(E26:E27) -> 0 | F28: =SUM(F26:F27) -> 0 | G28: =SUM(G26:G27) -> 0 | H28: =SUM(H26:H27) -> 0 | I28: =SUM(I26:I27) -> 0 | ... BI28: =SUM(BI26:BI27) -> 0
A30: CASH RECONCILIATION
A31: Opening unrestricted cash | B31: 0 | C31: =B33 -> 969418.93 | D31: =C33 -> 876116.85 | E31: =D33 -> 782814.78 | F31: =E33 -> 689512.7 | G31: =F33 -> 596210.63 | H31: =G33 -> 502908.55 | I31: =H33 -> 459964.37 | J31: =I33 -> 417020.2 | ... BI31: =BH33 -> 12756364
A32: Net change in unrestricted cash | B32: =B19+B23+B28 -> 969418.93 | C32: =C19+C23+C28 -> -93302.075 | D32: =D19+D23+D28 -> -93302.075 | E32: =E19+E23+E28 -> -93302.075 | F32: =F19+F23+F28 -> -93302.075 | G32: =G19+G23+G28 -> -93302.075 | H32: =H19+H23+H28 -> -42944.176 | I32: =I19+I23+I28 -> -42944.176 | ... BI32: =BI19+BI23+BI28 -> 873995.58
A33: Closing unrestricted cash | B33: =B31+B32 -> 969418.93 | C33: =C31+C32 -> 876116.85 | D33: =D31+D32 -> 782814.78 | E33: =E31+E32 -> 689512.7 | F33: =F31+F32 -> 596210.63 | G33: =G31+G32 -> 502908.55 | H33: =H31+H32 -> 459964.37 | I33: =I31+I32 -> 417020.2 | ... BI33: =BI31+BI32 -> 13630359
A34: Restricted contingency reserve held | B34: =-B27 -> 240000 | C34: =B34-C27 -> 240000 | D34: =C34-D27 -> 240000 | E34: =D34-E27 -> 240000 | F34: =E34-F27 -> 240000 | G34: =F34-G27 -> 240000 | H34: =G34-H27 -> 240000 | I34: =H34-I27 -> 240000 | J34: =I34-J27 -> 240000 | ... BI34: =BH34-BI27 -> 240000
A35: Closing cash incl. restricted reserve | B35: =B33+B34 -> 1209418.9 | C35: =C33+C34 -> 1116116.9 | D35: =D33+D34 -> 1022814.8 | E35: =E33+E34 -> 929512.7 | F35: =F33+F34 -> 836210.63 | G35: =G33+G34 -> 742908.55 | H35: =H33+H34 -> 699964.37 | I35: =I33+I34 -> 657020.2 | ... BI35: =BI33+BI34 -> 13870359
A37: BREAKEVEN / RUNWAY
A38: Operating cumulative cash flow before financing | B38: =B19 -> -93302.075 | C38: =B38+C19 -> -186604.15 | D38: =C38+D19 -> -279906.22 | E38: =D38+E19 -> -373208.3 | F38: =E38+F19 -> -466510.38 | G38: =F38+G19 -> -559812.45 | H38: =G38+H19 -> -602756.63 | I38: =H38+I19 -> -645700.8 | J38: =I38+J19 -> -688644.98 | ... BI38: =BH38+BI19 -> 12220136 | BK38: This is the monthly cash-flow break-even test before external financing.
A39: Cash-flow break-even status | B39: =IF(B38>=0,"Reached","Not yet") -> Not yet | C39: =IF(C38>=0,"Reached","Not yet") -> Not yet | D39: =IF(D38>=0,"Reached","Not yet") -> Not yet | E39: =IF(E38>=0,"Reached","Not yet") -> Not yet | F39: =IF(F38>=0,"Reached","Not yet") -> Not yet | G39: =IF(G38>=0,"Reached","Not yet") -> Not yet | H39: =IF(H38>=0,"Reached","Not yet") -> Not yet | I39: =IF(I38>=0,"Reached","Not yet") -> Not yet | ... BI39: =IF(BI38>=0,"Reached","Not yet") -> Reached
A40: Runway warning | B40: =IF(B33<0,"Cash shortfall","Funded") -> Funded | C40: =IF(C33<0,"Cash shortfall","Funded") -> Funded | D40: =IF(D33<0,"Cash shortfall","Funded") -> Funded | E40: =IF(E33<0,"Cash shortfall","Funded") -> Funded | F40: =IF(F33<0,"Cash shortfall","Funded") -> Funded | G40: =IF(G33<0,"Cash shortfall","Funded") -> Funded | H40: =IF(H33<0,"Cash shortfall","Funded") -> Funded | I40: =IF(I33<0,"Cash shortfall","Funded") -> Funded | ... BI40: =IF(BI33<0,"Cash shortfall","Funded") -> Funded
A43: Scenario comparison - monthly cash-flow break-even
A44: Scenario | B44: Cash-flow break-even month | C44: Peak cumulative operating deficit | D44: Month 60 cumulative operating cash | E44: EBITDA break-even | F44: Funding ask incl. contingency
A45: Low | B45: =IF(MAX(B52:BI52)<0,"Beyond Month 60",INDEX($B$9:$BI$9,1,MATCH(TRUE,INDEX(B52:BI52>=0,0),0))) -> Y5 M9 | C45: =-MIN(0,B52:BI52) -> 2290474.7 | D45: =BI52 -> 983353.42 | E45: =IF(Scenario_Low_PL!C61>=0,"Year 1",IF(Scenario_Low_PL!D61>=0,"Year 2",IF(Scenario_Low_PL!E61>=0,"Year 3",IF(Scenario_Low_PL!F61>=0,"Year 4",IF(Scenario_Low_PL!G61>=0,"Year 5","Beyond Year 5"))))) -> Year 5 | F45: =MAX(Scenario_Low_PL!C66:G66) -> 2977617
A46: Base | B46: =IF(MAX(B53:BI53)<0,"Beyond Month 60",INDEX($B$9:$BI$9,1,MATCH(TRUE,INDEX(B53:BI53>=0,0),0))) -> Y4 M5 | C46: =-MIN(0,B53:BI53) -> 1269402.1 | D46: =BI53 -> 12220136 | E46: =IF(Scenario_Base_PL!C61>=0,"Year 1",IF(Scenario_Base_PL!D61>=0,"Year 2",IF(Scenario_Base_PL!E61>=0,"Year 3",IF(Scenario_Base_PL!F61>=0,"Year 4",IF(Scenario_Base_PL!G61>=0,"Year 5","Beyond Year 5"))))) -> Year 3 | F46: =MAX(Scenario_Base_PL!C66:G66) -> 1650223
A47: High | B47: =IF(MAX(B54:BI54)<0,"Beyond Month 60",INDEX($B$9:$BI$9,1,MATCH(TRUE,INDEX(B54:BI54>=0,0),0))) -> Y3 M5 | C47: =-MIN(0,B54:BI54) -> 766670.51 | D47: =BI54 -> 31816705 | E47: =IF(Scenario_High_PL!C61>=0,"Year 1",IF(Scenario_High_PL!D61>=0,"Year 2",IF(Scenario_High_PL!E61>=0,"Year 3",IF(Scenario_High_PL!F61>=0,"Year 4",IF(Scenario_High_PL!G61>=0,"Year 5","Beyond Year 5"))))) -> Year 2 | F47: =MAX(Scenario_High_PL!C66:G66) -> 1236672
A49: Scenario cumulative operating cash flow before financing - monthly
A51: Scenario | B51: =Cash_Flow_Statement!B9 -> Y1 M1 | C51: =Cash_Flow_Statement!C9 -> Y1 M2 | D51: =Cash_Flow_Statement!D9 -> Y1 M3 | E51: =Cash_Flow_Statement!E9 -> Y1 M4 | F51: =Cash_Flow_Statement!F9 -> Y1 M5 | G51: =Cash_Flow_Statement!G9 -> Y1 M6 | H51: =Cash_Flow_Statement!H9 -> Y1 M7 | I51: =Cash_Flow_Statement!I9 -> Y1 M8 | ... BI51: =Cash_Flow_Statement!BI9 -> Y5 M12
A52: Low | B52: =(IF(B$7=1,IF(B$8<=Assumptions!$F$59,0,INDEX(Scenario_Low_PL!$C$18:$G$18,1,B$7)/MAX(1,12-Assumptions!$F$59)),INDEX(Scenario_Low_PL!$C$18:$G$18,1,B$7)/12))-(IF(B$7=1,IF(B$8<=Assumptions!$F$59,0,INDEX(Scenario_Low_PL!$C$29:$G$29,1,B$7)/MAX(1,12-Assumptions!$F$59)),INDEX(Scenario_Low_PL!$C$29:$G$29,1,B$7)/12))-(INDEX(Scenario_Low_PL!$C$42:$G$42,1,B$7)/12)-(INDEX(Scenario_Low_PL!$C$56:$G$56,1,B$7)/12)-(IF(B$6<=6,Scenario_Low_PL!$C$58/6,0)) -> -93302.075 | C52: =B52+((IF(C$7=1,IF(C$8<=Assumptions!$F$59,0,INDEX(Scenario_Low_PL!$C$18:$G$18,1,C$7)/MAX(1,12-Assumptions!$F$59)),INDEX(Scenario_Low_PL!$C$18:$G$18,1,C$7)/12))-(IF(C$7=1,IF(C$8<=Assumptions!$F$59,0,INDEX(Scenario_Low_PL!$C$29:$G$29,1,C$7)/MAX(1,12-Assumptions!$F$59)),INDEX(Scenario_Low_PL!$C$29:$G$29,1,C$7)/12))-(INDEX(Scenario_Low_PL!$C$42:$G$42,1,C$7)/12)-(INDEX(Scenario_Low_PL!$C$56:$G$56,1,C$7)/12)-(IF(C$6<=6,Scenario_Low_PL!$C$58/6,0))) -> -186604.15 | D52: =C52+((IF(D$7=1,IF(D$8<=Assumptions!$F$59,0,INDEX(Scenario_Low_PL!$C$18:$G$18,1,D$7)/MAX(1,12-Assumptions!$F$59)),INDEX(Scenario_Low_PL!$C$18:$G$18,1,D$7)/12))-(IF(D$7=1,IF(D$8<=Assumptions!$F$59,0,INDEX(Scenario_Low_PL!$C$29:$G$29,1,D$7)/MAX(1,12-Assumptions!$F$59)),INDEX(Scenario_Low_PL!$C$29:$G$29,1,D$7)/12))-(INDEX(Scenario_Low_PL!$C$42:$G$42,1,D$7)/12)-(INDEX(Scenario_Low_PL!$C$56:$G$56,1,D$7)/12)-(IF(D$6<=6,Scenario_Low_PL!$C$58/6,0))) -> -279906.22 | E52: =D52+((IF(E$7=1,IF(E$8<=Assumptions!$F$59,0,INDEX(Scenario_Low_PL!$C$18:$G$18,1,E$7)/MAX(1,12-Assumptions!$F$59)),INDEX(Scenario_Low_PL!$C$18:$G$18,1,E$7)/12))-(IF(E$7=1,IF(E$8<=Assumptions!$F$59,0,INDEX(Scenario_Low_PL!$C$29:$G$29,1,E$7)/MAX(1,12-Assumptions!$F$59)),INDEX(Scenario_Low_PL!$C$29:$G$29,1,E$7)/12))-(INDEX(Scenario_Low_PL!$C$42:$G$42,1,E$7)/12)-(INDEX(Scenario_Low_PL!$C$56:$G$56,1,E$7)/12)-(IF(E$6<=6,Scenario_Low_PL!$C$58/6,0))) -> -373208.3 | F52: =E52+((IF(F$7=1,IF(F$8<=Assumptions!$F$59,0,INDEX(Scenario_Low_PL!$C$18:$G$18,1,F$7)/MAX(1,12-Assumptions!$F$59)),INDEX(Scenario_Low_PL!$C$18:$G$18,1,F$7)/12))-(IF(F$7=1,IF(F$8<=Assumptions!$F$59,0,INDEX(Scenario_Low_PL!$C$29:$G$29,1,F$7)/MAX(1,12-Assumptions!$F$59)),INDEX(Scenario_Low_PL!$C$29:$G$29,1,F$7)/12))-(INDEX(Scenario_Low_PL!$C$42:$G$42,1,F$7)/12)-(INDEX(Scenario_Low_PL!$C$56:$G$56,1,F$7)/12)-(IF(F$6<=6,Scenario_Low_PL!$C$58/6,0))) -> -466510.38 | G52: =F52+((IF(G$7=1,IF(G$8<=Assumptions!$F$59,0,INDEX(Scenario_Low_PL!$C$18:$G$18,1,G$7)/MAX(1,12-Assumptions!$F$59)),INDEX(Scenario_Low_PL!$C$18:$G$18,1,G$7)/12))-(IF(G$7=1,IF(G$8<=Assumptions!$F$59,0,INDEX(Scenario_Low_PL!$C$29:$G$29,1,G$7)/MAX(1,12-Assumptions!$F$59)),INDEX(Scenario_Low_PL!$C$29:$G$29,1,G$7)/12))-(INDEX(Scenario_Low_PL!$C$42:$G$42,1,G$7)/12)-(INDEX(Scenario_Low_PL!$C$56:$G$56,1,G$7)/12)-(IF(G$6<=6,Scenario_Low_PL!$C$58/6,0))) -> -559812.45 | H52: =G52+((IF(H$7=1,IF(H$8<=Assumptions!$F$59,0,INDEX(Scenario_Low_PL!$C$18:$G$18,1,H$7)/MAX(1,12-Assumptions!$F$59)),INDEX(Scenario_Low_PL!$C$18:$G$18,1,H$7)/12))-(IF(H$7=1,IF(H$8<=Assumptions!$F$59,0,INDEX(Scenario_Low_PL!$C$29:$G$29,1,H$7)/MAX(1,12-Assumptions!$F$59)),INDEX(Scenario_Low_PL!$C$29:$G$29,1,H$7)/12))-(INDEX(Scenario_Low_PL!$C$42:$G$42,1,H$7)/12)-(INDEX(Scenario_Low_PL!$C$56:$G$56,1,H$7)/12)-(IF(H$6<=6,Scenario_Low_PL!$C$58/6,0))) -> -609184.45 | I52: =H52+((IF(I$7=1,IF(I$8<=Assumptions!$F$59,0,INDEX(Scenario_Low_PL!$C$18:$G$18,1,I$7)/MAX(1,12-Assumptions!$F$59)),INDEX(Scenario_Low_PL!$C$18:$G$18,1,I$7)/12))-(IF(I$7=1,IF(I$8<=Assumptions!$F$59,0,INDEX(Scenario_Low_PL!$C$29:$G$29,1,I$7)/MAX(1,12-Assumptions!$F$59)),INDEX(Scenario_Low_PL!$C$29:$G$29,1,I$7)/12))-(INDEX(Scenario_Low_PL!$C$42:$G$42,1,I$7)/12)-(INDEX(Scenario_Low_PL!$C$56:$G$56,1,I$7)/12)-(IF(I$6<=6,Scenario_Low_PL!$C$58/6,0))) -> -658556.44 | J52: =I52+((IF(J$7=1,IF(J$8<=Assumptions!$F$59,0,INDEX(Scenario_Low_PL!$C$18:$G$18,1,J$7)/MAX(1,12-Assumptions!$F$59)),INDEX(Scenario_Low_PL!$C$18:$G$18,1,J$7)/12))-(IF(J$7=1,IF(J$8<=Assumptions!$F$59,0,INDEX(Scenario_Low_PL!$C$29:$G$29,1,J$7)/MAX(1,12-Assumptions!$F$59)),INDEX(Scenario_Low_PL!$C$29:$G$29,1,J$7)/12))-(INDEX(Scenario_Low_PL!$C$42:$G$42,1,J$7)/12)-(INDEX(Scenario_Low_PL!$C$56:$G$56,1,J$7)/12)-(IF(J$6<=6,Scenario_Low_PL!$C$58/6,0))) -> -707928.44 | ... BI52: =BH52+((IF(BI$7=1,IF(BI$8<=Assumptions!$F$59,0,INDEX(Scenario_Low_PL!$C$18:$G$18,1,BI$7)/MAX(1,12-Assumptions!$F$59)),INDEX(Scenario_Low_PL!$C$18:$G$18,1,BI$7)/12))-(IF(BI$7=1,IF(BI$8<=Assumptions!$F$59,0,INDEX(Scenario_Low_PL!$C$29:$G$29,1,BI$7)/MAX(1,12-Assumptions!$F$59)),INDEX(Scenario_Low_PL!$C$29:$G$29,1,BI$7)/12))-(INDEX(Scenario_Low_PL!$C$42:$G$42,1,BI$7)/12)-(INDEX(Scenario_Low_PL!$C$56:$G$56,1,BI$7)/12)-(IF(BI$6<=6,Scenario_Low_PL!$C$58/6,0))) -> 983353.42
A53: Base | B53: =(IF(B$7=1,IF(B$8<=Assumptions!$F$59,0,INDEX(Scenario_Base_PL!$C$18:$G$18,1,B$7)/MAX(1,12-Assumptions!$F$59)),INDEX(Scenario_Base_PL!$C$18:$G$18,1,B$7)/12))-(IF(B$7=1,IF(B$8<=Assumptions!$F$59,0,INDEX(Scenario_Base_PL!$C$29:$G$29,1,B$7)/MAX(1,12-Assumptions!$F$59)),INDEX(Scenario_Base_PL!$C$29:$G$29,1,B$7)/12))-(INDEX(Scenario_Base_PL!$C$42:$G$42,1,B$7)/12)-(INDEX(Scenario_Base_PL!$C$56:$G$56,1,B$7)/12)-(IF(B$6<=6,Scenario_Base_PL!$C$58/6,0)) -> -93302.075 | C53: =B53+((IF(C$7=1,IF(C$8<=Assumptions!$F$59,0,INDEX(Scenario_Base_PL!$C$18:$G$18,1,C$7)/MAX(1,12-Assumptions!$F$59)),INDEX(Scenario_Base_PL!$C$18:$G$18,1,C$7)/12))-(IF(C$7=1,IF(C$8<=Assumptions!$F$59,0,INDEX(Scenario_Base_PL!$C$29:$G$29,1,C$7)/MAX(1,12-Assumptions!$F$59)),INDEX(Scenario_Base_PL!$C$29:$G$29,1,C$7)/12))-(INDEX(Scenario_Base_PL!$C$42:$G$42,1,C$7)/12)-(INDEX(Scenario_Base_PL!$C$56:$G$56,1,C$7)/12)-(IF(C$6<=6,Scenario_Base_PL!$C$58/6,0))) -> -186604.15 | D53: =C53+((IF(D$7=1,IF(D$8<=Assumptions!$F$59,0,INDEX(Scenario_Base_PL!$C$18:$G$18,1,D$7)/MAX(1,12-Assumptions!$F$59)),INDEX(Scenario_Base_PL!$C$18:$G$18,1,D$7)/12))-(IF(D$7=1,IF(D$8<=Assumptions!$F$59,0,INDEX(Scenario_Base_PL!$C$29:$G$29,1,D$7)/MAX(1,12-Assumptions!$F$59)),INDEX(Scenario_Base_PL!$C$29:$G$29,1,D$7)/12))-(INDEX(Scenario_Base_PL!$C$42:$G$42,1,D$7)/12)-(INDEX(Scenario_Base_PL!$C$56:$G$56,1,D$7)/12)-(IF(D$6<=6,Scenario_Base_PL!$C$58/6,0))) -> -279906.22 | E53: =D53+((IF(E$7=1,IF(E$8<=Assumptions!$F$59,0,INDEX(Scenario_Base_PL!$C$18:$G$18,1,E$7)/MAX(1,12-Assumptions!$F$59)),INDEX(Scenario_Base_PL!$C$18:$G$18,1,E$7)/12))-(IF(E$7=1,IF(E$8<=Assumptions!$F$59,0,INDEX(Scenario_Base_PL!$C$29:$G$29,1,E$7)/MAX(1,12-Assumptions!$F$59)),INDEX(Scenario_Base_PL!$C$29:$G$29,1,E$7)/12))-(INDEX(Scenario_Base_PL!$C$42:$G$42,1,E$7)/12)-(INDEX(Scenario_Base_PL!$C$56:$G$56,1,E$7)/12)-(IF(E$6<=6,Scenario_Base_PL!$C$58/6,0))) -> -373208.3 | F53: =E53+((IF(F$7=1,IF(F$8<=Assumptions!$F$59,0,INDEX(Scenario_Base_PL!$C$18:$G$18,1,F$7)/MAX(1,12-Assumptions!$F$59)),INDEX(Scenario_Base_PL!$C$18:$G$18,1,F$7)/12))-(IF(F$7=1,IF(F$8<=Assumptions!$F$59,0,INDEX(Scenario_Base_PL!$C$29:$G$29,1,F$7)/MAX(1,12-Assumptions!$F$59)),INDEX(Scenario_Base_PL!$C$29:$G$29,1,F$7)/12))-(INDEX(Scenario_Base_PL!$C$42:$G$42,1,F$7)/12)-(INDEX(Scenario_Base_PL!$C$56:$G$56,1,F$7)/12)-(IF(F$6<=6,Scenario_Base_PL!$C$58/6,0))) -> -466510.38 | G53: =F53+((IF(G$7=1,IF(G$8<=Assumptions!$F$59,0,INDEX(Scenario_Base_PL!$C$18:$G$18,1,G$7)/MAX(1,12-Assumptions!$F$59)),INDEX(Scenario_Base_PL!$C$18:$G$18,1,G$7)/12))-(IF(G$7=1,IF(G$8<=Assumptions!$F$59,0,INDEX(Scenario_Base_PL!$C$29:$G$29,1,G$7)/MAX(1,12-Assumptions!$F$59)),INDEX(Scenario_Base_PL!$C$29:$G$29,1,G$7)/12))-(INDEX(Scenario_Base_PL!$C$42:$G$42,1,G$7)/12)-(INDEX(Scenario_Base_PL!$C$56:$G$56,1,G$7)/12)-(IF(G$6<=6,Scenario_Base_PL!$C$58/6,0))) -> -559812.45 | H53: =G53+((IF(H$7=1,IF(H$8<=Assumptions!$F$59,0,INDEX(Scenario_Base_PL!$C$18:$G$18,1,H$7)/MAX(1,12-Assumptions!$F$59)),INDEX(Scenario_Base_PL!$C$18:$G$18,1,H$7)/12))-(IF(H$7=1,IF(H$8<=Assumptions!$F$59,0,INDEX(Scenario_Base_PL!$C$29:$G$29,1,H$7)/MAX(1,12-Assumptions!$F$59)),INDEX(Scenario_Base_PL!$C$29:$G$29,1,H$7)/12))-(INDEX(Scenario_Base_PL!$C$42:$G$42,1,H$7)/12)-(INDEX(Scenario_Base_PL!$C$56:$G$56,1,H$7)/12)-(IF(H$6<=6,Scenario_Base_PL!$C$58/6,0))) -> -602756.63 | I53: =H53+((IF(I$7=1,IF(I$8<=Assumptions!$F$59,0,INDEX(Scenario_Base_PL!$C$18:$G$18,1,I$7)/MAX(1,12-Assumptions!$F$59)),INDEX(Scenario_Base_PL!$C$18:$G$18,1,I$7)/12))-(IF(I$7=1,IF(I$8<=Assumptions!$F$59,0,INDEX(Scenario_Base_PL!$C$29:$G$29,1,I$7)/MAX(1,12-Assumptions!$F$59)),INDEX(Scenario_Base_PL!$C$29:$G$29,1,I$7)/12))-(INDEX(Scenario_Base_PL!$C$42:$G$42,1,I$7)/12)-(INDEX(Scenario_Base_PL!$C$56:$G$56,1,I$7)/12)-(IF(I$6<=6,Scenario_Base_PL!$C$58/6,0))) -> -645700.8 | J53: =I53+((IF(J$7=1,IF(J$8<=Assumptions!$F$59,0,INDEX(Scenario_Base_PL!$C$18:$G$18,1,J$7)/MAX(1,12-Assumptions!$F$59)),INDEX(Scenario_Base_PL!$C$18:$G$18,1,J$7)/12))-(IF(J$7=1,IF(J$8<=Assumptions!$F$59,0,INDEX(Scenario_Base_PL!$C$29:$G$29,1,J$7)/MAX(1,12-Assumptions!$F$59)),INDEX(Scenario_Base_PL!$C$29:$G$29,1,J$7)/12))-(INDEX(Scenario_Base_PL!$C$42:$G$42,1,J$7)/12)-(INDEX(Scenario_Base_PL!$C$56:$G$56,1,J$7)/12)-(IF(J$6<=6,Scenario_Base_PL!$C$58/6,0))) -> -688644.98 | ... BI53: =BH53+((IF(BI$7=1,IF(BI$8<=Assumptions!$F$59,0,INDEX(Scenario_Base_PL!$C$18:$G$18,1,BI$7)/MAX(1,12-Assumptions!$F$59)),INDEX(Scenario_Base_PL!$C$18:$G$18,1,BI$7)/12))-(IF(BI$7=1,IF(BI$8<=Assumptions!$F$59,0,INDEX(Scenario_Base_PL!$C$29:$G$29,1,BI$7)/MAX(1,12-Assumptions!$F$59)),INDEX(Scenario_Base_PL!$C$29:$G$29,1,BI$7)/12))-(INDEX(Scenario_Base_PL!$C$42:$G$42,1,BI$7)/12)-(INDEX(Scenario_Base_PL!$C$56:$G$56,1,BI$7)/12)-(IF(BI$6<=6,Scenario_Base_PL!$C$58/6,0))) -> 12220136
A54: High | B54: =(IF(B$7=1,IF(B$8<=Assumptions!$F$59,0,INDEX(Scenario_High_PL!$C$18:$G$18,1,B$7)/MAX(1,12-Assumptions!$F$59)),INDEX(Scenario_High_PL!$C$18:$G$18,1,B$7)/12))-(IF(B$7=1,IF(B$8<=Assumptions!$F$59,0,INDEX(Scenario_High_PL!$C$29:$G$29,1,B$7)/MAX(1,12-Assumptions!$F$59)),INDEX(Scenario_High_PL!$C$29:$G$29,1,B$7)/12))-(INDEX(Scenario_High_PL!$C$42:$G$42,1,B$7)/12)-(INDEX(Scenario_High_PL!$C$56:$G$56,1,B$7)/12)-(IF(B$6<=6,Scenario_High_PL!$C$58/6,0)) -> -93302.075 | C54: =B54+((IF(C$7=1,IF(C$8<=Assumptions!$F$59,0,INDEX(Scenario_High_PL!$C$18:$G$18,1,C$7)/MAX(1,12-Assumptions!$F$59)),INDEX(Scenario_High_PL!$C$18:$G$18,1,C$7)/12))-(IF(C$7=1,IF(C$8<=Assumptions!$F$59,0,INDEX(Scenario_High_PL!$C$29:$G$29,1,C$7)/MAX(1,12-Assumptions!$F$59)),INDEX(Scenario_High_PL!$C$29:$G$29,1,C$7)/12))-(INDEX(Scenario_High_PL!$C$42:$G$42,1,C$7)/12)-(INDEX(Scenario_High_PL!$C$56:$G$56,1,C$7)/12)-(IF(C$6<=6,Scenario_High_PL!$C$58/6,0))) -> -186604.15 | D54: =C54+((IF(D$7=1,IF(D$8<=Assumptions!$F$59,0,INDEX(Scenario_High_PL!$C$18:$G$18,1,D$7)/MAX(1,12-Assumptions!$F$59)),INDEX(Scenario_High_PL!$C$18:$G$18,1,D$7)/12))-(IF(D$7=1,IF(D$8<=Assumptions!$F$59,0,INDEX(Scenario_High_PL!$C$29:$G$29,1,D$7)/MAX(1,12-Assumptions!$F$59)),INDEX(Scenario_High_PL!$C$29:$G$29,1,D$7)/12))-(INDEX(Scenario_High_PL!$C$42:$G$42,1,D$7)/12)-(INDEX(Scenario_High_PL!$C$56:$G$56,1,D$7)/12)-(IF(D$6<=6,Scenario_High_PL!$C$58/6,0))) -> -279906.22 | E54: =D54+((IF(E$7=1,IF(E$8<=Assumptions!$F$59,0,INDEX(Scenario_High_PL!$C$18:$G$18,1,E$7)/MAX(1,12-Assumptions!$F$59)),INDEX(Scenario_High_PL!$C$18:$G$18,1,E$7)/12))-(IF(E$7=1,IF(E$8<=Assumptions!$F$59,0,INDEX(Scenario_High_PL!$C$29:$G$29,1,E$7)/MAX(1,12-Assumptions!$F$59)),INDEX(Scenario_High_PL!$C$29:$G$29,1,E$7)/12))-(INDEX(Scenario_High_PL!$C$42:$G$42,1,E$7)/12)-(INDEX(Scenario_High_PL!$C$56:$G$56,1,E$7)/12)-(IF(E$6<=6,Scenario_High_PL!$C$58/6,0))) -> -373208.3 | F54: =E54+((IF(F$7=1,IF(F$8<=Assumptions!$F$59,0,INDEX(Scenario_High_PL!$C$18:$G$18,1,F$7)/MAX(1,12-Assumptions!$F$59)),INDEX(Scenario_High_PL!$C$18:$G$18,1,F$7)/12))-(IF(F$7=1,IF(F$8<=Assumptions!$F$59,0,INDEX(Scenario_High_PL!$C$29:$G$29,1,F$7)/MAX(1,12-Assumptions!$F$59)),INDEX(Scenario_High_PL!$C$29:$G$29,1,F$7)/12))-(INDEX(Scenario_High_PL!$C$42:$G$42,1,F$7)/12)-(INDEX(Scenario_High_PL!$C$56:$G$56,1,F$7)/12)-(IF(F$6<=6,Scenario_High_PL!$C$58/6,0))) -> -466510.38 | G54: =F54+((IF(G$7=1,IF(G$8<=Assumptions!$F$59,0,INDEX(Scenario_High_PL!$C$18:$G$18,1,G$7)/MAX(1,12-Assumptions!$F$59)),INDEX(Scenario_High_PL!$C$18:$G$18,1,G$7)/12))-(IF(G$7=1,IF(G$8<=Assumptions!$F$59,0,INDEX(Scenario_High_PL!$C$29:$G$29,1,G$7)/MAX(1,12-Assumptions!$F$59)),INDEX(Scenario_High_PL!$C$29:$G$29,1,G$7)/12))-(INDEX(Scenario_High_PL!$C$42:$G$42,1,G$7)/12)-(INDEX(Scenario_High_PL!$C$56:$G$56,1,G$7)/12)-(IF(G$6<=6,Scenario_High_PL!$C$58/6,0))) -> -559812.45 | H54: =G54+((IF(H$7=1,IF(H$8<=Assumptions!$F$59,0,INDEX(Scenario_High_PL!$C$18:$G$18,1,H$7)/MAX(1,12-Assumptions!$F$59)),INDEX(Scenario_High_PL!$C$18:$G$18,1,H$7)/12))-(IF(H$7=1,IF(H$8<=Assumptions!$F$59,0,INDEX(Scenario_High_PL!$C$29:$G$29,1,H$7)/MAX(1,12-Assumptions!$F$59)),INDEX(Scenario_High_PL!$C$29:$G$29,1,H$7)/12))-(INDEX(Scenario_High_PL!$C$42:$G$42,1,H$7)/12)-(INDEX(Scenario_High_PL!$C$56:$G$56,1,H$7)/12)-(IF(H$6<=6,Scenario_High_PL!$C$58/6,0))) -> -594288.79 | I54: =H54+((IF(I$7=1,IF(I$8<=Assumptions!$F$59,0,INDEX(Scenario_High_PL!$C$18:$G$18,1,I$7)/MAX(1,12-Assumptions!$F$59)),INDEX(Scenario_High_PL!$C$18:$G$18,1,I$7)/12))-(IF(I$7=1,IF(I$8<=Assumptions!$F$59,0,INDEX(Scenario_High_PL!$C$29:$G$29,1,I$7)/MAX(1,12-Assumptions!$F$59)),INDEX(Scenario_High_PL!$C$29:$G$29,1,I$7)/12))-(INDEX(Scenario_High_PL!$C$42:$G$42,1,I$7)/12)-(INDEX(Scenario_High_PL!$C$56:$G$56,1,I$7)/12)-(IF(I$6<=6,Scenario_High_PL!$C$58/6,0))) -> -628765.14 | J54: =I54+((IF(J$7=1,IF(J$8<=Assumptions!$F$59,0,INDEX(Scenario_High_PL!$C$18:$G$18,1,J$7)/MAX(1,12-Assumptions!$F$59)),INDEX(Scenario_High_PL!$C$18:$G$18,1,J$7)/12))-(IF(J$7=1,IF(J$8<=Assumptions!$F$59,0,INDEX(Scenario_High_PL!$C$29:$G$29,1,J$7)/MAX(1,12-Assumptions!$F$59)),INDEX(Scenario_High_PL!$C$29:$G$29,1,J$7)/12))-(INDEX(Scenario_High_PL!$C$42:$G$42,1,J$7)/12)-(INDEX(Scenario_High_PL!$C$56:$G$56,1,J$7)/12)-(IF(J$6<=6,Scenario_High_PL!$C$58/6,0))) -> -663241.48 | ... BI54: =BH54+((IF(BI$7=1,IF(BI$8<=Assumptions!$F$59,0,INDEX(Scenario_High_PL!$C$18:$G$18,1,BI$7)/MAX(1,12-Assumptions!$F$59)),INDEX(Scenario_High_PL!$C$18:$G$18,1,BI$7)/12))-(IF(BI$7=1,IF(BI$8<=Assumptions!$F$59,0,INDEX(Scenario_High_PL!$C$29:$G$29,1,BI$7)/MAX(1,12-Assumptions!$F$59)),INDEX(Scenario_High_PL!$C$29:$G$29,1,BI$7)/12))-(INDEX(Scenario_High_PL!$C$42:$G$42,1,BI$7)/12)-(INDEX(Scenario_High_PL!$C$56:$G$56,1,BI$7)/12)-(IF(BI$6<=6,Scenario_High_PL!$C$58/6,0))) -> 31816705

Sheet P&L_5yr
B2: 5-Year P&L (annual) - driven by Assumptions sheet
B3: All figures GBP. Revenue & COGS scale with deal volume. Active scenario shown; change Assumptions!C4.
B5: Line item | C5: Year 1 | D5: Year 2 | E5: Year 3 | F5: Year 4 | G5: Year 5 | H5: Unit / note
B6: VOLUME & DRIVERS
B7: Deals processed | C7: =Assumptions!$F$11 -> 180 | D7: =Assumptions!$F$12 -> 900 | E7: =Assumptions!$F$13 -> 3000 | F7: =Assumptions!$F$155 -> 7500 | G7: =Assumptions!$F$156 -> 18000 | H7: From Assumptions
B8: Avg deal value (£) | C8: =Assumptions!$F$14 -> 30000 | D8: =C8*(1+Assumptions!$F$15) -> 40500 | E8: =D8*(1+Assumptions!$F$15) -> 54675 | F8: =E8*(1+Assumptions!$F$15) -> 73811.25 | G8: =F8*(1+Assumptions!$F$15) -> 99645.188 | H8: GMV per deal
B9: Gross trade value processed (GMV) | C9: =C7*C8 -> 5400000 | D9: =D7*D8 -> 36450000 | E9: =E7*E8 -> 164025000 | F9: =F7*F8 -> 553584375 | G9: =G7*G8 -> 1793613375 | H9: Deals × avg value (NOT revenue)
B10: Documents processed | C10: =Tier_Economics!E7 -> 1215 | D10: =Tier_Economics!I7 -> 5265 | E10: =Tier_Economics!M7 -> 15300 | F10: =Tier_Economics!Q7 -> 33300 | G10: =Tier_Economics!U7 -> 72900 | H10: Tier-weighted docs/deal from Tier_Economics
B11: New counterparties onboarded | C11: =C7*Assumptions!$F$16*Assumptions!$F$62 -> 180 | D11: =D7*Assumptions!$F$16*Assumptions!$F$62 -> 900 | E11: =E7*Assumptions!$F$16*Assumptions!$F$62 -> 3000 | F11: =F7*Assumptions!$F$16*Assumptions!$F$62 -> 7500 | G11: =G7*Assumptions!$F$16*Assumptions!$F$62 -> 18000 | H11: Deals x parties/deal x new-counterparty onboarding share
B12: Disputed/amended deals | C12: =Tier_Economics!E16 -> 23.58 | D12: =Tier_Economics!I16 -> 96.3 | E12: =Tier_Economics!M16 -> 264 | F12: =Tier_Economics!Q16 -> 540 | G12: =Tier_Economics!U16 -> 1134 | H12: Tier-weighted dispute rates
B13: REVENUE
B14: Escrow transaction fees | C14: =Tier_Economics!E12 -> 61515 | D14: =Tier_Economics!I12 -> 341718.75 | E14: =Tier_Economics!M12 -> 1369608.8 | F14: =Tier_Economics!Q12 -> 4162954.5 | G14: =Tier_Economics!U12 -> 12689815 | H14: Tiered fee by A/B/C mix
B15: Document review fees | C15: =Tier_Economics!E14 -> 29565 | D15: =Tier_Economics!I14 -> 110700 | E15: =Tier_Economics!M14 -> 276750 | F15: =Tier_Economics!Q14 -> 508500 | G15: =Tier_Economics!U14 -> 990000 | H15: Tiered document/review fee
B16: Dispute/amendment fees | C16: =Tier_Economics!E18 -> 8928 | D16: =Tier_Economics!I18 -> 31680 | E16: =Tier_Economics!M18 -> 74400 | F16: =Tier_Economics!Q18 -> 126000 | G16: =Tier_Economics!U18 -> 230400 | H16: Tiered dispute/amendment fee
B17: Partner/API + add-on revenue streams | C17: =Revenue_Risk_AddOns!B15 -> 7497 | D17: =Revenue_Risk_AddOns!C15 -> 114678 | E17: =Revenue_Risk_AddOns!D15 -> 238590 | F17: =Revenue_Risk_AddOns!E15 -> 422400 | G17: =Revenue_Risk_AddOns!F15 -> 830040 | H17: SaaS/API, setup/minimums, KYC fees, archive, expedited, Tier C pass-through, less first-deal discount
B18: Total revenue | C18: =SUM(C14:C17) -> 107505 | D18: =SUM(D14:D17) -> 598776.75 | E18: =SUM(E14:E17) -> 1959348.8 | F18: =SUM(F14:F17) -> 5219854.5 | G18: =SUM(G14:G17) -> 14740255 | H18: Sum of revenue lines
B19: COGS / VARIABLE COSTS
B20: Claude API (doc extraction) | C20: =C10*Assumptions!$F$19/Assumptions!$F$8 -> 28.476562 | D20: =D10*Assumptions!$F$19/Assumptions!$F$8 -> 123.39844 | E20: =E10*Assumptions!$F$19/Assumptions!$F$8 -> 358.59375 | F20: =F10*Assumptions!$F$19/Assumptions!$F$8 -> 780.46875 | G20: =G10*Assumptions!$F$19/Assumptions!$F$8 -> 1708.5938 | H20: USD→GBP
B21: KYB business onboarding | C21: =C11*Assumptions!$F$20/Assumptions!$F$8 -> 492.1875 | D21: =D11*Assumptions!$F$20/Assumptions!$F$8 -> 2460.9375 | E21: =E11*Assumptions!$F$20/Assumptions!$F$8 -> 8203.125 | F21: =F11*Assumptions!$F$20/Assumptions!$F$8 -> 20507.812 | G21: =G11*Assumptions!$F$20/Assumptions!$F$8 -> 49218.75 | H21: Fresh KYB only for new counterparties
B22: KYC/UBO + sanctions onboarding | C22: =C11*Assumptions!$F$21/Assumptions!$F$8 -> 189.84375 | D22: =D11*Assumptions!$F$21/Assumptions!$F$8 -> 949.21875 | E22: =E11*Assumptions!$F$21/Assumptions!$F$8 -> 3164.0625 | F22: =F11*Assumptions!$F$21/Assumptions!$F$8 -> 7910.1562 | G22: =G11*Assumptions!$F$21/Assumptions!$F$8 -> 18984.375 | H22: Fresh KYC/KYB only for new counterparties
B23: Tiered document verification ops | C23: =Tier_Economics!E19+Tier_Economics!E20 -> 22032 | D23: =Tier_Economics!I19+Tier_Economics!I20 -> 74520 | E23: =Tier_Economics!M19+Tier_Economics!M20 -> 165600 | F23: =Tier_Economics!Q19+Tier_Economics!Q20 -> 261000 | G23: =Tier_Economics!U19+Tier_Economics!U20 -> 453600 | H23: External eBL/API/paper + human examiner cost
B24: Blockchain gas | C24: =C7*Assumptions!$F$22/Assumptions!$F$8 -> 28.125 | D24: =D7*Assumptions!$F$22/Assumptions!$F$8 -> 140.625 | E24: =E7*Assumptions!$F$22/Assumptions!$F$8 -> 468.75 | F24: =F7*Assumptions!$F$22/Assumptions!$F$8 -> 1171.875 | G24: =G7*Assumptions!$F$22/Assumptions!$F$8 -> 2812.5 | H24: Base L2 USD→GBP
B25: RPC / node provider | C25: =C7*Assumptions!$F$23/Assumptions!$F$8 -> 1.40625 | D25: =D7*Assumptions!$F$23/Assumptions!$F$8 -> 7.03125 | E25: =E7*Assumptions!$F$23/Assumptions!$F$8 -> 23.4375 | F25: =F7*Assumptions!$F$23/Assumptions!$F$8 -> 58.59375 | G25: =G7*Assumptions!$F$23/Assumptions!$F$8 -> 140.625 | H25: Deals x RPC cost; USD to GBP
B26: Document / ledger storage | C26: =C7*Assumptions!$F$24/Assumptions!$F$8 -> 4.21875 | D26: =D7*Assumptions!$F$24/Assumptions!$F$8 -> 21.09375 | E26: =E7*Assumptions!$F$24/Assumptions!$F$8 -> 70.3125 | F26: =F7*Assumptions!$F$24/Assumptions!$F$8 -> 175.78125 | G26: =G7*Assumptions!$F$24/Assumptions!$F$8 -> 421.875 | H26: Deals x storage cost; USD to GBP
B27: Customer support | C27: =Tier_Economics!E21 -> 1980 | D27: =Tier_Economics!I21 -> 7470 | E27: =Tier_Economics!M21 -> 18900 | F27: =Tier_Economics!Q21 -> 35400 | G27: =Tier_Economics!U21 -> 70200 | H27: Tiered support load
B28: Dispute handling + retained-risk variable costs | C28: =Tier_Economics!E22+Revenue_Risk_AddOns!B24 -> 21713.8 | D28: =Tier_Economics!I22+Revenue_Risk_AddOns!C24 -> 103379 | E28: =Tier_Economics!M22+Revenue_Risk_AddOns!D24 -> 319948 | F28: =Tier_Economics!Q22+Revenue_Risk_AddOns!E24 -> 776041 | G28: =Tier_Economics!U22+Revenue_Risk_AddOns!F24 -> 1943181 | H28: Dispute handling plus QA, forum, reserves, commissions, fallback, leakage
B29: Total COGS | C29: =SUM(C20:C28) -> 46470.058 | D29: =SUM(D20:D28) -> 189071.3 | E29: =SUM(E20:E28) -> 516736.28 | F29: =SUM(F20:F28) -> 1103045.7 | G29: =SUM(G20:G28) -> 2540267.7 | H29: Sum of COGS lines
B30: Gross profit | C30: =C18-C29 -> 61034.942 | D30: =D18-D29 -> 409705.45 | E30: =E18-E29 -> 1442612.5 | F30: =F18-F29 -> 4116808.8 | G30: =G18-G29 -> 12199987 | H30: Total revenue minus total COGS
B31: Gross margin % | C31: =IF(C18=0,0,C30/C18) -> 0.5677405 | D31: =IF(D18=0,0,D30/D18) -> 0.6842374 | E31: =IF(E18=0,0,E30/E18) -> 0.73627141 | F31: =IF(F18=0,0,F30/F18) -> 0.78868268 | G31: =IF(G18=0,0,G30/G18) -> 0.8276646 | H31: Gross profit / revenue
B32: HEADCOUNT & PAYROLL
B33: Founders (FTE) | C33: =Assumptions!$F$39 -> 2 | D33: =Assumptions!$F$39 -> 2 | E33: =Assumptions!$F$39 -> 2 | F33: =Assumptions!$F$39 -> 2 | G33: =Assumptions!$F$39 -> 2 | H33: Founder headcount held flat
B34: Engineers (FTE) | C34: =Assumptions!$F$40+0 -> 2 | D34: =Assumptions!$F$40+1 -> 3 | E34: =Assumptions!$F$40+2 -> 4 | F34: =Assumptions!$F$40+3 -> 5 | G34: =Assumptions!$F$40+4 -> 6 | H34: Ramp +1/yr
B35: Compliance/ops (FTE) | C35: =Assumptions!$F$41+0 -> 1 | D35: =Assumptions!$F$41+1 -> 2 | E35: =Assumptions!$F$41+2 -> 3 | F35: =Assumptions!$F$41+3 -> 4 | G35: =Assumptions!$F$41+4 -> 5 | H35: Ramp
B36: Sales/BD/CS (FTE) | C36: =Assumptions!$F$42+0 -> 1 | D36: =Assumptions!$F$42+1 -> 2 | E36: =Assumptions!$F$42+2 -> 3 | F36: =Assumptions!$F$42+3 -> 4 | G36: =Assumptions!$F$42+4 -> 5 | H36: Ramp
B37: Total FTE | C37: =C33+C34+C35+C36 -> 6 | D37: =D33+D34+D35+D36 -> 9 | E37: =E33+E34+E35+E36 -> 12 | F37: =F33+F34+F35+F36 -> 15 | G37: =G33+G34+G35+G36 -> 18 | H37: Founders + engineers + compliance/ops + sales/BD/CS
B38: Gross salaries | C38: =C33*Assumptions!$F$44+C34*Assumptions!$F$45+C35*Assumptions!$F$46+C36*Assumptions!$F$47 -> 340000 | D38: =D33*Assumptions!$F$44+D34*Assumptions!$F$45+D35*Assumptions!$F$46+D36*Assumptions!$F$47 -> 520000 | E38: =E33*Assumptions!$F$44+E34*Assumptions!$F$45+E35*Assumptions!$F$46+E36*Assumptions!$F$47 -> 700000 | F38: =F33*Assumptions!$F$44+F34*Assumptions!$F$45+F35*Assumptions!$F$46+F36*Assumptions!$F$47 -> 880000 | G38: =G33*Assumptions!$F$44+G34*Assumptions!$F$45+G35*Assumptions!$F$46+G36*Assumptions!$F$47 -> 1060000 | H38: FTE × salary
B39: Employer NI | C39: =MAX(0,(C38-Assumptions!$F$49*C37)*Assumptions!$F$48-Assumptions!$F$60) -> 36000 | D39: =MAX(0,(D38-Assumptions!$F$49*D37)*Assumptions!$F$48-Assumptions!$F$60) -> 60750 | E39: =MAX(0,(E38-Assumptions!$F$49*E37)*Assumptions!$F$48-Assumptions!$F$60) -> 85500 | F39: =MAX(0,(F38-Assumptions!$F$49*F37)*Assumptions!$F$48-Assumptions!$F$60) -> 110250 | G39: =MAX(0,(G38-Assumptions!$F$49*G37)*Assumptions!$F$48-Assumptions!$F$60) -> 135000 | H39: 15% above threshold, less Employment Allowance; confirm eligibility
B40: Employer pension | C40: =C38*Assumptions!$F$50 -> 13600 | D40: =D38*Assumptions!$F$50 -> 20800 | E40: =E38*Assumptions!$F$50 -> 28000 | F40: =F38*Assumptions!$F$50 -> 35200 | G40: =G38*Assumptions!$F$50 -> 42400 | H40: Gross salaries x pension contribution
B41: Other employment on-costs | C41: =C38*Assumptions!$F$51 -> 10200 | D41: =D38*Assumptions!$F$51 -> 15600 | E41: =E38*Assumptions!$F$51 -> 21000 | F41: =F38*Assumptions!$F$51 -> 26400 | G41: =G38*Assumptions!$F$51 -> 31800 | H41: Gross salaries x other employment on-costs
B42: Total payroll cost | C42: =C38+C39+C40+C41 -> 399800 | D42: =D38+D39+D40+D41 -> 617150 | E42: =E38+E39+E40+E41 -> 834500 | F42: =F38+F39+F40+F41 -> 1051850 | G42: =G38+G39+G40+G41 -> 1269200 | H42: Gross salaries + employer NI + pension + other on-costs
B43: FIXED OPERATING COSTS (annual = monthly ×12)
B44: Cloud hosting (Vercel/AWS) | C44: =Assumptions!$F$26*12*1 -> 3000 | D44: =Assumptions!$F$26*12*1.5 -> 4500 | E44: =Assumptions!$F$26*12*2.5 -> 7500 | F44: =Assumptions!$F$26*12*4 -> 12000 | G44: =Assumptions!$F$26*12*6 -> 18000 | H44: Monthly base × scale factor
B45: Database + object storage | C45: =Assumptions!$F$27*12*1 -> 1440 | D45: =Assumptions!$F$27*12*1.5 -> 2160 | E45: =Assumptions!$F$27*12*2.5 -> 3600 | F45: =Assumptions!$F$27*12*4 -> 5760 | G45: =Assumptions!$F$27*12*6 -> 8640 | H45: Monthly base × scale factor
B46: Monitoring/logging/security tools | C46: =Assumptions!$F$28*12*1 -> 1800 | D46: =Assumptions!$F$28*12*1.5 -> 2700 | E46: =Assumptions!$F$28*12*2.5 -> 4500 | F46: =Assumptions!$F$28*12*4 -> 7200 | G46: =Assumptions!$F$28*12*6 -> 10800 | H46: Monthly base × scale factor
B47: GitHub + dev SaaS | C47: =Assumptions!$F$29*12*C37/6 -> 720 | D47: =Assumptions!$F$29*12*D37/6 -> 1080 | E47: =Assumptions!$F$29*12*E37/6 -> 1440 | F47: =Assumptions!$F$29*12*F37/6 -> 1800 | G47: =Assumptions!$F$29*12*G37/6 -> 2160 | H47: Monthly base × FTE scale
B48: Google Workspace / collab | C48: =Assumptions!$F$30*12*C37/6 -> 1080 | D48: =Assumptions!$F$30*12*D37/6 -> 1620 | E48: =Assumptions!$F$30*12*E37/6 -> 2160 | F48: =Assumptions!$F$30*12*F37/6 -> 2700 | G48: =Assumptions!$F$30*12*G37/6 -> 3240 | H48: Monthly base × FTE scale
B49: CRM + BD tooling | C49: =Assumptions!$F$31*12*MAX(1,C36) -> 960 | D49: =Assumptions!$F$31*12*MAX(1,D36) -> 1920 | E49: =Assumptions!$F$31*12*MAX(1,E36) -> 2880 | F49: =Assumptions!$F$31*12*MAX(1,F36) -> 3840 | G49: =Assumptions!$F$31*12*MAX(1,G36) -> 4800 | H49: Monthly base × sales/BD scale
B50: Accounting/payroll/bookkeeping | C50: =Assumptions!$F$32*12*1 -> 4200 | D50: =Assumptions!$F$32*12*1.25 -> 5250 | E50: =Assumptions!$F$32*12*1.5 -> 6300 | F50: =Assumptions!$F$32*12*1.75 -> 7350 | G50: =Assumptions!$F$32*12*2 -> 8400 | H50: Monthly base × scale factor
B51: Legal retainer (ongoing) | C51: =Assumptions!$F$33*12*1 -> 7200 | D51: =Assumptions!$F$33*12*1.5 -> 10800 | E51: =Assumptions!$F$33*12*2 -> 14400 | F51: =Assumptions!$F$33*12*2.5 -> 18000 | G51: =Assumptions!$F$33*12*3 -> 21600 | H51: Monthly base × complexity scale
B52: Compliance / MLRO + retained-risk infrastructure | C52: =Assumptions!$F$34*12*1+Revenue_Risk_AddOns!B36 -> 194400 | D52: =Assumptions!$F$34*12*1.5+Revenue_Risk_AddOns!C36 -> 162850 | E52: =Assumptions!$F$34*12*2+Revenue_Risk_AddOns!D36 -> 186300 | F52: =Assumptions!$F$34*12*2.5+Revenue_Risk_AddOns!E36 -> 217250 | G52: =Assumptions!$F$34*12*3+Revenue_Risk_AddOns!F36 -> 248200 | H52: MLRO support plus carrier/eBL integration, forensics retainer, fraud DB, key security, reg ops, incident reserve
B53: Marketing / conferences / partnerships | C53: =Assumptions!$F$35*12*1 -> 18000 | D53: =Assumptions!$F$35*12*2 -> 36000 | E53: =Assumptions!$F$35*12*3 -> 54000 | F53: =Assumptions!$F$35*12*4 -> 72000 | G53: =Assumptions!$F$35*12*5 -> 90000 | H53: Monthly base × sales/BD scale
B54: Office / coworking | C54: =Assumptions!$F$36*12*C37/6 -> 4800 | D54: =Assumptions!$F$36*12*D37/6 -> 7200 | E54: =Assumptions!$F$36*12*E37/6 -> 9600 | F54: =Assumptions!$F$36*12*F37/6 -> 12000 | G54: =Assumptions!$F$36*12*G37/6 -> 14400 | H54: Monthly base × FTE scale
B55: Insurance (PI+cyber+D&O) / mo | C55: =0 -> 0 | D55: =Assumptions!$F$37*12*1 -> 8400 | E55: =Assumptions!$F$37*12*1 -> 8400 | F55: =Assumptions!$F$37*12*1.25 -> 10500 | G55: =Assumptions!$F$37*12*1.5 -> 12600 | H55: Year 1 prepaid; Years 2–3 monthly ×12
B56: Total fixed opex | C56: =SUM(C44:C55) -> 237600 | D56: =SUM(D44:D55) -> 244480 | E56: =SUM(E44:E55) -> 301080 | F56: =SUM(F44:F55) -> 370400 | G56: =SUM(G44:G55) -> 442840 | H56: Sum of fixed opex lines
B57: ONE-OFF & STARTUP COSTS
B58: First-6-months one-off costs (Yr1) | C58: =Startup_6mo!F44 -> 241112.45 | D58: =0 -> 0 | E58: =0 -> 0 | F58: =0 -> 0 | G58: =0 -> 0 | H58: From Startup_6mo (Yr1 only)
B59: RESULT
B60: Total operating expenditure | C60: =C42+C56+C58 -> 878512.45 | D60: =D42+D56+D58 -> 861630 | E60: =E42+E56+E58 -> 1135580 | F60: =F42+F56+F58 -> 1422250 | G60: =G42+G56+G58 -> 1712040 | H60: Payroll+opex+one-off
B61: EBITDA (pre one-off) | C61: =C30-C42-C56 -> -576365.06 | D61: =D30-D42-D56 -> -451924.55 | E61: =E30-E42-E56 -> 307032.47 | F61: =F30-F42-F56 -> 2694558.8 | G61: =G30-G42-G56 -> 10487947 | H61: Gross profit − payroll − opex
B62: Net profit / (loss) incl. one-off | C62: =C30-C60 -> -817477.51 | D62: =D30-D60 -> -451924.55 | E62: =E30-E60 -> 307032.47 | F62: =F30-F60 -> 2694558.8 | G62: =G30-G60 -> 10487947 | H62: Gross profit minus total operating expenditure
B63: Cumulative net result | C63: =C62 -> -817477.51 | D63: =C63+D62 -> -1269402.1 | E63: =D63+E62 -> -962369.59 | F63: =E63+F62 -> 1732189.2 | G63: =F63+G62 -> 12220136 | H63: Running total
B64: Implied cash needed (peak cumulative deficit + buffer) | C64: =-MIN(0,C63)*(1+Assumptions!$F$58) -> 1062720.8 | D64: =-MIN(0,C63,D63)*(1+Assumptions!$F$58) -> 1650222.7 | E64: =-MIN(0,C63,D63,E63)*(1+Assumptions!$F$58) -> 1650222.7 | F64: =-MIN(0,C63,D63,E63,F63)*(1+Assumptions!$F$58) -> 1650222.7 | G64: =-MIN(0,C63,D63,E63,F63,G63)*(1+Assumptions!$F$58) -> 1650222.7 | H64: Peak cumulative deficit × linked buffer
B65: Funding-only contingency reserve | C65: =ROUND(Revenue_Risk_AddOns!B41,0) -> 240000 | D65: =ROUND(Revenue_Risk_AddOns!C41,0) -> 0 | E65: =ROUND(Revenue_Risk_AddOns!D41,0) -> 0 | F65: =ROUND(Revenue_Risk_AddOns!E41,0) -> 0 | G65: =ROUND(Revenue_Risk_AddOns!F41,0) -> 0 | H65: Regulatory delay reserve + zero delivery-liability reserve
B66: Implied funding ask incl. contingency | C66: =ROUND(C64+C65,0) -> 1302721 | D66: =ROUND(D64+D65,0) -> 1650223 | E66: =ROUND(E64+E65,0) -> 1650223 | F66: =ROUND(F64+F65,0) -> 1650223 | G66: =ROUND(G64+G65,0) -> 1650223 | H66: Cash need plus funding-only contingency
B67: CUSTOMER ACQUISITION CROSS-CHECK
B68: Line item | C68: Year 1 | D68: Year 2 | E68: Year 3 | F68: Year 4 | G68: Year 5 | H68: Unit / note
B69: Deals / active customer / year | C69: =Assumptions!$F$110 -> 3 | D69: =Assumptions!$F$111 -> 4 | E69: =Assumptions!$F$112 -> 6 | F69: =Assumptions!$F$165 -> 8 | G69: =Assumptions!$F$166 -> 10 | H69: Commercial sanity check from Assumptions
B70: Implied active customers | C70: =IF(C69=0,0,C7/C69) -> 60 | D70: =IF(D69=0,0,D7/D69) -> 225 | E70: =IF(E69=0,0,E7/E69) -> 500 | F70: =IF(F69=0,0,F7/F69) -> 937.5 | G70: =IF(G69=0,0,G7/G69) -> 1800 | H70: Deals / deals per active customer
B71: Revenue / deal | C71: =IF(C7=0,0,C18/C7) -> 597.25 | D71: =IF(D7=0,0,D18/D7) -> 665.3075 | E71: =IF(E7=0,0,E18/E7) -> 653.11625 | F71: =IF(F7=0,0,F18/F7) -> 695.9806 | G71: =IF(G7=0,0,G18/G7) -> 818.90303 | H71: Total revenue / deals
B72: Revenue / active customer | C72: =IF(C70=0,0,C18/C70) -> 1791.75 | D72: =IF(D70=0,0,D18/D70) -> 2661.23 | E72: =IF(E70=0,0,E18/E70) -> 3918.6975 | F72: =IF(F70=0,0,F18/F70) -> 5567.8448 | G72: =IF(G70=0,0,G18/G70) -> 8189.0303 | H72: Total revenue / implied customers
B73: VAT registration flag | C73: =IF(C18>Assumptions!$F$61,"Register / confirm VAT treatment","Below threshold") -> Register / confirm VAT treatment | D73: =IF(D18>Assumptions!$F$61,"Register / confirm VAT treatment","Below threshold") -> Register / confirm VAT treatment | E73: =IF(E18>Assumptions!$F$61,"Register / confirm VAT treatment","Below threshold") -> Register / confirm VAT treatment | F73: =IF(F18>Assumptions!$F$61,"Register / confirm VAT treatment","Below threshold") -> Register / confirm VAT treatment | G73: =IF(G18>Assumptions!$F$61,"Register / confirm VAT treatment","Below threshold") -> Register / confirm VAT treatment | H73: Revenue > threshold
B74: Gross margin sanity check | C74: =IF(AND(C31>0.9,C23>0),"Review COGS: margin may be optimistic","OK") -> OK | D74: =IF(AND(D31>0.9,D23>0),"Review COGS: margin may be optimistic","OK") -> OK | E74: =IF(AND(E31>0.9,E23>0),"Review COGS: margin may be optimistic","OK") -> OK | F74: =IF(AND(F31>0.9,F23>0),"Review COGS: margin may be optimistic","OK") -> OK | G74: =IF(AND(G31>0.9,G23>0),"Review COGS: margin may be optimistic","OK") -> OK | H74: Warn if >90% and tiered document-verification COGS is nonzero

Sheet Tier_Economics
A1: Tier Economics - revenue, cost and risk by document-intake tier
A3: Metric | B3: Tier A eBL Y1 | C3: Tier B API Y1 | D3: Tier C Paper Y1 | E3: Total Y1 | F3: Tier A eBL Y2 | G3: Tier B API Y2 | H3: Tier C Paper Y2 | I3: Total Y2 | J3: Tier A eBL Y3 | K3: Tier B API Y3 | L3: Tier C Paper Y3 | M3: Total Y3 | N3: Tier A eBL Y4 | O3: Tier B API Y4 | P3: Tier C Paper Y4 | Q3: Total Y4 | R3: Tier A eBL Y5 | S3: Tier B API Y5 | T3: Tier C Paper Y5 | U3: Total Y5
A4: Tier mix | B4: =Assumptions!$F$64 -> 0.15 | C4: =Assumptions!$F$65 -> 0.45 | D4: =Assumptions!$F$66 -> 0.4 | E4: =SUM(B4:D4) -> 1 | F4: =Assumptions!$F$67 -> 0.3 | G4: =Assumptions!$F$68 -> 0.45 | H4: =Assumptions!$F$69 -> 0.25 | I4: =SUM(F4:H4) -> 1 | J4: =Assumptions!$F$70 -> 0.45 | K4: =Assumptions!$F$71 -> 0.4 | L4: =Assumptions!$F$72 -> 0.15 | M4: =SUM(J4:L4) -> 1 | N4: =Assumptions!$F$157 -> 0.6 | O4: =Assumptions!$F$158 -> 0.32 | P4: =Assumptions!$F$159 -> 0.08 | Q4: =SUM(N4:P4) -> 1 | R4: =Assumptions!$F$160 -> 0.7 | S4: =Assumptions!$F$161 -> 0.25 | T4: =Assumptions!$F$162 -> 0.05 | U4: =SUM(R4:T4) -> 1
A5: Deals | B5: ='P&L_5yr'!$C$7*B4 -> 27 | C5: ='P&L_5yr'!$C$7*C4 -> 81 | D5: ='P&L_5yr'!$C$7*D4 -> 72 | E5: =SUM(B5:D5) -> 180 | F5: ='P&L_5yr'!$D$7*F4 -> 270 | G5: ='P&L_5yr'!$D$7*G4 -> 405 | H5: ='P&L_5yr'!$D$7*H4 -> 225 | I5: =SUM(F5:H5) -> 900 | J5: ='P&L_5yr'!$E$7*J4 -> 1350 | K5: ='P&L_5yr'!$E$7*K4 -> 1200 | L5: ='P&L_5yr'!$E$7*L4 -> 450 | M5: =SUM(J5:L5) -> 3000 | N5: ='P&L_5yr'!$F$7*N4 -> 4500 | O5: ='P&L_5yr'!$F$7*O4 -> 2400 | P5: ='P&L_5yr'!$F$7*P4 -> 600 | Q5: =SUM(N5:P5) -> 7500 | R5: ='P&L_5yr'!$G$7*R4 -> 12600 | S5: ='P&L_5yr'!$G$7*S4 -> 4500 | T5: ='P&L_5yr'!$G$7*T4 -> 900 | U5: =SUM(R5:T5) -> 18000
A6: Docs per deal | B6: =Assumptions!$F$106 -> 3 | C6: =Assumptions!$F$107 -> 6 | D6: =Assumptions!$F$108 -> 9 | E6: =IF(E5=0,0,E7/E5) -> 6.75 | F6: =Assumptions!$F$106 -> 3 | G6: =Assumptions!$F$107 -> 6 | H6: =Assumptions!$F$108 -> 9 | I6: =IF(I5=0,0,I7/I5) -> 5.85 | J6: =Assumptions!$F$106 -> 3 | K6: =Assumptions!$F$107 -> 6 | L6: =Assumptions!$F$108 -> 9 | M6: =IF(M5=0,0,M7/M5) -> 5.1 | N6: =Assumptions!$F$106 -> 3 | O6: =Assumptions!$F$107 -> 6 | P6: =Assumptions!$F$108 -> 9 | Q6: =IF(Q5=0,0,Q7/Q5) -> 4.44 | R6: =Assumptions!$F$106 -> 3 | S6: =Assumptions!$F$107 -> 6 | T6: =Assumptions!$F$108 -> 9 | U6: =IF(U5=0,0,U7/U5) -> 4.05
A7: Documents processed | B7: =B5*B6 -> 81 | C7: =C5*C6 -> 486 | D7: =D5*D6 -> 648 | E7: =SUM(B7:D7) -> 1215 | F7: =F5*F6 -> 810 | G7: =G5*G6 -> 2430 | H7: =H5*H6 -> 2025 | I7: =SUM(F7:H7) -> 5265 | J7: =J5*J6 -> 4050 | K7: =K5*K6 -> 7200 | L7: =L5*L6 -> 4050 | M7: =SUM(J7:L7) -> 15300 | N7: =N5*N6 -> 13500 | O7: =O5*O6 -> 14400 | P7: =P5*P6 -> 5400 | Q7: =SUM(N7:P7) -> 33300 | R7: =R5*R6 -> 37800 | S7: =S5*S6 -> 27000 | T7: =T5*T6 -> 8100 | U7: =SUM(R7:T7) -> 72900
A8: Avg deal value | B8: ='P&L_5yr'!$C$8 -> 30000 | C8: ='P&L_5yr'!$C$8 -> 30000 | D8: ='P&L_5yr'!$C$8 -> 30000 | E8: ='P&L_5yr'!$C$8 -> 30000 | F8: ='P&L_5yr'!$D$8 -> 40500 | G8: ='P&L_5yr'!$D$8 -> 40500 | H8: ='P&L_5yr'!$D$8 -> 40500 | I8: ='P&L_5yr'!$D$8 -> 40500 | J8: ='P&L_5yr'!$E$8 -> 54675 | K8: ='P&L_5yr'!$E$8 -> 54675 | L8: ='P&L_5yr'!$E$8 -> 54675 | M8: ='P&L_5yr'!$E$8 -> 54675 | N8: ='P&L_5yr'!$F$8 -> 73811.25 | O8: ='P&L_5yr'!$F$8 -> 73811.25 | P8: ='P&L_5yr'!$F$8 -> 73811.25 | Q8: ='P&L_5yr'!$F$8 -> 73811.25 | R8: ='P&L_5yr'!$G$8 -> 99645.188 | S8: ='P&L_5yr'!$G$8 -> 99645.188 | T8: ='P&L_5yr'!$G$8 -> 99645.188 | U8: ='P&L_5yr'!$G$8 -> 99645.188
A9: GMV | B9: =B5*B8 -> 810000 | C9: =C5*C8 -> 2430000 | D9: =D5*D8 -> 2160000 | E9: =SUM(B9:D9) -> 5400000 | F9: =F5*F8 -> 10935000 | G9: =G5*G8 -> 16402500 | H9: =H5*H8 -> 9112500 | I9: =SUM(F9:H9) -> 36450000 | J9: =J5*J8 -> 73811250 | K9: =K5*K8 -> 65610000 | L9: =L5*L8 -> 24603750 | M9: =SUM(J9:L9) -> 164025000 | N9: =N5*N8 -> 332150625 | O9: =O5*O8 -> 177147000 | P9: =P5*P8 -> 44286750 | Q9: =SUM(N9:P9) -> 553584375 | R9: =R5*R8 -> 1.2555294e+09 | S9: =S5*S8 -> 4.4840334e+08 | T9: =T5*T8 -> 89680669 | U9: =SUM(R9:T9) -> 1793613375
A10: Escrow take rate | B10: =Assumptions!$F$73 -> 0.006 | C10: =Assumptions!$F$74 -> 0.0085 | D10: =Assumptions!$F$75 -> 0.015 | E10: =IF(E9=0,0,SUM(B9*B10,C9*C10,D9*D10)/E9) -> 0.010725 | F10: =Assumptions!$F$73 -> 0.006 | G10: =Assumptions!$F$74 -> 0.0085 | H10: =Assumptions!$F$75 -> 0.015 | I10: =IF(I9=0,0,SUM(F9*F10,G9*G10,H9*H10)/I9) -> 0.009375 | J10: =Assumptions!$F$73 -> 0.006 | K10: =Assumptions!$F$74 -> 0.0085 | L10: =Assumptions!$F$75 -> 0.015 | M10: =IF(M9=0,0,SUM(J9*J10,K9*K10,L9*L10)/M9) -> 0.00835 | N10: =Assumptions!$F$73 -> 0.006 | O10: =Assumptions!$F$74 -> 0.0085 | P10: =Assumptions!$F$75 -> 0.015 | Q10: =IF(Q9=0,0,SUM(N9*N10,O9*O10,P9*P10)/Q9) -> 0.00752 | R10: =Assumptions!$F$73 -> 0.006 | S10: =Assumptions!$F$74 -> 0.0085 | T10: =Assumptions!$F$75 -> 0.015 | U10: =IF(U9=0,0,SUM(R9*R10,S9*S10,T9*T10)/U9) -> 0.007075
A11: Minimum escrow fee | B11: =Assumptions!$F$76 -> 150 | C11: =Assumptions!$F$77 -> 250 | D11: =Assumptions!$F$78 -> 500 | E11: =IF(E5=0,0,SUM(B5*B11,C5*C11,D5*D11)/E5) -> 335 | F11: =Assumptions!$F$76 -> 150 | G11: =Assumptions!$F$77 -> 250 | H11: =Assumptions!$F$78 -> 500 | I11: =IF(I5=0,0,SUM(F5*F11,G5*G11,H5*H11)/I5) -> 282.5 | J11: =Assumptions!$F$76 -> 150 | K11: =Assumptions!$F$77 -> 250 | L11: =Assumptions!$F$78 -> 500 | M11: =IF(M5=0,0,SUM(J5*J11,K5*K11,L5*L11)/M5) -> 242.5 | N11: =Assumptions!$F$76 -> 150 | O11: =Assumptions!$F$77 -> 250 | P11: =Assumptions!$F$78 -> 500 | Q11: =IF(Q5=0,0,SUM(N5*N11,O5*O11,P5*P11)/Q5) -> 210 | R11: =Assumptions!$F$76 -> 150 | S11: =Assumptions!$F$77 -> 250 | T11: =Assumptions!$F$78 -> 500 | U11: =IF(U5=0,0,SUM(R5*R11,S5*S11,T5*T11)/U5) -> 192.5
A12: Escrow fee revenue | B12: =B5*MAX(B8*B10,B11) -> 4860 | C12: =C5*MAX(C8*C10,C11) -> 20655 | D12: =D5*MAX(D8*D10,D11) -> 36000 | E12: =SUM(B12:D12) -> 61515 | F12: =F5*MAX(F8*F10,F11) -> 65610 | G12: =G5*MAX(G8*G10,G11) -> 139421.25 | H12: =H5*MAX(H8*H10,H11) -> 136687.5 | I12: =SUM(F12:H12) -> 341718.75 | J12: =J5*MAX(J8*J10,J11) -> 442867.5 | K12: =K5*MAX(K8*K10,K11) -> 557685 | L12: =L5*MAX(L8*L10,L11) -> 369056.25 | M12: =SUM(J12:L12) -> 1369608.8 | N12: =N5*MAX(N8*N10,N11) -> 1992903.8 | O12: =O5*MAX(O8*O10,O11) -> 1505749.5 | P12: =P5*MAX(P8*P10,P11) -> 664301.25 | Q12: =SUM(N12:P12) -> 4162954.5 | R12: =R5*MAX(R8*R10,R11) -> 7533176.2 | S12: =S5*MAX(S8*S10,S11) -> 3811428.4 | T12: =T5*MAX(T8*T10,T11) -> 1345210 | U12: =SUM(R12:T12) -> 12689815
A13: Doc/review fee per deal | B13: =Assumptions!$F$79 -> 25 | C13: =Assumptions!$F$80 -> 90 | D13: =Assumptions!$F$81 -> 300 | E13: =IF(E5=0,0,SUM(B5*B13,C5*C13,D5*D13)/E5) -> 164.25 | F13: =Assumptions!$F$79 -> 25 | G13: =Assumptions!$F$80 -> 90 | H13: =Assumptions!$F$81 -> 300 | I13: =IF(I5=0,0,SUM(F5*F13,G5*G13,H5*H13)/I5) -> 123 | J13: =Assumptions!$F$79 -> 25 | K13: =Assumptions!$F$80 -> 90 | L13: =Assumptions!$F$81 -> 300 | M13: =IF(M5=0,0,SUM(J5*J13,K5*K13,L5*L13)/M5) -> 92.25 | N13: =Assumptions!$F$79 -> 25 | O13: =Assumptions!$F$80 -> 90 | P13: =Assumptions!$F$81 -> 300 | Q13: =IF(Q5=0,0,SUM(N5*N13,O5*O13,P5*P13)/Q5) -> 67.8 | R13: =Assumptions!$F$79 -> 25 | S13: =Assumptions!$F$80 -> 90 | T13: =Assumptions!$F$81 -> 300 | U13: =IF(U5=0,0,SUM(R5*R13,S5*S13,T5*T13)/U5) -> 55
A14: Doc/review revenue | B14: =B5*B13 -> 675 | C14: =C5*C13 -> 7290 | D14: =D5*D13 -> 21600 | E14: =SUM(B14:D14) -> 29565 | F14: =F5*F13 -> 6750 | G14: =G5*G13 -> 36450 | H14: =H5*H13 -> 67500 | I14: =SUM(F14:H14) -> 110700 | J14: =J5*J13 -> 33750 | K14: =K5*K13 -> 108000 | L14: =L5*L13 -> 135000 | M14: =SUM(J14:L14) -> 276750 | N14: =N5*N13 -> 112500 | O14: =O5*O13 -> 216000 | P14: =P5*P13 -> 180000 | Q14: =SUM(N14:P14) -> 508500 | R14: =R5*R13 -> 315000 | S14: =S5*S13 -> 405000 | T14: =T5*T13 -> 270000 | U14: =SUM(R14:T14) -> 990000
A15: Dispute rate | B15: =Assumptions!$F$94 -> 0.04 | C15: =Assumptions!$F$95 -> 0.1 | D15: =Assumptions!$F$96 -> 0.2 | E15: =IF(E5=0,0,E16/E5) -> 0.131 | F15: =Assumptions!$F$94 -> 0.04 | G15: =Assumptions!$F$95 -> 0.1 | H15: =Assumptions!$F$96 -> 0.2 | I15: =IF(I5=0,0,I16/I5) -> 0.107 | J15: =Assumptions!$F$94 -> 0.04 | K15: =Assumptions!$F$95 -> 0.1 | L15: =Assumptions!$F$96 -> 0.2 | M15: =IF(M5=0,0,M16/M5) -> 0.088 | N15: =Assumptions!$F$94 -> 0.04 | O15: =Assumptions!$F$95 -> 0.1 | P15: =Assumptions!$F$96 -> 0.2 | Q15: =IF(Q5=0,0,Q16/Q5) -> 0.072 | R15: =Assumptions!$F$94 -> 0.04 | S15: =Assumptions!$F$95 -> 0.1 | T15: =Assumptions!$F$96 -> 0.2 | U15: =IF(U5=0,0,U16/U5) -> 0.063
A16: Disputed deals | B16: =B5*B15 -> 1.08 | C16: =C5*C15 -> 8.1 | D16: =D5*D15 -> 14.4 | E16: =SUM(B16:D16) -> 23.58 | F16: =F5*F15 -> 10.8 | G16: =G5*G15 -> 40.5 | H16: =H5*H15 -> 45 | I16: =SUM(F16:H16) -> 96.3 | J16: =J5*J15 -> 54 | K16: =K5*K15 -> 120 | L16: =L5*L15 -> 90 | M16: =SUM(J16:L16) -> 264 | N16: =N5*N15 -> 180 | O16: =O5*O15 -> 240 | P16: =P5*P15 -> 120 | Q16: =SUM(N16:P16) -> 540 | R16: =R5*R15 -> 504 | S16: =S5*S15 -> 450 | T16: =T5*T15 -> 180 | U16: =SUM(R16:T16) -> 1134
A17: Dispute/amendment fee | B17: =Assumptions!$F$82 -> 100 | C17: =Assumptions!$F$83 -> 200 | D17: =Assumptions!$F$84 -> 500 | E17: =IF(E16=0,0,SUM(B16*B17,C16*C17,D16*D17)/E16) -> 378.62595 | F17: =Assumptions!$F$82 -> 100 | G17: =Assumptions!$F$83 -> 200 | H17: =Assumptions!$F$84 -> 500 | I17: =IF(I16=0,0,SUM(F16*F17,G16*G17,H16*H17)/I16) -> 328.97196 | J17: =Assumptions!$F$82 -> 100 | K17: =Assumptions!$F$83 -> 200 | L17: =Assumptions!$F$84 -> 500 | M17: =IF(M16=0,0,SUM(J16*J17,K16*K17,L16*L17)/M16) -> 281.81818 | N17: =Assumptions!$F$82 -> 100 | O17: =Assumptions!$F$83 -> 200 | P17: =Assumptions!$F$84 -> 500 | Q17: =IF(Q16=0,0,SUM(N16*N17,O16*O17,P16*P17)/Q16) -> 233.33333 | R17: =Assumptions!$F$82 -> 100 | S17: =Assumptions!$F$83 -> 200 | T17: =Assumptions!$F$84 -> 500 | U17: =IF(U16=0,0,SUM(R16*R17,S16*S17,T16*T17)/U16) -> 203.1746
A18: Dispute/amendment revenue | B18: =B16*B17 -> 108 | C18: =C16*C17 -> 1620 | D18: =D16*D17 -> 7200 | E18: =SUM(B18:D18) -> 8928 | F18: =F16*F17 -> 1080 | G18: =G16*G17 -> 8100 | H18: =H16*H17 -> 22500 | I18: =SUM(F18:H18) -> 31680 | J18: =J16*J17 -> 5400 | K18: =K16*K17 -> 24000 | L18: =L16*L17 -> 45000 | M18: =SUM(J18:L18) -> 74400 | N18: =N16*N17 -> 18000 | O18: =O16*O17 -> 48000 | P18: =P16*P17 -> 60000 | Q18: =SUM(N18:P18) -> 126000 | R18: =R16*R17 -> 50400 | S18: =S16*S17 -> 90000 | T18: =T16*T17 -> 90000 | U18: =SUM(R18:T18) -> 230400
A19: External eBL/API/paper cost | B19: =B5*Assumptions!$F$85 -> 81 | C19: =C5*Assumptions!$F$86 -> 810 | D19: =D5*Assumptions!$F$87 -> 10800 | E19: =SUM(B19:D19) -> 11691 | F19: =F5*Assumptions!$F$85 -> 810 | G19: =G5*Assumptions!$F$86 -> 4050 | H19: =H5*Assumptions!$F$87 -> 33750 | I19: =SUM(F19:H19) -> 38610 | J19: =J5*Assumptions!$F$85 -> 4050 | K19: =K5*Assumptions!$F$86 -> 12000 | L19: =L5*Assumptions!$F$87 -> 67500 | M19: =SUM(J19:L19) -> 83550 | N19: =N5*Assumptions!$F$85 -> 13500 | O19: =O5*Assumptions!$F$86 -> 24000 | P19: =P5*Assumptions!$F$87 -> 90000 | Q19: =SUM(N19:P19) -> 127500 | R19: =R5*Assumptions!$F$85 -> 37800 | S19: =S5*Assumptions!$F$86 -> 45000 | T19: =T5*Assumptions!$F$87 -> 135000 | U19: =SUM(R19:T19) -> 217800
A20: Human review cost | B20: =B5*Assumptions!$F$88 -> 81 | C20: =C5*Assumptions!$F$89 -> 1620 | D20: =D5*Assumptions!$F$90 -> 8640 | E20: =SUM(B20:D20) -> 10341 | F20: =F5*Assumptions!$F$88 -> 810 | G20: =G5*Assumptions!$F$89 -> 8100 | H20: =H5*Assumptions!$F$90 -> 27000 | I20: =SUM(F20:H20) -> 35910 | J20: =J5*Assumptions!$F$88 -> 4050 | K20: =K5*Assumptions!$F$89 -> 24000 | L20: =L5*Assumptions!$F$90 -> 54000 | M20: =SUM(J20:L20) -> 82050 | N20: =N5*Assumptions!$F$88 -> 13500 | O20: =O5*Assumptions!$F$89 -> 48000 | P20: =P5*Assumptions!$F$90 -> 72000 | Q20: =SUM(N20:P20) -> 133500 | R20: =R5*Assumptions!$F$88 -> 37800 | S20: =S5*Assumptions!$F$89 -> 90000 | T20: =T5*Assumptions!$F$90 -> 108000 | U20: =SUM(R20:T20) -> 235800
A21: Support cost | B21: =B5*Assumptions!$F$91 -> 54 | C21: =C5*Assumptions!$F$92 -> 486 | D21: =D5*Assumptions!$F$93 -> 1440 | E21: =SUM(B21:D21) -> 1980 | F21: =F5*Assumptions!$F$91 -> 540 | G21: =G5*Assumptions!$F$92 -> 2430 | H21: =H5*Assumptions!$F$93 -> 4500 | I21: =SUM(F21:H21) -> 7470 | J21: =J5*Assumptions!$F$91 -> 2700 | K21: =K5*Assumptions!$F$92 -> 7200 | L21: =L5*Assumptions!$F$93 -> 9000 | M21: =SUM(J21:L21) -> 18900 | N21: =N5*Assumptions!$F$91 -> 9000 | O21: =O5*Assumptions!$F$92 -> 14400 | P21: =P5*Assumptions!$F$93 -> 12000 | Q21: =SUM(N21:P21) -> 35400 | R21: =R5*Assumptions!$F$91 -> 25200 | S21: =S5*Assumptions!$F$92 -> 27000 | T21: =T5*Assumptions!$F$93 -> 18000 | U21: =SUM(R21:T21) -> 70200
A22: Dispute handling cost | B22: =B16*Assumptions!$F$97 -> 64.8 | C22: =C16*Assumptions!$F$98 -> 972 | D22: =D16*Assumptions!$F$99 -> 5040 | E22: =SUM(B22:D22) -> 6076.8 | F22: =F16*Assumptions!$F$97 -> 648 | G22: =G16*Assumptions!$F$98 -> 4860 | H22: =H16*Assumptions!$F$99 -> 15750 | I22: =SUM(F22:H22) -> 21258 | J22: =J16*Assumptions!$F$97 -> 3240 | K22: =K16*Assumptions!$F$98 -> 14400 | L22: =L16*Assumptions!$F$99 -> 31500 | M22: =SUM(J22:L22) -> 49140 | N22: =N16*Assumptions!$F$97 -> 10800 | O22: =O16*Assumptions!$F$98 -> 28800 | P22: =P16*Assumptions!$F$99 -> 42000 | Q22: =SUM(N22:P22) -> 81600 | R22: =R16*Assumptions!$F$97 -> 30240 | S22: =S16*Assumptions!$F$98 -> 54000 | T22: =T16*Assumptions!$F$99 -> 63000 | U22: =SUM(R22:T22) -> 147240
A23: Total tier-specific COGS | B23: =SUM(B19:B22) -> 280.8 | C23: =SUM(C19:C22) -> 3888 | D23: =SUM(D19:D22) -> 25920 | E23: =SUM(B23:D23) -> 30088.8 | F23: =SUM(F19:F22) -> 2808 | G23: =SUM(G19:G22) -> 19440 | H23: =SUM(H19:H22) -> 81000 | I23: =SUM(F23:H23) -> 103248 | J23: =SUM(J19:J22) -> 14040 | K23: =SUM(K19:K22) -> 57600 | L23: =SUM(L19:L22) -> 162000 | M23: =SUM(J23:L23) -> 233640 | N23: =SUM(N19:N22) -> 46800 | O23: =SUM(O19:O22) -> 115200 | P23: =SUM(P19:P22) -> 216000 | Q23: =SUM(N23:P23) -> 378000 | R23: =SUM(R19:R22) -> 131040 | S23: =SUM(S19:S22) -> 216000 | T23: =SUM(T19:T22) -> 324000 | U23: =SUM(R23:T23) -> 671040
A24: Tier revenue | B24: =SUM(B12,B14,B18) -> 5643 | C24: =SUM(C12,C14,C18) -> 29565 | D24: =SUM(D12,D14,D18) -> 64800 | E24: =SUM(B24:D24) -> 100008 | F24: =SUM(F12,F14,F18) -> 73440 | G24: =SUM(G12,G14,G18) -> 183971.25 | H24: =SUM(H12,H14,H18) -> 226687.5 | I24: =SUM(F24:H24) -> 484098.75 | J24: =SUM(J12,J14,J18) -> 482017.5 | K24: =SUM(K12,K14,K18) -> 689685 | L24: =SUM(L12,L14,L18) -> 549056.25 | M24: =SUM(J24:L24) -> 1720758.8 | N24: =SUM(N12,N14,N18) -> 2123403.8 | O24: =SUM(O12,O14,O18) -> 1769749.5 | P24: =SUM(P12,P14,P18) -> 904301.25 | Q24: =SUM(N24:P24) -> 4797454.5 | R24: =SUM(R12,R14,R18) -> 7898576.2 | S24: =SUM(S12,S14,S18) -> 4306428.4 | T24: =SUM(T12,T14,T18) -> 1705210 | U24: =SUM(R24:T24) -> 13910215
A25: Gross profit before shared COGS | B25: =B24-B23 -> 5362.2 | C25: =C24-C23 -> 25677 | D25: =D24-D23 -> 38880 | E25: =E24-E23 -> 69919.2 | F25: =F24-F23 -> 70632 | G25: =G24-G23 -> 164531.25 | H25: =H24-H23 -> 145687.5 | I25: =I24-I23 -> 380850.75 | ... U25: =U24-U23 -> 13239175
A26: Gross margin | B26: =IF(B24=0,0,B25/B24) -> 0.95023923 | C26: =IF(C24=0,0,C25/C24) -> 0.86849315 | D26: =IF(D24=0,0,D25/D24) -> 0.6 | E26: =IF(E24=0,0,E25/E24) -> 0.69913607 | F26: =IF(F24=0,0,F25/F24) -> 0.96176471 | G26: =IF(G24=0,0,G25/G24) -> 0.89433132 | H26: =IF(H24=0,0,H25/H24) -> 0.6426799 | I26: =IF(I24=0,0,I25/I24) -> 0.7867212 | ... U26: =IF(U24=0,0,U25/U24) -> 0.95175919
A27: Weighted risk score | B27: =B4*Assumptions!$F$100 -> 0.15 | C27: =C4*Assumptions!$F$101 -> 1.35 | D27: =D4*Assumptions!$F$102 -> 2 | E27: =SUM(B27:D27) -> 3.5 | F27: =F4*Assumptions!$F$100 -> 0.3 | G27: =G4*Assumptions!$F$101 -> 1.35 | H27: =H4*Assumptions!$F$102 -> 1.25 | I27: =SUM(F27:H27) -> 2.9 | J27: =J4*Assumptions!$F$100 -> 0.45 | K27: =K4*Assumptions!$F$101 -> 1.2 | L27: =L4*Assumptions!$F$102 -> 0.75 | M27: =SUM(J27:L27) -> 2.4 | N27: =N4*Assumptions!$F$100 -> 0.6 | O27: =O4*Assumptions!$F$101 -> 0.96 | P27: =P4*Assumptions!$F$102 -> 0.4 | Q27: =SUM(N27:P27) -> 1.96 | R27: =R4*Assumptions!$F$100 -> 0.7 | S27: =S4*Assumptions!$F$101 -> 0.75 | T27: =T4*Assumptions!$F$102 -> 0.25 | U27: =SUM(R27:T27) -> 1.7
A28: SLA days | B28: =Assumptions!$F$103 -> 0.05 | C28: =Assumptions!$F$104 -> 0.5 | D28: =Assumptions!$F$105 -> 7 | E28: =IF(E5=0,0,SUM(B5*B28,C5*C28,D5*D28)/E5) -> 3.0325 | F28: =Assumptions!$F$103 -> 0.05 | G28: =Assumptions!$F$104 -> 0.5 | H28: =Assumptions!$F$105 -> 7 | I28: =IF(I5=0,0,SUM(F5*F28,G5*G28,H5*H28)/I5) -> 1.99 | J28: =Assumptions!$F$103 -> 0.05 | K28: =Assumptions!$F$104 -> 0.5 | L28: =Assumptions!$F$105 -> 7 | M28: =IF(M5=0,0,SUM(J5*J28,K5*K28,L5*L28)/M5) -> 1.2725 | N28: =Assumptions!$F$103 -> 0.05 | O28: =Assumptions!$F$104 -> 0.5 | P28: =Assumptions!$F$105 -> 7 | Q28: =IF(Q5=0,0,SUM(N5*N28,O5*O28,P5*P28)/Q5) -> 0.75 | R28: =Assumptions!$F$103 -> 0.05 | S28: =Assumptions!$F$104 -> 0.5 | T28: =Assumptions!$F$105 -> 7 | U28: =IF(U5=0,0,SUM(R5*R28,S5*S28,T5*T28)/U5) -> 0.51
A29: Tier mix sums check | E29: =IF(ABS(E4-1)<0.0001,"OK","CHECK MIX") -> OK | I29: =IF(ABS(I4-1)<0.0001,"OK","CHECK MIX") -> OK | M29: =IF(ABS(M4-1)<0.0001,"OK","CHECK MIX") -> OK | Q29: =IF(ABS(Q4-1)<0.0001,"OK","CHECK MIX") -> OK | U29: =IF(ABS(U4-1)<0.0001,"OK","CHECK MIX") -> OK
A30: Pricing / risk profile | B30: Fastest / lowest risk | C30: Core verified tier | D30: Highest cost / highest risk | E30: Portfolio blend | F30: Fastest / lowest risk | G30: Core verified tier | H30: Highest cost / highest risk | I30: Portfolio blend | J30: Fastest / lowest risk | K30: Core verified tier | L30: Highest cost / highest risk | M30: Portfolio blend | N30: Fastest / lowest risk | O30: Core verified tier | P30: Highest cost / highest risk | Q30: Portfolio blend | R30: Fastest / lowest risk | S30: Core verified tier | T30: Highest cost / highest risk | U30: Portfolio blend

Sheet Driver_Tables
B2: Driver Tables — Researched Cost & Revenue Assumptions
B3: Reference ranges in native quoted currency. The operating model itself is controlled from Assumptions: fixed inputs use Assumptions column F; scenario drivers use Low/Base/High.
A5: Cost/Revenue driver | B5: Category | C5: Reference low | D5: Model / reference base | E5: Reference high | F5: Currency | G5: Source quality | H5: Source URL / note | I5: Modelling note | J5: Model usage
A6: Escrow transaction fee (take rate) | B6: Revenue | C6: 0.30%-0.70% by tier | D6: Single price book | E6: Below LC/corporate escrow comps | F6: % | G6: estimate | H6: Comparable frame: bank LCs often 0.5%-1.5% issuance plus admin/confirmation; corporate escrow can be ~0.25%-1.0%+. | I6: Model uses one fixed Assumptions value; Low/Base/High scenarios do not change pricing. | J6: Reference; model input in Assumptions
A7: Minimum escrow fee | B7: Revenue | C7: A £150 / B £250 / C £500 | D7: Single price book | E7: Protects small-deal margin | F7: £ | G7: estimate | H7: Protects margin on small deals | I7: Model uses one fixed Assumptions value; Low/Base/High scenarios do not change pricing. | J7: Reference; model input in Assumptions
A8: Document review fee | B8: Revenue | C8: A £25 / B £90 / C £300 | D8: Single price book | E8: Below familiar LC discrepancy/admin fee burden | F8: £ | G8: estimate | H8: Flat per-deal doc-check charge | I8: Model uses one fixed Assumptions value; Low/Base/High scenarios do not change pricing. | J8: Reference; model input in Assumptions
A9: Dispute/amendment fee | B9: Revenue | C9: A £100 / B £200 / C £500 | D9: Single price book | E9: Admin-fee comparable | F9: £ | G9: estimate | H9: Charged only on disputed/amended deals | I9: Model uses one fixed Assumptions value; Low/Base/High scenarios do not change pricing. | J9: Reference; model input in Assumptions
A10: SaaS/API partner fee | B10: Revenue | C10: 0 | D10: 500 | E10: 1500 | F10: £ | G10: estimate | H10: White-label/API from Yr2 | I10: × partners × 12 | J10: Reference; model input in Assumptions
A11: Pilot→paid conversion | B11: Revenue | C11: 0.2 | D11: 0.35 | E11: 0.55 | F11: % | G11: benchmark | H11: B2B fintech pilots convert ~20–55%; feeds deal ramp | I11: Drives Yr1→Yr2 deal growth | J11: Scenario driver
A12: Companies House incorporation (digital) | B12: Startup cost | C12: 100 | D12: 100 | E12: 100 | F12: £ | G12: official | H12: https://changestoukcompanylaw.campaign.gov.uk/changes-to-companies-house-fees/ | I12: £100 from 1 Feb 2026 | J12: Reference; model input in Assumptions
A13: Confirmation statement | B13: Compliance/legal | C13: 50 | D13: 50 | E13: 50 | F13: £ | G13: official | H13: https://changestoukcompanylaw.campaign.gov.uk/changes-to-companies-house-fees/ | I13: £50 digital | J13: Reference; model input in Assumptions
A14: ACSP registration / director ID | B14: Compliance/legal | C14: 0 | D14: 63 | E14: 63 | F14: £ | G14: official | H14: https://www.icaew.com/ - CH fees 2026 | I14: £63 ACSP; One Login free | J14: Reference; model input in Assumptions
A15: Shareholder agreement | B15: Startup cost | C15: 375 | D15: 1500 | E15: 3000 | F15: £ | G15: benchmark | H15: https://founderdocuments.co.uk / lawyersonline.co.uk | I15: Fixed-fee range | J15: Reference; model input in Assumptions
A16: IP assignment | B16: Startup cost | C16: 200 | D16: 600 | E16: 1500 | F16: £ | G16: estimate | H16: Founder/contractor IP into NewCo | J16: Reference; model input in Assumptions
A17: Terms + privacy policy | B17: Startup cost | C17: 300 | D17: 900 | E17: 2500 | F17: £ | G17: estimate | H17: Fintech-grade | J17: Reference; model input in Assumptions
A18: Trade Escrow Agreement (bespoke) | B18: Compliance/legal | C18: 3000 | D18: 8000 | E18: 18000 | F18: £ | G18: estimate | H18: Core product contract; bespoke | I18: HIGH uncertainty | J18: Reference; model input in Assumptions
A19: Regulatory perimeter advice (crypto) | B19: Compliance/legal | C19: 8000 | D19: 25000 | E19: 60000 | F19: £ | G19: estimate | H19: FCA crypto regime in force Oct 2027; gateway 30 Sep 2026 | I19: HIGH RISK — verify scope | J19: Reference; model input in Assumptions
A20: AML/KYC/sanctions policy setup | B20: Compliance/legal | C20: 2000 | D20: 6000 | E20: 15000 | F20: £ | G20: estimate | H20: MLR 2017 + MLRO | J20: Reference; model input in Assumptions
A21: GDPR/data-protection setup | B21: Compliance/legal | C21: 1000 | D21: 3000 | E21: 8000 | F21: £ | G21: estimate | H21: DPIA, ROPA | J21: Reference; model input in Assumptions
A22: ICO data protection fee | B22: Compliance/legal | C22: 52 | D22: 60 | E22: 60 | F22: £ | G22: official | H22: https://ico.org.uk - data protection fee | I22: Tiered £40–£60 | J22: Reference; model input in Assumptions
A23: Smart-contract audit | B23: Startup cost | C23: 12000 | D23: 30000 | E23: 60000 | F23: £ | G23: benchmark | H23: https://www.zealynx.io/blogs/audit-pricing-2026; sherlock.xyz | I23: Moderate-complexity escrow | J23: Reference; model input in Assumptions
A24: Penetration test | B24: Startup cost | C24: 3000 | D24: 7000 | E24: 15000 | F24: £ | G24: estimate | H24: Pre-launch web app pentest | J24: Reference; model input in Assumptions
A25: Smart-contract development | B25: Startup cost | C25: 15000 | D25: 40000 | E25: 90000 | F25: £ | G25: estimate | H25: Contract build (days×rate) | J25: Reference; model input in Assumptions
A26: Web/full-stack build | B26: Startup cost | C26: 20000 | D26: 50000 | E26: 110000 | F26: £ | G26: estimate | H26: MVP incl integrations | J26: Reference; model input in Assumptions
A27: UI/UX design | B27: Startup cost | C27: 3000 | D27: 9000 | E27: 20000 | F27: £ | G27: estimate | J27: Reference; model input in Assumptions
A28: Brand + pitch deck | B28: Startup cost | C28: 1500 | D28: 5000 | E28: 12000 | F28: £ | G28: estimate | J28: Reference; model input in Assumptions
A29: Marketing website + domain | B29: Startup cost | C29: 1100 | D29: 4300 | E29: 10800 | F29: £ | G29: vendor/estimate | H29: Domain/Workspace vendor-priced | J29: Reference; model input in Assumptions
A30: 667 | B30: Business development | C30: 1000 | D30: 5000 | E30: 15000 | F30: £ | G30: estimate | H30: ME travel raises high end | J30: Reference; model input in Assumptions
A31: Claude API per document | B31: COGS/variable cost | C31: 0.01 | D31: 0.03 | E31: 0.08 | F31: $ | G31: vendor | H31: https://docs.claude.com (Haiku $1/$5, Sonnet $3/$15 per MTok) | I31: Use Haiku+caching; batch −50% | J31: Reference; model input in Assumptions
A32: OCR alternative (AWS Textract etc.) | B32: COGS/variable cost | C32: 0.0015 | D32: 0.01 | E32: 0.05 | F32: $ | G32: vendor | H32: AWS Textract ~$1.5/1000 pages forms-tier | I32: Fallback/complement to LLM | J32: Reference; model input in Assumptions
A33: KYB business verification | B33: COGS/variable cost | C33: 2 | D33: 3.5 | E33: 6 | F33: $ | G33: vendor | H33: https://didit.me (fr $2); https://sumsub.com/pricing | I33: Per entity | J33: Reference; model input in Assumptions
A34: KYC/UBO + sanctions | B34: COGS/variable cost | C34: 0.3 | D34: 1.35 | E34: 5 | F34: $ | G34: vendor | H34: https://sumsub.com/pricing ($1.35); Didit $0.30 | I34: Per counterparty/UBO | J34: Reference; model input in Assumptions
A35: Human document review | B35: COGS/variable cost | C35: 0.5 | D35: 4 | E35: 12 | F35: £ | G35: estimate | H35: Human-in-loop; automate down over time | I35: Scales with volume | J35: Reference; model input in Assumptions
A36: Blockchain gas (Base L2) | B36: COGS/variable cost | C36: 0.05 | D36: 0.2 | E36: 0.8 | F36: $ | G36: official | H36: https://docs.base.org/.../network-fees (~$0.002/200k gas) | I36: Several txns/deal (deploy+release) | J36: Reference; model input in Assumptions
A37: RPC/node provider | B37: COGS/variable cost | C37: 0.002 | D37: 0.01 | E37: 0.03 | F37: $ | G37: vendor | H37: Alchemy/QuickNode metered compute units | J37: Reference; model input in Assumptions
A38: Doc + ledger storage | B38: COGS/variable cost | C38: 0.01 | D38: 0.03 | E38: 0.08 | F38: $ | G38: vendor | H38: S3 + Glacier audit ledger | J38: Reference; model input in Assumptions
A39: Customer support | B39: COGS/variable cost | C39: 1 | D39: 3 | E39: 8 | F39: £ | G39: estimate | H39: Blended | J39: Reference; model input in Assumptions
A40: Dispute handling | B40: COGS/variable cost | C40: 20 | D40: 60 | E40: 150 | F40: £ | G40: estimate | H40: Manual labour | I40: × disputed deals | J40: Reference; model input in Assumptions
A41: Cloud hosting (Vercel/AWS) | B41: Fixed opex | C41: 50 | D41: 250 | E41: 900 | F41: £ | G41: vendor | H41: https://vercel.com/pricing ($20/seat) + AWS usage | I41: Watch usage overages | J41: Reference; model input in Assumptions
A42: Database + object storage | B42: Fixed opex | C42: 20 | D42: 120 | E42: 500 | F42: £ | G42: vendor/estimate | H42: Managed Postgres + S3 | J42: Reference; model input in Assumptions
A43: Monitoring/logging/security | B43: Fixed opex | C43: 30 | D43: 150 | E43: 500 | F43: £ | G43: vendor/estimate | H43: Sentry/Datadog/Snyk | J43: Reference; model input in Assumptions
A44: GitHub + dev SaaS | B44: Fixed opex | C44: 20 | D44: 60 | E44: 200 | F44: £ | G44: vendor | H44: GitHub $4–21/user | J44: Reference; model input in Assumptions
A45: Google Workspace | B45: Fixed opex | C45: 30 | D45: 90 | E45: 250 | F45: £ | G45: vendor | H45: ~£12/user Business Standard | J45: Reference; model input in Assumptions
A46: CRM + BD tooling | B46: Fixed opex | C46: 0 | D46: 80 | E46: 300 | F46: £ | G46: vendor/estimate | H46: HubSpot/Pipedrive | J46: Reference; model input in Assumptions
A47: Accounting/payroll/bookkeeping | B47: Fixed opex | C47: 150 | D47: 350 | E47: 800 | F47: £ | G47: estimate | H47: Outsourced | J47: Reference; model input in Assumptions
A48: Legal retainer | B48: Fixed opex | C48: 0 | D48: 600 | E48: 2000 | F48: £ | G48: estimate | H48: Ongoing commercial/reg | J48: Reference; model input in Assumptions
A49: Compliance / MLRO support | B49: Compliance/legal | C49: 0 | D49: 1200 | E49: 4000 | F49: £ | G49: benchmark/estimate | H49: Fractional MLRO/consultant | J49: Reference; model input in Assumptions
A50: Marketing / conferences | B50: Business development | C50: 200 | D50: 1500 | E50: 6000 | F50: £ | G50: estimate | J50: Reference; model input in Assumptions
A51: Office / coworking | B51: Fixed opex | C51: 0 | D51: 400 | E51: 1500 | F51: £ | G51: estimate | J51: Reference; model input in Assumptions
A52: Insurance PI+cyber+D&O | B52: Fixed opex | C52: 250 | D52: 700 | E52: 2000 | F52: £ | G52: benchmark/estimate | H52: Superscript/Lockton fintech; PI+cyber+D&O | I52: Annual /12; fintech loading | J52: Reference; model input in Assumptions
A53: Founder salary | B53: HR | C53: 30000 | D53: 45000 | E53: 65000 | F53: £ | G53: benchmark | H53: Pre-seed founder norm | J53: Reference; model input in Assumptions
A54: Software engineer salary | B54: HR | C54: 50000 | D54: 70000 | E54: 95000 | F54: £ | G54: benchmark | H54: https://savingtool.co.uk; glassdoor UK fintech SWE | J54: Reference; model input in Assumptions
A55: Compliance/ops salary | B55: HR | C55: 45000 | D55: 60000 | E55: 85000 | F55: £ | G55: benchmark | H55: https://live-digital.co.uk/blog/compliance-officer-salary | I55: FS compliance officer | J55: Reference; model input in Assumptions
A56: Sales/BD/CS salary | B56: HR | C56: 35000 | D56: 50000 | E56: 70000 | F56: £ | G56: benchmark | H56: Morgan McKinley / market | J56: Reference; model input in Assumptions
A57: Employer NI | B57: HR | C57: 0.15 | D57: 0.15 | E57: 0.15 | F57: % | G57: official | H57: https://www.gov.uk - NI rates 2026/27 | I57: 15% above £5,000 ST | J57: Reference; model input in Assumptions
A58: Employer pension | B58: HR | C58: 0.03 | D58: 0.04 | E58: 0.05 | F58: % | G58: official | H58: The Pensions Regulator auto-enrolment | I58: Min 3% employer | J58: Reference; model input in Assumptions
A59: Smart-contract dev day rate | B59: HR | C59: 600 | D59: 900 | E59: 1400 | F59: £ | G59: benchmark/estimate | H59: Specialist Solidity contractor | J59: Reference; model input in Assumptions
A60: Full-stack dev day rate | B60: HR | C60: 400 | D60: 600 | E60: 850 | F60: £ | G60: benchmark | H60: Inside/outside IR35 varies | J60: Reference; model input in Assumptions
A61: Compliance consultant day rate | B61: HR | C61: 600 | D61: 900 | E61: 1500 | F61: £ | G61: benchmark/estimate | H61: Crypto reg specialist | J61: Reference; model input in Assumptions
A62: UX/design day rate | B62: HR | C62: 350 | D62: 500 | E62: 750 | F62: £ | G62: benchmark | J62: Reference; model input in Assumptions
A63: Pre-seed raise (UK/EU) | B63: Funding | C63: 400000 | D63: 1000000 | E63: 2000000 | F63: £ | G63: benchmark | H63: Carta/PitchBook; UK/EU pre-seed via SAFE | I63: SAFE common <£4M-equiv | J63: Reference; model input in Assumptions
A64: Seed raise (UK/EU) | B64: Funding | C64: 2000000 | D64: 2800000 | E64: 4000000 | F64: £ | G64: benchmark | H64: Median seed $2.5–3.5M | I64: Priced round | J64: Reference; model input in Assumptions
A65: Seed raise (Middle East) | B65: Funding | C65: 2000000 | D65: 3700000 | E65: 6000000 | F65: $ | G65: benchmark | H65: ME avg seed ~$3.7M | I65: Higher dilution ~25% | J65: Reference; model input in Assumptions
A66: Pre-seed dilution | B66: Funding | C66: 0.1 | D66: 0.15 | E66: 0.2 | F66: % | G66: benchmark | H66: Carta State of Pre-Seed | J66: Reference; model input in Assumptions
A67: Runway buffer (regulated fintech) | B67: Funding | C67: 12 | D67: 18 | E67: 24 | F67: months | G67: benchmark/estimate | H67: Regulated fintech carries longer buffer | I67: Cash buffer guidance | J67: Reference; model input in Assumptions
A69: Tier A/B/C mix by year | B69: Revenue / risk | C69: See Assumptions rows 75-83 | D69: Base: A 15%->30%->45%; B 45%->45%->40%; C 40%->25%->15% | E69: Upside shifts faster to eBL | F69: % of deals | G69: estimate | H69: Derived from slide-09 six-layer verification stack and slide-10 tier mix | I69: Feeds Tier_Economics | J69: Scenario driver
A70: Tier A eBL take rate/min fee | B70: Revenue | C70: 0.30% / GBP150 | D70: 0.30% / GBP150 | E70: 0.30% / GBP150 | F70: % GMV / GBP | G70: estimate | H70: Single price book; eBL/source-of-truth rail priced below typical LC issuance economics. | I70: Model uses one fixed Assumptions value; Low/Base/High scenarios do not change pricing. | J70: Reference; model input in Assumptions
A71: Tier B carrier/API take rate/min fee | B71: Revenue | C71: 0.45% / GBP250 | D71: 0.45% / GBP250 | E71: 0.45% / GBP250 | F71: % GMV / GBP | G71: estimate | H71: Single price book; carrier/API verification priced below many LC/escrow all-in alternatives. | I71: Model uses one fixed Assumptions value; Low/Base/High scenarios do not change pricing. | J71: Reference; model input in Assumptions
A72: Tier C paper take rate/min fee | B72: Revenue | C72: 0.70% / GBP500 | D72: 0.70% / GBP500 | E72: 0.70% / GBP500 | F72: % GMV / GBP | G72: estimate | H72: Single price book; paper/originals tier is priced up for risk but remains LC-competitive. | I72: Model uses one fixed Assumptions value; Low/Base/High scenarios do not change pricing. | J72: Reference; model input in Assumptions
A73: Tier A eBL/API handling cost | B73: COGS/variable cost | C73: 1 | D73: 3 | E73: 8 | F73: GBP/deal | G73: estimate/quote-based | H73: eBL platform/API validation | I73: Model uses one fixed Assumptions value unless explicitly listed as a scenario driver. | J73: Reference; model input in Assumptions
A74: Tier B carrier/API handling cost | B74: COGS/variable cost | C74: 3 | D74: 10 | E74: 25 | F74: GBP/deal | G74: estimate/quote-based | H74: DCSA/carrier verification | I74: Model uses one fixed Assumptions value unless explicitly listed as a scenario driver. | J74: Reference; model input in Assumptions
A75: Tier C paper/forensics handling cost | B75: COGS/variable cost | C75: 50 | D75: 150 | E75: 400 | F75: GBP/deal | G75: estimate/quote-based | H75: Courier/originals/forensics partner | I75: Model uses one fixed Assumptions value unless explicitly listed as a scenario driver. | J75: Reference; model input in Assumptions
A76: Tier A human review cost | B76: COGS/variable cost | C76: 1 | D76: 3 | E76: 8 | F76: GBP/deal | G76: estimate | H76: Light examiner time | I76: Model uses one fixed Assumptions value unless explicitly listed as a scenario driver. | J76: Reference; model input in Assumptions
A77: Tier B human review cost | B77: COGS/variable cost | C77: 8 | D77: 20 | E77: 50 | F77: GBP/deal | G77: estimate | H77: Examiner plus source check | I77: Model uses one fixed Assumptions value unless explicitly listed as a scenario driver. | J77: Reference; model input in Assumptions
A78: Tier C human review cost | B78: COGS/variable cost | C78: 40 | D78: 120 | E78: 250 | F78: GBP/deal | G78: estimate | H78: Paper/manual examiner workflow | I78: Model uses one fixed Assumptions value unless explicitly listed as a scenario driver. | J78: Reference; model input in Assumptions
A79: Tier A dispute rate | B79: Risk | C79: 2% | D79: 4% | E79: 7% | F79: % deals | G79: estimate | H79: Lower document-source risk | I79: Model uses one fixed Assumptions value unless explicitly listed as a scenario driver. | J79: Reference; model input in Assumptions
A80: Tier B dispute rate | B80: Risk | C80: 6% | D80: 10% | E80: 15% | F80: % deals | G80: estimate | H80: Medium mismatch risk | I80: Model uses one fixed Assumptions value unless explicitly listed as a scenario driver. | J80: Reference; model input in Assumptions
A81: Tier C dispute rate | B81: Risk | C81: 12% | D81: 20% | E81: 30% | F81: % deals | G81: estimate | H81: Paper/originals risk | I81: Model uses one fixed Assumptions value unless explicitly listed as a scenario driver. | J81: Reference; model input in Assumptions
A82: Tier A SLA | B82: Risk / ops | C82: 0.02d | D82: 0.05d | E82: 0.1d | F82: days | G82: estimate | H82: Minutes to hours | I82: Model uses one fixed Assumptions value unless explicitly listed as a scenario driver. | J82: Reference; model input in Assumptions
A83: Tier B SLA | B83: Risk / ops | C83: 0.25d | D83: 0.5d | E83: 1d | F83: days | G83: estimate | H83: Same day to one day | I83: Model uses one fixed Assumptions value unless explicitly listed as a scenario driver. | J83: Reference; model input in Assumptions
A84: Tier C SLA | B84: Risk / ops | C84: 5d | D84: 7d | E84: 10d | F84: days | G84: estimate | H84: Physical originals path | I84: Model uses one fixed Assumptions value unless explicitly listed as a scenario driver. | J84: Reference; model input in Assumptions
A85: Tier A/B/C docs per deal | B85: COGS/variable cost | C85: A2/B4/C6 | D85: A3/B6/C9 | E85: A4/B8/C12 | F85: docs/deal | G85: estimate | H85: Different intake methods imply different document packs | I85: Model uses one fixed Assumptions value unless explicitly listed as a scenario driver. | J85: Reference; model input in Assumptions
A86: Tier risk score | B86: Risk | C86: A1/B2/C4 | D86: A1/B3/C5 | E86: A2/B3/C5 | F86: 1 low - 5 high | G86: estimate | H86: Narrative risk score for finance/pitch | I86: Model uses one fixed Assumptions value unless explicitly listed as a scenario driver. | J86: Reference; model input in Assumptions

Sheet Sensitivity
B2: Sensitivity Map
B3: Current 5-year model drivers, linked to the assumption rows that control each sensitivity.
B4: Use the links below to jump to the editable assumption. Scenario-driven rows use Low/Base/High; fixed rows use the active value in Assumptions column F.
B6: Rank | C6: Sensitivity lever | D6: Why it matters in this model | E6: Click to edit | F6: Related assumption rows | G6: Current model setting | H6: Outputs affected | I6: How to test it
B7: 1 | C7: Deal volume | D7: Master adoption driver. Revenue, GMV, variable costs, onboarding activity, and cash-flow timing all scale from deal count. | E7: Assumptions!B11 | F7: B11:B13; B155:B156 | G7: ="Y1-Y5 base deals: "&Assumptions!D11&" / "&Assumptions!D12&" / "&Assumptions!D13&" / "&Assumptions!D155&" / "&Assumptions!D156 -> Y1-Y5 base deals: 180 / 900 / 3000 / 7500 / 18000 | H7: Revenue, COGS, cash-flow break-even, funding ask | I7: Change deal counts by year or switch scenario in Assumptions!C4.
B8: 2 | C8: Document intake mix | D8: Tier A/B/C mix controls pricing, direct costs, dispute rates, SLA, and risk profile. | E8: Assumptions!B64 | F8: B64:B72; B157:B162 | G8: ="Y1 base A/B/C: "&ROUND(Assumptions!D64*100,0)&"%/"&ROUND(Assumptions!D65*100,0)&"%/"&ROUND(Assumptions!D66*100,0)&"%; Y5: "&ROUND(Assumptions!D160*100,0)&"%/"&ROUND(Assumptions!D161*100,0)&"%/"&ROUND(Assumptions!D162*100,0)&"%" -> Y1 base A/B/C: 15%/45%/40%; Y5: 70%/25%/5% | H8: Gross margin, risk costs, operations load | I8: Move volume away from Tier C over time to test automation / eBL adoption.
B9: 3 | C9: Tier price book | D9: Core revenue is tier-specific now. The old generic escrow fee is retired. | E9: Assumptions!B73 | F9: B73:B84 | G9: ="Take rates A/B/C: "&ROUND(Assumptions!F73*100,2)&"%/"&ROUND(Assumptions!F74*100,2)&"%/"&ROUND(Assumptions!F75*100,2)&"%; min fee A: GBP "&ROUND(Assumptions!F76,0) -> Take rates A/B/C: 0.6%/0.85%/1.5%; min fee A: GBP 150 | H9: Revenue per deal, gross margin, break-even timing | I9: Adjust tier take rates, minimum fees, document fees, and dispute fees.
B10: 4 | C10: Average deal value | D10: Multiplies take-rate revenue and GMV without changing document count one-for-one. | E10: Assumptions!B15 | F10: B14:B15 | G10: ="Y1-Y5 avg deal: GBP "&ROUND('P&L_5yr'!C8,0)&" / "&ROUND('P&L_5yr'!D8,0)&" / "&ROUND('P&L_5yr'!E8,0)&" / "&ROUND('P&L_5yr'!F8,0)&" / "&ROUND('P&L_5yr'!G8,0)&"; growth "&ROUND(Assumptions!F15*100,0)&"%" -> Y1-Y5 avg deal: GBP 30000 / 40500 / 54675 / 73811 / 99645; growth 35% | H10: GMV, escrow fee revenue, revenue/deal | I10: Test smaller SME transactions versus larger trade corridors.
B11: 5 | C11: Partner commercialization | D11: Partner counts create setup revenue and monthly minimums, but also affect integration/operating complexity. | E11: Assumptions!B17 | F11: B17; B113; B163:B164; B125:B126 | G11: ="Base partners Y2-Y5: "&Assumptions!D17&" / "&Assumptions!D113&" / "&Assumptions!D163&" / "&Assumptions!D164&"; setup GBP "&ROUND(Assumptions!F125,0) -> Base partners Y2-Y5: 3 / 6 / 10 / 18; setup GBP 7500 | H11: Add-on revenue, customer acquisition, cash runway | I11: Change partner count rows and setup/monthly minimum fees together.
B12: 6 | C12: Repeat usage / active customers | D12: Converts deal targets into implied active customers and checks whether adoption assumptions are believable. | E12: Assumptions!B110 | F12: B110:B112; B165:B166 | G12: ="Deals/customer base Y1-Y5: "&Assumptions!D110&" / "&Assumptions!D111&" / "&Assumptions!D112&" / "&Assumptions!D165&" / "&Assumptions!D166 -> Deals/customer base Y1-Y5: 3 / 4 / 6 / 8 / 10 | H12: Active customers, revenue/customer, sales load | I12: Lower repeat usage if customers are mostly one-off shipments.
B13: 7 | C13: KYC/KYB onboarding economics | D13: Repeat-counterparty treatment affects both onboarding revenue and screening cost. | E13: Assumptions!B62 | F13: B62; B19:B20; B120 | G13: ="New party share "&ROUND(Assumptions!F62*100,0)&"%; onboarding fee GBP "&ROUND(Assumptions!F120,0) -> New party share 50%; onboarding fee GBP 15 | H13: COGS, add-on revenue, margin on repeat customers | I13: Stress whether repeat customers require fresh checks every deal.
B14: 8 | C14: Tier C paper / forensics recovery | D14: Tier C is the high-risk fallback. Margin depends on passing through the expensive handling and forensics work. | E14: Assumptions!B87 | F14: B87; B90; B93; B121:B122 | G14: ="Handling cost GBP "&ROUND(Assumptions!F87,0)&"; markup "&ROUND(Assumptions!F121*100,0)&"%; courier fee GBP "&ROUND(Assumptions!F122,0) -> Handling cost GBP 150; markup 20%; courier fee GBP 75 | H14: Tier C gross margin, ops burden, risk reserve | I14: Increase Tier C costs or reduce pass-through to test downside exposure.
B15: 9 | C15: Disputes and retained-risk reserves | D15: Disputes drive service fees, human handling cost, external forum cost, and wrongful-release/process-error reserves. | E15: Assumptions!B94 | F15: B94:B99; B136:B148; B151:B153 | G15: ="Dispute rates A/B/C: "&ROUND(Assumptions!F94*100,0)&"%/"&ROUND(Assumptions!F95*100,0)&"%/"&ROUND(Assumptions!F96*100,0)&"%" -> Dispute rates A/B/C: 4%/10%/20% | H15: Risk costs, funding ask, gross margin | I15: Test a bad-doc environment by increasing Tier C dispute rates and forum cost.
B16: 10 | C16: Headcount and salaries | D16: Payroll is the dominant fixed cost and the biggest determinant of burn before scale. | E16: Assumptions!B39 | F16: B39:B51 | G16: ="Yr1 FTE founders/eng/ops/BD: "&Assumptions!F39&" / "&Assumptions!F40&" / "&Assumptions!F41&" / "&Assumptions!F42&"; engineer salary GBP "&ROUND(Assumptions!F45,0) -> Yr1 FTE founders/eng/ops/BD: 2 / 2 / 1 / 1; engineer salary GBP 70000 | H16: EBITDA, burn, funding ask, break-even | I16: Delay hires or increase salary/on-cost assumptions to test runway.
B17: 11 | C17: Fixed opex and compliance | D17: Ongoing legal, compliance, insurance, tooling, and infrastructure spend sets the monthly burn floor. | E17: Assumptions!B26 | F17: B26:B37; B132:B135; B141:B143 | G17: ="Compliance retainer/mo GBP "&ROUND(Assumptions!F34,0)&"; legal retainer/mo GBP "&ROUND(Assumptions!F33,0) -> Compliance retainer/mo GBP 1200; legal retainer/mo GBP 600 | H17: Operating burn, cash runway, funding ask | I17: Raise compliance/legal/insurance costs for regulated-market downside.
B18: 12 | C18: Cash buffer and regulatory delay | D18: Funding requirement is driven by peak deficit plus buffer and delay contingency. | E18: Assumptions!B58 | F18: B58:B59; B149:B150 | G18: ="Buffer "&ROUND(Assumptions!F58*100,0)&"%; delay reserve "&Assumptions!F149&" mo x GBP "&ROUND(Assumptions!F150,0) -> Buffer 30%; delay reserve 3 mo x GBP 80000 | H18: Funding ask, runway, contingency reserve | I18: Change the buffer and delay reserve to see how much extra seed capital is required.
B21: Accuracy check
B22: The old generic escrow-fee sensitivity is removed. Pricing sensitivity now points to tier-specific take rates, minimum fees, document/review fees, and dispute/amendment fees in Assumptions rows 72-83.
B23: Pilot-to-paid conversion is not a standalone model input. It is represented by deal volume, partner count, and repeat usage / active customer assumptions.

Sheet Risk_Register
B2: Risk Register — High-Risk, Quote-Based & Needs-Confirmation Items
B3: Items requiring legal/regulatory confirmation or a firm quote before the model can be relied on.
B5: Assumption / item | C5: Risk level | D5: Why it's high-risk / what to confirm | E5: Confirm with
B6: FCA regulatory perimeter (does Blockmediary need authorisation?) | C6: CRITICAL | D6: UK FSMA (Cryptoassets) Regs 2026 in force 25 Oct 2027; gateway opens 30 Sep 2026. 'Safeguarding qualifying cryptoassets' is a new regulated activity — a stablecoin escrow holding buyer funds may be in scope. Operating in-perimeter without authorisation risks criminal sanctions and unenforceable contracts. | E6: Specialist crypto regulatory counsel / FCA pre-app
B7: Stablecoin handling & e-money / payments perimeter | C7: CRITICAL | D7: Even excluding lending, holding/transferring stablecoin for third parties can touch payments, e-money and safeguarding rules across UK/EU (MiCA) and ME jurisdictions. Cross-border use multiplies this. | E7: Crypto/payments counsel in each jurisdiction
B8: Escrow take rate & revenue lines | C8: HIGH | D8: All revenue figures are 'estimate' quality — no clean public documentary-escrow comparable. The entire revenue model is a hypothesis until validated in paid pilots. | E8: Pilot pricing tests
B9: Trade Escrow Agreement enforceability | C9: HIGH | D9: Bespoke contract governing on-chain release of funds against off-chain documents; enforceability across buyer/seller jurisdictions is untested. | E9: Trade-finance + crypto counsel
B10: Smart-contract audit scope & cost | C10: MEDIUM | D10: Audit cost depends on final contract complexity; a contract holding client funds warrants a top-tier audit and possibly re-audit after changes. | E10: Audit firm quote (scoped)
B11: AML/KYC obligations & MLRO | C11: HIGH | D11: Cross-border SME trade with funds movement likely triggers MLR 2017 registration and an appointed MLRO; ME jurisdictions add local AML regimes. | E11: MLRO / compliance counsel
B12: Data protection across UK/EU/ME | C12: MEDIUM | D12: Handling trade documents (often containing personal data) across three regions engages UK GDPR, EU GDPR and local ME data laws; transfer mechanisms needed. | E12: Data-protection counsel
B13: Insurance availability & loading | C13: MEDIUM | D13: Crypto/fintech PI, cyber and D&O can be hard to place and carry heavy loadings or exclusions (e.g. crypto exclusions). Quotes will vary widely. | E13: Specialist fintech insurance broker
B14: Salary & contractor benchmarks | C14: LOW | D14: Ranges are benchmark-quality, not offers; actual hires may sit outside the band, especially scarce crypto/compliance talent. | E14: Recruiter / live market data
B15: Funding size & timing | C15: MEDIUM | D15: Round sizes are market benchmarks; regulated-fintech raises can be slower and require more proof of compliance readiness. | E15: Pre-seed/seed investors
B17: Goods delivery / quality / performance risk | C17: EXCLUDED | D17: Core premise: Blockmediary releases against documents, not actual delivery/condition. Must be drafted explicitly in TEA and customer terms. | E17: Trade finance counsel
... B24: Yield share upside | C24: HIGH | D24: Kept off in base case. Only use if regulated yield infrastructure and customer terms permit it. | E24: Crypto/payments counsel

Sheet Revenue_Risk_AddOns
A1: Revenue add-ons and retained-risk offsets
A3: Line item | B3: Year 1 | C3: Year 2 | D3: Year 3 | E3: Year 4 | F3: Year 5 | G3: Logic / note
A4: REVENUE ADD-ONS
A5: First-deal discount drag | B5: =IF(1=1,IFERROR(ROUND(-MIN('P&L_5yr'!C7,'P&L_5yr'!C70)*('P&L_5yr'!C14/'P&L_5yr'!C7)*Assumptions!$F$115,0),0),0) -> -10253 | C5: =IF(2=1,IFERROR(ROUND(-MIN('P&L_5yr'!D7,'P&L_5yr'!D70)*('P&L_5yr'!D14/'P&L_5yr'!D7)*Assumptions!$F$115,0),0),0) -> 0 | D5: =IF(3=1,IFERROR(ROUND(-MIN('P&L_5yr'!E7,'P&L_5yr'!E70)*('P&L_5yr'!E14/'P&L_5yr'!E7)*Assumptions!$F$115,0),0),0) -> 0 | E5: =IF(4=1,IFERROR(ROUND(-MIN('P&L_5yr'!F7,'P&L_5yr'!F70)*('P&L_5yr'!F14/'P&L_5yr'!F7)*Assumptions!$F$115,0),0),0) -> 0 | F5: =IF(5=1,IFERROR(ROUND(-MIN('P&L_5yr'!G7,'P&L_5yr'!G70)*('P&L_5yr'!G14/'P&L_5yr'!G7)*Assumptions!$F$115,0),0),0) -> 0 | G5: =IF(4=1,IFERROR(ROUND(-MIN('P&L_5yr'!F7,'P&L_5yr'!F70)*('P&L_5yr'!F14/'P&L_5yr'!F7)*Assumptions!$F$115,0),0),0) -> 0
A6: Expedited review fees | B6: =ROUND(Tier_Economics!C5*Assumptions!$F$116*Assumptions!$F$118+Tier_Economics!D5*Assumptions!$F$117*Assumptions!$F$119,0) -> 5535 | C6: =ROUND(Tier_Economics!G5*Assumptions!$F$116*Assumptions!$F$118+Tier_Economics!H5*Assumptions!$F$117*Assumptions!$F$119,0) -> 19575 | D6: =ROUND(Tier_Economics!K5*Assumptions!$F$116*Assumptions!$F$118+Tier_Economics!L5*Assumptions!$F$117*Assumptions!$F$119,0) -> 45000 | E6: =ROUND(Tier_Economics!O5*Assumptions!$F$116*Assumptions!$F$118+Tier_Economics!P5*Assumptions!$F$117*Assumptions!$F$119,0) -> 72000 | F6: =ROUND(Tier_Economics!S5*Assumptions!$F$116*Assumptions!$F$118+Tier_Economics!T5*Assumptions!$F$117*Assumptions!$F$119,0) -> 121500 | G6: =ROUND(Tier_Economics!O5*Assumptions!$F$116*Assumptions!$F$118+Tier_Economics!P5*Assumptions!$F$117*Assumptions!$F$119,0) -> 72000
A7: KYC/KYB onboarding fees | B7: =ROUND('P&L_5yr'!C11*Assumptions!$F$120,0) -> 2700 | C7: =ROUND('P&L_5yr'!D11*Assumptions!$F$120,0) -> 13500 | D7: =ROUND('P&L_5yr'!E11*Assumptions!$F$120,0) -> 45000 | E7: =ROUND('P&L_5yr'!F11*Assumptions!$F$120,0) -> 112500 | F7: =ROUND('P&L_5yr'!G11*Assumptions!$F$120,0) -> 270000 | G7: Fresh onboarding only; repeat counterparties not recharged every deal
A8: Tier C forensics pass-through margin | B8: =ROUND(Tier_Economics!D19*Assumptions!$F$121,0) -> 2160 | C8: =ROUND(Tier_Economics!H19*Assumptions!$F$121,0) -> 6750 | D8: =ROUND(Tier_Economics!L19*Assumptions!$F$121,0) -> 13500 | E8: =ROUND(Tier_Economics!P19*Assumptions!$F$121,0) -> 18000 | F8: =ROUND(Tier_Economics!T19*Assumptions!$F$121,0) -> 27000 | G8: =ROUND(Tier_Economics!P19*Assumptions!$F$121,0) -> 18000
A9: Tier C courier/original handling fees | B9: =ROUND(Tier_Economics!D5*Assumptions!$F$122,0) -> 5400 | C9: =ROUND(Tier_Economics!H5*Assumptions!$F$122,0) -> 16875 | D9: =ROUND(Tier_Economics!L5*Assumptions!$F$122,0) -> 33750 | E9: =ROUND(Tier_Economics!P5*Assumptions!$F$122,0) -> 45000 | F9: =ROUND(Tier_Economics!T5*Assumptions!$F$122,0) -> 67500 | G9: =ROUND(Tier_Economics!P5*Assumptions!$F$122,0) -> 45000
A10: Discrepancy cure / waiver fees | B10: =ROUND('P&L_5yr'!C12*Assumptions!$F$124*Assumptions!$F$123,0) -> 1415 | C10: =ROUND('P&L_5yr'!D12*Assumptions!$F$124*Assumptions!$F$123,0) -> 5778 | D10: =ROUND('P&L_5yr'!E12*Assumptions!$F$124*Assumptions!$F$123,0) -> 15840 | E10: =ROUND('P&L_5yr'!F12*Assumptions!$F$124*Assumptions!$F$123,0) -> 32400 | F10: =ROUND('P&L_5yr'!G12*Assumptions!$F$124*Assumptions!$F$123,0) -> 68040 | G10: =ROUND('P&L_5yr'!F12*Assumptions!$F$124*Assumptions!$F$123,0) -> 32400
A11: Partner setup / integration fees | B11: =ROUND(0,0) -> 0 | C11: =ROUND(Assumptions!$F$17*Assumptions!$F$125,0) -> 22500 | D11: =ROUND(MAX(0,Assumptions!$F$113-Assumptions!$F$17)*Assumptions!$F$125,0) -> 22500 | E11: =ROUND(MAX(0,Assumptions!$F$163-Assumptions!$F$113)*Assumptions!$F$125,0) -> 30000 | F11: =ROUND(MAX(0,Assumptions!$F$164-Assumptions!$F$163)*Assumptions!$F$125,0) -> 60000 | G11: Setup fees charged on net-new partners only
A12: Monthly minimum / committed volume fees | B12: =ROUND(0,0) -> 0 | C12: =ROUND(Assumptions!$F$17*Assumptions!$F$126*12,0) -> 27000 | D12: =ROUND(Assumptions!$F$113*Assumptions!$F$126*12,0) -> 54000 | E12: =ROUND(Assumptions!$F$163*Assumptions!$F$126*12,0) -> 90000 | F12: =ROUND(Assumptions!$F$164*Assumptions!$F$126*12,0) -> 162000 | G12: Monthly minimum uses live partner count by year
A13: Archive / audit record fees | B13: =ROUND('P&L_5yr'!C7*Assumptions!$F$127,0) -> 540 | C13: =ROUND('P&L_5yr'!D7*Assumptions!$F$127,0) -> 2700 | D13: =ROUND('P&L_5yr'!E7*Assumptions!$F$127,0) -> 9000 | E13: =ROUND('P&L_5yr'!F7*Assumptions!$F$127,0) -> 22500 | F13: =ROUND('P&L_5yr'!G7*Assumptions!$F$127,0) -> 54000 | G13: =ROUND('P&L_5yr'!F7*Assumptions!$F$127,0) -> 22500
A14: Yield share upside | B14: =ROUND(Assumptions!$F$128*Assumptions!$F$129*Assumptions!$F$130*'P&L_5yr'!C9,0) -> 0 | C14: =ROUND(Assumptions!$F$128*Assumptions!$F$129*Assumptions!$F$130*'P&L_5yr'!D9,0) -> 0 | D14: =ROUND(Assumptions!$F$128*Assumptions!$F$129*Assumptions!$F$130*'P&L_5yr'!E9,0) -> 0 | E14: =ROUND(Assumptions!$F$128*Assumptions!$F$129*Assumptions!$F$130*'P&L_5yr'!F9,0) -> 0 | F14: =ROUND(Assumptions!$F$128*Assumptions!$F$129*Assumptions!$F$130*'P&L_5yr'!G9,0) -> 0 | G14: =ROUND(Assumptions!$F$128*Assumptions!$F$129*Assumptions!$F$130*'P&L_5yr'!F9,0) -> 0
A15: Total additional revenue | B15: =ROUND(SUM(B5:B14),0) -> 7497 | C15: =ROUND(SUM(C5:C14),0) -> 114678 | D15: =ROUND(SUM(D5:D14),0) -> 238590 | E15: =ROUND(SUM(E5:E14),0) -> 422400 | F15: =ROUND(SUM(F5:F14),0) -> 830040 | G15: =ROUND(SUM(E5:E14),0) -> 422400
A17: RETAINED-RISK VARIABLE COSTS
A18: QA second-review cost | B18: =ROUND('P&L_5yr'!C7*Assumptions!$F$136*Assumptions!$F$137,0) -> 864 | C18: =ROUND('P&L_5yr'!D7*Assumptions!$F$136*Assumptions!$F$137,0) -> 4320 | D18: =ROUND('P&L_5yr'!E7*Assumptions!$F$136*Assumptions!$F$137,0) -> 14400 | E18: =ROUND('P&L_5yr'!F7*Assumptions!$F$136*Assumptions!$F$137,0) -> 36000 | F18: =ROUND('P&L_5yr'!G7*Assumptions!$F$136*Assumptions!$F$137,0) -> 86400 | G18: =ROUND('P&L_5yr'!F7*Assumptions!$F$136*Assumptions!$F$137,0) -> 36000
A19: External dispute forum cost | B19: =ROUND('P&L_5yr'!C7*Assumptions!$F$138*Assumptions!$F$139,0) -> 8100 | C19: =ROUND('P&L_5yr'!D7*Assumptions!$F$138*Assumptions!$F$139,0) -> 40500 | D19: =ROUND('P&L_5yr'!E7*Assumptions!$F$138*Assumptions!$F$139,0) -> 135000 | E19: =ROUND('P&L_5yr'!F7*Assumptions!$F$138*Assumptions!$F$139,0) -> 337500 | F19: =ROUND('P&L_5yr'!G7*Assumptions!$F$138*Assumptions!$F$139,0) -> 810000 | G19: =ROUND('P&L_5yr'!F7*Assumptions!$F$138*Assumptions!$F$139,0) -> 337500
A20: Operational error / wrongful-release reserve | B20: =ROUND('P&L_5yr'!C18*Assumptions!$F$140,0) -> 1075 | C20: =ROUND('P&L_5yr'!D18*Assumptions!$F$140,0) -> 5988 | D20: =ROUND('P&L_5yr'!E18*Assumptions!$F$140,0) -> 19593 | E20: =ROUND('P&L_5yr'!F18*Assumptions!$F$140,0) -> 52199 | F20: =ROUND('P&L_5yr'!G18*Assumptions!$F$140,0) -> 147403 | G20: =ROUND('P&L_5yr'!F18*Assumptions!$F$140,0) -> 52199
A21: Partner/channel commission | B21: =ROUND('P&L_5yr'!C18*Assumptions!$F$144,0) -> 5375 | C21: =ROUND('P&L_5yr'!D18*Assumptions!$F$144,0) -> 29939 | D21: =ROUND('P&L_5yr'!E18*Assumptions!$F$144,0) -> 97967 | E21: =ROUND('P&L_5yr'!F18*Assumptions!$F$144,0) -> 260993 | F21: =ROUND('P&L_5yr'!G18*Assumptions!$F$144,0) -> 737013 | G21: =ROUND('P&L_5yr'!F18*Assumptions!$F$144,0) -> 260993
A22: Fee collection leakage | B22: =ROUND((B7+B10+B12)*Assumptions!$F$145,0) -> 41 | C22: =ROUND((C7+C10+C12)*Assumptions!$F$145,0) -> 463 | D22: =ROUND((D7+D10+D12)*Assumptions!$F$145,0) -> 1148 | E22: =ROUND((E7+E10+E12)*Assumptions!$F$145,0) -> 2349 | F22: =ROUND((F7+F10+F12)*Assumptions!$F$145,0) -> 5000 | G22: =ROUND((E7+E10+E12)*Assumptions!$F$145,0) -> 2349
A23: Partner/API outage fallback | B23: =ROUND(Tier_Economics!C5*Assumptions!$F$146*Assumptions!$F$147,0) -> 182 | C23: =ROUND(Tier_Economics!G5*Assumptions!$F$146*Assumptions!$F$147,0) -> 911 | D23: =ROUND(Tier_Economics!K5*Assumptions!$F$146*Assumptions!$F$147,0) -> 2700 | E23: =ROUND(Tier_Economics!O5*Assumptions!$F$146*Assumptions!$F$147,0) -> 5400 | F23: =ROUND(Tier_Economics!S5*Assumptions!$F$146*Assumptions!$F$147,0) -> 10125 | G23: =ROUND(Tier_Economics!O5*Assumptions!$F$146*Assumptions!$F$147,0) -> 5400
A24: Total variable retained-risk costs | B24: =ROUND(SUM(B18:B23),0) -> 15637 | C24: =ROUND(SUM(C18:C23),0) -> 82121 | D24: =ROUND(SUM(D18:D23),0) -> 270808 | E24: =ROUND(SUM(E18:E23),0) -> 694441 | F24: =ROUND(SUM(F18:F23),0) -> 1795941 | G24: =ROUND(SUM(E18:E23),0) -> 694441
A26: RETAINED-RISK FIXED COSTS
A27: Carrier/eBL integration maintenance | B27: =ROUND(Assumptions!$F$132*1,0) -> 15000 | C27: =ROUND(Assumptions!$F$132*1.25,0) -> 18750 | D27: =ROUND(Assumptions!$F$132*1.5,0) -> 22500 | E27: =ROUND(Assumptions!$F$132*1.75,0) -> 26250 | F27: =ROUND(Assumptions!$F$132*2,0) -> 30000 | G27: =ROUND(Assumptions!$F$132*1.75,0) -> 26250
A28: Forensics partner retainer | B28: =ROUND(Assumptions!$F$133*1,0) -> 20000 | C28: =ROUND(Assumptions!$F$133*1.25,0) -> 25000 | D28: =ROUND(Assumptions!$F$133*1.5,0) -> 30000 | E28: =ROUND(Assumptions!$F$133*1.75,0) -> 35000 | F28: =ROUND(Assumptions!$F$133*2,0) -> 40000 | G28: =ROUND(Assumptions!$F$133*1.75,0) -> 35000
A29: Fraud database build / governance | B29: =ROUND(Assumptions!$F$134+Assumptions!$F$135,0) -> 55000 | C29: =ROUND(Assumptions!$F$135,0) -> 15000 | D29: =ROUND(Assumptions!$F$135,0) -> 15000 | E29: =ROUND(Assumptions!$F$135,0) -> 15000 | F29: =ROUND(Assumptions!$F$135,0) -> 15000 | G29: =ROUND(Assumptions!$F$135,0) -> 15000
A30: KMS / multisig / key security ops | B30: =ROUND(Assumptions!$F$142*1,0) -> 12000 | C30: =ROUND(Assumptions!$F$142*1.25,0) -> 15000 | D30: =ROUND(Assumptions!$F$142*1.5,0) -> 18000 | E30: =ROUND(Assumptions!$F$142*1.75,0) -> 21000 | F30: =ROUND(Assumptions!$F$142*2,0) -> 24000 | G30: =ROUND(Assumptions!$F$142*1.75,0) -> 21000
A31: Regulatory reporting ops | B31: =ROUND(Assumptions!$F$143*1,0) -> 18000 | C31: =ROUND(Assumptions!$F$143*1.25,0) -> 22500 | D31: =ROUND(Assumptions!$F$143*1.5,0) -> 27000 | E31: =ROUND(Assumptions!$F$143*1.75,0) -> 31500 | F31: =ROUND(Assumptions!$F$143*2,0) -> 36000 | G31: =ROUND(Assumptions!$F$143*1.75,0) -> 31500
A32: Insurance deductible reserve | B32: =ROUND(Assumptions!$F$141,0) -> 15000 | C32: =ROUND(Assumptions!$F$141,0) -> 15000 | D32: =ROUND(Assumptions!$F$141,0) -> 15000 | E32: =ROUND(Assumptions!$F$141,0) -> 15000 | F32: =ROUND(Assumptions!$F$141,0) -> 15000 | G32: =ROUND(Assumptions!$F$141,0) -> 15000
A33: Smart contract incident reserve | B33: =ROUND(Assumptions!$F$148*1,0) -> 30000 | C33: =ROUND(Assumptions!$F$148*1,0) -> 30000 | D33: =ROUND(Assumptions!$F$148*1,0) -> 30000 | E33: =ROUND(Assumptions!$F$148*1.25,0) -> 37500 | F33: =ROUND(Assumptions!$F$148*1.5,0) -> 45000 | G33: =ROUND(Assumptions!$F$148*1.25,0) -> 37500
A34: Liability wording legal review | B34: =ROUND(Assumptions!$F$152,0) -> 7500 | C34: =ROUND(0,0) -> 0 | D34: =ROUND(0,0) -> 0 | E34: =ROUND(0,0) -> 0 | F34: =ROUND(0,0) -> 0 | G34: =ROUND(0,0) -> 0
A35: Document-source indemnity legal review | B35: =ROUND(Assumptions!$F$153,0) -> 7500 | C35: =ROUND(0,0) -> 0 | D35: =ROUND(0,0) -> 0 | E35: =ROUND(0,0) -> 0 | F35: =ROUND(0,0) -> 0 | G35: =ROUND(0,0) -> 0
A36: Total fixed retained-risk costs | B36: =ROUND(SUM(B27:B35),0) -> 180000 | C36: =ROUND(SUM(C27:C35),0) -> 141250 | D36: =ROUND(SUM(D27:D35),0) -> 157500 | E36: =ROUND(SUM(E27:E35),0) -> 181250 | F36: =ROUND(SUM(F27:F35),0) -> 205000 | G36: =ROUND(SUM(E27:E35),0) -> 181250
A38: FUNDING / CONTINGENCY ONLY
A39: Regulatory delay contingency | B39: =ROUND(Assumptions!$F$149*Assumptions!$F$150,0) -> 240000 | C39: =ROUND(0,0) -> 0 | D39: =ROUND(0,0) -> 0 | E39: =ROUND(0,0) -> 0 | F39: =ROUND(0,0) -> 0 | G39: =ROUND(0,0) -> 0
A40: Delivery/performance liability reserve | B40: =ROUND(Assumptions!$F$151,0) -> 0 | C40: =ROUND(Assumptions!$F$151,0) -> 0 | D40: =ROUND(Assumptions!$F$151,0) -> 0 | E40: =ROUND(Assumptions!$F$151,0) -> 0 | F40: =ROUND(Assumptions!$F$151,0) -> 0 | G40: =ROUND(Assumptions!$F$151,0) -> 0
A41: Total funding-only contingency | B41: =ROUND(SUM(B39:B40),0) -> 240000 | C41: =ROUND(SUM(C39:C40),0) -> 0 | D41: =ROUND(SUM(D39:D40),0) -> 0 | E41: =ROUND(SUM(E39:E40),0) -> 0 | F41: =ROUND(SUM(F39:F40),0) -> 0 | G41: =ROUND(SUM(E39:E40),0) -> 0
A43: DOCUMENTS-NOT-GOODS POSITIONING
A44: Goods delivery / quality / performance risk | B44: Excluded reserve | C44: Excluded | D44: Excluded | E44: Excluded | F44: Excluded | G44: Documents-not-goods boundary; buyer/seller/carrier/insurer risk
A45: Document verification / wrongful release risk | B45: Retained and priced | C45: Retained | D45: Retained | E45: Operational/process error reserve + insurance/deductible reserve | G45: Operational/process error reserve + insurance/deductible reserve
A46: Carrier/eBL/API source failure risk | B46: Retained operationally | C46: Retained | D46: Retained | E46: Partner contracts, uptime SLAs, manual fallback cost | G46: Partner contracts, uptime SLAs, manual fallback cost
A47: Tier C paper/originals risk | B47: High-cost fallback | C47: High | D47: High | E47: Tier C priced up and margin-tested | G47: Tier C priced up and margin-tested
A48: Contractual risk posture | B48: Against documents | C48: Core premise | D48: Core premise | E48: Mirrors LC logic; legal review still required | G48: Mirrors LC logic; legal review still required

Sheet Scenario_Low_Tiers
A1: Tier Economics - revenue, cost and risk by document-intake tier
A3: Metric | B3: Tier A eBL Y1 | C3: Tier B API Y1 | D3: Tier C Paper Y1 | E3: Total Y1 | F3: Tier A eBL Y2 | G3: Tier B API Y2 | H3: Tier C Paper Y2 | I3: Total Y2 | J3: Tier A eBL Y3 | K3: Tier B API Y3 | L3: Tier C Paper Y3 | M3: Total Y3 | N3: Tier A eBL Y4 | O3: Tier B API Y4 | P3: Tier C Paper Y4 | Q3: Total Y4 | R3: Tier A eBL Y5 | S3: Tier B API Y5 | T3: Tier C Paper Y5 | U3: Total Y5
A4: Tier mix | B4: =Assumptions!$C$64 -> 0.05 | C4: =Assumptions!$C$65 -> 0.25 | D4: =Assumptions!$C$66 -> 0.7 | E4: =SUM(B4:D4) -> 1 | F4: =Assumptions!$C$67 -> 0.1 | G4: =Assumptions!$C$68 -> 0.35 | H4: =Assumptions!$C$69 -> 0.55 | I4: =SUM(F4:H4) -> 1 | J4: =Assumptions!$C$70 -> 0.2 | K4: =Assumptions!$C$71 -> 0.4 | L4: =Assumptions!$C$72 -> 0.4 | M4: =SUM(J4:L4) -> 1 | N4: =Assumptions!$C$157 -> 0.3 | O4: =Assumptions!$C$158 -> 0.45 | P4: =Assumptions!$C$159 -> 0.25 | Q4: =SUM(N4:P4) -> 1 | R4: =Assumptions!$C$160 -> 0.4 | S4: =Assumptions!$C$161 -> 0.45 | T4: =Assumptions!$C$162 -> 0.15 | U4: =SUM(R4:T4) -> 1
A5: Deals | B5: =Scenario_Low_PL!$C$7*B4 -> 3 | C5: =Scenario_Low_PL!$C$7*C4 -> 15 | D5: =Scenario_Low_PL!$C$7*D4 -> 42 | E5: =SUM(B5:D5) -> 60 | F5: =Scenario_Low_PL!$D$7*F4 -> 30 | G5: =Scenario_Low_PL!$D$7*G4 -> 105 | H5: =Scenario_Low_PL!$D$7*H4 -> 165 | I5: =SUM(F5:H5) -> 300 | J5: =Scenario_Low_PL!$E$7*J4 -> 180 | K5: =Scenario_Low_PL!$E$7*K4 -> 360 | L5: =Scenario_Low_PL!$E$7*L4 -> 360 | M5: =SUM(J5:L5) -> 900 | N5: =Scenario_Low_PL!$F$7*N4 -> 540 | O5: =Scenario_Low_PL!$F$7*O4 -> 810 | P5: =Scenario_Low_PL!$F$7*P4 -> 450 | Q5: =SUM(N5:P5) -> 1800 | R5: =Scenario_Low_PL!$G$7*R4 -> 2400 | S5: =Scenario_Low_PL!$G$7*S4 -> 2700 | T5: =Scenario_Low_PL!$G$7*T4 -> 900 | U5: =SUM(R5:T5) -> 6000
A6: Docs per deal | B6: =Assumptions!$F$106 -> 3 | C6: =Assumptions!$F$107 -> 6 | D6: =Assumptions!$F$108 -> 9 | E6: =IF(E5=0,0,E7/E5) -> 7.95 | F6: =Assumptions!$F$106 -> 3 | G6: =Assumptions!$F$107 -> 6 | H6: =Assumptions!$F$108 -> 9 | I6: =IF(I5=0,0,I7/I5) -> 7.35 | J6: =Assumptions!$F$106 -> 3 | K6: =Assumptions!$F$107 -> 6 | L6: =Assumptions!$F$108 -> 9 | M6: =IF(M5=0,0,M7/M5) -> 6.6 | N6: =Assumptions!$F$106 -> 3 | O6: =Assumptions!$F$107 -> 6 | P6: =Assumptions!$F$108 -> 9 | Q6: =IF(Q5=0,0,Q7/Q5) -> 5.85 | R6: =Assumptions!$F$106 -> 3 | S6: =Assumptions!$F$107 -> 6 | T6: =Assumptions!$F$108 -> 9 | U6: =IF(U5=0,0,U7/U5) -> 5.25
A7: Documents processed | B7: =B5*B6 -> 9 | C7: =C5*C6 -> 90 | D7: =D5*D6 -> 378 | E7: =SUM(B7:D7) -> 477 | F7: =F5*F6 -> 90 | G7: =G5*G6 -> 630 | H7: =H5*H6 -> 1485 | I7: =SUM(F7:H7) -> 2205 | J7: =J5*J6 -> 540 | K7: =K5*K6 -> 2160 | L7: =L5*L6 -> 3240 | M7: =SUM(J7:L7) -> 5940 | N7: =N5*N6 -> 1620 | O7: =O5*O6 -> 4860 | P7: =P5*P6 -> 4050 | Q7: =SUM(N7:P7) -> 10530 | R7: =R5*R6 -> 7200 | S7: =S5*S6 -> 16200 | T7: =T5*T6 -> 8100 | U7: =SUM(R7:T7) -> 31500
A8: Avg deal value | B8: =Scenario_Low_PL!$C$8 -> 30000 | C8: =Scenario_Low_PL!$C$8 -> 30000 | D8: =Scenario_Low_PL!$C$8 -> 30000 | E8: =Scenario_Low_PL!$C$8 -> 30000 | F8: =Scenario_Low_PL!$D$8 -> 40500 | G8: =Scenario_Low_PL!$D$8 -> 40500 | H8: =Scenario_Low_PL!$D$8 -> 40500 | I8: =Scenario_Low_PL!$D$8 -> 40500 | J8: =Scenario_Low_PL!$E$8 -> 54675 | K8: =Scenario_Low_PL!$E$8 -> 54675 | L8: =Scenario_Low_PL!$E$8 -> 54675 | M8: =Scenario_Low_PL!$E$8 -> 54675 | N8: =Scenario_Low_PL!$F$8 -> 73811.25 | O8: =Scenario_Low_PL!$F$8 -> 73811.25 | P8: =Scenario_Low_PL!$F$8 -> 73811.25 | Q8: =Scenario_Low_PL!$F$8 -> 73811.25 | R8: =Scenario_Low_PL!$G$8 -> 99645.188 | S8: =Scenario_Low_PL!$G$8 -> 99645.188 | T8: =Scenario_Low_PL!$G$8 -> 99645.188 | U8: =Scenario_Low_PL!$G$8 -> 99645.188
A9: GMV | B9: =B5*B8 -> 90000 | C9: =C5*C8 -> 450000 | D9: =D5*D8 -> 1260000 | E9: =SUM(B9:D9) -> 1800000 | F9: =F5*F8 -> 1215000 | G9: =G5*G8 -> 4252500 | H9: =H5*H8 -> 6682500 | I9: =SUM(F9:H9) -> 12150000 | J9: =J5*J8 -> 9841500 | K9: =K5*K8 -> 19683000 | L9: =L5*L8 -> 19683000 | M9: =SUM(J9:L9) -> 49207500 | N9: =N5*N8 -> 39858075 | O9: =O5*O8 -> 59787112 | P9: =P5*P8 -> 33215062 | Q9: =SUM(N9:P9) -> 132860250 | R9: =R5*R8 -> 239148450 | S9: =S5*S8 -> 2.6904201e+08 | T9: =T5*T8 -> 89680669 | U9: =SUM(R9:T9) -> 597871125
A10: Escrow take rate | B10: =Assumptions!$F$73 -> 0.006 | C10: =Assumptions!$F$74 -> 0.0085 | D10: =Assumptions!$F$75 -> 0.015 | E10: =IF(E9=0,0,SUM(B9*B10,C9*C10,D9*D10)/E9) -> 0.012925 | F10: =Assumptions!$F$73 -> 0.006 | G10: =Assumptions!$F$74 -> 0.0085 | H10: =Assumptions!$F$75 -> 0.015 | I10: =IF(I9=0,0,SUM(F9*F10,G9*G10,H9*H10)/I9) -> 0.011825 | J10: =Assumptions!$F$73 -> 0.006 | K10: =Assumptions!$F$74 -> 0.0085 | L10: =Assumptions!$F$75 -> 0.015 | M10: =IF(M9=0,0,SUM(J9*J10,K9*K10,L9*L10)/M9) -> 0.0106 | N10: =Assumptions!$F$73 -> 0.006 | O10: =Assumptions!$F$74 -> 0.0085 | P10: =Assumptions!$F$75 -> 0.015 | Q10: =IF(Q9=0,0,SUM(N9*N10,O9*O10,P9*P10)/Q9) -> 0.009375 | R10: =Assumptions!$F$73 -> 0.006 | S10: =Assumptions!$F$74 -> 0.0085 | T10: =Assumptions!$F$75 -> 0.015 | U10: =IF(U9=0,0,SUM(R9*R10,S9*S10,T9*T10)/U9) -> 0.008475
A11: Minimum escrow fee | B11: =Assumptions!$F$76 -> 150 | C11: =Assumptions!$F$77 -> 250 | D11: =Assumptions!$F$78 -> 500 | E11: =IF(E5=0,0,SUM(B5*B11,C5*C11,D5*D11)/E5) -> 420 | F11: =Assumptions!$F$76 -> 150 | G11: =Assumptions!$F$77 -> 250 | H11: =Assumptions!$F$78 -> 500 | I11: =IF(I5=0,0,SUM(F5*F11,G5*G11,H5*H11)/I5) -> 377.5 | J11: =Assumptions!$F$76 -> 150 | K11: =Assumptions!$F$77 -> 250 | L11: =Assumptions!$F$78 -> 500 | M11: =IF(M5=0,0,SUM(J5*J11,K5*K11,L5*L11)/M5) -> 330 | N11: =Assumptions!$F$76 -> 150 | O11: =Assumptions!$F$77 -> 250 | P11: =Assumptions!$F$78 -> 500 | Q11: =IF(Q5=0,0,SUM(N5*N11,O5*O11,P5*P11)/Q5) -> 282.5 | R11: =Assumptions!$F$76 -> 150 | S11: =Assumptions!$F$77 -> 250 | T11: =Assumptions!$F$78 -> 500 | U11: =IF(U5=0,0,SUM(R5*R11,S5*S11,T5*T11)/U5) -> 247.5
A12: Escrow fee revenue | B12: =B5*MAX(B8*B10,B11) -> 540 | C12: =C5*MAX(C8*C10,C11) -> 3825 | D12: =D5*MAX(D8*D10,D11) -> 21000 | E12: =SUM(B12:D12) -> 25365 | F12: =F5*MAX(F8*F10,F11) -> 7290 | G12: =G5*MAX(G8*G10,G11) -> 36146.25 | H12: =H5*MAX(H8*H10,H11) -> 100237.5 | I12: =SUM(F12:H12) -> 143673.75 | J12: =J5*MAX(J8*J10,J11) -> 59049 | K12: =K5*MAX(K8*K10,K11) -> 167305.5 | L12: =L5*MAX(L8*L10,L11) -> 295245 | M12: =SUM(J12:L12) -> 521599.5 | N12: =N5*MAX(N8*N10,N11) -> 239148.45 | O12: =O5*MAX(O8*O10,O11) -> 508190.46 | P12: =P5*MAX(P8*P10,P11) -> 498225.94 | Q12: =SUM(N12:P12) -> 1245564.8 | R12: =R5*MAX(R8*R10,R11) -> 1434890.7 | S12: =S5*MAX(S8*S10,S11) -> 2286857.1 | T12: =T5*MAX(T8*T10,T11) -> 1345210 | U12: =SUM(R12:T12) -> 5066957.8
A13: Doc/review fee per deal | B13: =Assumptions!$F$79 -> 25 | C13: =Assumptions!$F$80 -> 90 | D13: =Assumptions!$F$81 -> 300 | E13: =IF(E5=0,0,SUM(B5*B13,C5*C13,D5*D13)/E5) -> 233.75 | F13: =Assumptions!$F$79 -> 25 | G13: =Assumptions!$F$80 -> 90 | H13: =Assumptions!$F$81 -> 300 | I13: =IF(I5=0,0,SUM(F5*F13,G5*G13,H5*H13)/I5) -> 199 | J13: =Assumptions!$F$79 -> 25 | K13: =Assumptions!$F$80 -> 90 | L13: =Assumptions!$F$81 -> 300 | M13: =IF(M5=0,0,SUM(J5*J13,K5*K13,L5*L13)/M5) -> 161 | N13: =Assumptions!$F$79 -> 25 | O13: =Assumptions!$F$80 -> 90 | P13: =Assumptions!$F$81 -> 300 | Q13: =IF(Q5=0,0,SUM(N5*N13,O5*O13,P5*P13)/Q5) -> 123 | R13: =Assumptions!$F$79 -> 25 | S13: =Assumptions!$F$80 -> 90 | T13: =Assumptions!$F$81 -> 300 | U13: =IF(U5=0,0,SUM(R5*R13,S5*S13,T5*T13)/U5) -> 95.5
A14: Doc/review revenue | B14: =B5*B13 -> 75 | C14: =C5*C13 -> 1350 | D14: =D5*D13 -> 12600 | E14: =SUM(B14:D14) -> 14025 | F14: =F5*F13 -> 750 | G14: =G5*G13 -> 9450 | H14: =H5*H13 -> 49500 | I14: =SUM(F14:H14) -> 59700 | J14: =J5*J13 -> 4500 | K14: =K5*K13 -> 32400 | L14: =L5*L13 -> 108000 | M14: =SUM(J14:L14) -> 144900 | N14: =N5*N13 -> 13500 | O14: =O5*O13 -> 72900 | P14: =P5*P13 -> 135000 | Q14: =SUM(N14:P14) -> 221400 | R14: =R5*R13 -> 60000 | S14: =S5*S13 -> 243000 | T14: =T5*T13 -> 270000 | U14: =SUM(R14:T14) -> 573000
A15: Dispute rate | B15: =Assumptions!$F$94 -> 0.04 | C15: =Assumptions!$F$95 -> 0.1 | D15: =Assumptions!$F$96 -> 0.2 | E15: =IF(E5=0,0,E16/E5) -> 0.167 | F15: =Assumptions!$F$94 -> 0.04 | G15: =Assumptions!$F$95 -> 0.1 | H15: =Assumptions!$F$96 -> 0.2 | I15: =IF(I5=0,0,I16/I5) -> 0.149 | J15: =Assumptions!$F$94 -> 0.04 | K15: =Assumptions!$F$95 -> 0.1 | L15: =Assumptions!$F$96 -> 0.2 | M15: =IF(M5=0,0,M16/M5) -> 0.128 | N15: =Assumptions!$F$94 -> 0.04 | O15: =Assumptions!$F$95 -> 0.1 | P15: =Assumptions!$F$96 -> 0.2 | Q15: =IF(Q5=0,0,Q16/Q5) -> 0.107 | R15: =Assumptions!$F$94 -> 0.04 | S15: =Assumptions!$F$95 -> 0.1 | T15: =Assumptions!$F$96 -> 0.2 | U15: =IF(U5=0,0,U16/U5) -> 0.091
A16: Disputed deals | B16: =B5*B15 -> 0.12 | C16: =C5*C15 -> 1.5 | D16: =D5*D15 -> 8.4 | E16: =SUM(B16:D16) -> 10.02 | F16: =F5*F15 -> 1.2 | G16: =G5*G15 -> 10.5 | H16: =H5*H15 -> 33 | I16: =SUM(F16:H16) -> 44.7 | J16: =J5*J15 -> 7.2 | K16: =K5*K15 -> 36 | L16: =L5*L15 -> 72 | M16: =SUM(J16:L16) -> 115.2 | N16: =N5*N15 -> 21.6 | O16: =O5*O15 -> 81 | P16: =P5*P15 -> 90 | Q16: =SUM(N16:P16) -> 192.6 | R16: =R5*R15 -> 96 | S16: =S5*S15 -> 270 | T16: =T5*T15 -> 180 | U16: =SUM(R16:T16) -> 546
A17: Dispute/amendment fee | B17: =Assumptions!$F$82 -> 100 | C17: =Assumptions!$F$83 -> 200 | D17: =Assumptions!$F$84 -> 500 | E17: =IF(E16=0,0,SUM(B16*B17,C16*C17,D16*D17)/E16) -> 450.2994 | F17: =Assumptions!$F$82 -> 100 | G17: =Assumptions!$F$83 -> 200 | H17: =Assumptions!$F$84 -> 500 | I17: =IF(I16=0,0,SUM(F16*F17,G16*G17,H16*H17)/I16) -> 418.79195 | J17: =Assumptions!$F$82 -> 100 | K17: =Assumptions!$F$83 -> 200 | L17: =Assumptions!$F$84 -> 500 | M17: =IF(M16=0,0,SUM(J16*J17,K16*K17,L16*L17)/M16) -> 381.25 | N17: =Assumptions!$F$82 -> 100 | O17: =Assumptions!$F$83 -> 200 | P17: =Assumptions!$F$84 -> 500 | Q17: =IF(Q16=0,0,SUM(N16*N17,O16*O17,P16*P17)/Q16) -> 328.97196 | R17: =Assumptions!$F$82 -> 100 | S17: =Assumptions!$F$83 -> 200 | T17: =Assumptions!$F$84 -> 500 | U17: =IF(U16=0,0,SUM(R16*R17,S16*S17,T16*T17)/U16) -> 281.31868
A18: Dispute/amendment revenue | B18: =B16*B17 -> 12 | C18: =C16*C17 -> 300 | D18: =D16*D17 -> 4200 | E18: =SUM(B18:D18) -> 4512 | F18: =F16*F17 -> 120 | G18: =G16*G17 -> 2100 | H18: =H16*H17 -> 16500 | I18: =SUM(F18:H18) -> 18720 | J18: =J16*J17 -> 720 | K18: =K16*K17 -> 7200 | L18: =L16*L17 -> 36000 | M18: =SUM(J18:L18) -> 43920 | N18: =N16*N17 -> 2160 | O18: =O16*O17 -> 16200 | P18: =P16*P17 -> 45000 | Q18: =SUM(N18:P18) -> 63360 | R18: =R16*R17 -> 9600 | S18: =S16*S17 -> 54000 | T18: =T16*T17 -> 90000 | U18: =SUM(R18:T18) -> 153600
A19: External eBL/API/paper cost | B19: =B5*Assumptions!$F$85 -> 9 | C19: =C5*Assumptions!$F$86 -> 150 | D19: =D5*Assumptions!$F$87 -> 6300 | E19: =SUM(B19:D19) -> 6459 | F19: =F5*Assumptions!$F$85 -> 90 | G19: =G5*Assumptions!$F$86 -> 1050 | H19: =H5*Assumptions!$F$87 -> 24750 | I19: =SUM(F19:H19) -> 25890 | J19: =J5*Assumptions!$F$85 -> 540 | K19: =K5*Assumptions!$F$86 -> 3600 | L19: =L5*Assumptions!$F$87 -> 54000 | M19: =SUM(J19:L19) -> 58140 | N19: =N5*Assumptions!$F$85 -> 1620 | O19: =O5*Assumptions!$F$86 -> 8100 | P19: =P5*Assumptions!$F$87 -> 67500 | Q19: =SUM(N19:P19) -> 77220 | R19: =R5*Assumptions!$F$85 -> 7200 | S19: =S5*Assumptions!$F$86 -> 27000 | T19: =T5*Assumptions!$F$87 -> 135000 | U19: =SUM(R19:T19) -> 169200
A20: Human review cost | B20: =B5*Assumptions!$F$88 -> 9 | C20: =C5*Assumptions!$F$89 -> 300 | D20: =D5*Assumptions!$F$90 -> 5040 | E20: =SUM(B20:D20) -> 5349 | F20: =F5*Assumptions!$F$88 -> 90 | G20: =G5*Assumptions!$F$89 -> 2100 | H20: =H5*Assumptions!$F$90 -> 19800 | I20: =SUM(F20:H20) -> 21990 | J20: =J5*Assumptions!$F$88 -> 540 | K20: =K5*Assumptions!$F$89 -> 7200 | L20: =L5*Assumptions!$F$90 -> 43200 | M20: =SUM(J20:L20) -> 50940 | N20: =N5*Assumptions!$F$88 -> 1620 | O20: =O5*Assumptions!$F$89 -> 16200 | P20: =P5*Assumptions!$F$90 -> 54000 | Q20: =SUM(N20:P20) -> 71820 | R20: =R5*Assumptions!$F$88 -> 7200 | S20: =S5*Assumptions!$F$89 -> 54000 | T20: =T5*Assumptions!$F$90 -> 108000 | U20: =SUM(R20:T20) -> 169200
A21: Support cost | B21: =B5*Assumptions!$F$91 -> 6 | C21: =C5*Assumptions!$F$92 -> 90 | D21: =D5*Assumptions!$F$93 -> 840 | E21: =SUM(B21:D21) -> 936 | F21: =F5*Assumptions!$F$91 -> 60 | G21: =G5*Assumptions!$F$92 -> 630 | H21: =H5*Assumptions!$F$93 -> 3300 | I21: =SUM(F21:H21) -> 3990 | J21: =J5*Assumptions!$F$91 -> 360 | K21: =K5*Assumptions!$F$92 -> 2160 | L21: =L5*Assumptions!$F$93 -> 7200 | M21: =SUM(J21:L21) -> 9720 | N21: =N5*Assumptions!$F$91 -> 1080 | O21: =O5*Assumptions!$F$92 -> 4860 | P21: =P5*Assumptions!$F$93 -> 9000 | Q21: =SUM(N21:P21) -> 14940 | R21: =R5*Assumptions!$F$91 -> 4800 | S21: =S5*Assumptions!$F$92 -> 16200 | T21: =T5*Assumptions!$F$93 -> 18000 | U21: =SUM(R21:T21) -> 39000
A22: Dispute handling cost | B22: =B16*Assumptions!$F$97 -> 7.2 | C22: =C16*Assumptions!$F$98 -> 180 | D22: =D16*Assumptions!$F$99 -> 2940 | E22: =SUM(B22:D22) -> 3127.2 | F22: =F16*Assumptions!$F$97 -> 72 | G22: =G16*Assumptions!$F$98 -> 1260 | H22: =H16*Assumptions!$F$99 -> 11550 | I22: =SUM(F22:H22) -> 12882 | J22: =J16*Assumptions!$F$97 -> 432 | K22: =K16*Assumptions!$F$98 -> 4320 | L22: =L16*Assumptions!$F$99 -> 25200 | M22: =SUM(J22:L22) -> 29952 | N22: =N16*Assumptions!$F$97 -> 1296 | O22: =O16*Assumptions!$F$98 -> 9720 | P22: =P16*Assumptions!$F$99 -> 31500 | Q22: =SUM(N22:P22) -> 42516 | R22: =R16*Assumptions!$F$97 -> 5760 | S22: =S16*Assumptions!$F$98 -> 32400 | T22: =T16*Assumptions!$F$99 -> 63000 | U22: =SUM(R22:T22) -> 101160
A23: Total tier-specific COGS | B23: =SUM(B19:B22) -> 31.2 | C23: =SUM(C19:C22) -> 720 | D23: =SUM(D19:D22) -> 15120 | E23: =SUM(B23:D23) -> 15871.2 | F23: =SUM(F19:F22) -> 312 | G23: =SUM(G19:G22) -> 5040 | H23: =SUM(H19:H22) -> 59400 | I23: =SUM(F23:H23) -> 64752 | J23: =SUM(J19:J22) -> 1872 | K23: =SUM(K19:K22) -> 17280 | L23: =SUM(L19:L22) -> 129600 | M23: =SUM(J23:L23) -> 148752 | N23: =SUM(N19:N22) -> 5616 | O23: =SUM(O19:O22) -> 38880 | P23: =SUM(P19:P22) -> 162000 | Q23: =SUM(N23:P23) -> 206496 | R23: =SUM(R19:R22) -> 24960 | S23: =SUM(S19:S22) -> 129600 | T23: =SUM(T19:T22) -> 324000 | U23: =SUM(R23:T23) -> 478560
A24: Tier revenue | B24: =SUM(B12,B14,B18) -> 627 | C24: =SUM(C12,C14,C18) -> 5475 | D24: =SUM(D12,D14,D18) -> 37800 | E24: =SUM(B24:D24) -> 43902 | F24: =SUM(F12,F14,F18) -> 8160 | G24: =SUM(G12,G14,G18) -> 47696.25 | H24: =SUM(H12,H14,H18) -> 166237.5 | I24: =SUM(F24:H24) -> 222093.75 | J24: =SUM(J12,J14,J18) -> 64269 | K24: =SUM(K12,K14,K18) -> 206905.5 | L24: =SUM(L12,L14,L18) -> 439245 | M24: =SUM(J24:L24) -> 710419.5 | N24: =SUM(N12,N14,N18) -> 254808.45 | O24: =SUM(O12,O14,O18) -> 597290.46 | P24: =SUM(P12,P14,P18) -> 678225.94 | Q24: =SUM(N24:P24) -> 1530324.8 | R24: =SUM(R12,R14,R18) -> 1504490.7 | S24: =SUM(S12,S14,S18) -> 2583857.1 | T24: =SUM(T12,T14,T18) -> 1705210 | U24: =SUM(R24:T24) -> 5793557.8
A25: Gross profit before shared COGS | B25: =B24-B23 -> 595.8 | C25: =C24-C23 -> 4755 | D25: =D24-D23 -> 22680 | E25: =E24-E23 -> 28030.8 | F25: =F24-F23 -> 7848 | G25: =G24-G23 -> 42656.25 | H25: =H24-H23 -> 106837.5 | I25: =I24-I23 -> 157341.75 | ... U25: =U24-U23 -> 5314997.8
A26: Gross margin | B26: =IF(B24=0,0,B25/B24) -> 0.95023923 | C26: =IF(C24=0,0,C25/C24) -> 0.86849315 | D26: =IF(D24=0,0,D25/D24) -> 0.6 | E26: =IF(E24=0,0,E25/E24) -> 0.63848572 | F26: =IF(F24=0,0,F25/F24) -> 0.96176471 | G26: =IF(G24=0,0,G25/G24) -> 0.89433132 | H26: =IF(H24=0,0,H25/H24) -> 0.6426799 | I26: =IF(I24=0,0,I25/I24) -> 0.70844745 | ... U26: =IF(U24=0,0,U25/U24) -> 0.91739791
A27: Weighted risk score | B27: =B4*Assumptions!$F$100 -> 0.05 | C27: =C4*Assumptions!$F$101 -> 0.75 | D27: =D4*Assumptions!$F$102 -> 3.5 | E27: =SUM(B27:D27) -> 4.3 | F27: =F4*Assumptions!$F$100 -> 0.1 | G27: =G4*Assumptions!$F$101 -> 1.05 | H27: =H4*Assumptions!$F$102 -> 2.75 | I27: =SUM(F27:H27) -> 3.9 | J27: =J4*Assumptions!$F$100 -> 0.2 | K27: =K4*Assumptions!$F$101 -> 1.2 | L27: =L4*Assumptions!$F$102 -> 2 | M27: =SUM(J27:L27) -> 3.4 | N27: =N4*Assumptions!$F$100 -> 0.3 | O27: =O4*Assumptions!$F$101 -> 1.35 | P27: =P4*Assumptions!$F$102 -> 1.25 | Q27: =SUM(N27:P27) -> 2.9 | R27: =R4*Assumptions!$F$100 -> 0.4 | S27: =S4*Assumptions!$F$101 -> 1.35 | T27: =T4*Assumptions!$F$102 -> 0.75 | U27: =SUM(R27:T27) -> 2.5
A28: SLA days | B28: =Assumptions!$F$103 -> 0.05 | C28: =Assumptions!$F$104 -> 0.5 | D28: =Assumptions!$F$105 -> 7 | E28: =IF(E5=0,0,SUM(B5*B28,C5*C28,D5*D28)/E5) -> 5.0275 | F28: =Assumptions!$F$103 -> 0.05 | G28: =Assumptions!$F$104 -> 0.5 | H28: =Assumptions!$F$105 -> 7 | I28: =IF(I5=0,0,SUM(F5*F28,G5*G28,H5*H28)/I5) -> 4.03 | J28: =Assumptions!$F$103 -> 0.05 | K28: =Assumptions!$F$104 -> 0.5 | L28: =Assumptions!$F$105 -> 7 | M28: =IF(M5=0,0,SUM(J5*J28,K5*K28,L5*L28)/M5) -> 3.01 | N28: =Assumptions!$F$103 -> 0.05 | O28: =Assumptions!$F$104 -> 0.5 | P28: =Assumptions!$F$105 -> 7 | Q28: =IF(Q5=0,0,SUM(N5*N28,O5*O28,P5*P28)/Q5) -> 1.99 | R28: =Assumptions!$F$103 -> 0.05 | S28: =Assumptions!$F$104 -> 0.5 | T28: =Assumptions!$F$105 -> 7 | U28: =IF(U5=0,0,SUM(R5*R28,S5*S28,T5*T28)/U5) -> 1.295
A29: Tier mix sums check | E29: =IF(ABS(E4-1)<0.0001,"OK","CHECK MIX") -> OK | I29: =IF(ABS(I4-1)<0.0001,"OK","CHECK MIX") -> OK | M29: =IF(ABS(M4-1)<0.0001,"OK","CHECK MIX") -> OK | Q29: =IF(ABS(Q4-1)<0.0001,"OK","CHECK MIX") -> OK | U29: =IF(ABS(U4-1)<0.0001,"OK","CHECK MIX") -> OK
A30: Pricing / risk profile | B30: Fastest / lowest risk | C30: Core verified tier | D30: Highest cost / highest risk | E30: Portfolio blend | F30: Fastest / lowest risk | G30: Core verified tier | H30: Highest cost / highest risk | I30: Portfolio blend | J30: Fastest / lowest risk | K30: Core verified tier | L30: Highest cost / highest risk | M30: Portfolio blend | N30: Fastest / lowest risk | O30: Core verified tier | P30: Highest cost / highest risk | Q30: Portfolio blend | R30: Fastest / lowest risk | S30: Core verified tier | T30: Highest cost / highest risk | U30: Portfolio blend

Sheet Scenario_Low_AddOns
A1: Revenue add-ons and retained-risk offsets
A3: Line item | B3: Year 1 | C3: Year 2 | D3: Year 3 | E3: Year 4 | F3: Year 5 | G3: Logic / note
A4: REVENUE ADD-ONS
A5: First-deal discount drag | B5: =IF(1=1,IFERROR(ROUND(-MIN(Scenario_Low_PL!C7,Scenario_Low_PL!C70)*(Scenario_Low_PL!C14/Scenario_Low_PL!C7)*Assumptions!$F$115,0),0),0) -> -8455 | C5: =IF(2=1,IFERROR(ROUND(-MIN(Scenario_Low_PL!D7,Scenario_Low_PL!D70)*(Scenario_Low_PL!D14/Scenario_Low_PL!D7)*Assumptions!$F$115,0),0),0) -> 0 | D5: =IF(3=1,IFERROR(ROUND(-MIN(Scenario_Low_PL!E7,Scenario_Low_PL!E70)*(Scenario_Low_PL!E14/Scenario_Low_PL!E7)*Assumptions!$F$115,0),0),0) -> 0 | E5: =IF(4=1,IFERROR(ROUND(-MIN(Scenario_Low_PL!F7,Scenario_Low_PL!F70)*(Scenario_Low_PL!F14/Scenario_Low_PL!F7)*Assumptions!$F$115,0),0),0) -> 0 | F5: =IF(5=1,IFERROR(ROUND(-MIN(Scenario_Low_PL!G7,Scenario_Low_PL!G70)*(Scenario_Low_PL!G14/Scenario_Low_PL!G7)*Assumptions!$F$115,0),0),0) -> 0 | G5: =IF(4=1,IFERROR(ROUND(-MIN(Scenario_Low_PL!F7,Scenario_Low_PL!F70)*(Scenario_Low_PL!F14/Scenario_Low_PL!F7)*Assumptions!$F$115,0),0),0) -> 0
A6: Expedited review fees | B6: =ROUND(Scenario_Low_Tiers!C5*Assumptions!$F$116*Assumptions!$F$118+Scenario_Low_Tiers!D5*Assumptions!$F$117*Assumptions!$F$119,0) -> 2745 | C6: =ROUND(Scenario_Low_Tiers!G5*Assumptions!$F$116*Assumptions!$F$118+Scenario_Low_Tiers!H5*Assumptions!$F$117*Assumptions!$F$119,0) -> 11475 | D6: =ROUND(Scenario_Low_Tiers!K5*Assumptions!$F$116*Assumptions!$F$118+Scenario_Low_Tiers!L5*Assumptions!$F$117*Assumptions!$F$119,0) -> 27000 | E6: =ROUND(Scenario_Low_Tiers!O5*Assumptions!$F$116*Assumptions!$F$118+Scenario_Low_Tiers!P5*Assumptions!$F$117*Assumptions!$F$119,0) -> 39150 | F6: =ROUND(Scenario_Low_Tiers!S5*Assumptions!$F$116*Assumptions!$F$118+Scenario_Low_Tiers!T5*Assumptions!$F$117*Assumptions!$F$119,0) -> 94500 | G6: =ROUND(Scenario_Low_Tiers!O5*Assumptions!$F$116*Assumptions!$F$118+Scenario_Low_Tiers!P5*Assumptions!$F$117*Assumptions!$F$119,0) -> 39150
A7: KYC/KYB onboarding fees | B7: =ROUND(Scenario_Low_PL!C11*Assumptions!$F$120,0) -> 900 | C7: =ROUND(Scenario_Low_PL!D11*Assumptions!$F$120,0) -> 4500 | D7: =ROUND(Scenario_Low_PL!E11*Assumptions!$F$120,0) -> 13500 | E7: =ROUND(Scenario_Low_PL!F11*Assumptions!$F$120,0) -> 27000 | F7: =ROUND(Scenario_Low_PL!G11*Assumptions!$F$120,0) -> 90000 | G7: Fresh onboarding only; repeat counterparties not recharged every deal
A8: Tier C forensics pass-through margin | B8: =ROUND(Scenario_Low_Tiers!D19*Assumptions!$F$121,0) -> 1260 | C8: =ROUND(Scenario_Low_Tiers!H19*Assumptions!$F$121,0) -> 4950 | D8: =ROUND(Scenario_Low_Tiers!L19*Assumptions!$F$121,0) -> 10800 | E8: =ROUND(Scenario_Low_Tiers!P19*Assumptions!$F$121,0) -> 13500 | F8: =ROUND(Scenario_Low_Tiers!T19*Assumptions!$F$121,0) -> 27000 | G8: =ROUND(Scenario_Low_Tiers!P19*Assumptions!$F$121,0) -> 13500
A9: Tier C courier/original handling fees | B9: =ROUND(Scenario_Low_Tiers!D5*Assumptions!$F$122,0) -> 3150 | C9: =ROUND(Scenario_Low_Tiers!H5*Assumptions!$F$122,0) -> 12375 | D9: =ROUND(Scenario_Low_Tiers!L5*Assumptions!$F$122,0) -> 27000 | E9: =ROUND(Scenario_Low_Tiers!P5*Assumptions!$F$122,0) -> 33750 | F9: =ROUND(Scenario_Low_Tiers!T5*Assumptions!$F$122,0) -> 67500 | G9: =ROUND(Scenario_Low_Tiers!P5*Assumptions!$F$122,0) -> 33750
A10: Discrepancy cure / waiver fees | B10: =ROUND(Scenario_Low_PL!C12*Assumptions!$F$124*Assumptions!$F$123,0) -> 601 | C10: =ROUND(Scenario_Low_PL!D12*Assumptions!$F$124*Assumptions!$F$123,0) -> 2682 | D10: =ROUND(Scenario_Low_PL!E12*Assumptions!$F$124*Assumptions!$F$123,0) -> 6912 | E10: =ROUND(Scenario_Low_PL!F12*Assumptions!$F$124*Assumptions!$F$123,0) -> 11556 | F10: =ROUND(Scenario_Low_PL!G12*Assumptions!$F$124*Assumptions!$F$123,0) -> 32760 | G10: =ROUND(Scenario_Low_PL!F12*Assumptions!$F$124*Assumptions!$F$123,0) -> 11556
A11: Partner setup / integration fees | B11: =ROUND(0,0) -> 0 | C11: =ROUND(Assumptions!$C$17*Assumptions!$F$125,0) -> 0 | D11: =ROUND(MAX(0,Assumptions!$C$113-Assumptions!$C$17)*Assumptions!$F$125,0) -> 0 | E11: =ROUND(MAX(0,Assumptions!$C$163-Assumptions!$C$113)*Assumptions!$F$125,0) -> 7500 | F11: =ROUND(MAX(0,Assumptions!$C$164-Assumptions!$C$163)*Assumptions!$F$125,0) -> 15000 | G11: Setup fees charged on net-new partners only
A12: Monthly minimum / committed volume fees | B12: =ROUND(0,0) -> 0 | C12: =ROUND(Assumptions!$C$17*Assumptions!$F$126*12,0) -> 0 | D12: =ROUND(Assumptions!$C$113*Assumptions!$F$126*12,0) -> 0 | E12: =ROUND(Assumptions!$C$163*Assumptions!$F$126*12,0) -> 9000 | F12: =ROUND(Assumptions!$C$164*Assumptions!$F$126*12,0) -> 27000 | G12: Monthly minimum uses live partner count by year
A13: Archive / audit record fees | B13: =ROUND(Scenario_Low_PL!C7*Assumptions!$F$127,0) -> 180 | C13: =ROUND(Scenario_Low_PL!D7*Assumptions!$F$127,0) -> 900 | D13: =ROUND(Scenario_Low_PL!E7*Assumptions!$F$127,0) -> 2700 | E13: =ROUND(Scenario_Low_PL!F7*Assumptions!$F$127,0) -> 5400 | F13: =ROUND(Scenario_Low_PL!G7*Assumptions!$F$127,0) -> 18000 | G13: =ROUND(Scenario_Low_PL!F7*Assumptions!$F$127,0) -> 5400
A14: Yield share upside | B14: =ROUND(Assumptions!$F$128*Assumptions!$F$129*Assumptions!$F$130*Scenario_Low_PL!C9,0) -> 0 | C14: =ROUND(Assumptions!$F$128*Assumptions!$F$129*Assumptions!$F$130*Scenario_Low_PL!D9,0) -> 0 | D14: =ROUND(Assumptions!$F$128*Assumptions!$F$129*Assumptions!$F$130*Scenario_Low_PL!E9,0) -> 0 | E14: =ROUND(Assumptions!$F$128*Assumptions!$F$129*Assumptions!$F$130*Scenario_Low_PL!F9,0) -> 0 | F14: =ROUND(Assumptions!$F$128*Assumptions!$F$129*Assumptions!$F$130*Scenario_Low_PL!G9,0) -> 0 | G14: =ROUND(Assumptions!$F$128*Assumptions!$F$129*Assumptions!$F$130*Scenario_Low_PL!F9,0) -> 0
A15: Total additional revenue | B15: =ROUND(SUM(B5:B14),0) -> 381 | C15: =ROUND(SUM(C5:C14),0) -> 36882 | D15: =ROUND(SUM(D5:D14),0) -> 87912 | E15: =ROUND(SUM(E5:E14),0) -> 146856 | F15: =ROUND(SUM(F5:F14),0) -> 371760 | G15: =ROUND(SUM(E5:E14),0) -> 146856
A17: RETAINED-RISK VARIABLE COSTS
A18: QA second-review cost | B18: =ROUND(Scenario_Low_PL!C7*Assumptions!$F$136*Assumptions!$F$137,0) -> 288 | C18: =ROUND(Scenario_Low_PL!D7*Assumptions!$F$136*Assumptions!$F$137,0) -> 1440 | D18: =ROUND(Scenario_Low_PL!E7*Assumptions!$F$136*Assumptions!$F$137,0) -> 4320 | E18: =ROUND(Scenario_Low_PL!F7*Assumptions!$F$136*Assumptions!$F$137,0) -> 8640 | F18: =ROUND(Scenario_Low_PL!G7*Assumptions!$F$136*Assumptions!$F$137,0) -> 28800 | G18: =ROUND(Scenario_Low_PL!F7*Assumptions!$F$136*Assumptions!$F$137,0) -> 8640
A19: External dispute forum cost | B19: =ROUND(Scenario_Low_PL!C7*Assumptions!$F$138*Assumptions!$F$139,0) -> 2700 | C19: =ROUND(Scenario_Low_PL!D7*Assumptions!$F$138*Assumptions!$F$139,0) -> 13500 | D19: =ROUND(Scenario_Low_PL!E7*Assumptions!$F$138*Assumptions!$F$139,0) -> 40500 | E19: =ROUND(Scenario_Low_PL!F7*Assumptions!$F$138*Assumptions!$F$139,0) -> 81000 | F19: =ROUND(Scenario_Low_PL!G7*Assumptions!$F$138*Assumptions!$F$139,0) -> 270000 | G19: =ROUND(Scenario_Low_PL!F7*Assumptions!$F$138*Assumptions!$F$139,0) -> 81000
A20: Operational error / wrongful-release reserve | B20: =ROUND(Scenario_Low_PL!C18*Assumptions!$F$140,0) -> 443 | C20: =ROUND(Scenario_Low_PL!D18*Assumptions!$F$140,0) -> 2590 | D20: =ROUND(Scenario_Low_PL!E18*Assumptions!$F$140,0) -> 7983 | E20: =ROUND(Scenario_Low_PL!F18*Assumptions!$F$140,0) -> 16772 | F20: =ROUND(Scenario_Low_PL!G18*Assumptions!$F$140,0) -> 61653 | G20: =ROUND(Scenario_Low_PL!F18*Assumptions!$F$140,0) -> 16772
A21: Partner/channel commission | B21: =ROUND(Scenario_Low_PL!C18*Assumptions!$F$144,0) -> 2214 | C21: =ROUND(Scenario_Low_PL!D18*Assumptions!$F$144,0) -> 12949 | D21: =ROUND(Scenario_Low_PL!E18*Assumptions!$F$144,0) -> 39917 | E21: =ROUND(Scenario_Low_PL!F18*Assumptions!$F$144,0) -> 83859 | F21: =ROUND(Scenario_Low_PL!G18*Assumptions!$F$144,0) -> 308266 | G21: =ROUND(Scenario_Low_PL!F18*Assumptions!$F$144,0) -> 83859
A22: Fee collection leakage | B22: =ROUND((B7+B10+B12)*Assumptions!$F$145,0) -> 15 | C22: =ROUND((C7+C10+C12)*Assumptions!$F$145,0) -> 72 | D22: =ROUND((D7+D10+D12)*Assumptions!$F$145,0) -> 204 | E22: =ROUND((E7+E10+E12)*Assumptions!$F$145,0) -> 476 | F22: =ROUND((F7+F10+F12)*Assumptions!$F$145,0) -> 1498 | G22: =ROUND((E7+E10+E12)*Assumptions!$F$145,0) -> 476
A23: Partner/API outage fallback | B23: =ROUND(Scenario_Low_Tiers!C5*Assumptions!$F$146*Assumptions!$F$147,0) -> 34 | C23: =ROUND(Scenario_Low_Tiers!G5*Assumptions!$F$146*Assumptions!$F$147,0) -> 236 | D23: =ROUND(Scenario_Low_Tiers!K5*Assumptions!$F$146*Assumptions!$F$147,0) -> 810 | E23: =ROUND(Scenario_Low_Tiers!O5*Assumptions!$F$146*Assumptions!$F$147,0) -> 1823 | F23: =ROUND(Scenario_Low_Tiers!S5*Assumptions!$F$146*Assumptions!$F$147,0) -> 6075 | G23: =ROUND(Scenario_Low_Tiers!O5*Assumptions!$F$146*Assumptions!$F$147,0) -> 1823
A24: Total variable retained-risk costs | B24: =ROUND(SUM(B18:B23),0) -> 5694 | C24: =ROUND(SUM(C18:C23),0) -> 30787 | D24: =ROUND(SUM(D18:D23),0) -> 93734 | E24: =ROUND(SUM(E18:E23),0) -> 192570 | F24: =ROUND(SUM(F18:F23),0) -> 676292 | G24: =ROUND(SUM(E18:E23),0) -> 192570
A26: RETAINED-RISK FIXED COSTS
A27: Carrier/eBL integration maintenance | B27: =ROUND(Assumptions!$F$132*1,0) -> 15000 | C27: =ROUND(Assumptions!$F$132*1.25,0) -> 18750 | D27: =ROUND(Assumptions!$F$132*1.5,0) -> 22500 | E27: =ROUND(Assumptions!$F$132*1.75,0) -> 26250 | F27: =ROUND(Assumptions!$F$132*2,0) -> 30000 | G27: =ROUND(Assumptions!$F$132*1.75,0) -> 26250
A28: Forensics partner retainer | B28: =ROUND(Assumptions!$F$133*1,0) -> 20000 | C28: =ROUND(Assumptions!$F$133*1.25,0) -> 25000 | D28: =ROUND(Assumptions!$F$133*1.5,0) -> 30000 | E28: =ROUND(Assumptions!$F$133*1.75,0) -> 35000 | F28: =ROUND(Assumptions!$F$133*2,0) -> 40000 | G28: =ROUND(Assumptions!$F$133*1.75,0) -> 35000
A29: Fraud database build / governance | B29: =ROUND(Assumptions!$F$134+Assumptions!$F$135,0) -> 55000 | C29: =ROUND(Assumptions!$F$135,0) -> 15000 | D29: =ROUND(Assumptions!$F$135,0) -> 15000 | E29: =ROUND(Assumptions!$F$135,0) -> 15000 | F29: =ROUND(Assumptions!$F$135,0) -> 15000 | G29: =ROUND(Assumptions!$F$135,0) -> 15000
A30: KMS / multisig / key security ops | B30: =ROUND(Assumptions!$F$142*1,0) -> 12000 | C30: =ROUND(Assumptions!$F$142*1.25,0) -> 15000 | D30: =ROUND(Assumptions!$F$142*1.5,0) -> 18000 | E30: =ROUND(Assumptions!$F$142*1.75,0) -> 21000 | F30: =ROUND(Assumptions!$F$142*2,0) -> 24000 | G30: =ROUND(Assumptions!$F$142*1.75,0) -> 21000
A31: Regulatory reporting ops | B31: =ROUND(Assumptions!$F$143*1,0) -> 18000 | C31: =ROUND(Assumptions!$F$143*1.25,0) -> 22500 | D31: =ROUND(Assumptions!$F$143*1.5,0) -> 27000 | E31: =ROUND(Assumptions!$F$143*1.75,0) -> 31500 | F31: =ROUND(Assumptions!$F$143*2,0) -> 36000 | G31: =ROUND(Assumptions!$F$143*1.75,0) -> 31500
A32: Insurance deductible reserve | B32: =ROUND(Assumptions!$F$141,0) -> 15000 | C32: =ROUND(Assumptions!$F$141,0) -> 15000 | D32: =ROUND(Assumptions!$F$141,0) -> 15000 | E32: =ROUND(Assumptions!$F$141,0) -> 15000 | F32: =ROUND(Assumptions!$F$141,0) -> 15000 | G32: =ROUND(Assumptions!$F$141,0) -> 15000
A33: Smart contract incident reserve | B33: =ROUND(Assumptions!$F$148*1,0) -> 30000 | C33: =ROUND(Assumptions!$F$148*1,0) -> 30000 | D33: =ROUND(Assumptions!$F$148*1,0) -> 30000 | E33: =ROUND(Assumptions!$F$148*1.25,0) -> 37500 | F33: =ROUND(Assumptions!$F$148*1.5,0) -> 45000 | G33: =ROUND(Assumptions!$F$148*1.25,0) -> 37500
A34: Liability wording legal review | B34: =ROUND(Assumptions!$F$152,0) -> 7500 | C34: =ROUND(0,0) -> 0 | D34: =ROUND(0,0) -> 0 | E34: =ROUND(0,0) -> 0 | F34: =ROUND(0,0) -> 0 | G34: =ROUND(0,0) -> 0
A35: Document-source indemnity legal review | B35: =ROUND(Assumptions!$F$153,0) -> 7500 | C35: =ROUND(0,0) -> 0 | D35: =ROUND(0,0) -> 0 | E35: =ROUND(0,0) -> 0 | F35: =ROUND(0,0) -> 0 | G35: =ROUND(0,0) -> 0
A36: Total fixed retained-risk costs | B36: =ROUND(SUM(B27:B35),0) -> 180000 | C36: =ROUND(SUM(C27:C35),0) -> 141250 | D36: =ROUND(SUM(D27:D35),0) -> 157500 | E36: =ROUND(SUM(E27:E35),0) -> 181250 | F36: =ROUND(SUM(F27:F35),0) -> 205000 | G36: =ROUND(SUM(E27:E35),0) -> 181250
A38: FUNDING / CONTINGENCY ONLY
A39: Regulatory delay contingency | B39: =ROUND(Assumptions!$F$149*Assumptions!$F$150,0) -> 240000 | C39: =ROUND(0,0) -> 0 | D39: =ROUND(0,0) -> 0 | E39: =ROUND(0,0) -> 0 | F39: =ROUND(0,0) -> 0 | G39: =ROUND(0,0) -> 0
A40: Delivery/performance liability reserve | B40: =ROUND(Assumptions!$F$151,0) -> 0 | C40: =ROUND(Assumptions!$F$151,0) -> 0 | D40: =ROUND(Assumptions!$F$151,0) -> 0 | E40: =ROUND(Assumptions!$F$151,0) -> 0 | F40: =ROUND(Assumptions!$F$151,0) -> 0 | G40: =ROUND(Assumptions!$F$151,0) -> 0
A41: Total funding-only contingency | B41: =ROUND(SUM(B39:B40),0) -> 240000 | C41: =ROUND(SUM(C39:C40),0) -> 0 | D41: =ROUND(SUM(D39:D40),0) -> 0 | E41: =ROUND(SUM(E39:E40),0) -> 0 | F41: =ROUND(SUM(F39:F40),0) -> 0 | G41: =ROUND(SUM(E39:E40),0) -> 0
A43: DOCUMENTS-NOT-GOODS POSITIONING
A44: Goods delivery / quality / performance risk | B44: Excluded reserve | C44: Excluded | D44: Excluded | E44: Excluded | F44: Excluded | G44: Documents-not-goods boundary; buyer/seller/carrier/insurer risk
A45: Document verification / wrongful release risk | B45: Retained and priced | C45: Retained | D45: Retained | E45: Operational/process error reserve + insurance/deductible reserve | G45: Operational/process error reserve + insurance/deductible reserve
A46: Carrier/eBL/API source failure risk | B46: Retained operationally | C46: Retained | D46: Retained | E46: Partner contracts, uptime SLAs, manual fallback cost | G46: Partner contracts, uptime SLAs, manual fallback cost
A47: Tier C paper/originals risk | B47: High-cost fallback | C47: High | D47: High | E47: Tier C priced up and margin-tested | G47: Tier C priced up and margin-tested
A48: Contractual risk posture | B48: Against documents | C48: Core premise | D48: Core premise | E48: Mirrors LC logic; legal review still required | G48: Mirrors LC logic; legal review still required

Sheet Scenario_Low_PL
B2: 5-Year P&L (annual) - driven by Assumptions sheet
B3: All figures GBP. Revenue & COGS scale with deal volume. Active scenario shown; change Assumptions!C4.
B5: Line item | C5: Year 1 | D5: Year 2 | E5: Year 3 | F5: Year 4 | G5: Year 5 | H5: Unit / note
B6: VOLUME & DRIVERS
B7: Deals processed | C7: =Assumptions!$C$11 -> 60 | D7: =Assumptions!$C$12 -> 300 | E7: =Assumptions!$C$13 -> 900 | F7: =Assumptions!$C$155 -> 1800 | G7: =Assumptions!$C$156 -> 6000 | H7: From Assumptions
B8: Avg deal value (£) | C8: =Assumptions!$F$14 -> 30000 | D8: =C8*(1+Assumptions!$F$15) -> 40500 | E8: =D8*(1+Assumptions!$F$15) -> 54675 | F8: =E8*(1+Assumptions!$F$15) -> 73811.25 | G8: =F8*(1+Assumptions!$F$15) -> 99645.188 | H8: GMV per deal
B9: Gross trade value processed (GMV) | C9: =C7*C8 -> 1800000 | D9: =D7*D8 -> 12150000 | E9: =E7*E8 -> 49207500 | F9: =F7*F8 -> 132860250 | G9: =G7*G8 -> 597871125 | H9: Deals × avg value (NOT revenue)
B10: Documents processed | C10: =Scenario_Low_Tiers!E7 -> 477 | D10: =Scenario_Low_Tiers!I7 -> 2205 | E10: =Scenario_Low_Tiers!M7 -> 5940 | F10: =Scenario_Low_Tiers!Q7 -> 10530 | G10: =Scenario_Low_Tiers!U7 -> 31500 | H10: Tier-weighted docs/deal from Tier_Economics
B11: New counterparties onboarded | C11: =C7*Assumptions!$F$16*Assumptions!$F$62 -> 60 | D11: =D7*Assumptions!$F$16*Assumptions!$F$62 -> 300 | E11: =E7*Assumptions!$F$16*Assumptions!$F$62 -> 900 | F11: =F7*Assumptions!$F$16*Assumptions!$F$62 -> 1800 | G11: =G7*Assumptions!$F$16*Assumptions!$F$62 -> 6000 | H11: Deals x parties/deal x new-counterparty onboarding share
B12: Disputed/amended deals | C12: =Scenario_Low_Tiers!E16 -> 10.02 | D12: =Scenario_Low_Tiers!I16 -> 44.7 | E12: =Scenario_Low_Tiers!M16 -> 115.2 | F12: =Scenario_Low_Tiers!Q16 -> 192.6 | G12: =Scenario_Low_Tiers!U16 -> 546 | H12: Tier-weighted dispute rates
B13: REVENUE
B14: Escrow transaction fees | C14: =Scenario_Low_Tiers!E12 -> 25365 | D14: =Scenario_Low_Tiers!I12 -> 143673.75 | E14: =Scenario_Low_Tiers!M12 -> 521599.5 | F14: =Scenario_Low_Tiers!Q12 -> 1245564.8 | G14: =Scenario_Low_Tiers!U12 -> 5066957.8 | H14: Tiered fee by A/B/C mix
B15: Document review fees | C15: =Scenario_Low_Tiers!E14 -> 14025 | D15: =Scenario_Low_Tiers!I14 -> 59700 | E15: =Scenario_Low_Tiers!M14 -> 144900 | F15: =Scenario_Low_Tiers!Q14 -> 221400 | G15: =Scenario_Low_Tiers!U14 -> 573000 | H15: Tiered document/review fee
B16: Dispute/amendment fees | C16: =Scenario_Low_Tiers!E18 -> 4512 | D16: =Scenario_Low_Tiers!I18 -> 18720 | E16: =Scenario_Low_Tiers!M18 -> 43920 | F16: =Scenario_Low_Tiers!Q18 -> 63360 | G16: =Scenario_Low_Tiers!U18 -> 153600 | H16: Tiered dispute/amendment fee
B17: Partner/API + add-on revenue streams | C17: =Scenario_Low_AddOns!B15 -> 381 | D17: =Scenario_Low_AddOns!C15 -> 36882 | E17: =Scenario_Low_AddOns!D15 -> 87912 | F17: =Scenario_Low_AddOns!E15 -> 146856 | G17: =Scenario_Low_AddOns!F15 -> 371760 | H17: SaaS/API, setup/minimums, KYC fees, archive, expedited, Tier C pass-through, less first-deal discount
B18: Total revenue | C18: =SUM(C14:C17) -> 44283 | D18: =SUM(D14:D17) -> 258975.75 | E18: =SUM(E14:E17) -> 798331.5 | F18: =SUM(F14:F17) -> 1677180.8 | G18: =SUM(G14:G17) -> 6165317.8 | H18: =SUM(F14:F17) -> 1677180.8
B19: COGS / VARIABLE COSTS
B20: Claude API (doc extraction) | C20: =C10*Assumptions!$F$19/Assumptions!$F$8 -> 11.179687 | D20: =D10*Assumptions!$F$19/Assumptions!$F$8 -> 51.679687 | E20: =E10*Assumptions!$F$19/Assumptions!$F$8 -> 139.21875 | F20: =F10*Assumptions!$F$19/Assumptions!$F$8 -> 246.79687 | G20: =G10*Assumptions!$F$19/Assumptions!$F$8 -> 738.28125 | H20: USD→GBP
B21: KYB business onboarding | C21: =C11*Assumptions!$F$20/Assumptions!$F$8 -> 164.0625 | D21: =D11*Assumptions!$F$20/Assumptions!$F$8 -> 820.3125 | E21: =E11*Assumptions!$F$20/Assumptions!$F$8 -> 2460.9375 | F21: =F11*Assumptions!$F$20/Assumptions!$F$8 -> 4921.875 | G21: =G11*Assumptions!$F$20/Assumptions!$F$8 -> 16406.25 | H21: Fresh KYB only for new counterparties
B22: KYC/UBO + sanctions onboarding | C22: =C11*Assumptions!$F$21/Assumptions!$F$8 -> 63.28125 | D22: =D11*Assumptions!$F$21/Assumptions!$F$8 -> 316.40625 | E22: =E11*Assumptions!$F$21/Assumptions!$F$8 -> 949.21875 | F22: =F11*Assumptions!$F$21/Assumptions!$F$8 -> 1898.4375 | G22: =G11*Assumptions!$F$21/Assumptions!$F$8 -> 6328.125 | H22: Fresh KYC/KYB only for new counterparties
B23: Tiered document verification ops | C23: =Scenario_Low_Tiers!E19+Scenario_Low_Tiers!E20 -> 11808 | D23: =Scenario_Low_Tiers!I19+Scenario_Low_Tiers!I20 -> 47880 | E23: =Scenario_Low_Tiers!M19+Scenario_Low_Tiers!M20 -> 109080 | F23: =Scenario_Low_Tiers!Q19+Scenario_Low_Tiers!Q20 -> 149040 | G23: =Scenario_Low_Tiers!U19+Scenario_Low_Tiers!U20 -> 338400 | H23: External eBL/API/paper + human examiner cost
B24: Blockchain gas | C24: =C7*Assumptions!$F$22/Assumptions!$F$8 -> 9.375 | D24: =D7*Assumptions!$F$22/Assumptions!$F$8 -> 46.875 | E24: =E7*Assumptions!$F$22/Assumptions!$F$8 -> 140.625 | F24: =F7*Assumptions!$F$22/Assumptions!$F$8 -> 281.25 | G24: =G7*Assumptions!$F$22/Assumptions!$F$8 -> 937.5 | H24: Base L2 USD→GBP
B25: RPC / node provider | C25: =C7*Assumptions!$F$23/Assumptions!$F$8 -> 0.46875 | D25: =D7*Assumptions!$F$23/Assumptions!$F$8 -> 2.34375 | E25: =E7*Assumptions!$F$23/Assumptions!$F$8 -> 7.03125 | F25: =F7*Assumptions!$F$23/Assumptions!$F$8 -> 14.0625 | G25: =G7*Assumptions!$F$23/Assumptions!$F$8 -> 46.875 | H25: =F7*Assumptions!$F$23/Assumptions!$F$8 -> 14.0625
B26: Document / ledger storage | C26: =C7*Assumptions!$F$24/Assumptions!$F$8 -> 1.40625 | D26: =D7*Assumptions!$F$24/Assumptions!$F$8 -> 7.03125 | E26: =E7*Assumptions!$F$24/Assumptions!$F$8 -> 21.09375 | F26: =F7*Assumptions!$F$24/Assumptions!$F$8 -> 42.1875 | G26: =G7*Assumptions!$F$24/Assumptions!$F$8 -> 140.625 | H26: =F7*Assumptions!$F$24/Assumptions!$F$8 -> 42.1875
B27: Customer support | C27: =Scenario_Low_Tiers!E21 -> 936 | D27: =Scenario_Low_Tiers!I21 -> 3990 | E27: =Scenario_Low_Tiers!M21 -> 9720 | F27: =Scenario_Low_Tiers!Q21 -> 14940 | G27: =Scenario_Low_Tiers!U21 -> 39000 | H27: Tiered support load
B28: Dispute handling + retained-risk variable costs | C28: =Scenario_Low_Tiers!E22+Scenario_Low_AddOns!B24 -> 8821.2 | D28: =Scenario_Low_Tiers!I22+Scenario_Low_AddOns!C24 -> 43669 | E28: =Scenario_Low_Tiers!M22+Scenario_Low_AddOns!D24 -> 123686 | F28: =Scenario_Low_Tiers!Q22+Scenario_Low_AddOns!E24 -> 235086 | G28: =Scenario_Low_Tiers!U22+Scenario_Low_AddOns!F24 -> 777452 | H28: Dispute handling plus QA, forum, reserves, commissions, fallback, leakage
B29: Total COGS | C29: =SUM(C20:C28) -> 21814.973 | D29: =SUM(D20:D28) -> 96783.648 | E29: =SUM(E20:E28) -> 246204.12 | F29: =SUM(F20:F28) -> 406470.61 | G29: =SUM(G20:G28) -> 1179449.7 | H29: =SUM(F20:F28) -> 406470.61
B30: Gross profit | C30: =C18-C29 -> 22468.027 | D30: =D18-D29 -> 162192.1 | E30: =E18-E29 -> 552127.38 | F30: =F18-F29 -> 1270710.2 | G30: =G18-G29 -> 4985868.1 | H30: =F18-F29 -> 1270710.2
B31: Gross margin % | C31: =IF(C18=0,0,C30/C18) -> 0.50737363 | D31: =IF(D18=0,0,D30/D18) -> 0.62628297 | E31: =IF(E18=0,0,E30/E18) -> 0.69160164 | F31: =IF(F18=0,0,F30/F18) -> 0.75764652 | G31: =IF(G18=0,0,G30/G18) -> 0.80869605 | H31: =IF(F18=0,0,F30/F18) -> 0.75764652
B32: HEADCOUNT & PAYROLL
B33: Founders (FTE) | C33: =Assumptions!$F$39 -> 2 | D33: =Assumptions!$F$39 -> 2 | E33: =Assumptions!$F$39 -> 2 | F33: =Assumptions!$F$39 -> 2 | G33: =Assumptions!$F$39 -> 2 | H33: =Assumptions!$F$39 -> 2
B34: Engineers (FTE) | C34: =Assumptions!$F$40+0 -> 2 | D34: =Assumptions!$F$40+1 -> 3 | E34: =Assumptions!$F$40+2 -> 4 | F34: =Assumptions!$F$40+3 -> 5 | G34: =Assumptions!$F$40+4 -> 6 | H34: Ramp +1/yr
B35: Compliance/ops (FTE) | C35: =Assumptions!$F$41+0 -> 1 | D35: =Assumptions!$F$41+1 -> 2 | E35: =Assumptions!$F$41+2 -> 3 | F35: =Assumptions!$F$41+3 -> 4 | G35: =Assumptions!$F$41+4 -> 5 | H35: Ramp
B36: Sales/BD/CS (FTE) | C36: =Assumptions!$F$42+0 -> 1 | D36: =Assumptions!$F$42+1 -> 2 | E36: =Assumptions!$F$42+2 -> 3 | F36: =Assumptions!$F$42+3 -> 4 | G36: =Assumptions!$F$42+4 -> 5 | H36: Ramp
B37: Total FTE | C37: =C33+C34+C35+C36 -> 6 | D37: =D33+D34+D35+D36 -> 9 | E37: =E33+E34+E35+E36 -> 12 | F37: =F33+F34+F35+F36 -> 15 | G37: =G33+G34+G35+G36 -> 18 | H37: =F33+F34+F35+F36 -> 15
B38: Gross salaries | C38: =C33*Assumptions!$F$44+C34*Assumptions!$F$45+C35*Assumptions!$F$46+C36*Assumptions!$F$47 -> 340000 | D38: =D33*Assumptions!$F$44+D34*Assumptions!$F$45+D35*Assumptions!$F$46+D36*Assumptions!$F$47 -> 520000 | E38: =E33*Assumptions!$F$44+E34*Assumptions!$F$45+E35*Assumptions!$F$46+E36*Assumptions!$F$47 -> 700000 | F38: =F33*Assumptions!$F$44+F34*Assumptions!$F$45+F35*Assumptions!$F$46+F36*Assumptions!$F$47 -> 880000 | G38: =G33*Assumptions!$F$44+G34*Assumptions!$F$45+G35*Assumptions!$F$46+G36*Assumptions!$F$47 -> 1060000 | H38: FTE × salary
B39: Employer NI | C39: =MAX(0,(C38-Assumptions!$F$49*C37)*Assumptions!$F$48-Assumptions!$F$60) -> 36000 | D39: =MAX(0,(D38-Assumptions!$F$49*D37)*Assumptions!$F$48-Assumptions!$F$60) -> 60750 | E39: =MAX(0,(E38-Assumptions!$F$49*E37)*Assumptions!$F$48-Assumptions!$F$60) -> 85500 | F39: =MAX(0,(F38-Assumptions!$F$49*F37)*Assumptions!$F$48-Assumptions!$F$60) -> 110250 | G39: =MAX(0,(G38-Assumptions!$F$49*G37)*Assumptions!$F$48-Assumptions!$F$60) -> 135000 | H39: 15% above threshold, less Employment Allowance; confirm eligibility
B40: Employer pension | C40: =C38*Assumptions!$F$50 -> 13600 | D40: =D38*Assumptions!$F$50 -> 20800 | E40: =E38*Assumptions!$F$50 -> 28000 | F40: =F38*Assumptions!$F$50 -> 35200 | G40: =G38*Assumptions!$F$50 -> 42400 | H40: =F38*Assumptions!$F$50 -> 35200
B41: Other employment on-costs | C41: =C38*Assumptions!$F$51 -> 10200 | D41: =D38*Assumptions!$F$51 -> 15600 | E41: =E38*Assumptions!$F$51 -> 21000 | F41: =F38*Assumptions!$F$51 -> 26400 | G41: =G38*Assumptions!$F$51 -> 31800 | H41: =F38*Assumptions!$F$51 -> 26400
B42: Total payroll cost | C42: =C38+C39+C40+C41 -> 399800 | D42: =D38+D39+D40+D41 -> 617150 | E42: =E38+E39+E40+E41 -> 834500 | F42: =F38+F39+F40+F41 -> 1051850 | G42: =G38+G39+G40+G41 -> 1269200 | H42: =F38+F39+F40+F41 -> 1051850
B43: FIXED OPERATING COSTS (annual = monthly ×12)
B44: Cloud hosting (Vercel/AWS) | C44: =Assumptions!$F$26*12*1 -> 3000 | D44: =Assumptions!$F$26*12*1.5 -> 4500 | E44: =Assumptions!$F$26*12*2.5 -> 7500 | F44: =Assumptions!$F$26*12*4 -> 12000 | G44: =Assumptions!$F$26*12*6 -> 18000 | H44: Monthly base × scale factor
B45: Database + object storage | C45: =Assumptions!$F$27*12*1 -> 1440 | D45: =Assumptions!$F$27*12*1.5 -> 2160 | E45: =Assumptions!$F$27*12*2.5 -> 3600 | F45: =Assumptions!$F$27*12*4 -> 5760 | G45: =Assumptions!$F$27*12*6 -> 8640 | H45: Monthly base × scale factor
B46: Monitoring/logging/security tools | C46: =Assumptions!$F$28*12*1 -> 1800 | D46: =Assumptions!$F$28*12*1.5 -> 2700 | E46: =Assumptions!$F$28*12*2.5 -> 4500 | F46: =Assumptions!$F$28*12*4 -> 7200 | G46: =Assumptions!$F$28*12*6 -> 10800 | H46: Monthly base × scale factor
B47: GitHub + dev SaaS | C47: =Assumptions!$F$29*12*C37/6 -> 720 | D47: =Assumptions!$F$29*12*D37/6 -> 1080 | E47: =Assumptions!$F$29*12*E37/6 -> 1440 | F47: =Assumptions!$F$29*12*F37/6 -> 1800 | G47: =Assumptions!$F$29*12*G37/6 -> 2160 | H47: Monthly base × FTE scale
B48: Google Workspace / collab | C48: =Assumptions!$F$30*12*C37/6 -> 1080 | D48: =Assumptions!$F$30*12*D37/6 -> 1620 | E48: =Assumptions!$F$30*12*E37/6 -> 2160 | F48: =Assumptions!$F$30*12*F37/6 -> 2700 | G48: =Assumptions!$F$30*12*G37/6 -> 3240 | H48: Monthly base × FTE scale
B49: CRM + BD tooling | C49: =Assumptions!$F$31*12*MAX(1,C36) -> 960 | D49: =Assumptions!$F$31*12*MAX(1,D36) -> 1920 | E49: =Assumptions!$F$31*12*MAX(1,E36) -> 2880 | F49: =Assumptions!$F$31*12*MAX(1,F36) -> 3840 | G49: =Assumptions!$F$31*12*MAX(1,G36) -> 4800 | H49: Monthly base × sales/BD scale
B50: Accounting/payroll/bookkeeping | C50: =Assumptions!$F$32*12*1 -> 4200 | D50: =Assumptions!$F$32*12*1.25 -> 5250 | E50: =Assumptions!$F$32*12*1.5 -> 6300 | F50: =Assumptions!$F$32*12*1.75 -> 7350 | G50: =Assumptions!$F$32*12*2 -> 8400 | H50: Monthly base × scale factor
B51: Legal retainer (ongoing) | C51: =Assumptions!$F$33*12*1 -> 7200 | D51: =Assumptions!$F$33*12*1.5 -> 10800 | E51: =Assumptions!$F$33*12*2 -> 14400 | F51: =Assumptions!$F$33*12*2.5 -> 18000 | G51: =Assumptions!$F$33*12*3 -> 21600 | H51: Monthly base × complexity scale
B52: Compliance / MLRO + retained-risk infrastructure | C52: =Assumptions!$F$34*12*1+Scenario_Low_AddOns!B36 -> 194400 | D52: =Assumptions!$F$34*12*1.5+Scenario_Low_AddOns!C36 -> 162850 | E52: =Assumptions!$F$34*12*2+Scenario_Low_AddOns!D36 -> 186300 | F52: =Assumptions!$F$34*12*2.5+Scenario_Low_AddOns!E36 -> 217250 | G52: =Assumptions!$F$34*12*3+Scenario_Low_AddOns!F36 -> 248200 | H52: MLRO support plus carrier/eBL integration, forensics retainer, fraud DB, key security, reg ops, incident reserve
B53: Marketing / conferences / partnerships | C53: =Assumptions!$F$35*12*1 -> 18000 | D53: =Assumptions!$F$35*12*2 -> 36000 | E53: =Assumptions!$F$35*12*3 -> 54000 | F53: =Assumptions!$F$35*12*4 -> 72000 | G53: =Assumptions!$F$35*12*5 -> 90000 | H53: Monthly base × sales/BD scale
B54: Office / coworking | C54: =Assumptions!$F$36*12*C37/6 -> 4800 | D54: =Assumptions!$F$36*12*D37/6 -> 7200 | E54: =Assumptions!$F$36*12*E37/6 -> 9600 | F54: =Assumptions!$F$36*12*F37/6 -> 12000 | G54: =Assumptions!$F$36*12*G37/6 -> 14400 | H54: Monthly base × FTE scale
B55: Insurance (PI+cyber+D&O) / mo | C55: =0 -> 0 | D55: =Assumptions!$F$37*12*1 -> 8400 | E55: =Assumptions!$F$37*12*1 -> 8400 | F55: =Assumptions!$F$37*12*1.25 -> 10500 | G55: =Assumptions!$F$37*12*1.5 -> 12600 | H55: Year 1 prepaid; Years 2–3 monthly ×12
B56: Total fixed opex | C56: =SUM(C44:C55) -> 237600 | D56: =SUM(D44:D55) -> 244480 | E56: =SUM(E44:E55) -> 301080 | F56: =SUM(F44:F55) -> 370400 | G56: =SUM(G44:G55) -> 442840 | H56: =SUM(F44:F55) -> 370400
B57: ONE-OFF & STARTUP COSTS
B58: First-6-months one-off costs (Yr1) | C58: =Startup_6mo!F44 -> 241112.45 | D58: =0 -> 0 | E58: =0 -> 0 | F58: =0 -> 0 | G58: =0 -> 0 | H58: From Startup_6mo (Yr1 only)
B59: RESULT
B60: Total operating expenditure | C60: =C42+C56+C58 -> 878512.45 | D60: =D42+D56+D58 -> 861630 | E60: =E42+E56+E58 -> 1135580 | F60: =F42+F56+F58 -> 1422250 | G60: =G42+G56+G58 -> 1712040 | H60: Payroll+opex+one-off
B61: EBITDA (pre one-off) | C61: =C30-C42-C56 -> -614931.97 | D61: =D30-D42-D56 -> -699437.9 | E61: =E30-E42-E56 -> -583452.62 | F61: =F30-F42-F56 -> -151539.77 | G61: =G30-G42-G56 -> 3273828.1 | H61: Gross profit − payroll − opex
B62: Net profit / (loss) incl. one-off | C62: =C30-C60 -> -856044.42 | D62: =D30-D60 -> -699437.9 | E62: =E30-E60 -> -583452.62 | F62: =F30-F60 -> -151539.77 | G62: =G30-G60 -> 3273828.1 | H62: =F30-F60 -> -151539.77
B63: Cumulative net result | C63: =C62 -> -856044.42 | D63: =C63+D62 -> -1555482.3 | E63: =D63+E62 -> -2138934.9 | F63: =E63+F62 -> -2290474.7 | G63: =F63+G62 -> 983353.42 | H63: Running total
B64: Implied cash needed (peak cumulative deficit + buffer) | C64: =-MIN(0,C63)*(1+Assumptions!$F$58) -> 1112857.8 | D64: =-MIN(0,C63,D63)*(1+Assumptions!$F$58) -> 2022127 | E64: =-MIN(0,C63,D63,E63)*(1+Assumptions!$F$58) -> 2780615.4 | F64: =-MIN(0,C63,D63,E63,F63)*(1+Assumptions!$F$58) -> 2977617.1 | G64: =-MIN(0,C63,D63,E63,F63,G63)*(1+Assumptions!$F$58) -> 2977617.1 | H64: Peak cumulative deficit × linked buffer
B65: Funding-only contingency reserve | C65: =ROUND(Scenario_Low_AddOns!B41,0) -> 240000 | D65: =ROUND(Scenario_Low_AddOns!C41,0) -> 0 | E65: =ROUND(Scenario_Low_AddOns!D41,0) -> 0 | F65: =ROUND(Scenario_Low_AddOns!E41,0) -> 0 | G65: =ROUND(Scenario_Low_AddOns!F41,0) -> 0 | H65: Regulatory delay reserve + zero delivery-liability reserve
B66: Implied funding ask incl. contingency | C66: =ROUND(C64+C65,0) -> 1352858 | D66: =ROUND(D64+D65,0) -> 2022127 | E66: =ROUND(E64+E65,0) -> 2780615 | F66: =ROUND(F64+F65,0) -> 2977617 | G66: =ROUND(G64+G65,0) -> 2977617 | H66: Cash need plus funding-only contingency
B67: CUSTOMER ACQUISITION CROSS-CHECK
B68: Line item | C68: Year 1 | D68: Year 2 | E68: Year 3 | F68: Year 4 | G68: Year 5 | H68: Unit / note
B69: Deals / active customer / year | C69: =Assumptions!$C$110 -> 1.5 | D69: =Assumptions!$C$111 -> 2 | E69: =Assumptions!$C$112 -> 2.5 | F69: =Assumptions!$C$165 -> 3 | G69: =Assumptions!$C$166 -> 4 | H69: Commercial sanity check from Assumptions
B70: Implied active customers | C70: =IF(C69=0,0,C7/C69) -> 40 | D70: =IF(D69=0,0,D7/D69) -> 150 | E70: =IF(E69=0,0,E7/E69) -> 360 | F70: =IF(F69=0,0,F7/F69) -> 600 | G70: =IF(G69=0,0,G7/G69) -> 1500 | H70: Deals / deals per active customer
B71: Revenue / deal | C71: =IF(C7=0,0,C18/C7) -> 738.05 | D71: =IF(D7=0,0,D18/D7) -> 863.2525 | E71: =IF(E7=0,0,E18/E7) -> 887.035 | F71: =IF(F7=0,0,F18/F7) -> 931.76714 | G71: =IF(G7=0,0,G18/G7) -> 1027.553 | H71: Total revenue / deals
B72: Revenue / active customer | C72: =IF(C70=0,0,C18/C70) -> 1107.075 | D72: =IF(D70=0,0,D18/D70) -> 1726.505 | E72: =IF(E70=0,0,E18/E70) -> 2217.5875 | F72: =IF(F70=0,0,F18/F70) -> 2795.3014 | G72: =IF(G70=0,0,G18/G70) -> 4110.2119 | H72: Total revenue / implied customers
B73: VAT registration flag | C73: =IF(C18>Assumptions!$F$61,"Register / confirm VAT treatment","Below threshold") -> Below threshold | D73: =IF(D18>Assumptions!$F$61,"Register / confirm VAT treatment","Below threshold") -> Register / confirm VAT treatment | E73: =IF(E18>Assumptions!$F$61,"Register / confirm VAT treatment","Below threshold") -> Register / confirm VAT treatment | F73: =IF(F18>Assumptions!$F$61,"Register / confirm VAT treatment","Below threshold") -> Register / confirm VAT treatment | G73: =IF(G18>Assumptions!$F$61,"Register / confirm VAT treatment","Below threshold") -> Register / confirm VAT treatment | H73: Revenue > threshold
B74: Gross margin sanity check | C74: =IF(AND(C31>0.9,C23>0),"Review COGS: margin may be optimistic","OK") -> OK | D74: =IF(AND(D31>0.9,D23>0),"Review COGS: margin may be optimistic","OK") -> OK | E74: =IF(AND(E31>0.9,E23>0),"Review COGS: margin may be optimistic","OK") -> OK | F74: =IF(AND(F31>0.9,F23>0),"Review COGS: margin may be optimistic","OK") -> OK | G74: =IF(AND(G31>0.9,G23>0),"Review COGS: margin may be optimistic","OK") -> OK | H74: Warn if >90% and tiered document-verification COGS is nonzero

Sheet Scenario_Base_Tiers
A1: Tier Economics - revenue, cost and risk by document-intake tier
A3: Metric | B3: Tier A eBL Y1 | C3: Tier B API Y1 | D3: Tier C Paper Y1 | E3: Total Y1 | F3: Tier A eBL Y2 | G3: Tier B API Y2 | H3: Tier C Paper Y2 | I3: Total Y2 | J3: Tier A eBL Y3 | K3: Tier B API Y3 | L3: Tier C Paper Y3 | M3: Total Y3 | N3: Tier A eBL Y4 | O3: Tier B API Y4 | P3: Tier C Paper Y4 | Q3: Total Y4 | R3: Tier A eBL Y5 | S3: Tier B API Y5 | T3: Tier C Paper Y5 | U3: Total Y5
A4: Tier mix | B4: =Assumptions!$D$64 -> 0.15 | C4: =Assumptions!$D$65 -> 0.45 | D4: =Assumptions!$D$66 -> 0.4 | E4: =SUM(B4:D4) -> 1 | F4: =Assumptions!$D$67 -> 0.3 | G4: =Assumptions!$D$68 -> 0.45 | H4: =Assumptions!$D$69 -> 0.25 | I4: =SUM(F4:H4) -> 1 | J4: =Assumptions!$D$70 -> 0.45 | K4: =Assumptions!$D$71 -> 0.4 | L4: =Assumptions!$D$72 -> 0.15 | M4: =SUM(J4:L4) -> 1 | N4: =Assumptions!$D$157 -> 0.6 | O4: =Assumptions!$D$158 -> 0.32 | P4: =Assumptions!$D$159 -> 0.08 | Q4: =SUM(N4:P4) -> 1 | R4: =Assumptions!$D$160 -> 0.7 | S4: =Assumptions!$D$161 -> 0.25 | T4: =Assumptions!$D$162 -> 0.05 | U4: =SUM(R4:T4) -> 1
A5: Deals | B5: =Scenario_Base_PL!$C$7*B4 -> 27 | C5: =Scenario_Base_PL!$C$7*C4 -> 81 | D5: =Scenario_Base_PL!$C$7*D4 -> 72 | E5: =SUM(B5:D5) -> 180 | F5: =Scenario_Base_PL!$D$7*F4 -> 270 | G5: =Scenario_Base_PL!$D$7*G4 -> 405 | H5: =Scenario_Base_PL!$D$7*H4 -> 225 | I5: =SUM(F5:H5) -> 900 | J5: =Scenario_Base_PL!$E$7*J4 -> 1350 | K5: =Scenario_Base_PL!$E$7*K4 -> 1200 | L5: =Scenario_Base_PL!$E$7*L4 -> 450 | M5: =SUM(J5:L5) -> 3000 | N5: =Scenario_Base_PL!$F$7*N4 -> 4500 | O5: =Scenario_Base_PL!$F$7*O4 -> 2400 | P5: =Scenario_Base_PL!$F$7*P4 -> 600 | Q5: =SUM(N5:P5) -> 7500 | R5: =Scenario_Base_PL!$G$7*R4 -> 12600 | S5: =Scenario_Base_PL!$G$7*S4 -> 4500 | T5: =Scenario_Base_PL!$G$7*T4 -> 900 | U5: =SUM(R5:T5) -> 18000
A6: Docs per deal | B6: =Assumptions!$F$106 -> 3 | C6: =Assumptions!$F$107 -> 6 | D6: =Assumptions!$F$108 -> 9 | E6: =IF(E5=0,0,E7/E5) -> 6.75 | F6: =Assumptions!$F$106 -> 3 | G6: =Assumptions!$F$107 -> 6 | H6: =Assumptions!$F$108 -> 9 | I6: =IF(I5=0,0,I7/I5) -> 5.85 | J6: =Assumptions!$F$106 -> 3 | K6: =Assumptions!$F$107 -> 6 | L6: =Assumptions!$F$108 -> 9 | M6: =IF(M5=0,0,M7/M5) -> 5.1 | N6: =Assumptions!$F$106 -> 3 | O6: =Assumptions!$F$107 -> 6 | P6: =Assumptions!$F$108 -> 9 | Q6: =IF(Q5=0,0,Q7/Q5) -> 4.44 | R6: =Assumptions!$F$106 -> 3 | S6: =Assumptions!$F$107 -> 6 | T6: =Assumptions!$F$108 -> 9 | U6: =IF(U5=0,0,U7/U5) -> 4.05
A7: Documents processed | B7: =B5*B6 -> 81 | C7: =C5*C6 -> 486 | D7: =D5*D6 -> 648 | E7: =SUM(B7:D7) -> 1215 | F7: =F5*F6 -> 810 | G7: =G5*G6 -> 2430 | H7: =H5*H6 -> 2025 | I7: =SUM(F7:H7) -> 5265 | J7: =J5*J6 -> 4050 | K7: =K5*K6 -> 7200 | L7: =L5*L6 -> 4050 | M7: =SUM(J7:L7) -> 15300 | N7: =N5*N6 -> 13500 | O7: =O5*O6 -> 14400 | P7: =P5*P6 -> 5400 | Q7: =SUM(N7:P7) -> 33300 | R7: =R5*R6 -> 37800 | S7: =S5*S6 -> 27000 | T7: =T5*T6 -> 8100 | U7: =SUM(R7:T7) -> 72900
A8: Avg deal value | B8: =Scenario_Base_PL!$C$8 -> 30000 | C8: =Scenario_Base_PL!$C$8 -> 30000 | D8: =Scenario_Base_PL!$C$8 -> 30000 | E8: =Scenario_Base_PL!$C$8 -> 30000 | F8: =Scenario_Base_PL!$D$8 -> 40500 | G8: =Scenario_Base_PL!$D$8 -> 40500 | H8: =Scenario_Base_PL!$D$8 -> 40500 | I8: =Scenario_Base_PL!$D$8 -> 40500 | J8: =Scenario_Base_PL!$E$8 -> 54675 | K8: =Scenario_Base_PL!$E$8 -> 54675 | L8: =Scenario_Base_PL!$E$8 -> 54675 | M8: =Scenario_Base_PL!$E$8 -> 54675 | N8: =Scenario_Base_PL!$F$8 -> 73811.25 | O8: =Scenario_Base_PL!$F$8 -> 73811.25 | P8: =Scenario_Base_PL!$F$8 -> 73811.25 | Q8: =Scenario_Base_PL!$F$8 -> 73811.25 | R8: =Scenario_Base_PL!$G$8 -> 99645.188 | S8: =Scenario_Base_PL!$G$8 -> 99645.188 | T8: =Scenario_Base_PL!$G$8 -> 99645.188 | U8: =Scenario_Base_PL!$G$8 -> 99645.188
A9: GMV | B9: =B5*B8 -> 810000 | C9: =C5*C8 -> 2430000 | D9: =D5*D8 -> 2160000 | E9: =SUM(B9:D9) -> 5400000 | F9: =F5*F8 -> 10935000 | G9: =G5*G8 -> 16402500 | H9: =H5*H8 -> 9112500 | I9: =SUM(F9:H9) -> 36450000 | J9: =J5*J8 -> 73811250 | K9: =K5*K8 -> 65610000 | L9: =L5*L8 -> 24603750 | M9: =SUM(J9:L9) -> 164025000 | N9: =N5*N8 -> 332150625 | O9: =O5*O8 -> 177147000 | P9: =P5*P8 -> 44286750 | Q9: =SUM(N9:P9) -> 553584375 | R9: =R5*R8 -> 1.2555294e+09 | S9: =S5*S8 -> 4.4840334e+08 | T9: =T5*T8 -> 89680669 | U9: =SUM(R9:T9) -> 1793613375
A10: Escrow take rate | B10: =Assumptions!$F$73 -> 0.006 | C10: =Assumptions!$F$74 -> 0.0085 | D10: =Assumptions!$F$75 -> 0.015 | E10: =IF(E9=0,0,SUM(B9*B10,C9*C10,D9*D10)/E9) -> 0.010725 | F10: =Assumptions!$F$73 -> 0.006 | G10: =Assumptions!$F$74 -> 0.0085 | H10: =Assumptions!$F$75 -> 0.015 | I10: =IF(I9=0,0,SUM(F9*F10,G9*G10,H9*H10)/I9) -> 0.009375 | J10: =Assumptions!$F$73 -> 0.006 | K10: =Assumptions!$F$74 -> 0.0085 | L10: =Assumptions!$F$75 -> 0.015 | M10: =IF(M9=0,0,SUM(J9*J10,K9*K10,L9*L10)/M9) -> 0.00835 | N10: =Assumptions!$F$73 -> 0.006 | O10: =Assumptions!$F$74 -> 0.0085 | P10: =Assumptions!$F$75 -> 0.015 | Q10: =IF(Q9=0,0,SUM(N9*N10,O9*O10,P9*P10)/Q9) -> 0.00752 | R10: =Assumptions!$F$73 -> 0.006 | S10: =Assumptions!$F$74 -> 0.0085 | T10: =Assumptions!$F$75 -> 0.015 | U10: =IF(U9=0,0,SUM(R9*R10,S9*S10,T9*T10)/U9) -> 0.007075
A11: Minimum escrow fee | B11: =Assumptions!$F$76 -> 150 | C11: =Assumptions!$F$77 -> 250 | D11: =Assumptions!$F$78 -> 500 | E11: =IF(E5=0,0,SUM(B5*B11,C5*C11,D5*D11)/E5) -> 335 | F11: =Assumptions!$F$76 -> 150 | G11: =Assumptions!$F$77 -> 250 | H11: =Assumptions!$F$78 -> 500 | I11: =IF(I5=0,0,SUM(F5*F11,G5*G11,H5*H11)/I5) -> 282.5 | J11: =Assumptions!$F$76 -> 150 | K11: =Assumptions!$F$77 -> 250 | L11: =Assumptions!$F$78 -> 500 | M11: =IF(M5=0,0,SUM(J5*J11,K5*K11,L5*L11)/M5) -> 242.5 | N11: =Assumptions!$F$76 -> 150 | O11: =Assumptions!$F$77 -> 250 | P11: =Assumptions!$F$78 -> 500 | Q11: =IF(Q5=0,0,SUM(N5*N11,O5*O11,P5*P11)/Q5) -> 210 | R11: =Assumptions!$F$76 -> 150 | S11: =Assumptions!$F$77 -> 250 | T11: =Assumptions!$F$78 -> 500 | U11: =IF(U5=0,0,SUM(R5*R11,S5*S11,T5*T11)/U5) -> 192.5
A12: Escrow fee revenue | B12: =B5*MAX(B8*B10,B11) -> 4860 | C12: =C5*MAX(C8*C10,C11) -> 20655 | D12: =D5*MAX(D8*D10,D11) -> 36000 | E12: =SUM(B12:D12) -> 61515 | F12: =F5*MAX(F8*F10,F11) -> 65610 | G12: =G5*MAX(G8*G10,G11) -> 139421.25 | H12: =H5*MAX(H8*H10,H11) -> 136687.5 | I12: =SUM(F12:H12) -> 341718.75 | J12: =J5*MAX(J8*J10,J11) -> 442867.5 | K12: =K5*MAX(K8*K10,K11) -> 557685 | L12: =L5*MAX(L8*L10,L11) -> 369056.25 | M12: =SUM(J12:L12) -> 1369608.8 | N12: =N5*MAX(N8*N10,N11) -> 1992903.8 | O12: =O5*MAX(O8*O10,O11) -> 1505749.5 | P12: =P5*MAX(P8*P10,P11) -> 664301.25 | Q12: =SUM(N12:P12) -> 4162954.5 | R12: =R5*MAX(R8*R10,R11) -> 7533176.2 | S12: =S5*MAX(S8*S10,S11) -> 3811428.4 | T12: =T5*MAX(T8*T10,T11) -> 1345210 | U12: =SUM(R12:T12) -> 12689815
A13: Doc/review fee per deal | B13: =Assumptions!$F$79 -> 25 | C13: =Assumptions!$F$80 -> 90 | D13: =Assumptions!$F$81 -> 300 | E13: =IF(E5=0,0,SUM(B5*B13,C5*C13,D5*D13)/E5) -> 164.25 | F13: =Assumptions!$F$79 -> 25 | G13: =Assumptions!$F$80 -> 90 | H13: =Assumptions!$F$81 -> 300 | I13: =IF(I5=0,0,SUM(F5*F13,G5*G13,H5*H13)/I5) -> 123 | J13: =Assumptions!$F$79 -> 25 | K13: =Assumptions!$F$80 -> 90 | L13: =Assumptions!$F$81 -> 300 | M13: =IF(M5=0,0,SUM(J5*J13,K5*K13,L5*L13)/M5) -> 92.25 | N13: =Assumptions!$F$79 -> 25 | O13: =Assumptions!$F$80 -> 90 | P13: =Assumptions!$F$81 -> 300 | Q13: =IF(Q5=0,0,SUM(N5*N13,O5*O13,P5*P13)/Q5) -> 67.8 | R13: =Assumptions!$F$79 -> 25 | S13: =Assumptions!$F$80 -> 90 | T13: =Assumptions!$F$81 -> 300 | U13: =IF(U5=0,0,SUM(R5*R13,S5*S13,T5*T13)/U5) -> 55
A14: Doc/review revenue | B14: =B5*B13 -> 675 | C14: =C5*C13 -> 7290 | D14: =D5*D13 -> 21600 | E14: =SUM(B14:D14) -> 29565 | F14: =F5*F13 -> 6750 | G14: =G5*G13 -> 36450 | H14: =H5*H13 -> 67500 | I14: =SUM(F14:H14) -> 110700 | J14: =J5*J13 -> 33750 | K14: =K5*K13 -> 108000 | L14: =L5*L13 -> 135000 | M14: =SUM(J14:L14) -> 276750 | N14: =N5*N13 -> 112500 | O14: =O5*O13 -> 216000 | P14: =P5*P13 -> 180000 | Q14: =SUM(N14:P14) -> 508500 | R14: =R5*R13 -> 315000 | S14: =S5*S13 -> 405000 | T14: =T5*T13 -> 270000 | U14: =SUM(R14:T14) -> 990000
